Workbook
Name AUFTEILER_TPL_V2: 'Verkauf Cashflow'!$A$1
Name AUFTEILER_TPL_LAYOUT: 3

Sheet BESICHTIGUNG
A1: CHECKLISTE BESICHTIGUNG
A2: Datum Besichtigung
A3: Lead Herkunft
A5: EINKAUF
A6: Anschrift
A7: Wohnfläche in m²
A8: Baujahr
A9: Wohneinheiten im Haus
A10: Hausgeld pro Monat | B10: 0
A11: Rücklagen des Hauses | B11: 0
A12: Gewinn | B12: 0.3
A13: Inseratspreis
A14: Inseratspreis pro m² | B14: =B13/B7
A15: Besonderheiten Haus / Erster Eindruck Umgebung | B15: Text
A17: ZUSTAND (MIT BILDER DOKUMENTIEREN!)
A18: Dach | B18: Zustand?
A19: Fassade | B19: Zustand?
A20: Fenster | B20: Zustand?
A21: Stellplatz / Garage | B21: Vorhanden?
A22: Heizung | B22: Art? Baujahr?
A23: Elektrik | B23: Zustand?
A25: VERKÄUFER
A26: Wer ist der Eigentümer? | B26: Text
A27: Warum wird verkauft? | B27: Text
A28: Schmerzgrenze Preis?
A30: MIETSITUATION
A31: Wie viele Einheiten sind vermietet?
A32: Wie viele Einheiten stehen leer?
A33: IST Jahresnettokaltmiete? (JNKM)
A34: Kappungsgrenze? | B34: 0
A35: Wann waren die letzten Mieterhöhungen?
A36: SOLL Jahresnettokaltmiete? (JNKM)
A39: SONSTIGE NOTIZEN
A40: Text

Sheet KALKU
H2: HINWEISE ZUR KALKULATION / NOTIZEN
H3: =IF(AND(C13<250)," Wir empfehlen keine MFHs unter 250m²","")
H4: =IF(C14<1950," Achtung, Hinweis zum Baujahr!","")
B5: DATEN EINGABE → | C5: Wert eingeben | H5: =IF(AND(C15>1,C15<6)," Wir empfehlen Mehrfamilienhäuser ab 6 Einheiten","")
H6: =IF(((MIETER!L28/MIETER!M6)<0.6)," Achtung, Sehr geringe Miete!","")
B7: WERT WIRD BERECHNET → | C7: Wert wird berechnet | H7: =IF(J29>(600*C13)," Achtung, erhöhter Renovierungsaufwand!","")
B10: 1. EINKAUF | H10: 4. VORKALKULATION DER IMMOBILIE
B11: LINK ZU OBJEKTORDNER | C11: Drive Ordner | H11: PORTAL | I11: =" PORTALSPREIS (für ⌀"&TEXT(C13/C15,"#,##")&"m² Wohnfläche)" | K11: AUF- / ABSCHLÄGE | O11: VERKAUFSPREIS
B12: ANSCHRIFT | C12: =BESICHTIGUNG!B6 | K12: -0.05 | N12: =F41
B13: WOHNFLAECHE | C13: =BESICHTIGUNG!B7 | H13: Homeday Atlas | I13: 2800 | K13: =I13*(1+$K$12) | N13: =K13*(1+$F$41) | O13: =N13*$C$13
B14: BAUJAHR | C14: =BESICHTIGUNG!B8 | H14: IS24 Preisatlas | I14: 2900 | K14: =I14*(1+$K$12) | N14: =K14*(1+$F$41) | O14: =N14*$C$13
B15: WOHNEINHEITEN IM HAUS | C15: =BESICHTIGUNG!B9 | H15: Pricehubble / Check24 | I15: 2900 | K15: =I15*(1+$K$12) | N15: =K15*(1+$F$41) | O15: =N15*$C$13
B16: HAUSGELD PRO MONAT | C16: =1.5*C13 | H16: InterHyp | I16: 2700 | K16: =I16*(1+$K$12) | N16: =K16*(1+$F$41) | O16: =N16*$C$13
B17: RÜCKLAGEN DES HAUSES | C17: 0 | H17: Wohnungmarktbericht | I17: 2000 | K17: =IF(I17>0,I17*(1+$K$12),"") | N17: =IF(K17<>"",K17*(1+$F$41),"") | O17: =IF(N17<>"",N17*$C$13,"")
B18: GEWINN | C18: 0.35 | H18: ⌀ PORTALE | I18: =AVERAGE(I13:I17) | K18: =AVERAGE(K13:K17) | N18: =AVERAGE(N13:N17) | O18: =AVERAGE(O13:O17)
B19: SCHMERZGRENZE | C19: =BESICHTIGUNG!B28
B20: PREIS PRO m² | C20: =IFERROR(C19/C13,"") | H20: 5. BETEILIGUNG INVESTOR / DEALTRADER | M20: 9. FINANZIERUNG
B21: ZINSEN (variabel) | C21: 0.06 | D21: ZINSBINDUNG | F21: 12 | H21: GEWINNBETEILIGUNG DEALTRADER (%) | I21: 0 | J21: =I21*J40 | M21: GIK | P21: =J39
B22: EINMALKOSTEN FINANZIERUNG | C22: 0 | D22: =P24*C22 | H22: GEWINNBETEILIGUNG INVESTOR (%) | I22: 0 | J22: =I22*J40 | M22: - EK | P22: 0
B23: ZINS (B&H) | C23: 0.04 | H23: SONSTIGE BETEILIGUNG | I23: 0 | J23: 0 | M23: - Darlehen Investor | O23: 0 | P23: 0
B24: TILGUNG (B&H) | C24: 0.02 | H24: = RESTGEWINN HÄNDLER | I24: =J40-J21-J22 | M24: = Darlehen Bank | P24: =P21-P22-P23
B26: 2. NEBENKOSTENRECHNER | H26: 6. KOSTEN | M26: 10. WORST-CASE RECHNER (B&H)
B27: BUNDESLAND | D27: Nordrhein-Westfalen | H27: - FINANZIERUNGSKOSTEN | I27: =J27/C13 | J27: =(P23*(O23*(F21/12)))+(P24*(C21*(F21/12)))+D22 | M27: ZINSKOSTEN (pro Jahr B&H) | P27: =P24*(C23+C24)
B28: NOTAR- UND GRUNDBUCHKOSTEN | E28: =VLOOKUP(D27,NK!A2:C17,2,FALSE()) | F28: =E28*P37 | H28: =" - HAUSGELD ("&F21&" MONATE)" | I28: =J28/C13 | J28: =(C16*F21) | M28: HAUSGELD (pro Jahr B&H) | P28: =C16*12
B29: GRUNDERWERBSTEUER | E29: =VLOOKUP(D27,NK!A2:C17,3,FALSE()) | F29: =E29*P37 | H29: - AUFWERTUNGSKOSTEN (RENO BLATT) | I29: =J29/C13 | J29: =RENO!O8 | M29: JAHRESNETTOKALTMIETE SOLL | P29: =MIETER!N31
B30: MAKLERPROVISION | D30: 0.03 | E30: =D30*1.19 | F30: =E30*P37 | H30: - KAUFNEBENKOSTEN | I30: =J30/C13 | J30: =(J39-J27-J28-J29-J31)*(E31/(1+E31)) | M30: = CASHFLOW PRO JAHR | P30: =P29-P27-P28
B31: KAUFNEBENKOSTEN = | E31: =SUM(E28:E30) | F31: =SUM(F28:F30) | H31: =" - MIETEINNAHMEN IST ("&F21&" MONATE)" | J31: =(MIETER!J31*-1)*(F21/12) | M31: => RENDITE (JNKM zu KP+NK) Mietspiegel | P31: =P29/(P37+J30)
H32: = GESAMTKOSTEN | I32: =SUM(I27:I30) | J32: =SUM(J27:J31) | M32: => RENDITE (JNKM zu GIK) Modernisierung | P32: =MIETER!R31/J39
B34: 3. AUF-/ABSCHLAG | F34: =YEAR(TODAY()) | H34: 7. GEWINN & GIK | M34: 8. ANGEBOT
B35: ART DER HEIZUNG | C35: Zentral | E35: Elektro | F35: =IF(OR(E35="Öl", E35="Elektro"), -0.05, IF(E35="Gas", 0, IF(OR(E35="Pellet", E35="Wärmepumpe"), 0.05, ""))) | G35: =F34-E36 | H35: =" VERKAUFSPREIS aus VORKALKULATION (inkl. "&TEXT(C17-(20*C13),"#,##0 €")&" Rücklagen)" | I35: =J35/C13 | J35: =O18+C17-(50*C13) | M35: SCHMERZGRENZE | O35: =P35/C13 | P35: =C19
B36: BAUJAHR HEIZUNG | E36: 2024 | F36: =IF(ISBLANK(E36), 0, MAX(MIN(0.03 - 0.003 * (F34 - E36), 0.03), -0.09))
B37: FASSADE WIRD / IST GEDÄMMT? | E37: Ja | F37: =IF(E37="Nein",-0.04,0.04) | H37: VERKAUFSPREIS aus VERKAUFSMATRIX (Detailbetrachtung aller Wohnungen) | I37: =J37/C13 | J37: =VERKAUFSMATRIX!Y28 | M37: DEIN ANGEBOTSPREIS | O37: =P37/C13 | P37: =J39-J32
B38: ZÄHLERSCHRANK WIRD / WURDE ERNEUERT? | E38: 2024 | F38: =IF(ISBLANK(E38), 0, MAX(MIN(0.01 - 0.001 * (F34 - E38), 0.01), -0.02))
B39: TREPPENHAUS WIRD / WURDE RENOVIERT? | E39: Ja | F39: =IF(E39="Nein",-0.02,0.02) | H39: - GESAMTINVESTITIONSKOSTEN | I39: =J39/C13 | J39: =J37/(1+C18)
B40: INDIVIDUELLER AUF-/ABSCHLAG | F40: 0 | H40: =" = GEWINN "&TEXT(C18,"0%") | I40: =J40/C13 | J40: =J39*C18 | M40: DIFFERENZ (€) | O40: =P40/C13 | P40: =P37-P35
B41: AUF-/ABSCHLAG GESAMT = | F41: =SUM(F35:F40) | M41: DIFFERENZ (%) | O41: =IFERROR(1-(P37/P35),"")

Sheet RENO
B2: AUFWERTUNGSKALKULATION
B4: Anschrift | F4: =KALKU!C12 | K4: ="Kalkulierte Reno Kosten inkl. "&TEXT(I6,"0%")&" Puffer (Netto)" | O4: =P106*(1+I6) | P4: =IF(OR(F5=0,F5=""),"",O4/F5)
B5: Wohnfläche | F5: =KALKU!C13 | I5: 27
B6: Baujahr | F6: =KALKU!C14 | I6: 0.1 | K6: ="Kalkulierte Reno Kosten inkl. "&TEXT(I6,"0%")&" Puffer (Brutto)" | O6: =O4*(1+I7) | P6: =IF(OR(F5=0,F5=""),"",O6/F5)
B7: Marge Handwerker | F7: 0.3 | I7: 0.19
K8: Individueller Auf-/Abschlag | L8: 0 | M8: Meine Reno Kosten = | O8: =O6*(1+L8) | P8: =IF(OR(F5=0,F5=""),"",O8/F5) | R8: =SUM(R12:R105)
R10: ↑
B11: Gewerk | C11: Pos. | D11: Gewerk | E11: lfd. Nr. | F11: Maßnahmen | G11: Anteil Lohn- kosten in % | H11: Anteil Material in % | I11: Menge | J11: Einheit | K11: pschl. EP netto | L11: Zeit in h | M11: Zeit in Tagen | N11: Lohnkosten | O11: Materialkosten | P11: Gesamtkosten (Netto) | Q11: Summe pro Gewerk (Netto) | R11: Eingeholte Angebote von Handwerkern
B12: Entmietung | C12: =IF(I12>0,1,"") | D12: =B12 | E12: 1 | F12: Entmietung (Anwaltskosten, Umzugskosten etc.) | J12: Stk | K12: 4000 | L12: 0 | M12: 0 | N12: 0 | O12: 0 | P12: =I12*K12 | Q12: =P12
B13: Entrümpelung Entsorgung | C13: =IF(I13>0,MAX($C$12:C12)+1,"") | D13: =IF(ISBLANK(B13),D12,B13) | E13: 2 | F13: Entrümplung (ohne Entsorgungskosten) | G13: 0.8 | H13: 0.2 | J13: m² | K13: 40 | L13: =(N13/$I$5)/(1+$F$7) | M13: =L13/8 | N13: =P13*G13 | O13: =P13*H13 | P13: =I13*K13 | Q13: =SUM(P13:P14)
C14: =IF(I14>0,MAX($C$12:C13)+1,"") | D14: =IF(ISBLANK(B14),D13,B14) | E14: 3 | F14: Entkernung (Wohn- und Nutzfläche) | G14: 0.9 | H14: 0.1 | J14: m² Wfl. | K14: 55 | L14: =(N14/$I$5)/(1+$F$7) | M14: =L14/8 | N14: =P14*G14 | O14: =P14*H14 | P14: =I14*K14
B15: Fassade | C15: =IF(I15>0,MAX($C$12:C14)+1,"") | D15: =IF(ISBLANK(B15),D14,B15) | E15: 4 | F15: Gerüstkosten Auf-/Abbau (Einrüstung der Fassade) | G15: 0.9 | H15: 0.1 | J15: m² | K15: 8 | L15: =(N15/$I$5)/(1+$F$7) | M15: =L15/8 | N15: =P15*G15 | O15: =P15*H15 | P15: =I15*K15 | Q15: =SUM(P15:P22)
C16: =IF(I16>0,MAX($C$12:C15)+1,"") | D16: =IF(ISBLANK(B16),D15,B16) | E16: 5 | F16: Fassade reinigen | J16: m² | K16: 2.5 | L16: =(N16/$I$5)/(1+$F$7) | M16: =L16/8 | N16: =P16*G16 | O16: =P16*H16 | P16: =I16*K16
C17: =IF(I17>0,MAX($C$12:C16)+1,"") | D17: =IF(ISBLANK(B17),D16,B17) | E17: 6 | F17: Sockel Fassade aufarbeiten | J17: m² | K17: 15 | L17: =(N17/$I$5)/(1+$F$7) | M17: =L17/8 | N17: =P17*G17 | O17: =P17*H17 | P17: =I17*K17
C18: =IF(I18>0,MAX($C$12:C17)+1,"") | D18: =IF(ISBLANK(B18),D17,B18) | E18: 7 | F18: Dämmung WDVS (16mm) | J18: m² | K18: 45 | L18: =(N18/$I$5)/(1+$F$7) | M18: =L18/8 | N18: =P18*G18 | O18: =P18*H18 | P18: =I18*K18
C19: =IF(I19>0,MAX($C$12:C18)+1,"") | D19: =IF(ISBLANK(B19),D18,B19) | E19: 8 | F19: Gewebespachtel | J19: m² | K19: 20 | L19: =(N19/$I$5)/(1+$F$7) | M19: =L19/8 | N19: =P19*G19 | O19: =P19*H19 | P19: =I19*K19
C20: =IF(I20>0,MAX($C$12:C19)+1,"") | D20: =IF(ISBLANK(B20),D19,B20) | E20: 9 | F20: Fassade verputzen | G20: 0.7 | H20: 0.3 | J20: m² | K20: 20 | L20: =(N20/$I$5)/(1+$F$7) | M20: =L20/8 | N20: =P20*G20 | O20: =P20*H20 | P20: =I20*K20
C21: =IF(I21>0,MAX($C$12:C20)+1,"") | D21: =IF(ISBLANK(B21),D20,B21) | E21: 10 | F21: Fenster ausspitzen | J21: Stk | K21: 25 | L21: =(N21/$I$5)/(1+$F$7) | M21: =L21/8 | N21: =P21*G21 | O21: =P21*H21 | P21: =I21*K21
C22: =IF(I22>0,MAX($C$12:C21)+1,"") | D22: =IF(ISBLANK(B22),D20,B22) | E22: 11 | F22: Fassade neu streichen (zweifach) | G22: 0.75 | H22: 0.25 | J22: m² | K22: 12.5 | L22: =(N22/$I$5)/(1+$F$7) | M22: =L22/8 | N22: =P22*G22 | O22: =P22*H22 | P22: =I22*K22
B23: Dach | C23: =IF(I23>0,MAX($C$12:C22)+1,"") | D23: =IF(ISBLANK(B23),D22,B23) | E23: 12 | F23: Dachreinigung | G23: 0.8 | H23: 0.2 | J23: m² | K23: 5 | L23: =(N23/$I$5)/(1+$F$7) | M23: =L23/8 | N23: =P23*G23 | O23: =P23*H23 | P23: =I23*K23 | Q23: =SUM(P23:P27)
C24: =IF(I24>0,MAX($C$12:C23)+1,"") | D24: =IF(ISBLANK(B24),D22,B24) | E24: 13 | F24: Dachbeschichtung / Versiegelung (zweifach) | J24: m² | K24: 25 | L24: =(N24/$I$5)/(1+$F$7) | M24: =L24/8 | N24: =P24*G24 | O24: =P24*H24 | P24: =I24*K24
C25: =IF(I25>0,MAX($C$12:C24)+1,"") | D25: =IF(ISBLANK(B25),D23,B25) | E25: 14 | F25: Dach neu decken | G25: 0.8 | H25: 0.2 | J25: m² | K25: 95 | L25: =(N25/$I$5)/(1+$F$7) | M25: =L25/8 | N25: =P25*G25 | O25: =P25*H25 | P25: =I25*K25
C26: =IF(I26>0,MAX($C$12:C25)+1,"") | D26: =IF(ISBLANK(B26),D25,B26) | E26: 15 | F26: Dachrinne & Fallrohre erneuern | G26: 0.8 | H26: 0.2 | J26: lfd.m | K26: 50 | L26: =(N26/$I$5)/(1+$F$7) | M26: =L26/8 | N26: =P26*G26 | O26: =P26*H26 | P26: =I26*K26
C27: =IF(I27>0,MAX($C$12:C26)+1,"") | D27: =IF(ISBLANK(B27),D26,B27) | E27: 16 | F27: Dachdämmung (inkl. Dampfsperre) | G27: 0.6 | H27: 0.4 | J27: m² | K27: 90 | L27: =(N27/$I$5)/(1+$F$7) | M27: =L27/8 | N27: =P27*G27 | O27: =P27*H27 | P27: =I27*K27
B28: Wände und Decken | C28: =IF(I28>0,MAX($C$12:C27)+1,"") | D28: =IF(ISBLANK(B28),D27,B28) | E28: 17 | F28: Wände und Decken neu tapezieren und streichen | G28: 0.8 | H28: 0.2 | J28: m² Wfl. | K28: =18 | L28: =(N28/$I$5)/(1+$F$7) | M28: =L28/8 | N28: =P28*G28 | O28: =P28*H28 | P28: =I28*K28 | Q28: =SUM(P28:P33)
C29: =IF(I29>0,MAX($C$12:C28)+1,"") | D29: =IF(ISBLANK(B29),D28,B29) | E29: 18 | F29: Wände verputzen | G29: 0.7 | H29: 0.3 | J29: m² Wfl. | K29: 17 | L29: =(N29/$I$5)/(1+$F$7) | M29: =L29/8 | N29: =P29*G29 | O29: =P29*H29 | P29: =I29*K29
C30: =IF(I30>0,MAX($C$12:C29)+1,"") | D30: =IF(ISBLANK(B30),D29,B30) | E30: 19 | F30: Wand einziehen (Trockenbau) | G30: 0.7 | H30: 0.3 | J30: m² | K30: 60 | L30: =(N30/$I$5)/(1+$F$7) | M30: =L30/8 | N30: =P30*G30 | O30: =P30*H30 | P30: =I30*K30
C31: =IF(I31>0,MAX($C$12:C30)+1,"") | D31: =IF(ISBLANK(B31),D30,B31) | E31: 20 | F31: Decke abhängen (Trockenbau) | G31: 0.7 | H31: 0.3 | J31: m² | K31: 44 | L31: =(N31/$I$5)/(1+$F$7) | M31: =L31/8 | N31: =P31*G31 | O31: =P31*H31 | P31: =I31*K31
C32: =IF(I32>0,MAX($C$12:C31)+1,"") | D32: =IF(ISBLANK(B32),D31,B32) | E32: 21 | F32: Tapete entfernen | G32: 0.95 | H32: 0.05 | J32: m² Wfl. | K32: 7 | L32: =(N32/$I$5)/(1+$F$7) | M32: =L32/8 | N32: =P32*G32 | O32: =P32*H32 | P32: =I32*K32
C33: =IF(I33>0,MAX($C$12:C32)+1,"") | D33: =IF(ISBLANK(B33),D32,B33) | E33: 22 | F33: Wände und Decken streichen | G33: 0.8 | H33: 0.2 | J33: m² Wfl. | K33: 8.95 | L33: =(N33/$I$5)/(1+$F$7) | M33: =L33/8 | N33: =P33*G33 | O33: =P33*H33 | P33: =I33*K33
B34: Fussböden | C34: =IF(I34>0,MAX($C$12:C33)+1,"") | D34: =IF(ISBLANK(B34),D33,B34) | E34: 23 | F34: Alten Bodenbelag entfernen | G34: 0.9 | H34: 0.1 | J34: m² | K34: 5.2 | L34: =(N34/$I$5)/(1+$F$7) | M34: =L34/8 | N34: =P34*G34 | O34: =P34*H34 | P34: =I34*K34 | Q34: =SUM(P34:P39)
C35: =IF(I35>0,MAX($C$12:C34)+1,"") | D35: =IF(ISBLANK(B35),D34,B35) | E35: 24 | F35: Balkonfußboden beschichten | G35: 0.8 | H35: 0.2 | J35: Stk | K35: 350 | L35: =(N35/$I$5)/(1+$F$7) | M35: =L35/8 | N35: =P35*G35 | O35: =P35*H35 | P35: =I35*K35
C36: =IF(I36>0,MAX($C$12:C35)+1,"") | D36: =IF(ISBLANK(B36),D35,B36) | E36: 25 | F36: Sockelleisten erneuern pauschal pro Raum | G36: 0.8 | H36: 0.2 | J36: Raum | K36: 78 | L36: =(N36/$I$5)/(1+$F$7) | M36: =L36/8 | N36: =P36*G36 | O36: =P36*H36 | P36: =I36*K36
C37: =IF(I37>0,MAX($C$12:C36)+1,"") | D37: =IF(ISBLANK(B37),D36,B37) | E37: 26 | F37: Laminat / Vinyl verlegen | G37: 0.6 | H37: 0.4 | J37: m² Wfl. | K37: 38 | L37: =(N37/$I$5)/(1+$F$7) | M37: =L37/8 | N37: =P37*G37 | O37: =P37*H37 | P37: =I37*K37
C38: =IF(I38>0,MAX($C$12:C37)+1,"") | D38: =IF(ISBLANK(B38),D37,B38) | E38: 27 | F38: Laminat / Vinyl verlegen (mit Trittschalldämmung) | G38: 0.6 | H38: 0.4 | J38: m² Wfl. | K38: 50 | L38: =(N38/$I$5)/(1+$F$7) | M38: =L38/8 | N38: =P38*G38 | O38: =P38*H38 | P38: =I38*K38
C39: =IF(I39>0,MAX($C$12:C38)+1,"") | D39: =IF(ISBLANK(B39),D38,B39) | E39: 28 | F39: Parkett schleifen und lackieren | G39: 0.7 | H39: 0.3 | J39: m² Wfl. | K39: 80 | L39: =(N39/$I$5)/(1+$F$7) | M39: =L39/8 | N39: =P39*G39 | O39: =P39*H39 | P39: =I39*K39
B40: Fenster und Türen | C40: =IF(I40>0,MAX($C$12:C39)+1,"") | D40: =IF(ISBLANK(B40),D39,B40) | E40: 29 | F40: Geländer entrosten und streichen | G40: 0.85 | H40: 0.15 | J40: lfd.m | K40: 45 | L40: =(N40/$I$5)/(1+$F$7) | M40: =L40/8 | N40: =P40*G40 | O40: =P40*H40 | P40: =I40*K40 | Q40: =SUM(P40:P54)
C41: =IF(I41>0,MAX($C$12:C40)+1,"") | D41: =IF(ISBLANK(B41),D40,B41) | E41: 30 | F41: Holzfenster lackieren | G41: 0.8 | H41: 0.2 | J41: Stk | K41: 120 | L41: =(N41/$I$5)/(1+$F$7) | M41: =L41/8 | N41: =P41*G41 | O41: =P41*H41 | P41: =I41*K41
C42: =IF(I42>0,MAX($C$12:C41)+1,"") | D42: =IF(ISBLANK(B42),D41,B42) | E42: 31 | F42: Tür und Zarge lackieren | G42: 0.7 | H42: 0.3 | J42: Stk | K42: 180 | L42: =(N42/$I$5)/(1+$F$7) | M42: =L42/8 | N42: =P42*G42 | O42: =P42*H42 | P42: =I42*K42
C43: =IF(I43>0,MAX($C$12:C42)+1,"") | D43: =IF(ISBLANK(B43),D42,B43) | E43: 32 | F43: Zarge lackieren | G43: 0.7 | H43: 0.3 | J43: Stk | K43: 80 | L43: =(N43/$I$5)/(1+$F$7) | M43: =L43/8 | N43: =P43*G43 | O43: =P43*H43 | P43: =I43*K43
C44: =IF(I44>0,MAX($C$12:C43)+1,"") | D44: =IF(ISBLANK(B44),D43,B44) | E44: 33 | F44: Innentür mit Türzarge erneuern | G44: 0.2 | H44: 0.8 | J44: Stk | K44: 280 | L44: =(N44/$I$5)/(1+$F$7) | M44: =L44/8 | N44: =P44*G44 | O44: =P44*H44 | P44: =I44*K44
C45: =IF(I45>0,MAX($C$12:C44)+1,"") | D45: =IF(ISBLANK(B45),D44,B45) | E45: 34 | F45: Innentürblatt erneuern | G45: 0.1 | H45: 0.9 | J45: Stk | K45: 140 | L45: =(N45/$I$5)/(1+$F$7) | M45: =L45/8 | N45: =P45*G45 | O45: =P45*H45 | P45: =I45*K45
C46: =IF(I46>0,MAX($C$12:C45)+1,"") | D46: =IF(ISBLANK(B46),D45,B46) | E46: 35 | F46: Türbeschläge Innentür erneuern | G46: 0.2 | H46: 0.8 | J46: Stk | K46: 35 | L46: =(N46/$I$5)/(1+$F$7) | M46: =L46/8 | N46: =P46*G46 | O46: =P46*H46 | P46: =I46*K46
C47: =IF(I47>0,MAX($C$12:C46)+1,"") | D47: =IF(ISBLANK(B47),D46,B47) | E47: 36 | F47: Wohnungstür erneuern | G47: 0.3 | H47: 0.7 | J47: Stk | K47: 1400 | L47: =(N47/$I$5)/(1+$F$7) | M47: =L47/8 | N47: =P47*G47 | O47: =P47*H47 | P47: =I47*K47
C48: =IF(I48>0,MAX($C$12:C47)+1,"") | D48: =IF(ISBLANK(B48),D47,B48) | E48: 37 | F48: Hauseingangstür erneuern | G48: 0.25 | H48: 0.75 | J48: Stk | K48: 2750 | L48: =(N48/$I$5)/(1+$F$7) | M48: =L48/8 | N48: =P48*G48 | O48: =P48*H48 | P48: =I48*K48
C49: =IF(I49>0,MAX($C$12:C48)+1,"") | D49: =IF(ISBLANK(B49),D48,B49) | E49: 38 | F49: Fenster einstellen | G49: 1 | H49: 0 | J49: Stk | K49: 15 | L49: =(N49/$I$5)/(1+$F$7) | M49: =L49/8 | N49: =P49*G49 | O49: =P49*H49 | P49: =I49*K49
C50: =IF(I50>0,MAX($C$12:C49)+1,"") | D50: =IF(ISBLANK(B50),D49,B50) | E50: 39 | F50: Fenster erneuern (komplett) | G50: 0.5 | H50: 0.5 | J50: Stk | K50: 800 | L50: =(N50/$I$5)/(1+$F$7) | M50: =L50/8 | N50: =P50*G50 | O50: =P50*H50 | P50: =I50*K50
C51: =IF(I51>0,MAX($C$12:C50)+1,"") | D51: =IF(ISBLANK(B51),D50,B51) | E51: 40 | F51: Balkontür erneuern | G51: 0.2 | H51: 0.8 | J51: Stk. | K51: 900 | L51: =(N51/$I$5)/(1+$F$7) | M51: =L51/8 | N51: =P51*G51 | O51: =P51*H51 | P51: =I51*K51
C52: =IF(I52>0,MAX($C$12:C51)+1,"") | D52: =IF(ISBLANK(B52),D51,B52) | E52: 41 | F52: Fensterbänke | G52: 0.35 | H52: 0.65 | J52: Stk | K52: 75 | L52: =(N52/$I$5)/(1+$F$7) | M52: =L52/8 | N52: =P52*G52 | O52: =P52*H52 | P52: =I52*K52
... C54: =IF(I54>0,MAX($C$12:C53)+1,"") | D54: =IF(ISBLANK(B54),D53,B54) | E54: 43 | F54: Dachflächenfenster erneuern | G54: 0.3 | H54: 0.7 | J54: Stk | K54: 1000 | L54: =(N54/$I$5)/(1+$F$7) | M54: =L54/8 | N54: =P54*G54 | O54: =P54*H54 | P54: =I54*K54
B55: Fliesen | C55: =IF(I55>0,MAX($C$12:C54)+1,"") | D55: =IF(ISBLANK(B55),D54,B55) | E55: 44 | F55: Fliesenspiegel Küche lackieren | G55: 0.7 | H55: 0.3 | J55: psch | K55: 120 | L55: =(N55/$I$5)/(1+$F$7) | M55: =L55/8 | N55: =P55*G55 | O55: =P55*H55 | P55: =I55*K55 | Q55: =SUM(P55:P60)
C56: =IF(I56>0,MAX($C$12:C55)+1,"") | D56: =IF(ISBLANK(B56),D55,B56) | E56: 45 | F56: Wandfliesen erneuern | G56: 0.75 | H56: 0.25 | J56: m² | K56: 70 | L56: =(N56/$I$5)/(1+$F$7) | M56: =L56/8 | N56: =P56*G56 | O56: =P56*H56 | P56: =I56*K56
C57: =IF(I57>0,MAX($C$12:C56)+1,"") | D57: =IF(ISBLANK(B57),D56,B57) | E57: 46 | F57: Bodenfliesen erneuern | G57: 0.75 | H57: 0.25 | J57: m² | K57: 80 | L57: =(N57/$I$5)/(1+$F$7) | M57: =L57/8 | N57: =P57*G57 | O57: =P57*H57 | P57: =I57*K57
C58: =IF(I58>0,MAX($C$12:C57)+1,"") | D58: =IF(ISBLANK(B58),D57,B58) | E58: 47 | F58: Fliesenspiegel in Küche erneuern | G58: 0.75 | H58: 0.25 | J58: psch | K58: 250 | L58: =(N58/$I$5)/(1+$F$7) | M58: =L58/8 | N58: =P58*G58 | O58: =P58*H58 | P58: =I58*K58
C59: =IF(I59>0,MAX($C$12:C58)+1,"") | D59: =IF(ISBLANK(B59),D58,B59) | E59: 48 | F59: Silikonfugen im Bad erneuern | G59: 0.9 | H59: 0.1 | J59: psch | K59: 250 | L59: =(N59/$I$5)/(1+$F$7) | M59: =L59/8 | N59: =P59*G59 | O59: =P59*H59 | P59: =I59*K59
C60: =IF(I60>0,MAX($C$12:C59)+1,"") | D60: =IF(ISBLANK(B60),D59,B60) | E60: 49 | F60: Wandfliesen lackieren Bad | G60: 0.8 | H60: 0.2 | J60: psch | K60: 450 | L60: =(N60/$I$5)/(1+$F$7) | M60: =L60/8 | N60: =P60*G60 | O60: =P60*H60 | P60: =I60*K60
B61: Elektro | C61: =IF(I61>0,MAX($C$12:C60)+1,"") | D61: =IF(ISBLANK(B61),D60,B61) | E61: 50 | F61: E-Check in Wohnung | G61: 0.95 | H61: 0.05 | J61: Stk | K61: 500 | L61: =(N61/$I$5)/(1+$F$7) | M61: =L61/8 | N61: =P61*G61 | O61: =P61*H61 | P61: =I61*K61 | Q61: =SUM(P61:P69)
C62: =IF(I62>0,MAX($C$12:C61)+1,"") | D62: =IF(ISBLANK(B62),D61,B62) | E62: 51 | F62: Taster und Steckdosen austauschen | G62: 0.65 | H62: 0.35 | J62: Stk | K62: 30 | L62: =(N62/$I$5)/(1+$F$7) | M62: =L62/8 | N62: =P62*G62 | O62: =P62*H62 | P62: =I62*K62
C63: =IF(I63>0,MAX($C$12:C62)+1,"") | D63: =IF(ISBLANK(B63),D62,B63) | E63: 52 | F63: LED-Spots | G63: 0.5 | H63: 0.5 | J63: Stk | K63: 30 | L63: =(N63/$I$5)/(1+$F$7) | M63: =L63/8 | N63: =P63*G63 | O63: =P63*H63 | P63: =I63*K63
C64: =IF(I64>0,MAX($C$12:C63)+1,"") | D64: =IF(ISBLANK(B64),D63,B64) | E64: 53 | F64: Nachrüstung FI-Schutzschalter | G64: 0.85 | H64: 0.15 | J64: Stk | K64: 500 | L64: =(N64/$I$5)/(1+$F$7) | M64: =L64/8 | N64: =P64*G64 | O64: =P64*H64 | P64: =I64*K64
C65: =IF(I65>0,MAX($C$12:C64)+1,"") | D65: =IF(ISBLANK(B65),D64,B65) | E65: 54 | F65: Sprechanlage | J65: Stk | K65: 300 | L65: =(N65/$I$5)/(1+$F$7) | M65: =L65/8 | N65: =P65*G65 | O65: =P65*H65 | P65: =I65*K65
C66: =IF(I66>0,MAX($C$12:C65)+1,"") | D66: =IF(ISBLANK(B66),D65,B66) | E66: 55 | F66: Lampen erneuern (Treppenhaus, Keller, Hof, Eingang) | G66: 0.5 | H66: 0.5 | J66: Stk | K66: 50 | L66: =(N66/$I$5)/(1+$F$7) | M66: =L66/8 | N66: =P66*G66 | O66: =P66*H66 | P66: =I66*K66
C67: =IF(I67>0,MAX($C$12:C66)+1,"") | D67: =IF(ISBLANK(B67),D66,B67) | E67: 56 | F67: Unterverteilung Wohnung komplett erneuern | G67: 0.65 | H67: 0.35 | J67: Stk | K67: 600 | L67: =(N67/$I$5)/(1+$F$7) | M67: =L67/8 | N67: =P67*G67 | O67: =P67*H67 | P67: =I67*K67
C68: =IF(I68>0,MAX($C$12:C67)+1,"") | D68: =IF(ISBLANK(B68),D67,B68) | E68: 57 | F68: Neuer Zählerschrank für MFH | J68: WE | K68: 1000 | L68: =(N68/$I$5)/(1+$F$7) | M68: =L68/8 | N68: =P68*G68 | O68: =P68*H68 | P68: =I68*K68
C69: =IF(I69>0,MAX($C$12:C68)+1,"") | D69: =IF(ISBLANK(B69),D67,B69) | E69: 58 | F69: Elektroinstallation neu pro qm Wohnfläche | G69: 0.65 | H69: 0.35 | J69: m² | K69: 80 | L69: =(N69/$I$5)/(1+$F$7) | M69: =L69/8 | N69: =P69*G69 | O69: =P69*H69 | P69: =I69*K69
B70: Heizung / Heizkörper | C70: =IF(I70>0,MAX($C$12:C69)+1,"") | D70: =IF(ISBLANK(B70),D69,B70) | E70: 59 | F70: Heizkörper lackieren | G70: 0.75 | H70: 0.25 | J70: Stk | K70: 65 | L70: =(N70/$I$5)/(1+$F$7) | M70: =L70/8 | N70: =P70*G70 | O70: =P70*H70 | P70: =I70*K70 | Q70: =SUM(P70:P83)
C71: =IF(I71>0,MAX($C$12:C70)+1,"") | D71: =IF(ISBLANK(B71),D70,B71) | E71: 60 | F71: Thermostatkopfwechsel | G71: 0.3 | H71: 0.7 | J71: Stk | K71: 40 | L71: =(N71/$I$5)/(1+$F$7) | M71: =L71/8 | N71: =P71*G71 | O71: =P71*H71 | P71: =I71*K71
C72: =IF(I72>0,MAX($C$12:C71)+1,"") | D72: =IF(ISBLANK(B72),D71,B72) | E72: 61 | F72: Heizkörper überprüfen in Wohnung | G72: 1 | H72: 0 | J72: Stk | K72: 145 | L72: =(N72/$I$5)/(1+$F$7) | M72: =L72/8 | N72: =P72*G72 | O72: =P72*H72 | P72: =I72*K72
C73: =IF(I73>0,MAX($C$12:C72)+1,"") | D73: =IF(ISBLANK(B73),D72,B73) | E73: 62 | F73: Heizkörper mit Thermostat erneuern | G73: 0 | H73: 1 | J73: Stk | K73: 240 | L73: =(N73/$I$5)/(1+$F$7) | M73: =L73/8 | N73: =P73*G73 | O73: =P73*H73 | P73: =I73*K73
C74: =IF(I74>0,MAX($C$12:C73)+1,"") | D74: =IF(ISBLANK(B74),D73,B74) | E74: 63 | F74: Elekrodurchlauferhitzer erneuern | G74: 0.3 | H74: 0.7 | J74: Stk | K74: 750 | L74: =(N74/$I$5)/(1+$F$7) | M74: =L74/8 | N74: =P74*G74 | O74: =P74*H74 | P74: =I74*K74
C75: =IF(I75>0,MAX($C$12:C74)+1,"") | D75: =IF(ISBLANK(B75),D74,B75) | E75: 64 | F75: Heizleitungen erneuern pro qm Wfl. | G75: 0.7 | H75: 0.3 | J75: m² | K75: 40 | L75: =(N75/$I$5)/(1+$F$7) | M75: =L75/8 | N75: =P75*G75 | O75: =P75*H75 | P75: =I75*K75
C76: =IF(I76>0,MAX($C$12:C75)+1,"") | D76: =IF(ISBLANK(B76),D75,B76) | E76: 65 | F76: Badlüfter tauschen | G76: 0.35 | H76: 0.65 | J76: Stk | K76: 105 | L76: =(N76/$I$5)/(1+$F$7) | M76: =L76/8 | N76: =P76*G76 | O76: =P76*H76 | P76: =I76*K76
C77: =IF(I77>0,MAX($C$12:C76)+1,"") | D77: =IF(ISBLANK(B77),D76,B77) | E77: 66 | F77: Pelletheizung einbauen (ohne Leitungen & Heizkörper) | J77: WE | K77: 6500 | L77: =(N77/$I$5)/(1+$F$7) | M77: =L77/8 | N77: =P77*G77 | O77: =P77*H77 | P77: =I77*K77
C78: =IF(I78>0,MAX($C$12:C77)+1,"") | D78: =IF(ISBLANK(B78),D77,B78) | E78: 67 | F78: Gaszentralheizung erneuern | J78: WE
C79: =IF(I79>0,MAX($C$12:C78)+1,"") | D79: =IF(ISBLANK(B79),D78,B79) | E79: 68 | F79: Luft-Wärmepumpe erneuern | J79: WE
C80: =IF(I80>0,MAX($C$12:C79)+1,"") | D80: =IF(ISBLANK(B80),D76,B80) | E80: 69 | F80: Elektroheizung - Einbau Stromleitungen | G80: 0.4 | H80: 0.6 | J80: m² | K80: 10 | L80: =(N80/$I$5)/(1+$F$7) | M80: =L80/8 | N80: =P80*G80 | O80: =P80*H80 | P80: =I80*K80
C81: =IF(I81>0,MAX($C$12:C80)+1,"") | D81: =IF(ISBLANK(B81),D80,B81) | E81: 70 | F81: Elektroheizung | G81: 0.4 | H81: 0.6 | J81: m² | K81: 30 | L81: =(N81/$I$5)/(1+$F$7) | M81: =L81/8 | N81: =P81*G81 | O81: =P81*H81 | P81: =I81*K81
C82: =IF(I82>0,MAX($C$12:C81)+1,"") | D82: =IF(ISBLANK(B82),D81,B82) | E82: 71 | F82: Gastherme überprüfen | G82: 1 | H82: 0 | J82: Stk | K82: 200 | L82: =(N82/$I$5)/(1+$F$7) | M82: =L82/8 | N82: =P82*G82 | O82: =P82*H82 | P82: =I82*K82
C83: =IF(I83>0,MAX($C$12:C82)+1,"") | D83: =IF(ISBLANK(B83),D82,B83) | E83: 72 | F83: Gastherme erneuern | G83: 0.4 | H83: 0.6 | J83: Stk | K83: 4750 | L83: =(N83/$I$5)/(1+$F$7) | M83: =L83/8 | N83: =P83*G83 | O83: =P83*H83 | P83: =I83*K83
B84: Bad / Sanitär | C84: =IF(I84>0,MAX($C$12:C83)+1,"") | D84: =IF(ISBLANK(B84),D83,B84) | E84: 73 | F84: Badewanne erneuern | G84: 0.4 | H84: 0.6 | J84: Stk. | K84: 800 | L84: =(N84/$I$5)/(1+$F$7) | M84: =L84/8 | N84: =P84*G84 | O84: =P84*H84 | P84: =I84*K84 | Q84: =SUM(P84:P96)
C85: =IF(I85>0,MAX($C$12:C84)+1,"") | D85: =IF(ISBLANK(B85),D84,B85) | E85: 74 | F85: Armatur Badewanne inkl. Duschstange erneuern | G85: 0.4 | H85: 0.6 | J85: Stk. | K85: 250 | L85: =(N85/$I$5)/(1+$F$7) | M85: =L85/8 | N85: =P85*G85 | O85: =P85*H85 | P85: =I85*K85
C86: =IF(I86>0,MAX($C$12:C85)+1,"") | D86: =IF(ISBLANK(B86),D85,B86) | E86: 75 | F86: Duschwanne erneuern | G86: 0.4 | H86: 0.6 | J86: Stk. | K86: 600 | L86: =(N86/$I$5)/(1+$F$7) | M86: =L86/8 | N86: =P86*G86 | O86: =P86*H86 | P86: =I86*K86
C87: =IF(I87>0,MAX($C$12:C86)+1,"") | D87: =IF(ISBLANK(B87),D86,B87) | E87: 76 | F87: Handbrause mit Schlauch erneuern | G87: 0.3 | H87: 0.7 | J87: Stk. | K87: 70 | L87: =(N87/$I$5)/(1+$F$7) | M87: =L87/8 | N87: =P87*G87 | O87: =P87*H87 | P87: =I87*K87
C88: =IF(I88>0,MAX($C$12:C87)+1,"") | D88: =IF(ISBLANK(B88),D87,B88) | E88: 77 | F88: Waschbecken erneuern | G88: 0.6 | H88: 0.4 | J88: Stk. | K88: 280 | L88: =(N88/$I$5)/(1+$F$7) | M88: =L88/8 | N88: =P88*G88 | O88: =P88*H88 | P88: =I88*K88
C89: =IF(I89>0,MAX($C$12:C88)+1,"") | D89: =IF(ISBLANK(B89),D88,B89) | E89: 78 | F89: Armatur Waschbecken erneuern | G89: 0.4 | H89: 0.6 | J89: Stk. | K89: 120 | L89: =(N89/$I$5)/(1+$F$7) | M89: =L89/8 | N89: =P89*G89 | O89: =P89*H89 | P89: =I89*K89
C90: =IF(I90>0,MAX($C$12:C89)+1,"") | D90: =IF(ISBLANK(B90),D89,B90) | E90: 79 | F90: WC erneuern | G90: 0.4 | H90: 0.6 | J90: Stk. | K90: 220 | L90: =(N90/$I$5)/(1+$F$7) | M90: =L90/8 | N90: =P90*G90 | O90: =P90*H90 | P90: =I90*K90
C91: =IF(I91>0,MAX($C$12:C90)+1,"") | D91: =IF(ISBLANK(B91),D90,B91) | E91: 80 | F91: WC Sitz + Deckel erneuern | G91: 0.2 | H91: 0.8 | J91: Stk. | K91: 60 | L91: =(N91/$I$5)/(1+$F$7) | M91: =L91/8 | N91: =P91*G91 | O91: =P91*H91 | P91: =I91*K91
C92: =IF(I92>0,MAX($C$12:C91)+1,"") | D92: =IF(ISBLANK(B92),D91,B92) | E92: 81 | F92: WC Spülkasten erneuern | G92: 0.3 | H92: 0.7 | J92: Stk. | K92: 100 | L92: =(N92/$I$5)/(1+$F$7) | M92: =L92/8 | N92: =P92*G92 | O92: =P92*H92 | P92: =I92*K92
C93: =IF(I93>0,MAX($C$12:C92)+1,"") | D93: =IF(ISBLANK(B93),D92,B93) | E93: 82 | F93: Bad Komplettsanierung ohne Leitungen | G93: 0.7 | H93: 0.3 | J93: m² Wfl. | K93: 750 | L93: =(N93/$I$5)/(1+$F$7) | M93: =L93/8 | N93: =P93*G93 | O93: =P93*H93 | P93: =I93*K93
C94: =IF(I94>0,MAX($C$12:C93)+1,"") | D94: =IF(ISBLANK(B94),D93,B94) | E94: 83 | F94: Wasserleitungen erneuern | G94: 0.7 | H94: 0.3 | J94: m² | K94: 70 | L94: =(N94/$I$5)/(1+$F$7) | M94: =L94/8 | N94: =P94*G94 | O94: =P94*H94 | P94: =I94*K94
C95: =IF(I95>0,MAX($C$12:C94)+1,"") | D95: =IF(ISBLANK(B95),D94,B95) | E95: 84 | F95: Wasserzähler einbauen | G95: 0.4 | H95: 0.6 | J95: Stk. | K95: 350 | L95: =(N95/$I$5)/(1+$F$7) | M95: =L95/8 | N95: =P95*G95 | O95: =P95*H95 | P95: =I95*K95
C96: =IF(I96>0,MAX($C$12:C95)+1,"") | D96: =IF(ISBLANK(B96),D95,B96) | E96: 85 | F96: Waschmaschienen Anschluss herstellen | G96: 0.8 | H96: 0.2 | J96: Stk | K96: 300 | L96: =(N96/$I$5)/(1+$F$7) | M96: =L96/8 | N96: =P96*G96 | O96: =P96*H96 | P96: =I96*K96
B97: Außenanlage | C97: =IF(I97>0,MAX($C$12:C96)+1,"") | D97: =IF(ISBLANK(B97),D96,B97) | E97: 86 | F97: Gartenarbeiten | G97: 0.85 | H97: 0.15 | J97: Std | K97: 35 | L97: =(N97/$I$5)/(1+$F$7) | M97: =L97/8 | N97: =P97*G97 | O97: =P97*H97 | P97: =I97*K97 | Q97: =SUM(P97:P99)
C98: =IF(I98>0,MAX($C$12:C97)+1,"") | D98: =IF(ISBLANK(B98),D97,B98) | E98: 87 | F98: Asphalt / Betondecke abbrechen und entsorgen | J98: m² | K98: 25 | L98: =(N98/$I$5)/(1+$F$7) | M98: =L98/8 | N98: =P98*G98 | O98: =P98*H98 | P98: =I98*K98
C99: =IF(I99>0,MAX($C$12:C98)+1,"") | D99: =IF(ISBLANK(B99),D98,B99) | E99: 88 | F99: Hof pflastern (inkl. Steine) | J99: m² | K99: 80 | L99: =(N99/$I$5)/(1+$F$7) | M99: =L99/8 | N99: =P99*G99 | O99: =P99*H99 | P99: =I99*K99
B100: Reinigung | C100: =IF(I100>0,MAX($C$12:C99)+1,"") | D100: =IF(ISBLANK(B100),D99,B100) | E100: 89 | F100: Grundreinigung Wohnung / Bauendreinigung | G100: 1 | H100: 0 | J100: Stk | K100: 500 | L100: =(N100/$I$5)/(1+$F$7) | M100: =L100/8 | N100: =P100*G100 | O100: =P100*H100 | P100: =I100*K100 | Q100: =P100
B101: Home Staging | C101: =IF(I101>0,MAX($C$12:C100)+1,"") | D101: =IF(ISBLANK(B101),D100,B101) | E101: 90 | F101: Home Staging (Beispieleinrichtung für den Verkauf) | J101: m² | K101: 50 | L101: =(N101/$I$5)/(1+$F$7) | M101: =L101/8 | N101: =P101*G101 | O101: =P101*H101 | P101: =I101*K101 | Q101: =P101
B102: Sonstiges | C102: =IF(I102>0,MAX($C$12:C101)+1,"") | D102: =IF(ISBLANK(B102),D101,B102) | E102: 91 | F102: Einbauküche (inkl. Montage) | G102: 0.5 | H102: 0.5 | J102: Stk | K102: 3000 | L102: =(N102/$I$5)/(1+$F$7) | M102: =L102/8 | N102: =P102*G102 | O102: =P102*H102 | P102: =I102*K102 | Q102: =SUM(P102:P105)
C103: =IF(I103>0,MAX($C$12:C102)+1,"") | D103: =IF(ISBLANK(B103),D102,B103) | E103: 92 | F103: Scheune abreißen (inkl. Entsorgung) | G103: 0.5 | H103: 0.5 | J103: psch | K103: 10000 | L103: =(N103/$I$5)/(1+$F$7) | M103: =L103/8 | N103: =P103*G103 | O103: =P103*H103 | P103: =I103*K103
C104: =IF(I104>0,MAX($C$12:C103)+1,"") | D104: =IF(ISBLANK(B104),D103,B104) | E104: 93 | F104: WEG Aufteilung | G104: 0.5 | H104: 0.5 | J104: psch | K104: 12000 | L104: =(N104/$I$5)/(1+$F$7) | M104: =L104/8 | N104: =P104*G104 | O104: =P104*H104 | P104: =I104*K104
...

Sheet MIETER
A1: MIETAUFSTELLUNG
R3: § 559 BGB (Modernisierung)
N4: =TODAY() | R4: Modernisierungskosten =
N5: § 558 BGB (Mietspiegel) | R5: Davon 8% umlegbar auf JNKM = | T5: =T4*8%
L6: Mietspiegel → | M6: 10 | N6: Kappungsgrenze = | P6: 0.2 | R6: Erhöhung pro Monat pro qm WFL = | T6: =T5/12/F28 | U6: Tagesaktuelle Mietsituation während dem Projekt | Y6: Modul 4 Output
A7: Haus Nr. | B7: WHG Nr | C7: Etage | D7: Lage | E7: Zimmer | F7: Wohnfläche | G7: Name Mieter | H7: Beginn Miete | I7: letz. Erhöhung | J7: Kaltmiete IST | K7: Garagen-/Stellpl.- miete | L7: IST KM/qm | M7: Δ zu Mietspiegel | N7: Kaltmiete NEU | O7: Stellplätze | P7: NEU KM/qm | Q7: Δ zu Mietspiegel | R7: Kaltmiete SOLL | S7: Stellplätze | T7: SOLL KM/qm | U7: Kaltmiete | V7: Stellplätze | W7: IST KM/qm | X7: Notiz | Y7: Mietspiegel-Obergrenze EUR/m² (per WE)
F8: 62 | I8: 45352 | J8: 380 | K8: =IF(AND(NOT(ISNUMBER('Verkauf Cashflow'!AP3)),NOT(ISNUMBER('Verkauf Cashflow'!AQ3))),"",N('Verkauf Cashflow'!AP3)+N('Verkauf Cashflow'!AQ3)) | L8: =IFERROR(J8/F8,"") | M8: =IF(L8="", "", L8-$M$6) | N8: =IFERROR(IF(J8/F8>(Y8+$M$6)/2,J8,IF(I8<EDATE($N$4,-36),IF(J8*(1+$P$6)/F8<=(Y8+$M$6)/2,J8*(1+$P$6),F8*(Y8+$M$6)/2),J8)),"") | P8: =IFERROR(N8/F8,"") | Q8: =IF(P8="", "", P8-$M$6) | R8: =IF(Y8="","",IFERROR(MAX(J8,(Y8+$T$6)*F8),"")) | T8: =IFERROR(R8/F8,"") | W8: =IFERROR(U8/F8,"") | Y8: 7.2581
K9: =IF(AND(NOT(ISNUMBER('Verkauf Cashflow'!AP4)),NOT(ISNUMBER('Verkauf Cashflow'!AQ4))),"",N('Verkauf Cashflow'!AP4)+N('Verkauf Cashflow'!AQ4)) | L9: =IFERROR(J9/F9,"") | M9: =IF(L9="", "", L9-$M$6) | N9: =IFERROR(IF(J9/F9>(Y9+$M$6)/2,J9,IF(I9<EDATE($N$4,-36),IF(J9*(1+$P$6)/F9<=(Y9+$M$6)/2,J9*(1+$P$6),F9*(Y9+$M$6)/2),J9)),"") | P9: =IFERROR(N9/F9,"") | Q9: =IF(P9="", "", P9-$M$6) | R9: =IF(Y9="","",IFERROR(MAX(J9,(Y9+$T$6)*F9),"")) | T9: =IFERROR(R9/F9,"") | W9: =IFERROR(U9/F9,"")
K10: =IF(AND(NOT(ISNUMBER('Verkauf Cashflow'!AP5)),NOT(ISNUMBER('Verkauf Cashflow'!AQ5))),"",N('Verkauf Cashflow'!AP5)+N('Verkauf Cashflow'!AQ5)) | L10: =IFERROR(J10/F10,"") | M10: =IF(L10="", "", L10-$M$6) | N10: =IFERROR(IF(J10/F10>(Y10+$M$6)/2,J10,IF(I10<EDATE($N$4,-36),IF(J10*(1+$P$6)/F10<=(Y10+$M$6)/2,J10*(1+$P$6),F10*(Y10+$M$6)/2),J10)),"") | P10: =IFERROR(N10/F10,"") | Q10: =IF(P10="", "", P10-$M$6) | R10: =IF(Y10="","",IFERROR(MAX(J10,(Y10+$T$6)*F10),"")) | T10: =IFERROR(R10/F10,"") | W10: =IFERROR(U10/F10,"")
K11: =IF(AND(NOT(ISNUMBER('Verkauf Cashflow'!AP6)),NOT(ISNUMBER('Verkauf Cashflow'!AQ6))),"",N('Verkauf Cashflow'!AP6)+N('Verkauf Cashflow'!AQ6)) | L11: =IFERROR(J11/F11,"") | M11: =IF(L11="", "", L11-$M$6) | N11: =IFERROR(IF(J11/F11>(Y11+$M$6)/2,J11,IF(I11<EDATE($N$4,-36),IF(J11*(1+$P$6)/F11<=(Y11+$M$6)/2,J11*(1+$P$6),F11*(Y11+$M$6)/2),J11)),"") | P11: =IFERROR(N11/F11,"") | Q11: =IF(P11="", "", P11-$M$6) | R11: =IF(Y11="","",IFERROR(MAX(J11,(Y11+$T$6)*F11),"")) | T11: =IFERROR(R11/F11,"") | W11: =IFERROR(U11/F11,"")
K12: =IF(AND(NOT(ISNUMBER('Verkauf Cashflow'!AP7)),NOT(ISNUMBER('Verkauf Cashflow'!AQ7))),"",N('Verkauf Cashflow'!AP7)+N('Verkauf Cashflow'!AQ7)) | L12: =IFERROR(J12/F12,"") | M12: =IF(L12="", "", L12-$M$6) | N12: =IFERROR(IF(J12/F12>(Y12+$M$6)/2,J12,IF(I12<EDATE($N$4,-36),IF(J12*(1+$P$6)/F12<=(Y12+$M$6)/2,J12*(1+$P$6),F12*(Y12+$M$6)/2),J12)),"") | P12: =IFERROR(N12/F12,"") | Q12: =IF(P12="", "", P12-$M$6) | R12: =IF(Y12="","",IFERROR(MAX(J12,(Y12+$T$6)*F12),"")) | T12: =IFERROR(R12/F12,"") | W12: =IFERROR(U12/F12,"")
K13: =IF(AND(NOT(ISNUMBER('Verkauf Cashflow'!AP8)),NOT(ISNUMBER('Verkauf Cashflow'!AQ8))),"",N('Verkauf Cashflow'!AP8)+N('Verkauf Cashflow'!AQ8)) | L13: =IFERROR(J13/F13,"") | M13: =IF(L13="", "", L13-$M$6) | N13: =IFERROR(IF(J13/F13>(Y13+$M$6)/2,J13,IF(I13<EDATE($N$4,-36),IF(J13*(1+$P$6)/F13<=(Y13+$M$6)/2,J13*(1+$P$6),F13*(Y13+$M$6)/2),J13)),"") | P13: =IFERROR(N13/F13,"") | Q13: =IF(P13="", "", P13-$M$6) | R13: =IF(Y13="","",IFERROR(MAX(J13,(Y13+$T$6)*F13),"")) | T13: =IFERROR(R13/F13,"") | W13: =IFERROR(U13/F13,"")
K14: =IF(AND(NOT(ISNUMBER('Verkauf Cashflow'!AP9)),NOT(ISNUMBER('Verkauf Cashflow'!AQ9))),"",N('Verkauf Cashflow'!AP9)+N('Verkauf Cashflow'!AQ9)) | L14: =IFERROR(J14/F14,"") | M14: =IF(L14="", "", L14-$M$6) | N14: =IFERROR(IF(J14/F14>(Y14+$M$6)/2,J14,IF(I14<EDATE($N$4,-36),IF(J14*(1+$P$6)/F14<=(Y14+$M$6)/2,J14*(1+$P$6),F14*(Y14+$M$6)/2),J14)),"") | P14: =IFERROR(N14/F14,"") | Q14: =IF(P14="", "", P14-$M$6) | R14: =IF(Y14="","",IFERROR(MAX(J14,(Y14+$T$6)*F14),"")) | T14: =IFERROR(R14/F14,"") | W14: =IFERROR(U14/F14,"")
K15: =IF(AND(NOT(ISNUMBER('Verkauf Cashflow'!AP10)),NOT(ISNUMBER('Verkauf Cashflow'!AQ10))),"",N('Verkauf Cashflow'!AP10)+N('Verkauf Cashflow'!AQ10)) | L15: =IFERROR(J15/F15,"") | M15: =IF(L15="", "", L15-$M$6) | N15: =IFERROR(IF(J15/F15>(Y15+$M$6)/2,J15,IF(I15<EDATE($N$4,-36),IF(J15*(1+$P$6)/F15<=(Y15+$M$6)/2,J15*(1+$P$6),F15*(Y15+$M$6)/2),J15)),"") | P15: =IFERROR(N15/F15,"") | Q15: =IF(P15="", "", P15-$M$6) | R15: =IF(Y15="","",IFERROR(MAX(J15,(Y15+$T$6)*F15),"")) | T15: =IFERROR(R15/F15,"") | W15: =IFERROR(U15/F15,"")
K16: =IF(AND(NOT(ISNUMBER('Verkauf Cashflow'!AP11)),NOT(ISNUMBER('Verkauf Cashflow'!AQ11))),"",N('Verkauf Cashflow'!AP11)+N('Verkauf Cashflow'!AQ11)) | L16: =IFERROR(J16/F16,"") | M16: =IF(L16="", "", L16-$M$6) | N16: =IFERROR(IF(J16/F16>(Y16+$M$6)/2,J16,IF(I16<EDATE($N$4,-36),IF(J16*(1+$P$6)/F16<=(Y16+$M$6)/2,J16*(1+$P$6),F16*(Y16+$M$6)/2),J16)),"") | P16: =IFERROR(N16/F16,"") | Q16: =IF(P16="", "", P16-$M$6) | R16: =IF(Y16="","",IFERROR(MAX(J16,(Y16+$T$6)*F16),"")) | T16: =IFERROR(R16/F16,"") | W16: =IFERROR(U16/F16,"")
K17: =IF(AND(NOT(ISNUMBER('Verkauf Cashflow'!AP12)),NOT(ISNUMBER('Verkauf Cashflow'!AQ12))),"",N('Verkauf Cashflow'!AP12)+N('Verkauf Cashflow'!AQ12)) | L17: =IFERROR(J17/F17,"") | M17: =IF(L17="", "", L17-$M$6) | N17: =IFERROR(IF(J17/F17>(Y17+$M$6)/2,J17,IF(I17<EDATE($N$4,-36),IF(J17*(1+$P$6)/F17<=(Y17+$M$6)/2,J17*(1+$P$6),F17*(Y17+$M$6)/2),J17)),"") | P17: =IFERROR(N17/F17,"") | Q17: =IF(P17="", "", P17-$M$6) | R17: =IF(Y17="","",IFERROR(MAX(J17,(Y17+$T$6)*F17),"")) | T17: =IFERROR(R17/F17,"") | W17: =IFERROR(U17/F17,"")
K18: =IF(AND(NOT(ISNUMBER('Verkauf Cashflow'!AP13)),NOT(ISNUMBER('Verkauf Cashflow'!AQ13))),"",N('Verkauf Cashflow'!AP13)+N('Verkauf Cashflow'!AQ13)) | L18: =IFERROR(J18/F18,"") | M18: =IF(L18="", "", L18-$M$6) | N18: =IFERROR(IF(J18/F18>(Y18+$M$6)/2,J18,IF(I18<EDATE($N$4,-36),IF(J18*(1+$P$6)/F18<=(Y18+$M$6)/2,J18*(1+$P$6),F18*(Y18+$M$6)/2),J18)),"") | P18: =IFERROR(N18/F18,"") | Q18: =IF(P18="", "", P18-$M$6) | R18: =IF(Y18="","",IFERROR(MAX(J18,(Y18+$T$6)*F18),"")) | T18: =IFERROR(R18/F18,"") | W18: =IFERROR(U18/F18,"")
K19: =IF(AND(NOT(ISNUMBER('Verkauf Cashflow'!AP14)),NOT(ISNUMBER('Verkauf Cashflow'!AQ14))),"",N('Verkauf Cashflow'!AP14)+N('Verkauf Cashflow'!AQ14)) | L19: =IFERROR(J19/F19,"") | M19: =IF(L19="", "", L19-$M$6) | N19: =IFERROR(IF(J19/F19>(Y19+$M$6)/2,J19,IF(I19<EDATE($N$4,-36),IF(J19*(1+$P$6)/F19<=(Y19+$M$6)/2,J19*(1+$P$6),F19*(Y19+$M$6)/2),J19)),"") | P19: =IFERROR(N19/F19,"") | Q19: =IF(P19="", "", P19-$M$6) | R19: =IF(Y19="","",IFERROR(MAX(J19,(Y19+$T$6)*F19),"")) | T19: =IFERROR(R19/F19,"") | W19: =IFERROR(U19/F19,"")
K20: =IF(AND(NOT(ISNUMBER('Verkauf Cashflow'!AP15)),NOT(ISNUMBER('Verkauf Cashflow'!AQ15))),"",N('Verkauf Cashflow'!AP15)+N('Verkauf Cashflow'!AQ15)) | L20: =IFERROR(J20/F20,"") | M20: =IF(L20="", "", L20-$M$6) | N20: =IFERROR(IF(J20/F20>(Y20+$M$6)/2,J20,IF(I20<EDATE($N$4,-36),IF(J20*(1+$P$6)/F20<=(Y20+$M$6)/2,J20*(1+$P$6),F20*(Y20+$M$6)/2),J20)),"") | P20: =IFERROR(N20/F20,"") | Q20: =IF(P20="", "", P20-$M$6) | R20: =IF(Y20="","",IFERROR(MAX(J20,(Y20+$T$6)*F20),"")) | T20: =IFERROR(R20/F20,"") | W20: =IFERROR(U20/F20,"")
... K27: =IF(AND(NOT(ISNUMBER('Verkauf Cashflow'!AP22)),NOT(ISNUMBER('Verkauf Cashflow'!AQ22))),"",N('Verkauf Cashflow'!AP22)+N('Verkauf Cashflow'!AQ22)) | L27: =IFERROR(J27/F27,"") | M27: =IF(L27="", "", L27-$M$6) | N27: =IFERROR(IF(J27/F27>(Y27+$M$6)/2,J27,IF(I27<EDATE($N$4,-36),IF(J27*(1+$P$6)/F27<=(Y27+$M$6)/2,J27*(1+$P$6),F27*(Y27+$M$6)/2),J27)),"") | P27: =IFERROR(N27/F27,"") | Q27: =IF(P27="", "", P27-$M$6) | R27: =IF(Y27="","",IFERROR(MAX(J27,(Y27+$T$6)*F27),"")) | T27: =IFERROR(R27/F27,"") | W27: =IFERROR(U27/F27,"")
F28: =SUM(F8:F27) | J28: =SUM(J8:J27) | K28: =SUM(K8:K27) | L28: =AVERAGE(L8:L27) | N28: =SUM(N8:N27) | O28: =SUM(O8:O27) | P28: =AVERAGE(P8:P27) | R28: =SUM(R8:R27) | S28: =SUM(S8:S27) | T28: =AVERAGE(T8:T27) | U28: =SUM(U8:U27) | V28: =SUM(V8:V27) | W28: =IFERROR(AVERAGE(W8:W27),"")
J29: ↓ | K29: ↓ | N29: ↓ | O29: ↓ | R29: ↓ | S29: ↓
I30: pro Jahr = | J30: =J28*12 | K30: =K28*12 | N30: =N28*12 | O30: =O28*12 | R30: =R28*12 | S30: =S28*12
I31: JNKM = | J31: =J30+K30 | N31: =N30+O30 | R31: =R30+S30
J32: Rendite Einkauf (KP+NK) | K32: =J31/(KALKU!P37+KALKU!J30) | N32: Rendite Einkauf (KP+NK) | O32: =N31/(KALKU!P37+KALKU!J30) | R32: Rendite Einkauf (GIK) | S32: =R31/KALKU!J39

Sheet VERKAUFSMATRIX
A1: VERKAUFSMATRIX
A5: HAUS NR. | B5: WHG NR. | C5: ETAGE | D5: LAGE | E5: ZIMMER | F5: WOHN- FLÄCHE | G5: €/qm PORTALPREISE | H5: €/qm AUF/ABSCHLAG | I5: MIETSITUATION (- 10%) | J5: Auf-/Abschlag Mietsituation | K5: Δ zu Mietspiegel | L5: =MIETER!M6 | M5: BALKON (- 5%) | N5: Auf-/Abschlag Balkon | O5: Baujahr Etagenheizung | P5: Auf-/Abschlag Etagenheizung | Q5: ZUSTAND RENOVIERUNG IM VERKAUF (+5%/- 5%) | R5: Auf-/Abschlag Renovierung | S5: ETAGE / LAGE (- 5%) | T5: ETAGE / LAGE (- 5%) | U5: VERKAUFSPREIS WOHNUNG | V5: PREIS GARAGE / STELLPLATZ | W5: VORSCHLAG VERKAUFSPREIS | X5: INDIVIDUELLER AUF-/ABSCHLAG | Y5: MEIN VERKAUFSPREIS | Z5: VK / qm | AA5: % RENDITE MEIN PREIS
A6: =IF(ISNUMBER(MIETER!F8),IFERROR(MIETER!A8,""),"") | B6: =IF(ISNUMBER(MIETER!F8),IFERROR(MIETER!B8,""),"") | C6: =IF(ISNUMBER(MIETER!F8),IFERROR(MIETER!C8,""),"") | D6: =IF(ISNUMBER(MIETER!F8),IFERROR(MIETER!D8,""),"") | E6: =IF(ISNUMBER(MIETER!F8),IFERROR(MIETER!E8,""),"") | F6: =IF(ISNUMBER(MIETER!F8),IFERROR(MIETER!F8,""),"") | G6: =IF(ISNUMBER(MIETER!F8),KALKU!$I$18,"") | H6: =IF(ISNUMBER(MIETER!F8),KALKU!$N$18,"") | J6: =IF(ISNUMBER(MIETER!F8),IF(I6="vermietet",H6*(-0.1),H6*0),"") | K6: =IF(ISNUMBER(MIETER!F8),IFERROR(MIETER!Q8/MIETER!$M$6,""),"") | L6: =IF(ISNUMBER(MIETER!F8),IF(K6 >= 0%,H6*(0.01), IF(K6 >= -5%,H6*(-0.01), IF(K6 >= -10%,H6*(-0.02), IF(K6 >= -15%,H6*(-0.03), IF(K6 >= -20%,H6*(-0.04), IF(K6 >= -25%,H6*(-0.05), IF(K6 >= -30%,H6*(-0.06), IF(K6 >= -35%,H6*(-0.07), IF(K6 >= -40%,H6*(-0.08), IF(K6 >= -45%,H6*(-0.09), IF(K6 >= -50%, H6*(-0.1), H6*0 ) )))))))))),"") | N6: =IF(NOT(ISNUMBER(H6)),"",IF(M6="Kein Balkon",H6*(-0.05),H6*0)) | P6: =IF(NOT(ISNUMBER(H6)),"",IF(ISBLANK(O6),0,H6*MIN((YEAR(TODAY())-O6)*0.003,0.09)*-1)) | R6: =IF(ISNUMBER(MIETER!F8),IF(Q6="renoviert",H6*0.05,IF(Q6="teilweise renoviert",H6*0,IF(Q6="unrenoviert",H6*-0.05,0))),"") | S6: =IF(ISNUMBER(MIETER!F8),C6,"") | T6: =IF(ISNUMBER(MIETER!F8),IF(OR(S6="EG",S6="1.OG",S6="2.OG",S6="OG",S6="über 2.OG mit Aufzug"),H6*0,IF(OR(S6="UG",S6="über 2.OG ohne Aufzug"),H6*(-0.05),0)),"") | U6: =IF(ISNUMBER(MIETER!F8),IFERROR(F6*(H6+J6+L6+N6+P6+R6+T6),""),"") | V6: =IF(NOT(ISNUMBER(MIETER!F8)),"",N('Verkauf Cashflow'!U3)+N('Verkauf Cashflow'!V3)) | W6: =IF(ISNUMBER(MIETER!F8),U6+V6,"") | X6: =IF(AND(ISNUMBER('Verkauf Cashflow'!S3),LEFT('Verkauf Cashflow'!O3,6)="Regler"),'Verkauf Cashflow'!S3,"") | Y6: =IF(ISNUMBER('Verkauf Cashflow'!W3),'Verkauf Cashflow'!W3,"") | Z6: =IF(ISNUMBER(MIETER!F8),IFERROR(Y6/F6,""),"") | AA6: =IF(ISNUMBER('Verkauf Cashflow'!CA3),'Verkauf Cashflow'!CA3,"")
A7: =IF(ISNUMBER(MIETER!F9),IFERROR(MIETER!A9,""),"") | B7: =IF(ISNUMBER(MIETER!F9),IFERROR(MIETER!B9,""),"") | C7: =IF(ISNUMBER(MIETER!F9),IFERROR(MIETER!C9,""),"") | D7: =IF(ISNUMBER(MIETER!F9),IFERROR(MIETER!D9,""),"") | E7: =IF(ISNUMBER(MIETER!F9),IFERROR(MIETER!E9,""),"") | F7: =IF(ISNUMBER(MIETER!F9),IFERROR(MIETER!F9,""),"") | G7: =IF(ISNUMBER(MIETER!F9),KALKU!$I$18,"") | H7: =IF(ISNUMBER(MIETER!F9),KALKU!$N$18,"") | J7: =IF(ISNUMBER(MIETER!F9),IF(I7="vermietet",H7*(-0.1),H7*0),"") | K7: =IF(ISNUMBER(MIETER!F9),IFERROR(MIETER!Q9/MIETER!$M$6,""),"") | L7: =IF(ISNUMBER(MIETER!F9),IF(K7 >= 0%,H7*(0.01), IF(K7 >= -5%,H7*(-0.01), IF(K7 >= -10%,H7*(-0.02), IF(K7 >= -15%,H7*(-0.03), IF(K7 >= -20%,H7*(-0.04), IF(K7 >= -25%,H7*(-0.05), IF(K7 >= -30%,H7*(-0.06), IF(K7 >= -35%,H7*(-0.07), IF(K7 >= -40%,H7*(-0.08), IF(K7 >= -45%,H7*(-0.09), IF(K7 >= -50%, H7*(-0.1), H7* 0) )))))))))),"") | N7: =IF(NOT(ISNUMBER(H7)),"",IF(M7="Kein Balkon",H7*(-0.05),H7*0)) | P7: =IF(NOT(ISNUMBER(H7)),"",IF(ISBLANK(O7),0,H7*MIN((YEAR(TODAY())-O7)*0.003,0.09)*-1)) | R7: =IF(ISNUMBER(MIETER!F9),IF(Q7="renoviert",H7*0.05,IF(Q7="teilweise renoviert",H7*0,IF(Q7="unrenoviert",H7*-0.05,0))),"") | S7: =IF(ISNUMBER(MIETER!F9),C7,"") | T7: =IF(ISNUMBER(MIETER!F9),IF(OR(S7="EG",S7="1.OG",S7="2.OG",S7="OG",S7="über 2.OG mit Aufzug"),H7*0,IF(OR(S7="UG",S7="über 2.OG ohne Aufzug"),H7*(-0.05),0)),"") | U7: =IF(ISNUMBER(MIETER!F9),IFERROR(F7*(H7+J7+L7+N7+P7+R7+T7),""),"") | V7: =IF(NOT(ISNUMBER(MIETER!F9)),"",N('Verkauf Cashflow'!U4)+N('Verkauf Cashflow'!V4)) | W7: =IF(ISNUMBER(MIETER!F9),U7+V7,"") | X7: =IF(AND(ISNUMBER('Verkauf Cashflow'!S4),LEFT('Verkauf Cashflow'!O4,6)="Regler"),'Verkauf Cashflow'!S4,"") | Y7: =IF(ISNUMBER('Verkauf Cashflow'!W4),'Verkauf Cashflow'!W4,"") | Z7: =IF(ISNUMBER(MIETER!F9),IFERROR(Y7/F7,""),"") | AA7: =IF(ISNUMBER('Verkauf Cashflow'!CA4),'Verkauf Cashflow'!CA4,"")
A8: =IF(ISNUMBER(MIETER!F10),IFERROR(MIETER!A10,""),"") | B8: =IF(ISNUMBER(MIETER!F10),IFERROR(MIETER!B10,""),"") | C8: =IF(ISNUMBER(MIETER!F10),IFERROR(MIETER!C10,""),"") | D8: =IF(ISNUMBER(MIETER!F10),IFERROR(MIETER!D10,""),"") | E8: =IF(ISNUMBER(MIETER!F10),IFERROR(MIETER!E10,""),"") | F8: =IF(ISNUMBER(MIETER!F10),IFERROR(MIETER!F10,""),"") | G8: =IF(ISNUMBER(MIETER!F10),KALKU!$I$18,"") | H8: =IF(ISNUMBER(MIETER!F10),KALKU!$N$18,"") | J8: =IF(ISNUMBER(MIETER!F10),IF(I8="vermietet",H8*(-0.1),H8*0),"") | K8: =IF(ISNUMBER(MIETER!F10),IFERROR(MIETER!Q10/MIETER!$M$6,""),"") | L8: =IF(ISNUMBER(MIETER!F10),IF(K8 >= 0%,H8*(0.01), IF(K8 >= -5%,H8*(-0.01), IF(K8 >= -10%,H8*(-0.02), IF(K8 >= -15%,H8*(-0.03), IF(K8 >= -20%,H8*(-0.04), IF(K8 >= -25%,H8*(-0.05), IF(K8 >= -30%,H8*(-0.06), IF(K8 >= -35%,H8*(-0.07), IF(K8 >= -40%,H8*(-0.08), IF(K8 >= -45%,H8*(-0.09), IF(K8 >= -50%, H8*(-0.1), H8* 0) )))))))))),"") | N8: =IF(NOT(ISNUMBER(H8)),"",IF(M8="Kein Balkon",H8*(-0.05),H8*0)) | P8: =IF(NOT(ISNUMBER(H8)),"",IF(ISBLANK(O8),0,H8*MIN((YEAR(TODAY())-O8)*0.003,0.09)*-1)) | R8: =IF(ISNUMBER(MIETER!F10),IF(Q8="renoviert",H8*0.05,IF(Q8="teilweise renoviert",H8*0,IF(Q8="unrenoviert",H8*-0.05,0))),"") | S8: =IF(ISNUMBER(MIETER!F10),C8,"") | T8: =IF(ISNUMBER(MIETER!F10),IF(OR(S8="EG",S8="1.OG",S8="2.OG",S8="OG",S8="über 2.OG mit Aufzug"),H8*0,IF(OR(S8="UG",S8="über 2.OG ohne Aufzug"),H8*(-0.05),0)),"") | U8: =IF(ISNUMBER(MIETER!F10),IFERROR(F8*(H8+J8+L8+N8+P8+R8+T8),""),"") | V8: =IF(NOT(ISNUMBER(MIETER!F10)),"",N('Verkauf Cashflow'!U5)+N('Verkauf Cashflow'!V5)) | W8: =IF(ISNUMBER(MIETER!F10),U8+V8,"") | X8: =IF(AND(ISNUMBER('Verkauf Cashflow'!S5),LEFT('Verkauf Cashflow'!O5,6)="Regler"),'Verkauf Cashflow'!S5,"") | Y8: =IF(ISNUMBER('Verkauf Cashflow'!W5),'Verkauf Cashflow'!W5,"") | Z8: =IF(ISNUMBER(MIETER!F10),IFERROR(Y8/F8,""),"") | AA8: =IF(ISNUMBER('Verkauf Cashflow'!CA5),'Verkauf Cashflow'!CA5,"")
A9: =IF(ISNUMBER(MIETER!F11),IFERROR(MIETER!A11,""),"") | B9: =IF(ISNUMBER(MIETER!F11),IFERROR(MIETER!B11,""),"") | C9: =IF(ISNUMBER(MIETER!F11),IFERROR(MIETER!C11,""),"") | D9: =IF(ISNUMBER(MIETER!F11),IFERROR(MIETER!D11,""),"") | E9: =IF(ISNUMBER(MIETER!F11),IFERROR(MIETER!E11,""),"") | F9: =IF(ISNUMBER(MIETER!F11),IFERROR(MIETER!F11,""),"") | G9: =IF(ISNUMBER(MIETER!F11),KALKU!$I$18,"") | H9: =IF(ISNUMBER(MIETER!F11),KALKU!$N$18,"") | J9: =IF(ISNUMBER(MIETER!F11),IF(I9="vermietet",H9*(-0.1),H9*0),"") | K9: =IF(ISNUMBER(MIETER!F11),IFERROR(MIETER!Q11/MIETER!$M$6,""),"") | L9: =IF(ISNUMBER(MIETER!F11),IF(K9 >= 0%,H9*(0.01), IF(K9 >= -5%,H9*(-0.01), IF(K9 >= -10%,H9*(-0.02), IF(K9 >= -15%,H9*(-0.03), IF(K9 >= -20%,H9*(-0.04), IF(K9 >= -25%,H9*(-0.05), IF(K9 >= -30%,H9*(-0.06), IF(K9 >= -35%,H9*(-0.07), IF(K9 >= -40%,H9*(-0.08), IF(K9 >= -45%,H9*(-0.09), IF(K9 >= -50%, H9*(-0.1), H9* 0) )))))))))),"") | N9: =IF(NOT(ISNUMBER(H9)),"",IF(M9="Kein Balkon",H9*(-0.05),H9*0)) | P9: =IF(NOT(ISNUMBER(H9)),"",IF(ISBLANK(O9),0,H9*MIN((YEAR(TODAY())-O9)*0.003,0.09)*-1)) | R9: =IF(ISNUMBER(MIETER!F11),IF(Q9="renoviert",H9*0.05,IF(Q9="teilweise renoviert",H9*0,IF(Q9="unrenoviert",H9*-0.05,0))),"") | S9: =IF(ISNUMBER(MIETER!F11),C9,"") | T9: =IF(ISNUMBER(MIETER!F11),IF(OR(S9="EG",S9="1.OG",S9="2.OG",S9="OG",S9="über 2.OG mit Aufzug"),H9*0,IF(OR(S9="UG",S9="über 2.OG ohne Aufzug"),H9*(-0.05),0)),"") | U9: =IF(ISNUMBER(MIETER!F11),IFERROR(F9*(H9+J9+L9+N9+P9+R9+T9),""),"") | V9: =IF(NOT(ISNUMBER(MIETER!F11)),"",N('Verkauf Cashflow'!U6)+N('Verkauf Cashflow'!V6)) | W9: =IF(ISNUMBER(MIETER!F11),U9+V9,"") | X9: =IF(AND(ISNUMBER('Verkauf Cashflow'!S6),LEFT('Verkauf Cashflow'!O6,6)="Regler"),'Verkauf Cashflow'!S6,"") | Y9: =IF(ISNUMBER('Verkauf Cashflow'!W6),'Verkauf Cashflow'!W6,"") | Z9: =IF(ISNUMBER(MIETER!F11),IFERROR(Y9/F9,""),"") | AA9: =IF(ISNUMBER('Verkauf Cashflow'!CA6),'Verkauf Cashflow'!CA6,"")
A10: =IF(ISNUMBER(MIETER!F12),IFERROR(MIETER!A12,""),"") | B10: =IF(ISNUMBER(MIETER!F12),IFERROR(MIETER!B12,""),"") | C10: =IF(ISNUMBER(MIETER!F12),IFERROR(MIETER!C12,""),"") | D10: =IF(ISNUMBER(MIETER!F12),IFERROR(MIETER!D12,""),"") | E10: =IF(ISNUMBER(MIETER!F12),IFERROR(MIETER!E12,""),"") | F10: =IF(ISNUMBER(MIETER!F12),IFERROR(MIETER!F12,""),"") | G10: =IF(ISNUMBER(MIETER!F12),KALKU!$I$18,"") | H10: =IF(ISNUMBER(MIETER!F12),KALKU!$N$18,"") | J10: =IF(ISNUMBER(MIETER!F12),IF(I10="vermietet",H10*(-0.1),H10*0),"") | K10: =IF(ISNUMBER(MIETER!F12),IFERROR(MIETER!Q12/MIETER!$M$6,""),"") | L10: =IF(ISNUMBER(MIETER!F12),IF(K10 >= 0%,H10*(0.01), IF(K10 >= -5%,H10*(-0.01), IF(K10 >= -10%,H10*(-0.02), IF(K10 >= -15%,H10*(-0.03), IF(K10 >= -20%,H10*(-0.04), IF(K10 >= -25%,H10*(-0.05), IF(K10 >= -30%,H10*(-0.06), IF(K10 >= -35%,H10*(-0.07), IF(K10 >= -40%,H10*(-0.08), IF(K10 >= -45%,H10*(-0.09), IF(K10 >= -50%, H10*(-0.1), H10* 0) )))))))))),"") | N10: =IF(NOT(ISNUMBER(H10)),"",IF(M10="Kein Balkon",H10*(-0.05),H10*0)) | P10: =IF(NOT(ISNUMBER(H10)),"",IF(ISBLANK(O10),0,H10*MIN((YEAR(TODAY())-O10)*0.003,0.09)*-1)) | R10: =IF(ISNUMBER(MIETER!F12),IF(Q10="renoviert",H10*0.05,IF(Q10="teilweise renoviert",H10*0,IF(Q10="unrenoviert",H10*-0.05,0))),"") | S10: =IF(ISNUMBER(MIETER!F12),C10,"") | T10: =IF(ISNUMBER(MIETER!F12),IF(OR(S10="EG",S10="1.OG",S10="2.OG",S10="OG",S10="über 2.OG mit Aufzug"),H10*0,IF(OR(S10="UG",S10="über 2.OG ohne Aufzug"),H10*(-0.05),0)),"") | U10: =IF(ISNUMBER(MIETER!F12),IFERROR(F10*(H10+J10+L10+N10+P10+R10+T10),""),"") | V10: =IF(NOT(ISNUMBER(MIETER!F12)),"",N('Verkauf Cashflow'!U7)+N('Verkauf Cashflow'!V7)) | W10: =IF(ISNUMBER(MIETER!F12),U10+V10,"") | X10: =IF(AND(ISNUMBER('Verkauf Cashflow'!S7),LEFT('Verkauf Cashflow'!O7,6)="Regler"),'Verkauf Cashflow'!S7,"") | Y10: =IF(ISNUMBER('Verkauf Cashflow'!W7),'Verkauf Cashflow'!W7,"") | Z10: =IF(ISNUMBER(MIETER!F12),IFERROR(Y10/F10,""),"") | AA10: =IF(ISNUMBER('Verkauf Cashflow'!CA7),'Verkauf Cashflow'!CA7,"")
A11: =IF(ISNUMBER(MIETER!F13),IFERROR(MIETER!A13,""),"") | B11: =IF(ISNUMBER(MIETER!F13),IFERROR(MIETER!B13,""),"") | C11: =IF(ISNUMBER(MIETER!F13),IFERROR(MIETER!C13,""),"") | D11: =IF(ISNUMBER(MIETER!F13),IFERROR(MIETER!D13,""),"") | E11: =IF(ISNUMBER(MIETER!F13),IFERROR(MIETER!E13,""),"") | F11: =IF(ISNUMBER(MIETER!F13),IFERROR(MIETER!F13,""),"") | G11: =IF(ISNUMBER(MIETER!F13),KALKU!$I$18,"") | H11: =IF(ISNUMBER(MIETER!F13),KALKU!$N$18,"") | J11: =IF(ISNUMBER(MIETER!F13),IF(I11="vermietet",H11*(-0.1),H11*0),"") | K11: =IF(ISNUMBER(MIETER!F13),IFERROR(MIETER!Q13/MIETER!$M$6,""),"") | L11: =IF(ISNUMBER(MIETER!F13),IF(K11 >= 0%,H11*(0.01), IF(K11 >= -5%,H11*(-0.01), IF(K11 >= -10%,H11*(-0.02), IF(K11 >= -15%,H11*(-0.03), IF(K11 >= -20%,H11*(-0.04), IF(K11 >= -25%,H11*(-0.05), IF(K11 >= -30%,H11*(-0.06), IF(K11 >= -35%,H11*(-0.07), IF(K11 >= -40%,H11*(-0.08), IF(K11 >= -45%,H11*(-0.09), IF(K11 >= -50%, H11*(-0.1), H11* 0) )))))))))),"") | N11: =IF(NOT(ISNUMBER(H11)),"",IF(M11="Kein Balkon",H11*(-0.05),H11*0)) | P11: =IF(NOT(ISNUMBER(H11)),"",IF(ISBLANK(O11),0,H11*MIN((YEAR(TODAY())-O11)*0.003,0.09)*-1)) | R11: =IF(ISNUMBER(MIETER!F13),IF(Q11="renoviert",H11*0.05,IF(Q11="teilweise renoviert",H11*0,IF(Q11="unrenoviert",H11*-0.05,0))),"") | S11: =IF(ISNUMBER(MIETER!F13),C11,"") | T11: =IF(ISNUMBER(MIETER!F13),IF(OR(S11="EG",S11="1.OG",S11="2.OG",S11="OG",S11="über 2.OG mit Aufzug"),H11*0,IF(OR(S11="UG",S11="über 2.OG ohne Aufzug"),H11*(-0.05),0)),"") | U11: =IF(ISNUMBER(MIETER!F13),IFERROR(F11*(H11+J11+L11+N11+P11+R11+T11),""),"") | V11: =IF(NOT(ISNUMBER(MIETER!F13)),"",N('Verkauf Cashflow'!U8)+N('Verkauf Cashflow'!V8)) | W11: =IF(ISNUMBER(MIETER!F13),U11+V11,"") | X11: =IF(AND(ISNUMBER('Verkauf Cashflow'!S8),LEFT('Verkauf Cashflow'!O8,6)="Regler"),'Verkauf Cashflow'!S8,"") | Y11: =IF(ISNUMBER('Verkauf Cashflow'!W8),'Verkauf Cashflow'!W8,"") | Z11: =IF(ISNUMBER(MIETER!F13),IFERROR(Y11/F11,""),"") | AA11: =IF(ISNUMBER('Verkauf Cashflow'!CA8),'Verkauf Cashflow'!CA8,"")
A12: =IF(ISNUMBER(MIETER!F14),IFERROR(MIETER!A14,""),"") | B12: =IF(ISNUMBER(MIETER!F14),IFERROR(MIETER!B14,""),"") | C12: =IF(ISNUMBER(MIETER!F14),IFERROR(MIETER!C14,""),"") | D12: =IF(ISNUMBER(MIETER!F14),IFERROR(MIETER!D14,""),"") | E12: =IF(ISNUMBER(MIETER!F14),IFERROR(MIETER!E14,""),"") | F12: =IF(ISNUMBER(MIETER!F14),IFERROR(MIETER!F14,""),"") | G12: =IF(ISNUMBER(MIETER!F14),KALKU!$I$18,"") | H12: =IF(ISNUMBER(MIETER!F14),KALKU!$N$18,"") | J12: =IF(ISNUMBER(MIETER!F14),IF(I12="vermietet",H12*(-0.1),H12*0),"") | K12: =IF(ISNUMBER(MIETER!F14),IFERROR(MIETER!Q14/MIETER!$M$6,""),"") | L12: =IF(ISNUMBER(MIETER!F14),IF(K12 >= 0%,H12*(0.01), IF(K12 >= -5%,H12*(-0.01), IF(K12 >= -10%,H12*(-0.02), IF(K12 >= -15%,H12*(-0.03), IF(K12 >= -20%,H12*(-0.04), IF(K12 >= -25%,H12*(-0.05), IF(K12 >= -30%,H12*(-0.06), IF(K12 >= -35%,H12*(-0.07), IF(K12 >= -40%,H12*(-0.08), IF(K12 >= -45%,H12*(-0.09), IF(K12 >= -50%, H12*(-0.1), H12* 0) )))))))))),"") | N12: =IF(NOT(ISNUMBER(H12)),"",IF(M12="Kein Balkon",H12*(-0.05),H12*0)) | P12: =IF(NOT(ISNUMBER(H12)),"",IF(ISBLANK(O12),0,H12*MIN((YEAR(TODAY())-O12)*0.003,0.09)*-1)) | R12: =IF(ISNUMBER(MIETER!F14),IF(Q12="renoviert",H12*0.05,IF(Q12="teilweise renoviert",H12*0,IF(Q12="unrenoviert",H12*-0.05,0))),"") | S12: =IF(ISNUMBER(MIETER!F14),C12,"") | T12: =IF(ISNUMBER(MIETER!F14),IF(OR(S12="EG",S12="1.OG",S12="2.OG",S12="OG",S12="über 2.OG mit Aufzug"),H12*0,IF(OR(S12="UG",S12="über 2.OG ohne Aufzug"),H12*(-0.05),0)),"") | U12: =IF(ISNUMBER(MIETER!F14),IFERROR(F12*(H12+J12+L12+N12+P12+R12+T12),""),"") | V12: =IF(NOT(ISNUMBER(MIETER!F14)),"",N('Verkauf Cashflow'!U9)+N('Verkauf Cashflow'!V9)) | W12: =IF(ISNUMBER(MIETER!F14),U12+V12,"") | X12: =IF(AND(ISNUMBER('Verkauf Cashflow'!S9),LEFT('Verkauf Cashflow'!O9,6)="Regler"),'Verkauf Cashflow'!S9,"") | Y12: =IF(ISNUMBER('Verkauf Cashflow'!W9),'Verkauf Cashflow'!W9,"") | Z12: =IF(ISNUMBER(MIETER!F14),IFERROR(Y12/F12,""),"") | AA12: =IF(ISNUMBER('Verkauf Cashflow'!CA9),'Verkauf Cashflow'!CA9,"")
A13: =IF(ISNUMBER(MIETER!F15),IFERROR(MIETER!A15,""),"") | B13: =IF(ISNUMBER(MIETER!F15),IFERROR(MIETER!B15,""),"") | C13: =IF(ISNUMBER(MIETER!F15),IFERROR(MIETER!C15,""),"") | D13: =IF(ISNUMBER(MIETER!F15),IFERROR(MIETER!D15,""),"") | E13: =IF(ISNUMBER(MIETER!F15),IFERROR(MIETER!E15,""),"") | F13: =IF(ISNUMBER(MIETER!F15),IFERROR(MIETER!F15,""),"") | G13: =IF(ISNUMBER(MIETER!F15),KALKU!$I$18,"") | H13: =IF(ISNUMBER(MIETER!F15),KALKU!$N$18,"") | J13: =IF(ISNUMBER(MIETER!F15),IF(I13="vermietet",H13*(-0.1),H13*0),"") | K13: =IF(ISNUMBER(MIETER!F15),IFERROR(MIETER!Q15/MIETER!$M$6,""),"") | L13: =IF(ISNUMBER(MIETER!F15),IF(K13 >= 0%,H13*(0.01), IF(K13 >= -5%,H13*(-0.01), IF(K13 >= -10%,H13*(-0.02), IF(K13 >= -15%,H13*(-0.03), IF(K13 >= -20%,H13*(-0.04), IF(K13 >= -25%,H13*(-0.05), IF(K13 >= -30%,H13*(-0.06), IF(K13 >= -35%,H13*(-0.07), IF(K13 >= -40%,H13*(-0.08), IF(K13 >= -45%,H13*(-0.09), IF(K13 >= -50%, H13*(-0.1), H13* 0) )))))))))),"") | N13: =IF(NOT(ISNUMBER(H13)),"",IF(M13="Kein Balkon",H13*(-0.05),H13*0)) | P13: =IF(NOT(ISNUMBER(H13)),"",IF(ISBLANK(O13),0,H13*MIN((YEAR(TODAY())-O13)*0.003,0.09)*-1)) | R13: =IF(ISNUMBER(MIETER!F15),IF(Q13="renoviert",H13*0.05,IF(Q13="teilweise renoviert",H13*0,IF(Q13="unrenoviert",H13*-0.05,0))),"") | S13: =IF(ISNUMBER(MIETER!F15),C13,"") | T13: =IF(ISNUMBER(MIETER!F15),IF(OR(S13="EG",S13="1.OG",S13="2.OG",S13="OG",S13="über 2.OG mit Aufzug"),H13*0,IF(OR(S13="UG",S13="über 2.OG ohne Aufzug"),H13*(-0.05),0)),"") | U13: =IF(ISNUMBER(MIETER!F15),IFERROR(F13*(H13+J13+L13+N13+P13+R13+T13),""),"") | V13: =IF(NOT(ISNUMBER(MIETER!F15)),"",N('Verkauf Cashflow'!U10)+N('Verkauf Cashflow'!V10)) | W13: =IF(ISNUMBER(MIETER!F15),U13+V13,"") | X13: =IF(AND(ISNUMBER('Verkauf Cashflow'!S10),LEFT('Verkauf Cashflow'!O10,6)="Regler"),'Verkauf Cashflow'!S10,"") | Y13: =IF(ISNUMBER('Verkauf Cashflow'!W10),'Verkauf Cashflow'!W10,"") | Z13: =IF(ISNUMBER(MIETER!F15),IFERROR(Y13/F13,""),"") | AA13: =IF(ISNUMBER('Verkauf Cashflow'!CA10),'Verkauf Cashflow'!CA10,"")
A14: =IF(ISNUMBER(MIETER!F16),IFERROR(MIETER!A16,""),"") | B14: =IF(ISNUMBER(MIETER!F16),IFERROR(MIETER!B16,""),"") | C14: =IF(ISNUMBER(MIETER!F16),IFERROR(MIETER!C16,""),"") | D14: =IF(ISNUMBER(MIETER!F16),IFERROR(MIETER!D16,""),"") | E14: =IF(ISNUMBER(MIETER!F16),IFERROR(MIETER!E16,""),"") | F14: =IF(ISNUMBER(MIETER!F16),IFERROR(MIETER!F16,""),"") | G14: =IF(ISNUMBER(MIETER!F16),KALKU!$I$18,"") | H14: =IF(ISNUMBER(MIETER!F16),KALKU!$N$18,"") | J14: =IF(ISNUMBER(MIETER!F16),IF(I14="vermietet",H14*(-0.1),H14*0),"") | K14: =IF(ISNUMBER(MIETER!F16),IFERROR(MIETER!Q16/MIETER!$M$6,""),"") | L14: =IF(ISNUMBER(MIETER!F16),IF(K14 >= 0%,H14*(0.01), IF(K14 >= -5%,H14*(-0.01), IF(K14 >= -10%,H14*(-0.02), IF(K14 >= -15%,H14*(-0.03), IF(K14 >= -20%,H14*(-0.04), IF(K14 >= -25%,H14*(-0.05), IF(K14 >= -30%,H14*(-0.06), IF(K14 >= -35%,H14*(-0.07), IF(K14 >= -40%,H14*(-0.08), IF(K14 >= -45%,H14*(-0.09), IF(K14 >= -50%, H14*(-0.1), H14* 0) )))))))))),"") | N14: =IF(NOT(ISNUMBER(H14)),"",IF(M14="Kein Balkon",H14*(-0.05),H14*0)) | P14: =IF(NOT(ISNUMBER(H14)),"",IF(ISBLANK(O14),0,H14*MIN((YEAR(TODAY())-O14)*0.003,0.09)*-1)) | R14: =IF(ISNUMBER(MIETER!F16),IF(Q14="renoviert",H14*0.05,IF(Q14="teilweise renoviert",H14*0,IF(Q14="unrenoviert",H14*-0.05,0))),"") | S14: =IF(ISNUMBER(MIETER!F16),C14,"") | T14: =IF(ISNUMBER(MIETER!F16),IF(OR(S14="EG",S14="1.OG",S14="2.OG",S14="OG",S14="über 2.OG mit Aufzug"),H14*0,IF(OR(S14="UG",S14="über 2.OG ohne Aufzug"),H14*(-0.05),0)),"") | U14: =IF(ISNUMBER(MIETER!F16),IFERROR(F14*(H14+J14+L14+N14+P14+R14+T14),""),"") | V14: =IF(NOT(ISNUMBER(MIETER!F16)),"",N('Verkauf Cashflow'!U11)+N('Verkauf Cashflow'!V11)) | W14: =IF(ISNUMBER(MIETER!F16),U14+V14,"") | X14: =IF(AND(ISNUMBER('Verkauf Cashflow'!S11),LEFT('Verkauf Cashflow'!O11,6)="Regler"),'Verkauf Cashflow'!S11,"") | Y14: =IF(ISNUMBER('Verkauf Cashflow'!W11),'Verkauf Cashflow'!W11,"") | Z14: =IF(ISNUMBER(MIETER!F16),IFERROR(Y14/F14,""),"") | AA14: =IF(ISNUMBER('Verkauf Cashflow'!CA11),'Verkauf Cashflow'!CA11,"")
A15: =IF(ISNUMBER(MIETER!F17),IFERROR(MIETER!A17,""),"") | B15: =IF(ISNUMBER(MIETER!F17),IFERROR(MIETER!B17,""),"") | C15: =IF(ISNUMBER(MIETER!F17),IFERROR(MIETER!C17,""),"") | D15: =IF(ISNUMBER(MIETER!F17),IFERROR(MIETER!D17,""),"") | E15: =IF(ISNUMBER(MIETER!F17),IFERROR(MIETER!E17,""),"") | F15: =IF(ISNUMBER(MIETER!F17),IFERROR(MIETER!F17,""),"") | G15: =IF(ISNUMBER(MIETER!F17),KALKU!$I$18,"") | H15: =IF(ISNUMBER(MIETER!F17),KALKU!$N$18,"") | J15: =IF(ISNUMBER(MIETER!F17),IF(I15="vermietet",H15*(-0.1),H15*0),"") | K15: =IF(ISNUMBER(MIETER!F17),IFERROR(MIETER!Q17/MIETER!$M$6,""),"") | L15: =IF(ISNUMBER(MIETER!F17),IF(K15 >= 0%,H15*(0.01), IF(K15 >= -5%,H15*(-0.01), IF(K15 >= -10%,H15*(-0.02), IF(K15 >= -15%,H15*(-0.03), IF(K15 >= -20%,H15*(-0.04), IF(K15 >= -25%,H15*(-0.05), IF(K15 >= -30%,H15*(-0.06), IF(K15 >= -35%,H15*(-0.07), IF(K15 >= -40%,H15*(-0.08), IF(K15 >= -45%,H15*(-0.09), IF(K15 >= -50%, H15*(-0.1), H15* 0) )))))))))),"") | N15: =IF(NOT(ISNUMBER(H15)),"",IF(M15="Kein Balkon",H15*(-0.05),H15*0)) | P15: =IF(NOT(ISNUMBER(H15)),"",IF(ISBLANK(O15),0,H15*MIN((YEAR(TODAY())-O15)*0.003,0.09)*-1)) | R15: =IF(ISNUMBER(MIETER!F17),IF(Q15="renoviert",H15*0.05,IF(Q15="teilweise renoviert",H15*0,IF(Q15="unrenoviert",H15*-0.05,0))),"") | S15: =IF(ISNUMBER(MIETER!F17),C15,"") | T15: =IF(ISNUMBER(MIETER!F17),IF(OR(S15="EG",S15="1.OG",S15="2.OG",S15="OG",S15="über 2.OG mit Aufzug"),H15*0,IF(OR(S15="UG",S15="über 2.OG ohne Aufzug"),H15*(-0.05),0)),"") | U15: =IF(ISNUMBER(MIETER!F17),IFERROR(F15*(H15+J15+L15+N15+P15+R15+T15),""),"") | V15: =IF(NOT(ISNUMBER(MIETER!F17)),"",N('Verkauf Cashflow'!U12)+N('Verkauf Cashflow'!V12)) | W15: =IF(ISNUMBER(MIETER!F17),U15+V15,"") | X15: =IF(AND(ISNUMBER('Verkauf Cashflow'!S12),LEFT('Verkauf Cashflow'!O12,6)="Regler"),'Verkauf Cashflow'!S12,"") | Y15: =IF(ISNUMBER('Verkauf Cashflow'!W12),'Verkauf Cashflow'!W12,"") | Z15: =IF(ISNUMBER(MIETER!F17),IFERROR(Y15/F15,""),"") | AA15: =IF(ISNUMBER('Verkauf Cashflow'!CA12),'Verkauf Cashflow'!CA12,"")
A16: =IF(ISNUMBER(MIETER!F18),IFERROR(MIETER!A18,""),"") | B16: =IF(ISNUMBER(MIETER!F18),IFERROR(MIETER!B18,""),"") | C16: =IF(ISNUMBER(MIETER!F18),IFERROR(MIETER!C18,""),"") | D16: =IF(ISNUMBER(MIETER!F18),IFERROR(MIETER!D18,""),"") | E16: =IF(ISNUMBER(MIETER!F18),IFERROR(MIETER!E18,""),"") | F16: =IF(ISNUMBER(MIETER!F18),IFERROR(MIETER!F18,""),"") | G16: =IF(ISNUMBER(MIETER!F18),KALKU!$I$18,"") | H16: =IF(ISNUMBER(MIETER!F18),KALKU!$N$18,"") | J16: =IF(ISNUMBER(MIETER!F18),IF(I16="vermietet",H16*(-0.1),H16*0),"") | K16: =IF(ISNUMBER(MIETER!F18),IFERROR(MIETER!Q18/MIETER!$M$6,""),"") | L16: =IF(ISNUMBER(MIETER!F18),IF(K16 >= 0%,H16*(0.01), IF(K16 >= -5%,H16*(-0.01), IF(K16 >= -10%,H16*(-0.02), IF(K16 >= -15%,H16*(-0.03), IF(K16 >= -20%,H16*(-0.04), IF(K16 >= -25%,H16*(-0.05), IF(K16 >= -30%,H16*(-0.06), IF(K16 >= -35%,H16*(-0.07), IF(K16 >= -40%,H16*(-0.08), IF(K16 >= -45%,H16*(-0.09), IF(K16 >= -50%, H16*(-0.1), H16* 0) )))))))))),"") | N16: =IF(NOT(ISNUMBER(H16)),"",IF(M16="Kein Balkon",H16*(-0.05),H16*0)) | P16: =IF(NOT(ISNUMBER(H16)),"",IF(ISBLANK(O16),0,H16*MIN((YEAR(TODAY())-O16)*0.003,0.09)*-1)) | R16: =IF(ISNUMBER(MIETER!F18),IF(Q16="renoviert",H16*0.05,IF(Q16="teilweise renoviert",H16*0,IF(Q16="unrenoviert",H16*-0.05,0))),"") | S16: =IF(ISNUMBER(MIETER!F18),C16,"") | T16: =IF(ISNUMBER(MIETER!F18),IF(OR(S16="EG",S16="1.OG",S16="2.OG",S16="OG",S16="über 2.OG mit Aufzug"),H16*0,IF(OR(S16="UG",S16="über 2.OG ohne Aufzug"),H16*(-0.05),0)),"") | U16: =IF(ISNUMBER(MIETER!F18),IFERROR(F16*(H16+J16+L16+N16+P16+R16+T16),""),"") | V16: =IF(NOT(ISNUMBER(MIETER!F18)),"",N('Verkauf Cashflow'!U13)+N('Verkauf Cashflow'!V13)) | W16: =IF(ISNUMBER(MIETER!F18),U16+V16,"") | X16: =IF(AND(ISNUMBER('Verkauf Cashflow'!S13),LEFT('Verkauf Cashflow'!O13,6)="Regler"),'Verkauf Cashflow'!S13,"") | Y16: =IF(ISNUMBER('Verkauf Cashflow'!W13),'Verkauf Cashflow'!W13,"") | Z16: =IF(ISNUMBER(MIETER!F18),IFERROR(Y16/F16,""),"") | AA16: =IF(ISNUMBER('Verkauf Cashflow'!CA13),'Verkauf Cashflow'!CA13,"")
A17: =IF(ISNUMBER(MIETER!F19),IFERROR(MIETER!A19,""),"") | B17: =IF(ISNUMBER(MIETER!F19),IFERROR(MIETER!B19,""),"") | C17: =IF(ISNUMBER(MIETER!F19),IFERROR(MIETER!C19,""),"") | D17: =IF(ISNUMBER(MIETER!F19),IFERROR(MIETER!D19,""),"") | E17: =IF(ISNUMBER(MIETER!F19),IFERROR(MIETER!E19,""),"") | F17: =IF(ISNUMBER(MIETER!F19),IFERROR(MIETER!F19,""),"") | G17: =IF(ISNUMBER(MIETER!F19),KALKU!$I$18,"") | H17: =IF(ISNUMBER(MIETER!F19),KALKU!$N$18,"") | J17: =IF(ISNUMBER(MIETER!F19),IF(I17="vermietet",H17*(-0.1),H17*0),"") | K17: =IF(ISNUMBER(MIETER!F19),IFERROR(MIETER!Q19/MIETER!$M$6,""),"") | L17: =IF(ISNUMBER(MIETER!F19),IF(K17 >= 0%,H17*(0.01), IF(K17 >= -5%,H17*(-0.01), IF(K17 >= -10%,H17*(-0.02), IF(K17 >= -15%,H17*(-0.03), IF(K17 >= -20%,H17*(-0.04), IF(K17 >= -25%,H17*(-0.05), IF(K17 >= -30%,H17*(-0.06), IF(K17 >= -35%,H17*(-0.07), IF(K17 >= -40%,H17*(-0.08), IF(K17 >= -45%,H17*(-0.09), IF(K17 >= -50%, H17*(-0.1), H17* 0) )))))))))),"") | N17: =IF(NOT(ISNUMBER(H17)),"",IF(M17="Kein Balkon",H17*(-0.05),H17*0)) | P17: =IF(NOT(ISNUMBER(H17)),"",IF(ISBLANK(O17),0,H17*MIN((YEAR(TODAY())-O17)*0.003,0.09)*-1)) | R17: =IF(ISNUMBER(MIETER!F19),IF(Q17="renoviert",H17*0.05,IF(Q17="teilweise renoviert",H17*0,IF(Q17="unrenoviert",H17*-0.05,0))),"") | S17: =IF(ISNUMBER(MIETER!F19),C17,"") | T17: =IF(ISNUMBER(MIETER!F19),IF(OR(S17="EG",S17="1.OG",S17="2.OG",S17="OG",S17="über 2.OG mit Aufzug"),H17*0,IF(OR(S17="UG",S17="über 2.OG ohne Aufzug"),H17*(-0.05),0)),"") | U17: =IF(ISNUMBER(MIETER!F19),IFERROR(F17*(H17+J17+L17+N17+P17+R17+T17),""),"") | V17: =IF(NOT(ISNUMBER(MIETER!F19)),"",N('Verkauf Cashflow'!U14)+N('Verkauf Cashflow'!V14)) | W17: =IF(ISNUMBER(MIETER!F19),U17+V17,"") | X17: =IF(AND(ISNUMBER('Verkauf Cashflow'!S14),LEFT('Verkauf Cashflow'!O14,6)="Regler"),'Verkauf Cashflow'!S14,"") | Y17: =IF(ISNUMBER('Verkauf Cashflow'!W14),'Verkauf Cashflow'!W14,"") | Z17: =IF(ISNUMBER(MIETER!F19),IFERROR(Y17/F17,""),"") | AA17: =IF(ISNUMBER('Verkauf Cashflow'!CA14),'Verkauf Cashflow'!CA14,"")
A18: =IF(ISNUMBER(MIETER!F20),IFERROR(MIETER!A20,""),"") | B18: =IF(ISNUMBER(MIETER!F20),IFERROR(MIETER!B20,""),"") | C18: =IF(ISNUMBER(MIETER!F20),IFERROR(MIETER!C20,""),"") | D18: =IF(ISNUMBER(MIETER!F20),IFERROR(MIETER!D20,""),"") | E18: =IF(ISNUMBER(MIETER!F20),IFERROR(MIETER!E20,""),"") | F18: =IF(ISNUMBER(MIETER!F20),IFERROR(MIETER!F20,""),"") | G18: =IF(ISNUMBER(MIETER!F20),KALKU!$I$18,"") | H18: =IF(ISNUMBER(MIETER!F20),KALKU!$N$18,"") | J18: =IF(ISNUMBER(MIETER!F20),IF(I18="vermietet",H18*(-0.1),H18*0),"") | K18: =IF(ISNUMBER(MIETER!F20),IFERROR(MIETER!Q20/MIETER!$M$6,""),"") | L18: =IF(ISNUMBER(MIETER!F20),IF(K18 >= 0%,H18*(0.01), IF(K18 >= -5%,H18*(-0.01), IF(K18 >= -10%,H18*(-0.02), IF(K18 >= -15%,H18*(-0.03), IF(K18 >= -20%,H18*(-0.04), IF(K18 >= -25%,H18*(-0.05), IF(K18 >= -30%,H18*(-0.06), IF(K18 >= -35%,H18*(-0.07), IF(K18 >= -40%,H18*(-0.08), IF(K18 >= -45%,H18*(-0.09), IF(K18 >= -50%, H18*(-0.1), H18* 0) )))))))))),"") | N18: =IF(NOT(ISNUMBER(H18)),"",IF(M18="Kein Balkon",H18*(-0.05),H18*0)) | P18: =IF(NOT(ISNUMBER(H18)),"",IF(ISBLANK(O18),0,H18*MIN((YEAR(TODAY())-O18)*0.003,0.09)*-1)) | R18: =IF(ISNUMBER(MIETER!F20),IF(Q18="renoviert",H18*0.05,IF(Q18="teilweise renoviert",H18*0,IF(Q18="unrenoviert",H18*-0.05,0))),"") | S18: =IF(ISNUMBER(MIETER!F20),C18,"") | T18: =IF(ISNUMBER(MIETER!F20),IF(OR(S18="EG",S18="1.OG",S18="2.OG",S18="OG",S18="über 2.OG mit Aufzug"),H18*0,IF(OR(S18="UG",S18="über 2.OG ohne Aufzug"),H18*(-0.05),0)),"") | U18: =IF(ISNUMBER(MIETER!F20),IFERROR(F18*(H18+J18+L18+N18+P18+R18+T18),""),"") | V18: =IF(NOT(ISNUMBER(MIETER!F20)),"",N('Verkauf Cashflow'!U15)+N('Verkauf Cashflow'!V15)) | W18: =IF(ISNUMBER(MIETER!F20),U18+V18,"") | X18: =IF(AND(ISNUMBER('Verkauf Cashflow'!S15),LEFT('Verkauf Cashflow'!O15,6)="Regler"),'Verkauf Cashflow'!S15,"") | Y18: =IF(ISNUMBER('Verkauf Cashflow'!W15),'Verkauf Cashflow'!W15,"") | Z18: =IF(ISNUMBER(MIETER!F20),IFERROR(Y18/F18,""),"") | AA18: =IF(ISNUMBER('Verkauf Cashflow'!CA15),'Verkauf Cashflow'!CA15,"")
... A25: =IF(ISNUMBER(MIETER!F27),IFERROR(MIETER!A27,""),"") | B25: =IF(ISNUMBER(MIETER!F27),IFERROR(MIETER!B27,""),"") | C25: =IF(ISNUMBER(MIETER!F27),IFERROR(MIETER!C27,""),"") | D25: =IF(ISNUMBER(MIETER!F27),IFERROR(MIETER!D27,""),"") | E25: =IF(ISNUMBER(MIETER!F27),IFERROR(MIETER!E27,""),"") | F25: =IF(ISNUMBER(MIETER!F27),IFERROR(MIETER!F27,""),"") | G25: =IF(ISNUMBER(MIETER!F27),KALKU!$I$18,"") | H25: =IF(ISNUMBER(MIETER!F27),KALKU!$N$18,"") | J25: =IF(ISNUMBER(MIETER!F27),IF(I25="vermietet",H25*(-0.1),H25*0),"") | K25: =IF(ISNUMBER(MIETER!F27),IFERROR(MIETER!Q27/MIETER!$M$6,""),"") | L25: =IF(ISNUMBER(MIETER!F27),IF(K25 >= 0%,H25*(0.01), IF(K25 >= -5%,H25*(-0.01), IF(K25 >= -10%,H25*(-0.02), IF(K25 >= -15%,H25*(-0.03), IF(K25 >= -20%,H25*(-0.04), IF(K25 >= -25%,H25*(-0.05), IF(K25 >= -30%,H25*(-0.06), IF(K25 >= -35%,H25*(-0.07), IF(K25 >= -40%,H25*(-0.08), IF(K25 >= -45%,H25*(-0.09), IF(K25 >= -50%, H25*(-0.1), H25* 0) )))))))))),"") | N25: =IF(NOT(ISNUMBER(H25)),"",IF(M25="Kein Balkon",H25*(-0.05),H25*0)) | P25: =IF(NOT(ISNUMBER(H25)),"",IF(ISBLANK(O25),0,H25*MIN((YEAR(TODAY())-O25)*0.003,0.09)*-1)) | R25: =IF(ISNUMBER(MIETER!F27),IF(Q25="renoviert",H25*0.05,IF(Q25="teilweise renoviert",H25*0,IF(Q25="unrenoviert",H25*-0.05,0))),"") | S25: =IF(ISNUMBER(MIETER!F27),C25,"") | T25: =IF(ISNUMBER(MIETER!F27),IF(OR(S25="EG",S25="1.OG",S25="2.OG",S25="OG",S25="über 2.OG mit Aufzug"),H25*0,IF(OR(S25="UG",S25="über 2.OG ohne Aufzug"),H25*(-0.05),0)),"") | U25: =IF(ISNUMBER(MIETER!F27),IFERROR(F25*(H25+J25+L25+N25+P25+R25+T25),""),"") | V25: =IF(NOT(ISNUMBER(MIETER!F27)),"",N('Verkauf Cashflow'!U22)+N('Verkauf Cashflow'!V22)) | W25: =IF(ISNUMBER(MIETER!F27),U25+V25,"") | X25: =IF(AND(ISNUMBER('Verkauf Cashflow'!S22),LEFT('Verkauf Cashflow'!O22,6)="Regler"),'Verkauf Cashflow'!S22,"") | Y25: =IF(ISNUMBER('Verkauf Cashflow'!W22),'Verkauf Cashflow'!W22,"") | Z25: =IF(ISNUMBER(MIETER!F27),IFERROR(Y25/F25,""),"") | AA25: =IF(ISNUMBER('Verkauf Cashflow'!CA22),'Verkauf Cashflow'!CA22,"")
C26: Rücklage
C27: Subventionskosten
C28: Summe | F28: =SUM(F6:F25) | G28: =AVERAGEIF(G6:G25, ">0") | H28: =AVERAGEIF(H6:H25, ">0") | U28: =SUM(U6:U25) | V28: =SUM(V6:V25) | W28: =SUM(W6:W25) | X28: =SUM(X6:X25) | Y28: =SUM(Y6:Y27) | Z28: =IFERROR(AVERAGEIF(Z6:Z25, ">0"),"") | AA28: =IFERROR(AVERAGE(AA6:AA25),"")

Sheet Verkauf Cashflow
A1: STAMM | L1: PREIS | AK1: MIETE | BA1: BEWIRTSCHAFTUNG | BI1: STEUER | BW1: ERGEBNIS
A2: WE | B2: Haus | C2: WHG | D2: Etage | E2: Lage | F2: Wohnfläche m2 | G2: Leer- stand | H2: Gar. Anz. | I2: Stpl. Anz. | J2: MEA Zähler | K2: MEA- Anteil | L2: REGLER Abgabe €/m² | M2: Ziel-Rendite je WE (leer=oben) | N2: Ziel-CF n.St. je WE (leer=oben) | O2: Preis aus | P2: Ergebnis €/m² Wohnung | Q2: Markt €/m² | R2: Delta zu Markt | S2: Indiv. Auf-/ Abschlag € | T2: Abgabepreis Wohnung | U2: Abgabepreis Garage | V2: Abgabepreis Stellplatz | W2: Abgabepreis gesamt | X2: Provision % (leer=Std.) | Y2: Provision effektiv | Z2: Provision EUR | AA2: Kaufpreis gesamt | AB2: Kaufpreis Wohnung | AC2: Abgabe ges. €/m² (CRM) | AD2: Kaufpreis Whg €/m² | AE2: Beurkundeter KP Wohnung | AF2: Kauf- nebenkosten | AG2: Kapital- bedarf | AH2: Darlehen (Finanzierung) | AI2: Eigen- kapital | AJ2: Nebenkosten finanziert | AK2: Kaltmiete manuell €/Mo | AL2: Kaltmiete IST €/Mo | AM2: Soll-/Zielmiete €/Mo | AN2: Subvention Tag 1 €/Mo | AO2: Subvention Ø Modul 5 €/Mo | AP2: Miete Garage | AQ2: Miete Stellplatz | AR2: Miete gesamt ohne Subv. | AS2: Einnahmen CF (inkl. Subv.) | AT2: Kaltmiete €/m² | AU2: letzte Erhöhung | AV2: nächste Erhöhung ab | AW2: Reach-Time Mo (Modul 5) | AX2: Rest- monate | AY2: Subvention gesamt € | AZ2: Soll-Vorschlag 2 Kappungen | BA2: Bewirt. % (Schaetzung) | BB2: Hausgeld n.u. (leer=Std.) | BC2: Hausgeld n.u. €/Mo | BD2: davon Rücklage (leer=Std.) | BE2: davon Rücklage €/Mo | BF2: Bewirt.quote % v. NKM IST | BG2: 1 % Bewirt. €/Mo v. NKM | BH2: 1 %-Pkt Bewirt. = € Kaufpreis | BI2: Bodenwert WE € | BJ2: Gebäudeanteil lt. Vertrag | BK2: Gebäudeanteil aus BRW (100 %) | BL2: Gebäudeanteil effektiv (Quote) | BM2: Anteil- Quelle | BN2: AfA-Satz WE (leer=Std.) | BO2: AfA-Satz effektiv | BP2: AfA-Basis Wohnung | BQ2: AfA €/Mo | BR2: Zinsen €/Mo | BS2: Annuitaet €/Mo | BT2: Steuerbasis €/Mo | BU2: Erstattung (+) Steuer (-) | BV2: Rücklage spaeter abziehbar €/Mo | BW2: CF vor Steuern €/Mo | BX2: CF nach Steuern €/Mo | BY2: CF n.St. ohne Subvention | BZ2: Faktor (Soll inkl. Subv.) | CA2: Brutto- mietrendite (Soll) | CB2: Rechenhilfe: Ertrag n.St. o. Fin. | CC2: Rechenhilfe: Garage/Stpl. netto | CD2: Rechenhilfe: k (Finanzierung) | CE2: Rechenhilfe: KP Whg aus Ziel
A3: =IF(NOT(ISNUMBER(MIETER!F8)),"",ROW()-2) | B3: =IF(NOT(ISNUMBER(MIETER!F8)),"",IF(MIETER!A8="","",MIETER!A8)) | C3: =IF(NOT(ISNUMBER(MIETER!F8)),"",IF(MIETER!B8="","",MIETER!B8)) | D3: =IF(NOT(ISNUMBER(MIETER!F8)),"",IF(MIETER!C8="","",MIETER!C8)) | E3: =IF(NOT(ISNUMBER(MIETER!F8)),"",IF(MIETER!D8="","",MIETER!D8)) | F3: =IF(NOT(ISNUMBER(MIETER!F8)),"",MIETER!F8) | H3: 1 | J3: 103 | K3: =IF(OR(NOT(ISNUMBER(F3)),NOT(ISNUMBER(J3)),NOT(ISNUMBER($H$29)),$H$29=0),"",J3/$H$29) | L3: 2270.9677 | O3: =IF(NOT(ISNUMBER(F3)),"",IF(NOT(ISNUMBER(T3)),"kein Preis",IF(ISNUMBER(CE3),IF(N($O$26)=2,"Rendite","Cashflow"),IF(OR(N($O$26)=2,N($O$26)=3),"Regler (Rückfall)","Regler")))) | P3: =IF(OR(NOT(ISNUMBER(T3)),NOT(ISNUMBER(F3)),F3=0),"",T3/F3) | Q3: =IF(OR(NOT(ISNUMBER(F3)),F3=0,NOT(ISNUMBER(VERKAUFSMATRIX!U6))),"",VERKAUFSMATRIX!U6/F3) | R3: =IF(OR(NOT(ISNUMBER(P3)),NOT(ISNUMBER(Q3)),Q3=0),"",P3/Q3-1) | T3: =IF(NOT(ISNUMBER(F3)),"",IF(ISNUMBER(CE3),IF(NOT(ISNUMBER(Y3)),"",(CE3+N(U3)+N(V3))/(1+Y3)-N(U3)-N(V3)),IF(NOT(ISNUMBER(L3)),"",F3*L3+N(S3)))) | U3: 8000 | W3: =IF(NOT(ISNUMBER(T3)),"",T3+N(U3)+N(V3)) | Y3: =IF(NOT(ISNUMBER(F3)),"",IF(ISNUMBER(X3),X3,IF(NOT(ISNUMBER($H$26)),"",$H$26))) | Z3: =IF(OR(NOT(ISNUMBER(W3)),NOT(ISNUMBER(Y3))),"",W3*Y3) | AA3: =IF(OR(NOT(ISNUMBER(W3)),NOT(ISNUMBER(Y3))),"",W3*(1+Y3)) | AB3: =IF(NOT(ISNUMBER(AA3)),"",AA3-N(U3)-N(V3)) | AC3: =IF(OR(NOT(ISNUMBER(W3)),NOT(ISNUMBER(F3)),F3=0),"",W3/F3) | AD3: =IF(OR(NOT(ISNUMBER(AB3)),NOT(ISNUMBER(F3)),F3=0),"",AB3/F3) | AE3: =IF(NOT(ISNUMBER(AB3)),"",AB3) | AF3: =IF(OR(NOT(ISNUMBER(AA3)),NOT(ISNUMBER($C$35))),"",AA3*$C$35) | AG3: =IF(OR(NOT(ISNUMBER(AA3)),NOT(ISNUMBER(AF3))),"",AA3+AF3) | AH3: =IF(OR(NOT(ISNUMBER(AA3)),NOT(ISNUMBER($H$33))),"",AA3*$H$33) | AI3: =IF(OR(NOT(ISNUMBER(AG3)),NOT(ISNUMBER(AH3))),"",MAX(0,AG3-AH3)) | AJ3: =IF(OR(NOT(ISNUMBER(AH3)),NOT(ISNUMBER(AA3))),"",AH3-AA3) | AL3: =IF(OR(NOT(ISNUMBER(MIETER!F8)),$G3="ja"),"",IF(NOT(ISNUMBER(MIETER!J8)),"",IF(ISNUMBER(AK3),MAX(MIETER!J8,AK3),MIETER!J8))) | AM3: 450 | AN3: =IF(OR(NOT(ISNUMBER(AL3)),NOT(ISNUMBER(AM3))),"",MAX(0,AM3-AL3)) | AP3: 50 | AR3: =IF(NOT(ISNUMBER(F3)),"",IF(AND(NOT(ISNUMBER(AL3)),NOT(ISNUMBER(AP3)),NOT(ISNUMBER(AQ3))),"",N(AL3)+N(AP3)+N(AQ3))) | AS3: =IF(OR($G3="ja",NOT(ISNUMBER(AL3)),NOT(ISNUMBER(AR3))),"",AR3+N(AN3)) | AT3: =IF(OR(NOT(ISNUMBER(AL3)),NOT(ISNUMBER(F3)),F3=0),"",AL3/F3) | AU3: =IF(OR(NOT(ISNUMBER(MIETER!F8)),NOT(ISNUMBER(MIETER!I8))),"",MIETER!I8) | AV3: =IF(OR(NOT(ISNUMBER(AU3)),$G3="ja",NOT(ISNUMBER($H$34))),"",EDATE(AU3,$H$34)) | AX3: =IF(NOT(ISNUMBER(F3)),"",IF(ISNUMBER(AW3),AW3,IF(NOT(ISNUMBER(AV3)),"",MAX(0,(YEAR(AV3)-YEAR(TODAY()))*12+MONTH(AV3)-MONTH(TODAY()))))) | AY3: =IF(NOT(ISNUMBER(AX3)),"",IF(ISNUMBER(AO3),AO3*AX3,IF(NOT(ISNUMBER(AN3)),"",AN3*AX3))) | AZ3: =IF(OR(NOT(ISNUMBER(AL3)),NOT(ISNUMBER(MIETER!$P$6))),"",ROUND(AL3*(1+MIETER!$P$6)^2,0)) | BC3: =IF(NOT(ISNUMBER(F3)),"",IF(ISNUMBER(BB3),BB3,IF(AND(ISNUMBER(BA3),ISNUMBER(AL3),AL3>0),AL3*BA3,IF(OR(NOT(ISNUMBER($C$62)),NOT(ISNUMBER($C$64))),"",$C$62+$C$64*F3/12)))) | BE3: =IF(NOT(ISNUMBER(BC3)),"",IF(ISNUMBER(BD3),MIN(BC3,BD3),IF(OR(NOT(ISNUMBER(F3)),NOT(ISNUMBER($C$64))),0,MIN(BC3,$C$64*F3/12)))) | BF3: =IF(OR(NOT(ISNUMBER(BC3)),NOT(ISNUMBER(AL3)),AL3=0),"",BC3/AL3) | BG3: =IF(NOT(ISNUMBER(AL3)),"",AL3*0.01) | BH3: =IF(OR(NOT(ISNUMBER(AL3)),NOT(ISNUMBER($C$28)),NOT(ISNUMBER(CD3)),CD3<=0),"",AL3*0.01*(1-$C$28)/CD3) | BI3: =IF(OR(NOT(ISNUMBER(K3)),NOT(ISNUMBER($H$30))),"",$H$30*K3) | BK3: =IF(OR(NOT(ISNUMBER(BI3)),NOT(ISNUMBER(AB3)),AB3<=0),"",1-BI3/AB3) | BL3: =IF(NOT(ISNUMBER(AB3)),"",IF(ISNUMBER(BJ3),BJ3,IF(AND(ISNUMBER(BI3),ISNUMBER(AE3),AE3>0),1-BI3/AE3,IF(NOT(ISNUMBER($C$31)),"",$C$31)))) | BM3: =IF(NOT(ISNUMBER(F3)),"",IF(ISNUMBER(BJ3),"vertrag",IF(ISNUMBER(BI3),"berechnet","standard"))) | BO3: =IF(NOT(ISNUMBER(F3)),"",IF(ISNUMBER(BN3),BN3,IF(NOT(ISNUMBER($C$30)),"",$C$30))) | BP3: =IF(OR(NOT(ISNUMBER(AE3)),NOT(ISNUMBER(BL3)),NOT(ISNUMBER($C$35))),"",AE3*(1+$C$35)*BL3) | BQ3: =IF(OR(NOT(ISNUMBER(BP3)),NOT(ISNUMBER(BO3)),NOT(ISNUMBER($C$35))),"",(BP3*BO3+N(U3)*(1+$C$35)*N($H$31)+N(V3)*(1+$C$35)*N($H$32))/12) | BR3: =IF(OR(NOT(ISNUMBER(AH3)),NOT(ISNUMBER($C$26))),"",AH3*$C$26/12) | BS3: =IF(OR(NOT(ISNUMBER(AH3)),NOT(ISNUMBER($C$26)),NOT(ISNUMBER($C$27))),"",ROUND(AH3*($C$26+$C$27)/12,0)) | BT3: =IF(OR(NOT(ISNUMBER(AS3)),NOT(ISNUMBER(BQ3)),NOT(ISNUMBER(BR3)),NOT(ISNUMBER(BC3))),"",AS3-BR3-BQ3-(BC3-N(BE3))) | BU3: =IF(OR(NOT(ISNUMBER(BT3)),NOT(ISNUMBER($C$28))),"",ROUND(-BT3*$C$28,0)) | BV3: =IF(OR(NOT(ISNUMBER(BE3)),NOT(ISNUMBER($C$28))),"",BE3*$C$28) | BW3: =IF(OR(NOT(ISNUMBER(AS3)),NOT(ISNUMBER(BS3)),NOT(ISNUMBER(BC3))),"",ROUND(AS3,0)-BS3-ROUND(BC3,0)) | BX3: =IF(OR(NOT(ISNUMBER(BW3)),NOT(ISNUMBER(BU3))),"",BW3+BU3) | BY3: =IF(OR(NOT(ISNUMBER(AR3)),NOT(ISNUMBER(BS3)),NOT(ISNUMBER(BC3)),NOT(ISNUMBER(BT3)),NOT(ISNUMBER($C$28))),"",ROUND(AR3,0)-BS3-ROUND(BC3,0)+ROUND(-(BT3-N(AN3))*$C$28,0)) | BZ3: =IF(OR(NOT(ISNUMBER(AA3)),NOT(ISNUMBER(AS3)),AS3=0),"",AA3/(AS3*12)) | CA3: =IF(OR(NOT(ISNUMBER(AA3)),NOT(ISNUMBER(AS3)),AA3=0),"",AS3*12/AA3) | CB3: =IF(OR(NOT(ISNUMBER(AS3)),NOT(ISNUMBER(BC3)),NOT(ISNUMBER(BO3)),NOT(ISNUMBER($C$28)),NOT(ISNUMBER($C$35))),"",(AS3-BC3)*(1-$C$28)-$C$28*N(BE3)-IF(BM3="berechnet",$C$28*(1+$C$35)*BO3*N(BI3)/12,0)) | CC3: =IF(OR(NOT(ISNUMBER(F3)),NOT(ISNUMBER($C$26)),NOT(ISNUMBER($C$27)),NOT(ISNUMBER($C$28)),NOT(ISNUMBER($C$35)),NOT(ISNUMBER($H$33))),"",($C$28*(1+$C$35)*(N(U3)*N($H$31)+N(V3)*N($H$32))-(N(U3)+N(V3))*$H$33*(($C$26+$C$27)-$C$28*$C$26))/12) | CD3: =IF(OR(NOT(ISNUMBER(BO3)),NOT(ISNUMBER($C$26)),NOT(ISNUMBER($C$27)),NOT(ISNUMBER($C$28)),NOT(ISNUMBER($C$35)),NOT(ISNUMBER($H$33)),BM3="",AND(BM3="standard",NOT(ISNUMBER($C$31)))),"",($H$33*(($C$26+$C$27)-$C$28*$C$26)-$C$28*(1+$C$35)*BO3*IF(BM3="berechnet",1,IF(BM3="vertrag",BJ3,$C$31)))/12) | CE3: =IF(NOT(ISNUMBER(F3)),"",IF(N($O$26)=2,IF(OR(NOT(ISNUMBER(AS3)),NOT(ISNUMBER(AN3)),IF(ISNUMBER(M3),M3,N($O$28))<=0),"",IF(AS3*12/IF(ISNUMBER(M3),M3,N($O$28))-N(U3)-N(V3)<=0,"",AS3*12/IF(ISNUMBER(M3),M3,N($O$28))-N(U3)-N(V3))),IF(N($O$26)=3,IF(OR(NOT(ISNUMBER(CB3)),NOT(ISNUMBER(CC3)),NOT(ISNUMBER(CD3)),N(CD3)<=0),"",IF((CB3+CC3+ROUND(AS3,0)-AS3-ROUND(BC3,0)+BC3-IF(ISNUMBER(N3),N3,N($O$29)))/CD3<=0,"",(CB3+CC3+ROUND(AS3,0)-AS3-ROUND(BC3,0)+BC3-IF(ISNUMBER(N3),N3,N($O$29)))/CD3)),"")))
A4: =IF(NOT(ISNUMBER(MIETER!F9)),"",ROW()-2) | B4: =IF(NOT(ISNUMBER(MIETER!F9)),"",IF(MIETER!A9="","",MIETER!A9)) | C4: =IF(NOT(ISNUMBER(MIETER!F9)),"",IF(MIETER!B9="","",MIETER!B9)) | D4: =IF(NOT(ISNUMBER(MIETER!F9)),"",IF(MIETER!C9="","",MIETER!C9)) | E4: =IF(NOT(ISNUMBER(MIETER!F9)),"",IF(MIETER!D9="","",MIETER!D9)) | F4: =IF(NOT(ISNUMBER(MIETER!F9)),"",MIETER!F9) | K4: =IF(OR(NOT(ISNUMBER(F4)),NOT(ISNUMBER(J4)),NOT(ISNUMBER($H$29)),$H$29=0),"",J4/$H$29) | O4: =IF(NOT(ISNUMBER(F4)),"",IF(NOT(ISNUMBER(T4)),"kein Preis",IF(ISNUMBER(CE4),IF(N($O$26)=2,"Rendite","Cashflow"),IF(OR(N($O$26)=2,N($O$26)=3),"Regler (Rückfall)","Regler")))) | P4: =IF(OR(NOT(ISNUMBER(T4)),NOT(ISNUMBER(F4)),F4=0),"",T4/F4) | Q4: =IF(OR(NOT(ISNUMBER(F4)),F4=0,NOT(ISNUMBER(VERKAUFSMATRIX!U7))),"",VERKAUFSMATRIX!U7/F4) | R4: =IF(OR(NOT(ISNUMBER(P4)),NOT(ISNUMBER(Q4)),Q4=0),"",P4/Q4-1) | T4: =IF(NOT(ISNUMBER(F4)),"",IF(ISNUMBER(CE4),IF(NOT(ISNUMBER(Y4)),"",(CE4+N(U4)+N(V4))/(1+Y4)-N(U4)-N(V4)),IF(NOT(ISNUMBER(L4)),"",F4*L4+N(S4)))) | W4: =IF(NOT(ISNUMBER(T4)),"",T4+N(U4)+N(V4)) | Y4: =IF(NOT(ISNUMBER(F4)),"",IF(ISNUMBER(X4),X4,IF(NOT(ISNUMBER($H$26)),"",$H$26))) | Z4: =IF(OR(NOT(ISNUMBER(W4)),NOT(ISNUMBER(Y4))),"",W4*Y4) | AA4: =IF(OR(NOT(ISNUMBER(W4)),NOT(ISNUMBER(Y4))),"",W4*(1+Y4)) | AB4: =IF(NOT(ISNUMBER(AA4)),"",AA4-N(U4)-N(V4)) | AC4: =IF(OR(NOT(ISNUMBER(W4)),NOT(ISNUMBER(F4)),F4=0),"",W4/F4) | AD4: =IF(OR(NOT(ISNUMBER(AB4)),NOT(ISNUMBER(F4)),F4=0),"",AB4/F4) | AE4: =IF(NOT(ISNUMBER(AB4)),"",AB4) | AF4: =IF(OR(NOT(ISNUMBER(AA4)),NOT(ISNUMBER($C$35))),"",AA4*$C$35) | AG4: =IF(OR(NOT(ISNUMBER(AA4)),NOT(ISNUMBER(AF4))),"",AA4+AF4) | AH4: =IF(OR(NOT(ISNUMBER(AA4)),NOT(ISNUMBER($H$33))),"",AA4*$H$33) | AI4: =IF(OR(NOT(ISNUMBER(AG4)),NOT(ISNUMBER(AH4))),"",MAX(0,AG4-AH4)) | AJ4: =IF(OR(NOT(ISNUMBER(AH4)),NOT(ISNUMBER(AA4))),"",AH4-AA4) | AL4: =IF(OR(NOT(ISNUMBER(MIETER!F9)),$G4="ja"),"",IF(NOT(ISNUMBER(MIETER!J9)),"",IF(ISNUMBER(AK4),MAX(MIETER!J9,AK4),MIETER!J9))) | AN4: =IF(OR(NOT(ISNUMBER(AL4)),NOT(ISNUMBER(AM4))),"",MAX(0,AM4-AL4)) | AR4: =IF(NOT(ISNUMBER(F4)),"",IF(AND(NOT(ISNUMBER(AL4)),NOT(ISNUMBER(AP4)),NOT(ISNUMBER(AQ4))),"",N(AL4)+N(AP4)+N(AQ4))) | AS4: =IF(OR($G4="ja",NOT(ISNUMBER(AL4)),NOT(ISNUMBER(AR4))),"",AR4+N(AN4)) | AT4: =IF(OR(NOT(ISNUMBER(AL4)),NOT(ISNUMBER(F4)),F4=0),"",AL4/F4) | AU4: =IF(OR(NOT(ISNUMBER(MIETER!F9)),NOT(ISNUMBER(MIETER!I9))),"",MIETER!I9) | AV4: =IF(OR(NOT(ISNUMBER(AU4)),$G4="ja",NOT(ISNUMBER($H$34))),"",EDATE(AU4,$H$34)) | AX4: =IF(NOT(ISNUMBER(F4)),"",IF(ISNUMBER(AW4),AW4,IF(NOT(ISNUMBER(AV4)),"",MAX(0,(YEAR(AV4)-YEAR(TODAY()))*12+MONTH(AV4)-MONTH(TODAY()))))) | AY4: =IF(NOT(ISNUMBER(AX4)),"",IF(ISNUMBER(AO4),AO4*AX4,IF(NOT(ISNUMBER(AN4)),"",AN4*AX4))) | AZ4: =IF(OR(NOT(ISNUMBER(AL4)),NOT(ISNUMBER(MIETER!$P$6))),"",ROUND(AL4*(1+MIETER!$P$6)^2,0)) | BC4: =IF(NOT(ISNUMBER(F4)),"",IF(ISNUMBER(BB4),BB4,IF(AND(ISNUMBER(BA4),ISNUMBER(AL4),AL4>0),AL4*BA4,IF(OR(NOT(ISNUMBER($C$62)),NOT(ISNUMBER($C$64))),"",$C$62+$C$64*F4/12)))) | BE4: =IF(NOT(ISNUMBER(BC4)),"",IF(ISNUMBER(BD4),MIN(BC4,BD4),IF(OR(NOT(ISNUMBER(F4)),NOT(ISNUMBER($C$64))),0,MIN(BC4,$C$64*F4/12)))) | BF4: =IF(OR(NOT(ISNUMBER(BC4)),NOT(ISNUMBER(AL4)),AL4=0),"",BC4/AL4) | BG4: =IF(NOT(ISNUMBER(AL4)),"",AL4*0.01) | BH4: =IF(OR(NOT(ISNUMBER(AL4)),NOT(ISNUMBER($C$28)),NOT(ISNUMBER(CD4)),CD4<=0),"",AL4*0.01*(1-$C$28)/CD4) | BI4: =IF(OR(NOT(ISNUMBER(K4)),NOT(ISNUMBER($H$30))),"",$H$30*K4) | BK4: =IF(OR(NOT(ISNUMBER(BI4)),NOT(ISNUMBER(AB4)),AB4<=0),"",1-BI4/AB4) | BL4: =IF(NOT(ISNUMBER(AB4)),"",IF(ISNUMBER(BJ4),BJ4,IF(AND(ISNUMBER(BI4),ISNUMBER(AE4),AE4>0),1-BI4/AE4,IF(NOT(ISNUMBER($C$31)),"",$C$31)))) | BM4: =IF(NOT(ISNUMBER(F4)),"",IF(ISNUMBER(BJ4),"vertrag",IF(ISNUMBER(BI4),"berechnet","standard"))) | BO4: =IF(NOT(ISNUMBER(F4)),"",IF(ISNUMBER(BN4),BN4,IF(NOT(ISNUMBER($C$30)),"",$C$30))) | BP4: =IF(OR(NOT(ISNUMBER(AE4)),NOT(ISNUMBER(BL4)),NOT(ISNUMBER($C$35))),"",AE4*(1+$C$35)*BL4) | BQ4: =IF(OR(NOT(ISNUMBER(BP4)),NOT(ISNUMBER(BO4)),NOT(ISNUMBER($C$35))),"",(BP4*BO4+N(U4)*(1+$C$35)*N($H$31)+N(V4)*(1+$C$35)*N($H$32))/12) | BR4: =IF(OR(NOT(ISNUMBER(AH4)),NOT(ISNUMBER($C$26))),"",AH4*$C$26/12) | BS4: =IF(OR(NOT(ISNUMBER(AH4)),NOT(ISNUMBER($C$26)),NOT(ISNUMBER($C$27))),"",ROUND(AH4*($C$26+$C$27)/12,0)) | BT4: =IF(OR(NOT(ISNUMBER(AS4)),NOT(ISNUMBER(BQ4)),NOT(ISNUMBER(BR4)),NOT(ISNUMBER(BC4))),"",AS4-BR4-BQ4-(BC4-N(BE4))) | BU4: =IF(OR(NOT(ISNUMBER(BT4)),NOT(ISNUMBER($C$28))),"",ROUND(-BT4*$C$28,0)) | BV4: =IF(OR(NOT(ISNUMBER(BE4)),NOT(ISNUMBER($C$28))),"",BE4*$C$28) | BW4: =IF(OR(NOT(ISNUMBER(AS4)),NOT(ISNUMBER(BS4)),NOT(ISNUMBER(BC4))),"",ROUND(AS4,0)-BS4-ROUND(BC4,0)) | BX4: =IF(OR(NOT(ISNUMBER(BW4)),NOT(ISNUMBER(BU4))),"",BW4+BU4) | BY4: =IF(OR(NOT(ISNUMBER(AR4)),NOT(ISNUMBER(BS4)),NOT(ISNUMBER(BC4)),NOT(ISNUMBER(BT4)),NOT(ISNUMBER($C$28))),"",ROUND(AR4,0)-BS4-ROUND(BC4,0)+ROUND(-(BT4-N(AN4))*$C$28,0)) | BZ4: =IF(OR(NOT(ISNUMBER(AA4)),NOT(ISNUMBER(AS4)),AS4=0),"",AA4/(AS4*12)) | CA4: =IF(OR(NOT(ISNUMBER(AA4)),NOT(ISNUMBER(AS4)),AA4=0),"",AS4*12/AA4) | CB4: =IF(OR(NOT(ISNUMBER(AS4)),NOT(ISNUMBER(BC4)),NOT(ISNUMBER(BO4)),NOT(ISNUMBER($C$28)),NOT(ISNUMBER($C$35))),"",(AS4-BC4)*(1-$C$28)-$C$28*N(BE4)-IF(BM4="berechnet",$C$28*(1+$C$35)*BO4*N(BI4)/12,0)) | CC4: =IF(OR(NOT(ISNUMBER(F4)),NOT(ISNUMBER($C$26)),NOT(ISNUMBER($C$27)),NOT(ISNUMBER($C$28)),NOT(ISNUMBER($C$35)),NOT(ISNUMBER($H$33))),"",($C$28*(1+$C$35)*(N(U4)*N($H$31)+N(V4)*N($H$32))-(N(U4)+N(V4))*$H$33*(($C$26+$C$27)-$C$28*$C$26))/12) | CD4: =IF(OR(NOT(ISNUMBER(BO4)),NOT(ISNUMBER($C$26)),NOT(ISNUMBER($C$27)),NOT(ISNUMBER($C$28)),NOT(ISNUMBER($C$35)),NOT(ISNUMBER($H$33)),BM4="",AND(BM4="standard",NOT(ISNUMBER($C$31)))),"",($H$33*(($C$26+$C$27)-$C$28*$C$26)-$C$28*(1+$C$35)*BO4*IF(BM4="berechnet",1,IF(BM4="vertrag",BJ4,$C$31)))/12) | CE4: =IF(NOT(ISNUMBER(F4)),"",IF(N($O$26)=2,IF(OR(NOT(ISNUMBER(AS4)),NOT(ISNUMBER(AN4)),IF(ISNUMBER(M4),M4,N($O$28))<=0),"",IF(AS4*12/IF(ISNUMBER(M4),M4,N($O$28))-N(U4)-N(V4)<=0,"",AS4*12/IF(ISNUMBER(M4),M4,N($O$28))-N(U4)-N(V4))),IF(N($O$26)=3,IF(OR(NOT(ISNUMBER(CB4)),NOT(ISNUMBER(CC4)),NOT(ISNUMBER(CD4)),N(CD4)<=0),"",IF((CB4+CC4+ROUND(AS4,0)-AS4-ROUND(BC4,0)+BC4-IF(ISNUMBER(N4),N4,N($O$29)))/CD4<=0,"",(CB4+CC4+ROUND(AS4,0)-AS4-ROUND(BC4,0)+BC4-IF(ISNUMBER(N4),N4,N($O$29)))/CD4)),"")))
A5: =IF(NOT(ISNUMBER(MIETER!F10)),"",ROW()-2) | B5: =IF(NOT(ISNUMBER(MIETER!F10)),"",IF(MIETER!A10="","",MIETER!A10)) | C5: =IF(NOT(ISNUMBER(MIETER!F10)),"",IF(MIETER!B10="","",MIETER!B10)) | D5: =IF(NOT(ISNUMBER(MIETER!F10)),"",IF(MIETER!C10="","",MIETER!C10)) | E5: =IF(NOT(ISNUMBER(MIETER!F10)),"",IF(MIETER!D10="","",MIETER!D10)) | F5: =IF(NOT(ISNUMBER(MIETER!F10)),"",MIETER!F10) | K5: =IF(OR(NOT(ISNUMBER(F5)),NOT(ISNUMBER(J5)),NOT(ISNUMBER($H$29)),$H$29=0),"",J5/$H$29) | O5: =IF(NOT(ISNUMBER(F5)),"",IF(NOT(ISNUMBER(T5)),"kein Preis",IF(ISNUMBER(CE5),IF(N($O$26)=2,"Rendite","Cashflow"),IF(OR(N($O$26)=2,N($O$26)=3),"Regler (Rückfall)","Regler")))) | P5: =IF(OR(NOT(ISNUMBER(T5)),NOT(ISNUMBER(F5)),F5=0),"",T5/F5) | Q5: =IF(OR(NOT(ISNUMBER(F5)),F5=0,NOT(ISNUMBER(VERKAUFSMATRIX!U8))),"",VERKAUFSMATRIX!U8/F5) | R5: =IF(OR(NOT(ISNUMBER(P5)),NOT(ISNUMBER(Q5)),Q5=0),"",P5/Q5-1) | T5: =IF(NOT(ISNUMBER(F5)),"",IF(ISNUMBER(CE5),IF(NOT(ISNUMBER(Y5)),"",(CE5+N(U5)+N(V5))/(1+Y5)-N(U5)-N(V5)),IF(NOT(ISNUMBER(L5)),"",F5*L5+N(S5)))) | W5: =IF(NOT(ISNUMBER(T5)),"",T5+N(U5)+N(V5)) | Y5: =IF(NOT(ISNUMBER(F5)),"",IF(ISNUMBER(X5),X5,IF(NOT(ISNUMBER($H$26)),"",$H$26))) | Z5: =IF(OR(NOT(ISNUMBER(W5)),NOT(ISNUMBER(Y5))),"",W5*Y5) | AA5: =IF(OR(NOT(ISNUMBER(W5)),NOT(ISNUMBER(Y5))),"",W5*(1+Y5)) | AB5: =IF(NOT(ISNUMBER(AA5)),"",AA5-N(U5)-N(V5)) | AC5: =IF(OR(NOT(ISNUMBER(W5)),NOT(ISNUMBER(F5)),F5=0),"",W5/F5) | AD5: =IF(OR(NOT(ISNUMBER(AB5)),NOT(ISNUMBER(F5)),F5=0),"",AB5/F5) | AE5: =IF(NOT(ISNUMBER(AB5)),"",AB5) | AF5: =IF(OR(NOT(ISNUMBER(AA5)),NOT(ISNUMBER($C$35))),"",AA5*$C$35) | AG5: =IF(OR(NOT(ISNUMBER(AA5)),NOT(ISNUMBER(AF5))),"",AA5+AF5) | AH5: =IF(OR(NOT(ISNUMBER(AA5)),NOT(ISNUMBER($H$33))),"",AA5*$H$33) | AI5: =IF(OR(NOT(ISNUMBER(AG5)),NOT(ISNUMBER(AH5))),"",MAX(0,AG5-AH5)) | AJ5: =IF(OR(NOT(ISNUMBER(AH5)),NOT(ISNUMBER(AA5))),"",AH5-AA5) | AL5: =IF(OR(NOT(ISNUMBER(MIETER!F10)),$G5="ja"),"",IF(NOT(ISNUMBER(MIETER!J10)),"",IF(ISNUMBER(AK5),MAX(MIETER!J10,AK5),MIETER!J10))) | AN5: =IF(OR(NOT(ISNUMBER(AL5)),NOT(ISNUMBER(AM5))),"",MAX(0,AM5-AL5)) | AR5: =IF(NOT(ISNUMBER(F5)),"",IF(AND(NOT(ISNUMBER(AL5)),NOT(ISNUMBER(AP5)),NOT(ISNUMBER(AQ5))),"",N(AL5)+N(AP5)+N(AQ5))) | AS5: =IF(OR($G5="ja",NOT(ISNUMBER(AL5)),NOT(ISNUMBER(AR5))),"",AR5+N(AN5)) | AT5: =IF(OR(NOT(ISNUMBER(AL5)),NOT(ISNUMBER(F5)),F5=0),"",AL5/F5) | AU5: =IF(OR(NOT(ISNUMBER(MIETER!F10)),NOT(ISNUMBER(MIETER!I10))),"",MIETER!I10) | AV5: =IF(OR(NOT(ISNUMBER(AU5)),$G5="ja",NOT(ISNUMBER($H$34))),"",EDATE(AU5,$H$34)) | AX5: =IF(NOT(ISNUMBER(F5)),"",IF(ISNUMBER(AW5),AW5,IF(NOT(ISNUMBER(AV5)),"",MAX(0,(YEAR(AV5)-YEAR(TODAY()))*12+MONTH(AV5)-MONTH(TODAY()))))) | AY5: =IF(NOT(ISNUMBER(AX5)),"",IF(ISNUMBER(AO5),AO5*AX5,IF(NOT(ISNUMBER(AN5)),"",AN5*AX5))) | AZ5: =IF(OR(NOT(ISNUMBER(AL5)),NOT(ISNUMBER(MIETER!$P$6))),"",ROUND(AL5*(1+MIETER!$P$6)^2,0)) | BC5: =IF(NOT(ISNUMBER(F5)),"",IF(ISNUMBER(BB5),BB5,IF(AND(ISNUMBER(BA5),ISNUMBER(AL5),AL5>0),AL5*BA5,IF(OR(NOT(ISNUMBER($C$62)),NOT(ISNUMBER($C$64))),"",$C$62+$C$64*F5/12)))) | BE5: =IF(NOT(ISNUMBER(BC5)),"",IF(ISNUMBER(BD5),MIN(BC5,BD5),IF(OR(NOT(ISNUMBER(F5)),NOT(ISNUMBER($C$64))),0,MIN(BC5,$C$64*F5/12)))) | BF5: =IF(OR(NOT(ISNUMBER(BC5)),NOT(ISNUMBER(AL5)),AL5=0),"",BC5/AL5) | BG5: =IF(NOT(ISNUMBER(AL5)),"",AL5*0.01) | BH5: =IF(OR(NOT(ISNUMBER(AL5)),NOT(ISNUMBER($C$28)),NOT(ISNUMBER(CD5)),CD5<=0),"",AL5*0.01*(1-$C$28)/CD5) | BI5: =IF(OR(NOT(ISNUMBER(K5)),NOT(ISNUMBER($H$30))),"",$H$30*K5) | BK5: =IF(OR(NOT(ISNUMBER(BI5)),NOT(ISNUMBER(AB5)),AB5<=0),"",1-BI5/AB5) | BL5: =IF(NOT(ISNUMBER(AB5)),"",IF(ISNUMBER(BJ5),BJ5,IF(AND(ISNUMBER(BI5),ISNUMBER(AE5),AE5>0),1-BI5/AE5,IF(NOT(ISNUMBER($C$31)),"",$C$31)))) | BM5: =IF(NOT(ISNUMBER(F5)),"",IF(ISNUMBER(BJ5),"vertrag",IF(ISNUMBER(BI5),"berechnet","standard"))) | BO5: =IF(NOT(ISNUMBER(F5)),"",IF(ISNUMBER(BN5),BN5,IF(NOT(ISNUMBER($C$30)),"",$C$30))) | BP5: =IF(OR(NOT(ISNUMBER(AE5)),NOT(ISNUMBER(BL5)),NOT(ISNUMBER($C$35))),"",AE5*(1+$C$35)*BL5) | BQ5: =IF(OR(NOT(ISNUMBER(BP5)),NOT(ISNUMBER(BO5)),NOT(ISNUMBER($C$35))),"",(BP5*BO5+N(U5)*(1+$C$35)*N($H$31)+N(V5)*(1+$C$35)*N($H$32))/12) | BR5: =IF(OR(NOT(ISNUMBER(AH5)),NOT(ISNUMBER($C$26))),"",AH5*$C$26/12) | BS5: =IF(OR(NOT(ISNUMBER(AH5)),NOT(ISNUMBER($C$26)),NOT(ISNUMBER($C$27))),"",ROUND(AH5*($C$26+$C$27)/12,0)) | BT5: =IF(OR(NOT(ISNUMBER(AS5)),NOT(ISNUMBER(BQ5)),NOT(ISNUMBER(BR5)),NOT(ISNUMBER(BC5))),"",AS5-BR5-BQ5-(BC5-N(BE5))) | BU5: =IF(OR(NOT(ISNUMBER(BT5)),NOT(ISNUMBER($C$28))),"",ROUND(-BT5*$C$28,0)) | BV5: =IF(OR(NOT(ISNUMBER(BE5)),NOT(ISNUMBER($C$28))),"",BE5*$C$28) | BW5: =IF(OR(NOT(ISNUMBER(AS5)),NOT(ISNUMBER(BS5)),NOT(ISNUMBER(BC5))),"",ROUND(AS5,0)-BS5-ROUND(BC5,0)) | BX5: =IF(OR(NOT(ISNUMBER(BW5)),NOT(ISNUMBER(BU5))),"",BW5+BU5) | BY5: =IF(OR(NOT(ISNUMBER(AR5)),NOT(ISNUMBER(BS5)),NOT(ISNUMBER(BC5)),NOT(ISNUMBER(BT5)),NOT(ISNUMBER($C$28))),"",ROUND(AR5,0)-BS5-ROUND(BC5,0)+ROUND(-(BT5-N(AN5))*$C$28,0)) | BZ5: =IF(OR(NOT(ISNUMBER(AA5)),NOT(ISNUMBER(AS5)),AS5=0),"",AA5/(AS5*12)) | CA5: =IF(OR(NOT(ISNUMBER(AA5)),NOT(ISNUMBER(AS5)),AA5=0),"",AS5*12/AA5) | CB5: =IF(OR(NOT(ISNUMBER(AS5)),NOT(ISNUMBER(BC5)),NOT(ISNUMBER(BO5)),NOT(ISNUMBER($C$28)),NOT(ISNUMBER($C$35))),"",(AS5-BC5)*(1-$C$28)-$C$28*N(BE5)-IF(BM5="berechnet",$C$28*(1+$C$35)*BO5*N(BI5)/12,0)) | CC5: =IF(OR(NOT(ISNUMBER(F5)),NOT(ISNUMBER($C$26)),NOT(ISNUMBER($C$27)),NOT(ISNUMBER($C$28)),NOT(ISNUMBER($C$35)),NOT(ISNUMBER($H$33))),"",($C$28*(1+$C$35)*(N(U5)*N($H$31)+N(V5)*N($H$32))-(N(U5)+N(V5))*$H$33*(($C$26+$C$27)-$C$28*$C$26))/12) | CD5: =IF(OR(NOT(ISNUMBER(BO5)),NOT(ISNUMBER($C$26)),NOT(ISNUMBER($C$27)),NOT(ISNUMBER($C$28)),NOT(ISNUMBER($C$35)),NOT(ISNUMBER($H$33)),BM5="",AND(BM5="standard",NOT(ISNUMBER($C$31)))),"",($H$33*(($C$26+$C$27)-$C$28*$C$26)-$C$28*(1+$C$35)*BO5*IF(BM5="berechnet",1,IF(BM5="vertrag",BJ5,$C$31)))/12) | CE5: =IF(NOT(ISNUMBER(F5)),"",IF(N($O$26)=2,IF(OR(NOT(ISNUMBER(AS5)),NOT(ISNUMBER(AN5)),IF(ISNUMBER(M5),M5,N($O$28))<=0),"",IF(AS5*12/IF(ISNUMBER(M5),M5,N($O$28))-N(U5)-N(V5)<=0,"",AS5*12/IF(ISNUMBER(M5),M5,N($O$28))-N(U5)-N(V5))),IF(N($O$26)=3,IF(OR(NOT(ISNUMBER(CB5)),NOT(ISNUMBER(CC5)),NOT(ISNUMBER(CD5)),N(CD5)<=0),"",IF((CB5+CC5+ROUND(AS5,0)-AS5-ROUND(BC5,0)+BC5-IF(ISNUMBER(N5),N5,N($O$29)))/CD5<=0,"",(CB5+CC5+ROUND(AS5,0)-AS5-ROUND(BC5,0)+BC5-IF(ISNUMBER(N5),N5,N($O$29)))/CD5)),"")))
A6: =IF(NOT(ISNUMBER(MIETER!F11)),"",ROW()-2) | B6: =IF(NOT(ISNUMBER(MIETER!F11)),"",IF(MIETER!A11="","",MIETER!A11)) | C6: =IF(NOT(ISNUMBER(MIETER!F11)),"",IF(MIETER!B11="","",MIETER!B11)) | D6: =IF(NOT(ISNUMBER(MIETER!F11)),"",IF(MIETER!C11="","",MIETER!C11)) | E6: =IF(NOT(ISNUMBER(MIETER!F11)),"",IF(MIETER!D11="","",MIETER!D11)) | F6: =IF(NOT(ISNUMBER(MIETER!F11)),"",MIETER!F11) | K6: =IF(OR(NOT(ISNUMBER(F6)),NOT(ISNUMBER(J6)),NOT(ISNUMBER($H$29)),$H$29=0),"",J6/$H$29) | O6: =IF(NOT(ISNUMBER(F6)),"",IF(NOT(ISNUMBER(T6)),"kein Preis",IF(ISNUMBER(CE6),IF(N($O$26)=2,"Rendite","Cashflow"),IF(OR(N($O$26)=2,N($O$26)=3),"Regler (Rückfall)","Regler")))) | P6: =IF(OR(NOT(ISNUMBER(T6)),NOT(ISNUMBER(F6)),F6=0),"",T6/F6) | Q6: =IF(OR(NOT(ISNUMBER(F6)),F6=0,NOT(ISNUMBER(VERKAUFSMATRIX!U9))),"",VERKAUFSMATRIX!U9/F6) | R6: =IF(OR(NOT(ISNUMBER(P6)),NOT(ISNUMBER(Q6)),Q6=0),"",P6/Q6-1) | T6: =IF(NOT(ISNUMBER(F6)),"",IF(ISNUMBER(CE6),IF(NOT(ISNUMBER(Y6)),"",(CE6+N(U6)+N(V6))/(1+Y6)-N(U6)-N(V6)),IF(NOT(ISNUMBER(L6)),"",F6*L6+N(S6)))) | W6: =IF(NOT(ISNUMBER(T6)),"",T6+N(U6)+N(V6)) | Y6: =IF(NOT(ISNUMBER(F6)),"",IF(ISNUMBER(X6),X6,IF(NOT(ISNUMBER($H$26)),"",$H$26))) | Z6: =IF(OR(NOT(ISNUMBER(W6)),NOT(ISNUMBER(Y6))),"",W6*Y6) | AA6: =IF(OR(NOT(ISNUMBER(W6)),NOT(ISNUMBER(Y6))),"",W6*(1+Y6)) | AB6: =IF(NOT(ISNUMBER(AA6)),"",AA6-N(U6)-N(V6)) | AC6: =IF(OR(NOT(ISNUMBER(W6)),NOT(ISNUMBER(F6)),F6=0),"",W6/F6) | AD6: =IF(OR(NOT(ISNUMBER(AB6)),NOT(ISNUMBER(F6)),F6=0),"",AB6/F6) | AE6: =IF(NOT(ISNUMBER(AB6)),"",AB6) | AF6: =IF(OR(NOT(ISNUMBER(AA6)),NOT(ISNUMBER($C$35))),"",AA6*$C$35) | AG6: =IF(OR(NOT(ISNUMBER(AA6)),NOT(ISNUMBER(AF6))),"",AA6+AF6) | AH6: =IF(OR(NOT(ISNUMBER(AA6)),NOT(ISNUMBER($H$33))),"",AA6*$H$33) | AI6: =IF(OR(NOT(ISNUMBER(AG6)),NOT(ISNUMBER(AH6))),"",MAX(0,AG6-AH6)) | AJ6: =IF(OR(NOT(ISNUMBER(AH6)),NOT(ISNUMBER(AA6))),"",AH6-AA6) | AL6: =IF(OR(NOT(ISNUMBER(MIETER!F11)),$G6="ja"),"",IF(NOT(ISNUMBER(MIETER!J11)),"",IF(ISNUMBER(AK6),MAX(MIETER!J11,AK6),MIETER!J11))) | AN6: =IF(OR(NOT(ISNUMBER(AL6)),NOT(ISNUMBER(AM6))),"",MAX(0,AM6-AL6)) | AR6: =IF(NOT(ISNUMBER(F6)),"",IF(AND(NOT(ISNUMBER(AL6)),NOT(ISNUMBER(AP6)),NOT(ISNUMBER(AQ6))),"",N(AL6)+N(AP6)+N(AQ6))) | AS6: =IF(OR($G6="ja",NOT(ISNUMBER(AL6)),NOT(ISNUMBER(AR6))),"",AR6+N(AN6)) | AT6: =IF(OR(NOT(ISNUMBER(AL6)),NOT(ISNUMBER(F6)),F6=0),"",AL6/F6) | AU6: =IF(OR(NOT(ISNUMBER(MIETER!F11)),NOT(ISNUMBER(MIETER!I11))),"",MIETER!I11) | AV6: =IF(OR(NOT(ISNUMBER(AU6)),$G6="ja",NOT(ISNUMBER($H$34))),"",EDATE(AU6,$H$34)) | AX6: =IF(NOT(ISNUMBER(F6)),"",IF(ISNUMBER(AW6),AW6,IF(NOT(ISNUMBER(AV6)),"",MAX(0,(YEAR(AV6)-YEAR(TODAY()))*12+MONTH(AV6)-MONTH(TODAY()))))) | AY6: =IF(NOT(ISNUMBER(AX6)),"",IF(ISNUMBER(AO6),AO6*AX6,IF(NOT(ISNUMBER(AN6)),"",AN6*AX6))) | AZ6: =IF(OR(NOT(ISNUMBER(AL6)),NOT(ISNUMBER(MIETER!$P$6))),"",ROUND(AL6*(1+MIETER!$P$6)^2,0)) | BC6: =IF(NOT(ISNUMBER(F6)),"",IF(ISNUMBER(BB6),BB6,IF(AND(ISNUMBER(BA6),ISNUMBER(AL6),AL6>0),AL6*BA6,IF(OR(NOT(ISNUMBER($C$62)),NOT(ISNUMBER($C$64))),"",$C$62+$C$64*F6/12)))) | BE6: =IF(NOT(ISNUMBER(BC6)),"",IF(ISNUMBER(BD6),MIN(BC6,BD6),IF(OR(NOT(ISNUMBER(F6)),NOT(ISNUMBER($C$64))),0,MIN(BC6,$C$64*F6/12)))) | BF6: =IF(OR(NOT(ISNUMBER(BC6)),NOT(ISNUMBER(AL6)),AL6=0),"",BC6/AL6) | BG6: =IF(NOT(ISNUMBER(AL6)),"",AL6*0.01) | BH6: =IF(OR(NOT(ISNUMBER(AL6)),NOT(ISNUMBER($C$28)),NOT(ISNUMBER(CD6)),CD6<=0),"",AL6*0.01*(1-$C$28)/CD6) | BI6: =IF(OR(NOT(ISNUMBER(K6)),NOT(ISNUMBER($H$30))),"",$H$30*K6) | BK6: =IF(OR(NOT(ISNUMBER(BI6)),NOT(ISNUMBER(AB6)),AB6<=0),"",1-BI6/AB6) | BL6: =IF(NOT(ISNUMBER(AB6)),"",IF(ISNUMBER(BJ6),BJ6,IF(AND(ISNUMBER(BI6),ISNUMBER(AE6),AE6>0),1-BI6/AE6,IF(NOT(ISNUMBER($C$31)),"",$C$31)))) | BM6: =IF(NOT(ISNUMBER(F6)),"",IF(ISNUMBER(BJ6),"vertrag",IF(ISNUMBER(BI6),"berechnet","standard"))) | BO6: =IF(NOT(ISNUMBER(F6)),"",IF(ISNUMBER(BN6),BN6,IF(NOT(ISNUMBER($C$30)),"",$C$30))) | BP6: =IF(OR(NOT(ISNUMBER(AE6)),NOT(ISNUMBER(BL6)),NOT(ISNUMBER($C$35))),"",AE6*(1+$C$35)*BL6) | BQ6: =IF(OR(NOT(ISNUMBER(BP6)),NOT(ISNUMBER(BO6)),NOT(ISNUMBER($C$35))),"",(BP6*BO6+N(U6)*(1+$C$35)*N($H$31)+N(V6)*(1+$C$35)*N($H$32))/12) | BR6: =IF(OR(NOT(ISNUMBER(AH6)),NOT(ISNUMBER($C$26))),"",AH6*$C$26/12) | BS6: =IF(OR(NOT(ISNUMBER(AH6)),NOT(ISNUMBER($C$26)),NOT(ISNUMBER($C$27))),"",ROUND(AH6*($C$26+$C$27)/12,0)) | BT6: =IF(OR(NOT(ISNUMBER(AS6)),NOT(ISNUMBER(BQ6)),NOT(ISNUMBER(BR6)),NOT(ISNUMBER(BC6))),"",AS6-BR6-BQ6-(BC6-N(BE6))) | BU6: =IF(OR(NOT(ISNUMBER(BT6)),NOT(ISNUMBER($C$28))),"",ROUND(-BT6*$C$28,0)) | BV6: =IF(OR(NOT(ISNUMBER(BE6)),NOT(ISNUMBER($C$28))),"",BE6*$C$28) | BW6: =IF(OR(NOT(ISNUMBER(AS6)),NOT(ISNUMBER(BS6)),NOT(ISNUMBER(BC6))),"",ROUND(AS6,0)-BS6-ROUND(BC6,0)) | BX6: =IF(OR(NOT(ISNUMBER(BW6)),NOT(ISNUMBER(BU6))),"",BW6+BU6) | BY6: =IF(OR(NOT(ISNUMBER(AR6)),NOT(ISNUMBER(BS6)),NOT(ISNUMBER(BC6)),NOT(ISNUMBER(BT6)),NOT(ISNUMBER($C$28))),"",ROUND(AR6,0)-BS6-ROUND(BC6,0)+ROUND(-(BT6-N(AN6))*$C$28,0)) | BZ6: =IF(OR(NOT(ISNUMBER(AA6)),NOT(ISNUMBER(AS6)),AS6=0),"",AA6/(AS6*12)) | CA6: =IF(OR(NOT(ISNUMBER(AA6)),NOT(ISNUMBER(AS6)),AA6=0),"",AS6*12/AA6) | CB6: =IF(OR(NOT(ISNUMBER(AS6)),NOT(ISNUMBER(BC6)),NOT(ISNUMBER(BO6)),NOT(ISNUMBER($C$28)),NOT(ISNUMBER($C$35))),"",(AS6-BC6)*(1-$C$28)-$C$28*N(BE6)-IF(BM6="berechnet",$C$28*(1+$C$35)*BO6*N(BI6)/12,0)) | CC6: =IF(OR(NOT(ISNUMBER(F6)),NOT(ISNUMBER($C$26)),NOT(ISNUMBER($C$27)),NOT(ISNUMBER($C$28)),NOT(ISNUMBER($C$35)),NOT(ISNUMBER($H$33))),"",($C$28*(1+$C$35)*(N(U6)*N($H$31)+N(V6)*N($H$32))-(N(U6)+N(V6))*$H$33*(($C$26+$C$27)-$C$28*$C$26))/12) | CD6: =IF(OR(NOT(ISNUMBER(BO6)),NOT(ISNUMBER($C$26)),NOT(ISNUMBER($C$27)),NOT(ISNUMBER($C$28)),NOT(ISNUMBER($C$35)),NOT(ISNUMBER($H$33)),BM6="",AND(BM6="standard",NOT(ISNUMBER($C$31)))),"",($H$33*(($C$26+$C$27)-$C$28*$C$26)-$C$28*(1+$C$35)*BO6*IF(BM6="berechnet",1,IF(BM6="vertrag",BJ6,$C$31)))/12) | CE6: =IF(NOT(ISNUMBER(F6)),"",IF(N($O$26)=2,IF(OR(NOT(ISNUMBER(AS6)),NOT(ISNUMBER(AN6)),IF(ISNUMBER(M6),M6,N($O$28))<=0),"",IF(AS6*12/IF(ISNUMBER(M6),M6,N($O$28))-N(U6)-N(V6)<=0,"",AS6*12/IF(ISNUMBER(M6),M6,N($O$28))-N(U6)-N(V6))),IF(N($O$26)=3,IF(OR(NOT(ISNUMBER(CB6)),NOT(ISNUMBER(CC6)),NOT(ISNUMBER(CD6)),N(CD6)<=0),"",IF((CB6+CC6+ROUND(AS6,0)-AS6-ROUND(BC6,0)+BC6-IF(ISNUMBER(N6),N6,N($O$29)))/CD6<=0,"",(CB6+CC6+ROUND(AS6,0)-AS6-ROUND(BC6,0)+BC6-IF(ISNUMBER(N6),N6,N($O$29)))/CD6)),"")))
A7: =IF(NOT(ISNUMBER(MIETER!F12)),"",ROW()-2) | B7: =IF(NOT(ISNUMBER(MIETER!F12)),"",IF(MIETER!A12="","",MIETER!A12)) | C7: =IF(NOT(ISNUMBER(MIETER!F12)),"",IF(MIETER!B12="","",MIETER!B12)) | D7: =IF(NOT(ISNUMBER(MIETER!F12)),"",IF(MIETER!C12="","",MIETER!C12)) | E7: =IF(NOT(ISNUMBER(MIETER!F12)),"",IF(MIETER!D12="","",MIETER!D12)) | F7: =IF(NOT(ISNUMBER(MIETER!F12)),"",MIETER!F12) | K7: =IF(OR(NOT(ISNUMBER(F7)),NOT(ISNUMBER(J7)),NOT(ISNUMBER($H$29)),$H$29=0),"",J7/$H$29) | O7: =IF(NOT(ISNUMBER(F7)),"",IF(NOT(ISNUMBER(T7)),"kein Preis",IF(ISNUMBER(CE7),IF(N($O$26)=2,"Rendite","Cashflow"),IF(OR(N($O$26)=2,N($O$26)=3),"Regler (Rückfall)","Regler")))) | P7: =IF(OR(NOT(ISNUMBER(T7)),NOT(ISNUMBER(F7)),F7=0),"",T7/F7) | Q7: =IF(OR(NOT(ISNUMBER(F7)),F7=0,NOT(ISNUMBER(VERKAUFSMATRIX!U10))),"",VERKAUFSMATRIX!U10/F7) | R7: =IF(OR(NOT(ISNUMBER(P7)),NOT(ISNUMBER(Q7)),Q7=0),"",P7/Q7-1) | T7: =IF(NOT(ISNUMBER(F7)),"",IF(ISNUMBER(CE7),IF(NOT(ISNUMBER(Y7)),"",(CE7+N(U7)+N(V7))/(1+Y7)-N(U7)-N(V7)),IF(NOT(ISNUMBER(L7)),"",F7*L7+N(S7)))) | W7: =IF(NOT(ISNUMBER(T7)),"",T7+N(U7)+N(V7)) | Y7: =IF(NOT(ISNUMBER(F7)),"",IF(ISNUMBER(X7),X7,IF(NOT(ISNUMBER($H$26)),"",$H$26))) | Z7: =IF(OR(NOT(ISNUMBER(W7)),NOT(ISNUMBER(Y7))),"",W7*Y7) | AA7: =IF(OR(NOT(ISNUMBER(W7)),NOT(ISNUMBER(Y7))),"",W7*(1+Y7)) | AB7: =IF(NOT(ISNUMBER(AA7)),"",AA7-N(U7)-N(V7)) | AC7: =IF(OR(NOT(ISNUMBER(W7)),NOT(ISNUMBER(F7)),F7=0),"",W7/F7) | AD7: =IF(OR(NOT(ISNUMBER(AB7)),NOT(ISNUMBER(F7)),F7=0),"",AB7/F7) | AE7: =IF(NOT(ISNUMBER(AB7)),"",AB7) | AF7: =IF(OR(NOT(ISNUMBER(AA7)),NOT(ISNUMBER($C$35))),"",AA7*$C$35) | AG7: =IF(OR(NOT(ISNUMBER(AA7)),NOT(ISNUMBER(AF7))),"",AA7+AF7) | AH7: =IF(OR(NOT(ISNUMBER(AA7)),NOT(ISNUMBER($H$33))),"",AA7*$H$33) | AI7: =IF(OR(NOT(ISNUMBER(AG7)),NOT(ISNUMBER(AH7))),"",MAX(0,AG7-AH7)) | AJ7: =IF(OR(NOT(ISNUMBER(AH7)),NOT(ISNUMBER(AA7))),"",AH7-AA7) | AL7: =IF(OR(NOT(ISNUMBER(MIETER!F12)),$G7="ja"),"",IF(NOT(ISNUMBER(MIETER!J12)),"",IF(ISNUMBER(AK7),MAX(MIETER!J12,AK7),MIETER!J12))) | AN7: =IF(OR(NOT(ISNUMBER(AL7)),NOT(ISNUMBER(AM7))),"",MAX(0,AM7-AL7)) | AR7: =IF(NOT(ISNUMBER(F7)),"",IF(AND(NOT(ISNUMBER(AL7)),NOT(ISNUMBER(AP7)),NOT(ISNUMBER(AQ7))),"",N(AL7)+N(AP7)+N(AQ7))) | AS7: =IF(OR($G7="ja",NOT(ISNUMBER(AL7)),NOT(ISNUMBER(AR7))),"",AR7+N(AN7)) | AT7: =IF(OR(NOT(ISNUMBER(AL7)),NOT(ISNUMBER(F7)),F7=0),"",AL7/F7) | AU7: =IF(OR(NOT(ISNUMBER(MIETER!F12)),NOT(ISNUMBER(MIETER!I12))),"",MIETER!I12) | AV7: =IF(OR(NOT(ISNUMBER(AU7)),$G7="ja",NOT(ISNUMBER($H$34))),"",EDATE(AU7,$H$34)) | AX7: =IF(NOT(ISNUMBER(F7)),"",IF(ISNUMBER(AW7),AW7,IF(NOT(ISNUMBER(AV7)),"",MAX(0,(YEAR(AV7)-YEAR(TODAY()))*12+MONTH(AV7)-MONTH(TODAY()))))) | AY7: =IF(NOT(ISNUMBER(AX7)),"",IF(ISNUMBER(AO7),AO7*AX7,IF(NOT(ISNUMBER(AN7)),"",AN7*AX7))) | AZ7: =IF(OR(NOT(ISNUMBER(AL7)),NOT(ISNUMBER(MIETER!$P$6))),"",ROUND(AL7*(1+MIETER!$P$6)^2,0)) | BC7: =IF(NOT(ISNUMBER(F7)),"",IF(ISNUMBER(BB7),BB7,IF(AND(ISNUMBER(BA7),ISNUMBER(AL7),AL7>0),AL7*BA7,IF(OR(NOT(ISNUMBER($C$62)),NOT(ISNUMBER($C$64))),"",$C$62+$C$64*F7/12)))) | BE7: =IF(NOT(ISNUMBER(BC7)),"",IF(ISNUMBER(BD7),MIN(BC7,BD7),IF(OR(NOT(ISNUMBER(F7)),NOT(ISNUMBER($C$64))),0,MIN(BC7,$C$64*F7/12)))) | BF7: =IF(OR(NOT(ISNUMBER(BC7)),NOT(ISNUMBER(AL7)),AL7=0),"",BC7/AL7) | BG7: =IF(NOT(ISNUMBER(AL7)),"",AL7*0.01) | BH7: =IF(OR(NOT(ISNUMBER(AL7)),NOT(ISNUMBER($C$28)),NOT(ISNUMBER(CD7)),CD7<=0),"",AL7*0.01*(1-$C$28)/CD7) | BI7: =IF(OR(NOT(ISNUMBER(K7)),NOT(ISNUMBER($H$30))),"",$H$30*K7) | BK7: =IF(OR(NOT(ISNUMBER(BI7)),NOT(ISNUMBER(AB7)),AB7<=0),"",1-BI7/AB7) | BL7: =IF(NOT(ISNUMBER(AB7)),"",IF(ISNUMBER(BJ7),BJ7,IF(AND(ISNUMBER(BI7),ISNUMBER(AE7),AE7>0),1-BI7/AE7,IF(NOT(ISNUMBER($C$31)),"",$C$31)))) | BM7: =IF(NOT(ISNUMBER(F7)),"",IF(ISNUMBER(BJ7),"vertrag",IF(ISNUMBER(BI7),"berechnet","standard"))) | BO7: =IF(NOT(ISNUMBER(F7)),"",IF(ISNUMBER(BN7),BN7,IF(NOT(ISNUMBER($C$30)),"",$C$30))) | BP7: =IF(OR(NOT(ISNUMBER(AE7)),NOT(ISNUMBER(BL7)),NOT(ISNUMBER($C$35))),"",AE7*(1+$C$35)*BL7) | BQ7: =IF(OR(NOT(ISNUMBER(BP7)),NOT(ISNUMBER(BO7)),NOT(ISNUMBER($C$35))),"",(BP7*BO7+N(U7)*(1+$C$35)*N($H$31)+N(V7)*(1+$C$35)*N($H$32))/12) | BR7: =IF(OR(NOT(ISNUMBER(AH7)),NOT(ISNUMBER($C$26))),"",AH7*$C$26/12) | BS7: =IF(OR(NOT(ISNUMBER(AH7)),NOT(ISNUMBER($C$26)),NOT(ISNUMBER($C$27))),"",ROUND(AH7*($C$26+$C$27)/12,0)) | BT7: =IF(OR(NOT(ISNUMBER(AS7)),NOT(ISNUMBER(BQ7)),NOT(ISNUMBER(BR7)),NOT(ISNUMBER(BC7))),"",AS7-BR7-BQ7-(BC7-N(BE7))) | BU7: =IF(OR(NOT(ISNUMBER(BT7)),NOT(ISNUMBER($C$28))),"",ROUND(-BT7*$C$28,0)) | BV7: =IF(OR(NOT(ISNUMBER(BE7)),NOT(ISNUMBER($C$28))),"",BE7*$C$28) | BW7: =IF(OR(NOT(ISNUMBER(AS7)),NOT(ISNUMBER(BS7)),NOT(ISNUMBER(BC7))),"",ROUND(AS7,0)-BS7-ROUND(BC7,0)) | BX7: =IF(OR(NOT(ISNUMBER(BW7)),NOT(ISNUMBER(BU7))),"",BW7+BU7) | BY7: =IF(OR(NOT(ISNUMBER(AR7)),NOT(ISNUMBER(BS7)),NOT(ISNUMBER(BC7)),NOT(ISNUMBER(BT7)),NOT(ISNUMBER($C$28))),"",ROUND(AR7,0)-BS7-ROUND(BC7,0)+ROUND(-(BT7-N(AN7))*$C$28,0)) | BZ7: =IF(OR(NOT(ISNUMBER(AA7)),NOT(ISNUMBER(AS7)),AS7=0),"",AA7/(AS7*12)) | CA7: =IF(OR(NOT(ISNUMBER(AA7)),NOT(ISNUMBER(AS7)),AA7=0),"",AS7*12/AA7) | CB7: =IF(OR(NOT(ISNUMBER(AS7)),NOT(ISNUMBER(BC7)),NOT(ISNUMBER(BO7)),NOT(ISNUMBER($C$28)),NOT(ISNUMBER($C$35))),"",(AS7-BC7)*(1-$C$28)-$C$28*N(BE7)-IF(BM7="berechnet",$C$28*(1+$C$35)*BO7*N(BI7)/12,0)) | CC7: =IF(OR(NOT(ISNUMBER(F7)),NOT(ISNUMBER($C$26)),NOT(ISNUMBER($C$27)),NOT(ISNUMBER($C$28)),NOT(ISNUMBER($C$35)),NOT(ISNUMBER($H$33))),"",($C$28*(1+$C$35)*(N(U7)*N($H$31)+N(V7)*N($H$32))-(N(U7)+N(V7))*$H$33*(($C$26+$C$27)-$C$28*$C$26))/12) | CD7: =IF(OR(NOT(ISNUMBER(BO7)),NOT(ISNUMBER($C$26)),NOT(ISNUMBER($C$27)),NOT(ISNUMBER($C$28)),NOT(ISNUMBER($C$35)),NOT(ISNUMBER($H$33)),BM7="",AND(BM7="standard",NOT(ISNUMBER($C$31)))),"",($H$33*(($C$26+$C$27)-$C$28*$C$26)-$C$28*(1+$C$35)*BO7*IF(BM7="berechnet",1,IF(BM7="vertrag",BJ7,$C$31)))/12) | CE7: =IF(NOT(ISNUMBER(F7)),"",IF(N($O$26)=2,IF(OR(NOT(ISNUMBER(AS7)),NOT(ISNUMBER(AN7)),IF(ISNUMBER(M7),M7,N($O$28))<=0),"",IF(AS7*12/IF(ISNUMBER(M7),M7,N($O$28))-N(U7)-N(V7)<=0,"",AS7*12/IF(ISNUMBER(M7),M7,N($O$28))-N(U7)-N(V7))),IF(N($O$26)=3,IF(OR(NOT(ISNUMBER(CB7)),NOT(ISNUMBER(CC7)),NOT(ISNUMBER(CD7)),N(CD7)<=0),"",IF((CB7+CC7+ROUND(AS7,0)-AS7-ROUND(BC7,0)+BC7-IF(ISNUMBER(N7),N7,N($O$29)))/CD7<=0,"",(CB7+CC7+ROUND(AS7,0)-AS7-ROUND(BC7,0)+BC7-IF(ISNUMBER(N7),N7,N($O$29)))/CD7)),"")))
A8: =IF(NOT(ISNUMBER(MIETER!F13)),"",ROW()-2) | B8: =IF(NOT(ISNUMBER(MIETER!F13)),"",IF(MIETER!A13="","",MIETER!A13)) | C8: =IF(NOT(ISNUMBER(MIETER!F13)),"",IF(MIETER!B13="","",MIETER!B13)) | D8: =IF(NOT(ISNUMBER(MIETER!F13)),"",IF(MIETER!C13="","",MIETER!C13)) | E8: =IF(NOT(ISNUMBER(MIETER!F13)),"",IF(MIETER!D13="","",MIETER!D13)) | F8: =IF(NOT(ISNUMBER(MIETER!F13)),"",MIETER!F13) | K8: =IF(OR(NOT(ISNUMBER(F8)),NOT(ISNUMBER(J8)),NOT(ISNUMBER($H$29)),$H$29=0),"",J8/$H$29) | O8: =IF(NOT(ISNUMBER(F8)),"",IF(NOT(ISNUMBER(T8)),"kein Preis",IF(ISNUMBER(CE8),IF(N($O$26)=2,"Rendite","Cashflow"),IF(OR(N($O$26)=2,N($O$26)=3),"Regler (Rückfall)","Regler")))) | P8: =IF(OR(NOT(ISNUMBER(T8)),NOT(ISNUMBER(F8)),F8=0),"",T8/F8) | Q8: =IF(OR(NOT(ISNUMBER(F8)),F8=0,NOT(ISNUMBER(VERKAUFSMATRIX!U11))),"",VERKAUFSMATRIX!U11/F8) | R8: =IF(OR(NOT(ISNUMBER(P8)),NOT(ISNUMBER(Q8)),Q8=0),"",P8/Q8-1) | T8: =IF(NOT(ISNUMBER(F8)),"",IF(ISNUMBER(CE8),IF(NOT(ISNUMBER(Y8)),"",(CE8+N(U8)+N(V8))/(1+Y8)-N(U8)-N(V8)),IF(NOT(ISNUMBER(L8)),"",F8*L8+N(S8)))) | W8: =IF(NOT(ISNUMBER(T8)),"",T8+N(U8)+N(V8)) | Y8: =IF(NOT(ISNUMBER(F8)),"",IF(ISNUMBER(X8),X8,IF(NOT(ISNUMBER($H$26)),"",$H$26))) | Z8: =IF(OR(NOT(ISNUMBER(W8)),NOT(ISNUMBER(Y8))),"",W8*Y8) | AA8: =IF(OR(NOT(ISNUMBER(W8)),NOT(ISNUMBER(Y8))),"",W8*(1+Y8)) | AB8: =IF(NOT(ISNUMBER(AA8)),"",AA8-N(U8)-N(V8)) | AC8: =IF(OR(NOT(ISNUMBER(W8)),NOT(ISNUMBER(F8)),F8=0),"",W8/F8) | AD8: =IF(OR(NOT(ISNUMBER(AB8)),NOT(ISNUMBER(F8)),F8=0),"",AB8/F8) | AE8: =IF(NOT(ISNUMBER(AB8)),"",AB8) | AF8: =IF(OR(NOT(ISNUMBER(AA8)),NOT(ISNUMBER($C$35))),"",AA8*$C$35) | AG8: =IF(OR(NOT(ISNUMBER(AA8)),NOT(ISNUMBER(AF8))),"",AA8+AF8) | AH8: =IF(OR(NOT(ISNUMBER(AA8)),NOT(ISNUMBER($H$33))),"",AA8*$H$33) | AI8: =IF(OR(NOT(ISNUMBER(AG8)),NOT(ISNUMBER(AH8))),"",MAX(0,AG8-AH8)) | AJ8: =IF(OR(NOT(ISNUMBER(AH8)),NOT(ISNUMBER(AA8))),"",AH8-AA8) | AL8: =IF(OR(NOT(ISNUMBER(MIETER!F13)),$G8="ja"),"",IF(NOT(ISNUMBER(MIETER!J13)),"",IF(ISNUMBER(AK8),MAX(MIETER!J13,AK8),MIETER!J13))) | AN8: =IF(OR(NOT(ISNUMBER(AL8)),NOT(ISNUMBER(AM8))),"",MAX(0,AM8-AL8)) | AR8: =IF(NOT(ISNUMBER(F8)),"",IF(AND(NOT(ISNUMBER(AL8)),NOT(ISNUMBER(AP8)),NOT(ISNUMBER(AQ8))),"",N(AL8)+N(AP8)+N(AQ8))) | AS8: =IF(OR($G8="ja",NOT(ISNUMBER(AL8)),NOT(ISNUMBER(AR8))),"",AR8+N(AN8)) | AT8: =IF(OR(NOT(ISNUMBER(AL8)),NOT(ISNUMBER(F8)),F8=0),"",AL8/F8) | AU8: =IF(OR(NOT(ISNUMBER(MIETER!F13)),NOT(ISNUMBER(MIETER!I13))),"",MIETER!I13) | AV8: =IF(OR(NOT(ISNUMBER(AU8)),$G8="ja",NOT(ISNUMBER($H$34))),"",EDATE(AU8,$H$34)) | AX8: =IF(NOT(ISNUMBER(F8)),"",IF(ISNUMBER(AW8),AW8,IF(NOT(ISNUMBER(AV8)),"",MAX(0,(YEAR(AV8)-YEAR(TODAY()))*12+MONTH(AV8)-MONTH(TODAY()))))) | AY8: =IF(NOT(ISNUMBER(AX8)),"",IF(ISNUMBER(AO8),AO8*AX8,IF(NOT(ISNUMBER(AN8)),"",AN8*AX8))) | AZ8: =IF(OR(NOT(ISNUMBER(AL8)),NOT(ISNUMBER(MIETER!$P$6))),"",ROUND(AL8*(1+MIETER!$P$6)^2,0)) | BC8: =IF(NOT(ISNUMBER(F8)),"",IF(ISNUMBER(BB8),BB8,IF(AND(ISNUMBER(BA8),ISNUMBER(AL8),AL8>0),AL8*BA8,IF(OR(NOT(ISNUMBER($C$62)),NOT(ISNUMBER($C$64))),"",$C$62+$C$64*F8/12)))) | BE8: =IF(NOT(ISNUMBER(BC8)),"",IF(ISNUMBER(BD8),MIN(BC8,BD8),IF(OR(NOT(ISNUMBER(F8)),NOT(ISNUMBER($C$64))),0,MIN(BC8,$C$64*F8/12)))) | BF8: =IF(OR(NOT(ISNUMBER(BC8)),NOT(ISNUMBER(AL8)),AL8=0),"",BC8/AL8) | BG8: =IF(NOT(ISNUMBER(AL8)),"",AL8*0.01) | BH8: =IF(OR(NOT(ISNUMBER(AL8)),NOT(ISNUMBER($C$28)),NOT(ISNUMBER(CD8)),CD8<=0),"",AL8*0.01*(1-$C$28)/CD8) | BI8: =IF(OR(NOT(ISNUMBER(K8)),NOT(ISNUMBER($H$30))),"",$H$30*K8) | BK8: =IF(OR(NOT(ISNUMBER(BI8)),NOT(ISNUMBER(AB8)),AB8<=0),"",1-BI8/AB8) | BL8: =IF(NOT(ISNUMBER(AB8)),"",IF(ISNUMBER(BJ8),BJ8,IF(AND(ISNUMBER(BI8),ISNUMBER(AE8),AE8>0),1-BI8/AE8,IF(NOT(ISNUMBER($C$31)),"",$C$31)))) | BM8: =IF(NOT(ISNUMBER(F8)),"",IF(ISNUMBER(BJ8),"vertrag",IF(ISNUMBER(BI8),"berechnet","standard"))) | BO8: =IF(NOT(ISNUMBER(F8)),"",IF(ISNUMBER(BN8),BN8,IF(NOT(ISNUMBER($C$30)),"",$C$30))) | BP8: =IF(OR(NOT(ISNUMBER(AE8)),NOT(ISNUMBER(BL8)),NOT(ISNUMBER($C$35))),"",AE8*(1+$C$35)*BL8) | BQ8: =IF(OR(NOT(ISNUMBER(BP8)),NOT(ISNUMBER(BO8)),NOT(ISNUMBER($C$35))),"",(BP8*BO8+N(U8)*(1+$C$35)*N($H$31)+N(V8)*(1+$C$35)*N($H$32))/12) | BR8: =IF(OR(NOT(ISNUMBER(AH8)),NOT(ISNUMBER($C$26))),"",AH8*$C$26/12) | BS8: =IF(OR(NOT(ISNUMBER(AH8)),NOT(ISNUMBER($C$26)),NOT(ISNUMBER($C$27))),"",ROUND(AH8*($C$26+$C$27)/12,0)) | BT8: =IF(OR(NOT(ISNUMBER(AS8)),NOT(ISNUMBER(BQ8)),NOT(ISNUMBER(BR8)),NOT(ISNUMBER(BC8))),"",AS8-BR8-BQ8-(BC8-N(BE8))) | BU8: =IF(OR(NOT(ISNUMBER(BT8)),NOT(ISNUMBER($C$28))),"",ROUND(-BT8*$C$28,0)) | BV8: =IF(OR(NOT(ISNUMBER(BE8)),NOT(ISNUMBER($C$28))),"",BE8*$C$28) | BW8: =IF(OR(NOT(ISNUMBER(AS8)),NOT(ISNUMBER(BS8)),NOT(ISNUMBER(BC8))),"",ROUND(AS8,0)-BS8-ROUND(BC8,0)) | BX8: =IF(OR(NOT(ISNUMBER(BW8)),NOT(ISNUMBER(BU8))),"",BW8+BU8) | BY8: =IF(OR(NOT(ISNUMBER(AR8)),NOT(ISNUMBER(BS8)),NOT(ISNUMBER(BC8)),NOT(ISNUMBER(BT8)),NOT(ISNUMBER($C$28))),"",ROUND(AR8,0)-BS8-ROUND(BC8,0)+ROUND(-(BT8-N(AN8))*$C$28,0)) | BZ8: =IF(OR(NOT(ISNUMBER(AA8)),NOT(ISNUMBER(AS8)),AS8=0),"",AA8/(AS8*12)) | CA8: =IF(OR(NOT(ISNUMBER(AA8)),NOT(ISNUMBER(AS8)),AA8=0),"",AS8*12/AA8) | CB8: =IF(OR(NOT(ISNUMBER(AS8)),NOT(ISNUMBER(BC8)),NOT(ISNUMBER(BO8)),NOT(ISNUMBER($C$28)),NOT(ISNUMBER($C$35))),"",(AS8-BC8)*(1-$C$28)-$C$28*N(BE8)-IF(BM8="berechnet",$C$28*(1+$C$35)*BO8*N(BI8)/12,0)) | CC8: =IF(OR(NOT(ISNUMBER(F8)),NOT(ISNUMBER($C$26)),NOT(ISNUMBER($C$27)),NOT(ISNUMBER($C$28)),NOT(ISNUMBER($C$35)),NOT(ISNUMBER($H$33))),"",($C$28*(1+$C$35)*(N(U8)*N($H$31)+N(V8)*N($H$32))-(N(U8)+N(V8))*$H$33*(($C$26+$C$27)-$C$28*$C$26))/12) | CD8: =IF(OR(NOT(ISNUMBER(BO8)),NOT(ISNUMBER($C$26)),NOT(ISNUMBER($C$27)),NOT(ISNUMBER($C$28)),NOT(ISNUMBER($C$35)),NOT(ISNUMBER($H$33)),BM8="",AND(BM8="standard",NOT(ISNUMBER($C$31)))),"",($H$33*(($C$26+$C$27)-$C$28*$C$26)-$C$28*(1+$C$35)*BO8*IF(BM8="berechnet",1,IF(BM8="vertrag",BJ8,$C$31)))/12) | CE8: =IF(NOT(ISNUMBER(F8)),"",IF(N($O$26)=2,IF(OR(NOT(ISNUMBER(AS8)),NOT(ISNUMBER(AN8)),IF(ISNUMBER(M8),M8,N($O$28))<=0),"",IF(AS8*12/IF(ISNUMBER(M8),M8,N($O$28))-N(U8)-N(V8)<=0,"",AS8*12/IF(ISNUMBER(M8),M8,N($O$28))-N(U8)-N(V8))),IF(N($O$26)=3,IF(OR(NOT(ISNUMBER(CB8)),NOT(ISNUMBER(CC8)),NOT(ISNUMBER(CD8)),N(CD8)<=0),"",IF((CB8+CC8+ROUND(AS8,0)-AS8-ROUND(BC8,0)+BC8-IF(ISNUMBER(N8),N8,N($O$29)))/CD8<=0,"",(CB8+CC8+ROUND(AS8,0)-AS8-ROUND(BC8,0)+BC8-IF(ISNUMBER(N8),N8,N($O$29)))/CD8)),"")))
A9: =IF(NOT(ISNUMBER(MIETER!F14)),"",ROW()-2) | B9: =IF(NOT(ISNUMBER(MIETER!F14)),"",IF(MIETER!A14="","",MIETER!A14)) | C9: =IF(NOT(ISNUMBER(MIETER!F14)),"",IF(MIETER!B14="","",MIETER!B14)) | D9: =IF(NOT(ISNUMBER(MIETER!F14)),"",IF(MIETER!C14="","",MIETER!C14)) | E9: =IF(NOT(ISNUMBER(MIETER!F14)),"",IF(MIETER!D14="","",MIETER!D14)) | F9: =IF(NOT(ISNUMBER(MIETER!F14)),"",MIETER!F14) | K9: =IF(OR(NOT(ISNUMBER(F9)),NOT(ISNUMBER(J9)),NOT(ISNUMBER($H$29)),$H$29=0),"",J9/$H$29) | O9: =IF(NOT(ISNUMBER(F9)),"",IF(NOT(ISNUMBER(T9)),"kein Preis",IF(ISNUMBER(CE9),IF(N($O$26)=2,"Rendite","Cashflow"),IF(OR(N($O$26)=2,N($O$26)=3),"Regler (Rückfall)","Regler")))) | P9: =IF(OR(NOT(ISNUMBER(T9)),NOT(ISNUMBER(F9)),F9=0),"",T9/F9) | Q9: =IF(OR(NOT(ISNUMBER(F9)),F9=0,NOT(ISNUMBER(VERKAUFSMATRIX!U12))),"",VERKAUFSMATRIX!U12/F9) | R9: =IF(OR(NOT(ISNUMBER(P9)),NOT(ISNUMBER(Q9)),Q9=0),"",P9/Q9-1) | T9: =IF(NOT(ISNUMBER(F9)),"",IF(ISNUMBER(CE9),IF(NOT(ISNUMBER(Y9)),"",(CE9+N(U9)+N(V9))/(1+Y9)-N(U9)-N(V9)),IF(NOT(ISNUMBER(L9)),"",F9*L9+N(S9)))) | W9: =IF(NOT(ISNUMBER(T9)),"",T9+N(U9)+N(V9)) | Y9: =IF(NOT(ISNUMBER(F9)),"",IF(ISNUMBER(X9),X9,IF(NOT(ISNUMBER($H$26)),"",$H$26))) | Z9: =IF(OR(NOT(ISNUMBER(W9)),NOT(ISNUMBER(Y9))),"",W9*Y9) | AA9: =IF(OR(NOT(ISNUMBER(W9)),NOT(ISNUMBER(Y9))),"",W9*(1+Y9)) | AB9: =IF(NOT(ISNUMBER(AA9)),"",AA9-N(U9)-N(V9)) | AC9: =IF(OR(NOT(ISNUMBER(W9)),NOT(ISNUMBER(F9)),F9=0),"",W9/F9) | AD9: =IF(OR(NOT(ISNUMBER(AB9)),NOT(ISNUMBER(F9)),F9=0),"",AB9/F9) | AE9: =IF(NOT(ISNUMBER(AB9)),"",AB9) | AF9: =IF(OR(NOT(ISNUMBER(AA9)),NOT(ISNUMBER($C$35))),"",AA9*$C$35) | AG9: =IF(OR(NOT(ISNUMBER(AA9)),NOT(ISNUMBER(AF9))),"",AA9+AF9) | AH9: =IF(OR(NOT(ISNUMBER(AA9)),NOT(ISNUMBER($H$33))),"",AA9*$H$33) | AI9: =IF(OR(NOT(ISNUMBER(AG9)),NOT(ISNUMBER(AH9))),"",MAX(0,AG9-AH9)) | AJ9: =IF(OR(NOT(ISNUMBER(AH9)),NOT(ISNUMBER(AA9))),"",AH9-AA9) | AL9: =IF(OR(NOT(ISNUMBER(MIETER!F14)),$G9="ja"),"",IF(NOT(ISNUMBER(MIETER!J14)),"",IF(ISNUMBER(AK9),MAX(MIETER!J14,AK9),MIETER!J14))) | AN9: =IF(OR(NOT(ISNUMBER(AL9)),NOT(ISNUMBER(AM9))),"",MAX(0,AM9-AL9)) | AR9: =IF(NOT(ISNUMBER(F9)),"",IF(AND(NOT(ISNUMBER(AL9)),NOT(ISNUMBER(AP9)),NOT(ISNUMBER(AQ9))),"",N(AL9)+N(AP9)+N(AQ9))) | AS9: =IF(OR($G9="ja",NOT(ISNUMBER(AL9)),NOT(ISNUMBER(AR9))),"",AR9+N(AN9)) | AT9: =IF(OR(NOT(ISNUMBER(AL9)),NOT(ISNUMBER(F9)),F9=0),"",AL9/F9) | AU9: =IF(OR(NOT(ISNUMBER(MIETER!F14)),NOT(ISNUMBER(MIETER!I14))),"",MIETER!I14) | AV9: =IF(OR(NOT(ISNUMBER(AU9)),$G9="ja",NOT(ISNUMBER($H$34))),"",EDATE(AU9,$H$34)) | AX9: =IF(NOT(ISNUMBER(F9)),"",IF(ISNUMBER(AW9),AW9,IF(NOT(ISNUMBER(AV9)),"",MAX(0,(YEAR(AV9)-YEAR(TODAY()))*12+MONTH(AV9)-MONTH(TODAY()))))) | AY9: =IF(NOT(ISNUMBER(AX9)),"",IF(ISNUMBER(AO9),AO9*AX9,IF(NOT(ISNUMBER(AN9)),"",AN9*AX9))) | AZ9: =IF(OR(NOT(ISNUMBER(AL9)),NOT(ISNUMBER(MIETER!$P$6))),"",ROUND(AL9*(1+MIETER!$P$6)^2,0)) | BC9: =IF(NOT(ISNUMBER(F9)),"",IF(ISNUMBER(BB9),BB9,IF(AND(ISNUMBER(BA9),ISNUMBER(AL9),AL9>0),AL9*BA9,IF(OR(NOT(ISNUMBER($C$62)),NOT(ISNUMBER($C$64))),"",$C$62+$C$64*F9/12)))) | BE9: =IF(NOT(ISNUMBER(BC9)),"",IF(ISNUMBER(BD9),MIN(BC9,BD9),IF(OR(NOT(ISNUMBER(F9)),NOT(ISNUMBER($C$64))),0,MIN(BC9,$C$64*F9/12)))) | BF9: =IF(OR(NOT(ISNUMBER(BC9)),NOT(ISNUMBER(AL9)),AL9=0),"",BC9/AL9) | BG9: =IF(NOT(ISNUMBER(AL9)),"",AL9*0.01) | BH9: =IF(OR(NOT(ISNUMBER(AL9)),NOT(ISNUMBER($C$28)),NOT(ISNUMBER(CD9)),CD9<=0),"",AL9*0.01*(1-$C$28)/CD9) | BI9: =IF(OR(NOT(ISNUMBER(K9)),NOT(ISNUMBER($H$30))),"",$H$30*K9) | BK9: =IF(OR(NOT(ISNUMBER(BI9)),NOT(ISNUMBER(AB9)),AB9<=0),"",1-BI9/AB9) | BL9: =IF(NOT(ISNUMBER(AB9)),"",IF(ISNUMBER(BJ9),BJ9,IF(AND(ISNUMBER(BI9),ISNUMBER(AE9),AE9>0),1-BI9/AE9,IF(NOT(ISNUMBER($C$31)),"",$C$31)))) | BM9: =IF(NOT(ISNUMBER(F9)),"",IF(ISNUMBER(BJ9),"vertrag",IF(ISNUMBER(BI9),"berechnet","standard"))) | BO9: =IF(NOT(ISNUMBER(F9)),"",IF(ISNUMBER(BN9),BN9,IF(NOT(ISNUMBER($C$30)),"",$C$30))) | BP9: =IF(OR(NOT(ISNUMBER(AE9)),NOT(ISNUMBER(BL9)),NOT(ISNUMBER($C$35))),"",AE9*(1+$C$35)*BL9) | BQ9: =IF(OR(NOT(ISNUMBER(BP9)),NOT(ISNUMBER(BO9)),NOT(ISNUMBER($C$35))),"",(BP9*BO9+N(U9)*(1+$C$35)*N($H$31)+N(V9)*(1+$C$35)*N($H$32))/12) | BR9: =IF(OR(NOT(ISNUMBER(AH9)),NOT(ISNUMBER($C$26))),"",AH9*$C$26/12) | BS9: =IF(OR(NOT(ISNUMBER(AH9)),NOT(ISNUMBER($C$26)),NOT(ISNUMBER($C$27))),"",ROUND(AH9*($C$26+$C$27)/12,0)) | BT9: =IF(OR(NOT(ISNUMBER(AS9)),NOT(ISNUMBER(BQ9)),NOT(ISNUMBER(BR9)),NOT(ISNUMBER(BC9))),"",AS9-BR9-BQ9-(BC9-N(BE9))) | BU9: =IF(OR(NOT(ISNUMBER(BT9)),NOT(ISNUMBER($C$28))),"",ROUND(-BT9*$C$28,0)) | BV9: =IF(OR(NOT(ISNUMBER(BE9)),NOT(ISNUMBER($C$28))),"",BE9*$C$28) | BW9: =IF(OR(NOT(ISNUMBER(AS9)),NOT(ISNUMBER(BS9)),NOT(ISNUMBER(BC9))),"",ROUND(AS9,0)-BS9-ROUND(BC9,0)) | BX9: =IF(OR(NOT(ISNUMBER(BW9)),NOT(ISNUMBER(BU9))),"",BW9+BU9) | BY9: =IF(OR(NOT(ISNUMBER(AR9)),NOT(ISNUMBER(BS9)),NOT(ISNUMBER(BC9)),NOT(ISNUMBER(BT9)),NOT(ISNUMBER($C$28))),"",ROUND(AR9,0)-BS9-ROUND(BC9,0)+ROUND(-(BT9-N(AN9))*$C$28,0)) | BZ9: =IF(OR(NOT(ISNUMBER(AA9)),NOT(ISNUMBER(AS9)),AS9=0),"",AA9/(AS9*12)) | CA9: =IF(OR(NOT(ISNUMBER(AA9)),NOT(ISNUMBER(AS9)),AA9=0),"",AS9*12/AA9) | CB9: =IF(OR(NOT(ISNUMBER(AS9)),NOT(ISNUMBER(BC9)),NOT(ISNUMBER(BO9)),NOT(ISNUMBER($C$28)),NOT(ISNUMBER($C$35))),"",(AS9-BC9)*(1-$C$28)-$C$28*N(BE9)-IF(BM9="berechnet",$C$28*(1+$C$35)*BO9*N(BI9)/12,0)) | CC9: =IF(OR(NOT(ISNUMBER(F9)),NOT(ISNUMBER($C$26)),NOT(ISNUMBER($C$27)),NOT(ISNUMBER($C$28)),NOT(ISNUMBER($C$35)),NOT(ISNUMBER($H$33))),"",($C$28*(1+$C$35)*(N(U9)*N($H$31)+N(V9)*N($H$32))-(N(U9)+N(V9))*$H$33*(($C$26+$C$27)-$C$28*$C$26))/12) | CD9: =IF(OR(NOT(ISNUMBER(BO9)),NOT(ISNUMBER($C$26)),NOT(ISNUMBER($C$27)),NOT(ISNUMBER($C$28)),NOT(ISNUMBER($C$35)),NOT(ISNUMBER($H$33)),BM9="",AND(BM9="standard",NOT(ISNUMBER($C$31)))),"",($H$33*(($C$26+$C$27)-$C$28*$C$26)-$C$28*(1+$C$35)*BO9*IF(BM9="berechnet",1,IF(BM9="vertrag",BJ9,$C$31)))/12) | CE9: =IF(NOT(ISNUMBER(F9)),"",IF(N($O$26)=2,IF(OR(NOT(ISNUMBER(AS9)),NOT(ISNUMBER(AN9)),IF(ISNUMBER(M9),M9,N($O$28))<=0),"",IF(AS9*12/IF(ISNUMBER(M9),M9,N($O$28))-N(U9)-N(V9)<=0,"",AS9*12/IF(ISNUMBER(M9),M9,N($O$28))-N(U9)-N(V9))),IF(N($O$26)=3,IF(OR(NOT(ISNUMBER(CB9)),NOT(ISNUMBER(CC9)),NOT(ISNUMBER(CD9)),N(CD9)<=0),"",IF((CB9+CC9+ROUND(AS9,0)-AS9-ROUND(BC9,0)+BC9-IF(ISNUMBER(N9),N9,N($O$29)))/CD9<=0,"",(CB9+CC9+ROUND(AS9,0)-AS9-ROUND(BC9,0)+BC9-IF(ISNUMBER(N9),N9,N($O$29)))/CD9)),"")))
A10: =IF(NOT(ISNUMBER(MIETER!F15)),"",ROW()-2) | B10: =IF(NOT(ISNUMBER(MIETER!F15)),"",IF(MIETER!A15="","",MIETER!A15)) | C10: =IF(NOT(ISNUMBER(MIETER!F15)),"",IF(MIETER!B15="","",MIETER!B15)) | D10: =IF(NOT(ISNUMBER(MIETER!F15)),"",IF(MIETER!C15="","",MIETER!C15)) | E10: =IF(NOT(ISNUMBER(MIETER!F15)),"",IF(MIETER!D15="","",MIETER!D15)) | F10: =IF(NOT(ISNUMBER(MIETER!F15)),"",MIETER!F15) | K10: =IF(OR(NOT(ISNUMBER(F10)),NOT(ISNUMBER(J10)),NOT(ISNUMBER($H$29)),$H$29=0),"",J10/$H$29) | O10: =IF(NOT(ISNUMBER(F10)),"",IF(NOT(ISNUMBER(T10)),"kein Preis",IF(ISNUMBER(CE10),IF(N($O$26)=2,"Rendite","Cashflow"),IF(OR(N($O$26)=2,N($O$26)=3),"Regler (Rückfall)","Regler")))) | P10: =IF(OR(NOT(ISNUMBER(T10)),NOT(ISNUMBER(F10)),F10=0),"",T10/F10) | Q10: =IF(OR(NOT(ISNUMBER(F10)),F10=0,NOT(ISNUMBER(VERKAUFSMATRIX!U13))),"",VERKAUFSMATRIX!U13/F10) | R10: =IF(OR(NOT(ISNUMBER(P10)),NOT(ISNUMBER(Q10)),Q10=0),"",P10/Q10-1) | T10: =IF(NOT(ISNUMBER(F10)),"",IF(ISNUMBER(CE10),IF(NOT(ISNUMBER(Y10)),"",(CE10+N(U10)+N(V10))/(1+Y10)-N(U10)-N(V10)),IF(NOT(ISNUMBER(L10)),"",F10*L10+N(S10)))) | W10: =IF(NOT(ISNUMBER(T10)),"",T10+N(U10)+N(V10)) | Y10: =IF(NOT(ISNUMBER(F10)),"",IF(ISNUMBER(X10),X10,IF(NOT(ISNUMBER($H$26)),"",$H$26))) | Z10: =IF(OR(NOT(ISNUMBER(W10)),NOT(ISNUMBER(Y10))),"",W10*Y10) | AA10: =IF(OR(NOT(ISNUMBER(W10)),NOT(ISNUMBER(Y10))),"",W10*(1+Y10)) | AB10: =IF(NOT(ISNUMBER(AA10)),"",AA10-N(U10)-N(V10)) | AC10: =IF(OR(NOT(ISNUMBER(W10)),NOT(ISNUMBER(F10)),F10=0),"",W10/F10) | AD10: =IF(OR(NOT(ISNUMBER(AB10)),NOT(ISNUMBER(F10)),F10=0),"",AB10/F10) | AE10: =IF(NOT(ISNUMBER(AB10)),"",AB10) | AF10: =IF(OR(NOT(ISNUMBER(AA10)),NOT(ISNUMBER($C$35))),"",AA10*$C$35) | AG10: =IF(OR(NOT(ISNUMBER(AA10)),NOT(ISNUMBER(AF10))),"",AA10+AF10) | AH10: =IF(OR(NOT(ISNUMBER(AA10)),NOT(ISNUMBER($H$33))),"",AA10*$H$33) | AI10: =IF(OR(NOT(ISNUMBER(AG10)),NOT(ISNUMBER(AH10))),"",MAX(0,AG10-AH10)) | AJ10: =IF(OR(NOT(ISNUMBER(AH10)),NOT(ISNUMBER(AA10))),"",AH10-AA10) | AL10: =IF(OR(NOT(ISNUMBER(MIETER!F15)),$G10="ja"),"",IF(NOT(ISNUMBER(MIETER!J15)),"",IF(ISNUMBER(AK10),MAX(MIETER!J15,AK10),MIETER!J15))) | AN10: =IF(OR(NOT(ISNUMBER(AL10)),NOT(ISNUMBER(AM10))),"",MAX(0,AM10-AL10)) | AR10: =IF(NOT(ISNUMBER(F10)),"",IF(AND(NOT(ISNUMBER(AL10)),NOT(ISNUMBER(AP10)),NOT(ISNUMBER(AQ10))),"",N(AL10)+N(AP10)+N(AQ10))) | AS10: =IF(OR($G10="ja",NOT(ISNUMBER(AL10)),NOT(ISNUMBER(AR10))),"",AR10+N(AN10)) | AT10: =IF(OR(NOT(ISNUMBER(AL10)),NOT(ISNUMBER(F10)),F10=0),"",AL10/F10) | AU10: =IF(OR(NOT(ISNUMBER(MIETER!F15)),NOT(ISNUMBER(MIETER!I15))),"",MIETER!I15) | AV10: =IF(OR(NOT(ISNUMBER(AU10)),$G10="ja",NOT(ISNUMBER($H$34))),"",EDATE(AU10,$H$34)) | AX10: =IF(NOT(ISNUMBER(F10)),"",IF(ISNUMBER(AW10),AW10,IF(NOT(ISNUMBER(AV10)),"",MAX(0,(YEAR(AV10)-YEAR(TODAY()))*12+MONTH(AV10)-MONTH(TODAY()))))) | AY10: =IF(NOT(ISNUMBER(AX10)),"",IF(ISNUMBER(AO10),AO10*AX10,IF(NOT(ISNUMBER(AN10)),"",AN10*AX10))) | AZ10: =IF(OR(NOT(ISNUMBER(AL10)),NOT(ISNUMBER(MIETER!$P$6))),"",ROUND(AL10*(1+MIETER!$P$6)^2,0)) | BC10: =IF(NOT(ISNUMBER(F10)),"",IF(ISNUMBER(BB10),BB10,IF(AND(ISNUMBER(BA10),ISNUMBER(AL10),AL10>0),AL10*BA10,IF(OR(NOT(ISNUMBER($C$62)),NOT(ISNUMBER($C$64))),"",$C$62+$C$64*F10/12)))) | BE10: =IF(NOT(ISNUMBER(BC10)),"",IF(ISNUMBER(BD10),MIN(BC10,BD10),IF(OR(NOT(ISNUMBER(F10)),NOT(ISNUMBER($C$64))),0,MIN(BC10,$C$64*F10/12)))) | BF10: =IF(OR(NOT(ISNUMBER(BC10)),NOT(ISNUMBER(AL10)),AL10=0),"",BC10/AL10) | BG10: =IF(NOT(ISNUMBER(AL10)),"",AL10*0.01) | BH10: =IF(OR(NOT(ISNUMBER(AL10)),NOT(ISNUMBER($C$28)),NOT(ISNUMBER(CD10)),CD10<=0),"",AL10*0.01*(1-$C$28)/CD10) | BI10: =IF(OR(NOT(ISNUMBER(K10)),NOT(ISNUMBER($H$30))),"",$H$30*K10) | BK10: =IF(OR(NOT(ISNUMBER(BI10)),NOT(ISNUMBER(AB10)),AB10<=0),"",1-BI10/AB10) | BL10: =IF(NOT(ISNUMBER(AB10)),"",IF(ISNUMBER(BJ10),BJ10,IF(AND(ISNUMBER(BI10),ISNUMBER(AE10),AE10>0),1-BI10/AE10,IF(NOT(ISNUMBER($C$31)),"",$C$31)))) | BM10: =IF(NOT(ISNUMBER(F10)),"",IF(ISNUMBER(BJ10),"vertrag",IF(ISNUMBER(BI10),"berechnet","standard"))) | BO10: =IF(NOT(ISNUMBER(F10)),"",IF(ISNUMBER(BN10),BN10,IF(NOT(ISNUMBER($C$30)),"",$C$30))) | BP10: =IF(OR(NOT(ISNUMBER(AE10)),NOT(ISNUMBER(BL10)),NOT(ISNUMBER($C$35))),"",AE10*(1+$C$35)*BL10) | BQ10: =IF(OR(NOT(ISNUMBER(BP10)),NOT(ISNUMBER(BO10)),NOT(ISNUMBER($C$35))),"",(BP10*BO10+N(U10)*(1+$C$35)*N($H$31)+N(V10)*(1+$C$35)*N($H$32))/12) | BR10: =IF(OR(NOT(ISNUMBER(AH10)),NOT(ISNUMBER($C$26))),"",AH10*$C$26/12) | BS10: =IF(OR(NOT(ISNUMBER(AH10)),NOT(ISNUMBER($C$26)),NOT(ISNUMBER($C$27))),"",ROUND(AH10*($C$26+$C$27)/12,0)) | BT10: =IF(OR(NOT(ISNUMBER(AS10)),NOT(ISNUMBER(BQ10)),NOT(ISNUMBER(BR10)),NOT(ISNUMBER(BC10))),"",AS10-BR10-BQ10-(BC10-N(BE10))) | BU10: =IF(OR(NOT(ISNUMBER(BT10)),NOT(ISNUMBER($C$28))),"",ROUND(-BT10*$C$28,0)) | BV10: =IF(OR(NOT(ISNUMBER(BE10)),NOT(ISNUMBER($C$28))),"",BE10*$C$28) | BW10: =IF(OR(NOT(ISNUMBER(AS10)),NOT(ISNUMBER(BS10)),NOT(ISNUMBER(BC10))),"",ROUND(AS10,0)-BS10-ROUND(BC10,0)) | BX10: =IF(OR(NOT(ISNUMBER(BW10)),NOT(ISNUMBER(BU10))),"",BW10+BU10) | BY10: =IF(OR(NOT(ISNUMBER(AR10)),NOT(ISNUMBER(BS10)),NOT(ISNUMBER(BC10)),NOT(ISNUMBER(BT10)),NOT(ISNUMBER($C$28))),"",ROUND(AR10,0)-BS10-ROUND(BC10,0)+ROUND(-(BT10-N(AN10))*$C$28,0)) | BZ10: =IF(OR(NOT(ISNUMBER(AA10)),NOT(ISNUMBER(AS10)),AS10=0),"",AA10/(AS10*12)) | CA10: =IF(OR(NOT(ISNUMBER(AA10)),NOT(ISNUMBER(AS10)),AA10=0),"",AS10*12/AA10) | CB10: =IF(OR(NOT(ISNUMBER(AS10)),NOT(ISNUMBER(BC10)),NOT(ISNUMBER(BO10)),NOT(ISNUMBER($C$28)),NOT(ISNUMBER($C$35))),"",(AS10-BC10)*(1-$C$28)-$C$28*N(BE10)-IF(BM10="berechnet",$C$28*(1+$C$35)*BO10*N(BI10)/12,0)) | CC10: =IF(OR(NOT(ISNUMBER(F10)),NOT(ISNUMBER($C$26)),NOT(ISNUMBER($C$27)),NOT(ISNUMBER($C$28)),NOT(ISNUMBER($C$35)),NOT(ISNUMBER($H$33))),"",($C$28*(1+$C$35)*(N(U10)*N($H$31)+N(V10)*N($H$32))-(N(U10)+N(V10))*$H$33*(($C$26+$C$27)-$C$28*$C$26))/12) | CD10: =IF(OR(NOT(ISNUMBER(BO10)),NOT(ISNUMBER($C$26)),NOT(ISNUMBER($C$27)),NOT(ISNUMBER($C$28)),NOT(ISNUMBER($C$35)),NOT(ISNUMBER($H$33)),BM10="",AND(BM10="standard",NOT(ISNUMBER($C$31)))),"",($H$33*(($C$26+$C$27)-$C$28*$C$26)-$C$28*(1+$C$35)*BO10*IF(BM10="berechnet",1,IF(BM10="vertrag",BJ10,$C$31)))/12) | CE10: =IF(NOT(ISNUMBER(F10)),"",IF(N($O$26)=2,IF(OR(NOT(ISNUMBER(AS10)),NOT(ISNUMBER(AN10)),IF(ISNUMBER(M10),M10,N($O$28))<=0),"",IF(AS10*12/IF(ISNUMBER(M10),M10,N($O$28))-N(U10)-N(V10)<=0,"",AS10*12/IF(ISNUMBER(M10),M10,N($O$28))-N(U10)-N(V10))),IF(N($O$26)=3,IF(OR(NOT(ISNUMBER(CB10)),NOT(ISNUMBER(CC10)),NOT(ISNUMBER(CD10)),N(CD10)<=0),"",IF((CB10+CC10+ROUND(AS10,0)-AS10-ROUND(BC10,0)+BC10-IF(ISNUMBER(N10),N10,N($O$29)))/CD10<=0,"",(CB10+CC10+ROUND(AS10,0)-AS10-ROUND(BC10,0)+BC10-IF(ISNUMBER(N10),N10,N($O$29)))/CD10)),"")))
A11: =IF(NOT(ISNUMBER(MIETER!F16)),"",ROW()-2) | B11: =IF(NOT(ISNUMBER(MIETER!F16)),"",IF(MIETER!A16="","",MIETER!A16)) | C11: =IF(NOT(ISNUMBER(MIETER!F16)),"",IF(MIETER!B16="","",MIETER!B16)) | D11: =IF(NOT(ISNUMBER(MIETER!F16)),"",IF(MIETER!C16="","",MIETER!C16)) | E11: =IF(NOT(ISNUMBER(MIETER!F16)),"",IF(MIETER!D16="","",MIETER!D16)) | F11: =IF(NOT(ISNUMBER(MIETER!F16)),"",MIETER!F16) | K11: =IF(OR(NOT(ISNUMBER(F11)),NOT(ISNUMBER(J11)),NOT(ISNUMBER($H$29)),$H$29=0),"",J11/$H$29) | O11: =IF(NOT(ISNUMBER(F11)),"",IF(NOT(ISNUMBER(T11)),"kein Preis",IF(ISNUMBER(CE11),IF(N($O$26)=2,"Rendite","Cashflow"),IF(OR(N($O$26)=2,N($O$26)=3),"Regler (Rückfall)","Regler")))) | P11: =IF(OR(NOT(ISNUMBER(T11)),NOT(ISNUMBER(F11)),F11=0),"",T11/F11) | Q11: =IF(OR(NOT(ISNUMBER(F11)),F11=0,NOT(ISNUMBER(VERKAUFSMATRIX!U14))),"",VERKAUFSMATRIX!U14/F11) | R11: =IF(OR(NOT(ISNUMBER(P11)),NOT(ISNUMBER(Q11)),Q11=0),"",P11/Q11-1) | T11: =IF(NOT(ISNUMBER(F11)),"",IF(ISNUMBER(CE11),IF(NOT(ISNUMBER(Y11)),"",(CE11+N(U11)+N(V11))/(1+Y11)-N(U11)-N(V11)),IF(NOT(ISNUMBER(L11)),"",F11*L11+N(S11)))) | W11: =IF(NOT(ISNUMBER(T11)),"",T11+N(U11)+N(V11)) | Y11: =IF(NOT(ISNUMBER(F11)),"",IF(ISNUMBER(X11),X11,IF(NOT(ISNUMBER($H$26)),"",$H$26))) | Z11: =IF(OR(NOT(ISNUMBER(W11)),NOT(ISNUMBER(Y11))),"",W11*Y11) | AA11: =IF(OR(NOT(ISNUMBER(W11)),NOT(ISNUMBER(Y11))),"",W11*(1+Y11)) | AB11: =IF(NOT(ISNUMBER(AA11)),"",AA11-N(U11)-N(V11)) | AC11: =IF(OR(NOT(ISNUMBER(W11)),NOT(ISNUMBER(F11)),F11=0),"",W11/F11) | AD11: =IF(OR(NOT(ISNUMBER(AB11)),NOT(ISNUMBER(F11)),F11=0),"",AB11/F11) | AE11: =IF(NOT(ISNUMBER(AB11)),"",AB11) | AF11: =IF(OR(NOT(ISNUMBER(AA11)),NOT(ISNUMBER($C$35))),"",AA11*$C$35) | AG11: =IF(OR(NOT(ISNUMBER(AA11)),NOT(ISNUMBER(AF11))),"",AA11+AF11) | AH11: =IF(OR(NOT(ISNUMBER(AA11)),NOT(ISNUMBER($H$33))),"",AA11*$H$33) | AI11: =IF(OR(NOT(ISNUMBER(AG11)),NOT(ISNUMBER(AH11))),"",MAX(0,AG11-AH11)) | AJ11: =IF(OR(NOT(ISNUMBER(AH11)),NOT(ISNUMBER(AA11))),"",AH11-AA11) | AL11: =IF(OR(NOT(ISNUMBER(MIETER!F16)),$G11="ja"),"",IF(NOT(ISNUMBER(MIETER!J16)),"",IF(ISNUMBER(AK11),MAX(MIETER!J16,AK11),MIETER!J16))) | AN11: =IF(OR(NOT(ISNUMBER(AL11)),NOT(ISNUMBER(AM11))),"",MAX(0,AM11-AL11)) | AR11: =IF(NOT(ISNUMBER(F11)),"",IF(AND(NOT(ISNUMBER(AL11)),NOT(ISNUMBER(AP11)),NOT(ISNUMBER(AQ11))),"",N(AL11)+N(AP11)+N(AQ11))) | AS11: =IF(OR($G11="ja",NOT(ISNUMBER(AL11)),NOT(ISNUMBER(AR11))),"",AR11+N(AN11)) | AT11: =IF(OR(NOT(ISNUMBER(AL11)),NOT(ISNUMBER(F11)),F11=0),"",AL11/F11) | AU11: =IF(OR(NOT(ISNUMBER(MIETER!F16)),NOT(ISNUMBER(MIETER!I16))),"",MIETER!I16) | AV11: =IF(OR(NOT(ISNUMBER(AU11)),$G11="ja",NOT(ISNUMBER($H$34))),"",EDATE(AU11,$H$34)) | AX11: =IF(NOT(ISNUMBER(F11)),"",IF(ISNUMBER(AW11),AW11,IF(NOT(ISNUMBER(AV11)),"",MAX(0,(YEAR(AV11)-YEAR(TODAY()))*12+MONTH(AV11)-MONTH(TODAY()))))) | AY11: =IF(NOT(ISNUMBER(AX11)),"",IF(ISNUMBER(AO11),AO11*AX11,IF(NOT(ISNUMBER(AN11)),"",AN11*AX11))) | AZ11: =IF(OR(NOT(ISNUMBER(AL11)),NOT(ISNUMBER(MIETER!$P$6))),"",ROUND(AL11*(1+MIETER!$P$6)^2,0)) | BC11: =IF(NOT(ISNUMBER(F11)),"",IF(ISNUMBER(BB11),BB11,IF(AND(ISNUMBER(BA11),ISNUMBER(AL11),AL11>0),AL11*BA11,IF(OR(NOT(ISNUMBER($C$62)),NOT(ISNUMBER($C$64))),"",$C$62+$C$64*F11/12)))) | BE11: =IF(NOT(ISNUMBER(BC11)),"",IF(ISNUMBER(BD11),MIN(BC11,BD11),IF(OR(NOT(ISNUMBER(F11)),NOT(ISNUMBER($C$64))),0,MIN(BC11,$C$64*F11/12)))) | BF11: =IF(OR(NOT(ISNUMBER(BC11)),NOT(ISNUMBER(AL11)),AL11=0),"",BC11/AL11) | BG11: =IF(NOT(ISNUMBER(AL11)),"",AL11*0.01) | BH11: =IF(OR(NOT(ISNUMBER(AL11)),NOT(ISNUMBER($C$28)),NOT(ISNUMBER(CD11)),CD11<=0),"",AL11*0.01*(1-$C$28)/CD11) | BI11: =IF(OR(NOT(ISNUMBER(K11)),NOT(ISNUMBER($H$30))),"",$H$30*K11) | BK11: =IF(OR(NOT(ISNUMBER(BI11)),NOT(ISNUMBER(AB11)),AB11<=0),"",1-BI11/AB11) | BL11: =IF(NOT(ISNUMBER(AB11)),"",IF(ISNUMBER(BJ11),BJ11,IF(AND(ISNUMBER(BI11),ISNUMBER(AE11),AE11>0),1-BI11/AE11,IF(NOT(ISNUMBER($C$31)),"",$C$31)))) | BM11: =IF(NOT(ISNUMBER(F11)),"",IF(ISNUMBER(BJ11),"vertrag",IF(ISNUMBER(BI11),"berechnet","standard"))) | BO11: =IF(NOT(ISNUMBER(F11)),"",IF(ISNUMBER(BN11),BN11,IF(NOT(ISNUMBER($C$30)),"",$C$30))) | BP11: =IF(OR(NOT(ISNUMBER(AE11)),NOT(ISNUMBER(BL11)),NOT(ISNUMBER($C$35))),"",AE11*(1+$C$35)*BL11) | BQ11: =IF(OR(NOT(ISNUMBER(BP11)),NOT(ISNUMBER(BO11)),NOT(ISNUMBER($C$35))),"",(BP11*BO11+N(U11)*(1+$C$35)*N($H$31)+N(V11)*(1+$C$35)*N($H$32))/12) | BR11: =IF(OR(NOT(ISNUMBER(AH11)),NOT(ISNUMBER($C$26))),"",AH11*$C$26/12) | BS11: =IF(OR(NOT(ISNUMBER(AH11)),NOT(ISNUMBER($C$26)),NOT(ISNUMBER($C$27))),"",ROUND(AH11*($C$26+$C$27)/12,0)) | BT11: =IF(OR(NOT(ISNUMBER(AS11)),NOT(ISNUMBER(BQ11)),NOT(ISNUMBER(BR11)),NOT(ISNUMBER(BC11))),"",AS11-BR11-BQ11-(BC11-N(BE11))) | BU11: =IF(OR(NOT(ISNUMBER(BT11)),NOT(ISNUMBER($C$28))),"",ROUND(-BT11*$C$28,0)) | BV11: =IF(OR(NOT(ISNUMBER(BE11)),NOT(ISNUMBER($C$28))),"",BE11*$C$28) | BW11: =IF(OR(NOT(ISNUMBER(AS11)),NOT(ISNUMBER(BS11)),NOT(ISNUMBER(BC11))),"",ROUND(AS11,0)-BS11-ROUND(BC11,0)) | BX11: =IF(OR(NOT(ISNUMBER(BW11)),NOT(ISNUMBER(BU11))),"",BW11+BU11) | BY11: =IF(OR(NOT(ISNUMBER(AR11)),NOT(ISNUMBER(BS11)),NOT(ISNUMBER(BC11)),NOT(ISNUMBER(BT11)),NOT(ISNUMBER($C$28))),"",ROUND(AR11,0)-BS11-ROUND(BC11,0)+ROUND(-(BT11-N(AN11))*$C$28,0)) | BZ11: =IF(OR(NOT(ISNUMBER(AA11)),NOT(ISNUMBER(AS11)),AS11=0),"",AA11/(AS11*12)) | CA11: =IF(OR(NOT(ISNUMBER(AA11)),NOT(ISNUMBER(AS11)),AA11=0),"",AS11*12/AA11) | CB11: =IF(OR(NOT(ISNUMBER(AS11)),NOT(ISNUMBER(BC11)),NOT(ISNUMBER(BO11)),NOT(ISNUMBER($C$28)),NOT(ISNUMBER($C$35))),"",(AS11-BC11)*(1-$C$28)-$C$28*N(BE11)-IF(BM11="berechnet",$C$28*(1+$C$35)*BO11*N(BI11)/12,0)) | CC11: =IF(OR(NOT(ISNUMBER(F11)),NOT(ISNUMBER($C$26)),NOT(ISNUMBER($C$27)),NOT(ISNUMBER($C$28)),NOT(ISNUMBER($C$35)),NOT(ISNUMBER($H$33))),"",($C$28*(1+$C$35)*(N(U11)*N($H$31)+N(V11)*N($H$32))-(N(U11)+N(V11))*$H$33*(($C$26+$C$27)-$C$28*$C$26))/12) | CD11: =IF(OR(NOT(ISNUMBER(BO11)),NOT(ISNUMBER($C$26)),NOT(ISNUMBER($C$27)),NOT(ISNUMBER($C$28)),NOT(ISNUMBER($C$35)),NOT(ISNUMBER($H$33)),BM11="",AND(BM11="standard",NOT(ISNUMBER($C$31)))),"",($H$33*(($C$26+$C$27)-$C$28*$C$26)-$C$28*(1+$C$35)*BO11*IF(BM11="berechnet",1,IF(BM11="vertrag",BJ11,$C$31)))/12) | CE11: =IF(NOT(ISNUMBER(F11)),"",IF(N($O$26)=2,IF(OR(NOT(ISNUMBER(AS11)),NOT(ISNUMBER(AN11)),IF(ISNUMBER(M11),M11,N($O$28))<=0),"",IF(AS11*12/IF(ISNUMBER(M11),M11,N($O$28))-N(U11)-N(V11)<=0,"",AS11*12/IF(ISNUMBER(M11),M11,N($O$28))-N(U11)-N(V11))),IF(N($O$26)=3,IF(OR(NOT(ISNUMBER(CB11)),NOT(ISNUMBER(CC11)),NOT(ISNUMBER(CD11)),N(CD11)<=0),"",IF((CB11+CC11+ROUND(AS11,0)-AS11-ROUND(BC11,0)+BC11-IF(ISNUMBER(N11),N11,N($O$29)))/CD11<=0,"",(CB11+CC11+ROUND(AS11,0)-AS11-ROUND(BC11,0)+BC11-IF(ISNUMBER(N11),N11,N($O$29)))/CD11)),"")))
A12: =IF(NOT(ISNUMBER(MIETER!F17)),"",ROW()-2) | B12: =IF(NOT(ISNUMBER(MIETER!F17)),"",IF(MIETER!A17="","",MIETER!A17)) | C12: =IF(NOT(ISNUMBER(MIETER!F17)),"",IF(MIETER!B17="","",MIETER!B17)) | D12: =IF(NOT(ISNUMBER(MIETER!F17)),"",IF(MIETER!C17="","",MIETER!C17)) | E12: =IF(NOT(ISNUMBER(MIETER!F17)),"",IF(MIETER!D17="","",MIETER!D17)) | F12: =IF(NOT(ISNUMBER(MIETER!F17)),"",MIETER!F17) | K12: =IF(OR(NOT(ISNUMBER(F12)),NOT(ISNUMBER(J12)),NOT(ISNUMBER($H$29)),$H$29=0),"",J12/$H$29) | O12: =IF(NOT(ISNUMBER(F12)),"",IF(NOT(ISNUMBER(T12)),"kein Preis",IF(ISNUMBER(CE12),IF(N($O$26)=2,"Rendite","Cashflow"),IF(OR(N($O$26)=2,N($O$26)=3),"Regler (Rückfall)","Regler")))) | P12: =IF(OR(NOT(ISNUMBER(T12)),NOT(ISNUMBER(F12)),F12=0),"",T12/F12) | Q12: =IF(OR(NOT(ISNUMBER(F12)),F12=0,NOT(ISNUMBER(VERKAUFSMATRIX!U15))),"",VERKAUFSMATRIX!U15/F12) | R12: =IF(OR(NOT(ISNUMBER(P12)),NOT(ISNUMBER(Q12)),Q12=0),"",P12/Q12-1) | T12: =IF(NOT(ISNUMBER(F12)),"",IF(ISNUMBER(CE12),IF(NOT(ISNUMBER(Y12)),"",(CE12+N(U12)+N(V12))/(1+Y12)-N(U12)-N(V12)),IF(NOT(ISNUMBER(L12)),"",F12*L12+N(S12)))) | W12: =IF(NOT(ISNUMBER(T12)),"",T12+N(U12)+N(V12)) | Y12: =IF(NOT(ISNUMBER(F12)),"",IF(ISNUMBER(X12),X12,IF(NOT(ISNUMBER($H$26)),"",$H$26))) | Z12: =IF(OR(NOT(ISNUMBER(W12)),NOT(ISNUMBER(Y12))),"",W12*Y12) | AA12: =IF(OR(NOT(ISNUMBER(W12)),NOT(ISNUMBER(Y12))),"",W12*(1+Y12)) | AB12: =IF(NOT(ISNUMBER(AA12)),"",AA12-N(U12)-N(V12)) | AC12: =IF(OR(NOT(ISNUMBER(W12)),NOT(ISNUMBER(F12)),F12=0),"",W12/F12) | AD12: =IF(OR(NOT(ISNUMBER(AB12)),NOT(ISNUMBER(F12)),F12=0),"",AB12/F12) | AE12: =IF(NOT(ISNUMBER(AB12)),"",AB12) | AF12: =IF(OR(NOT(ISNUMBER(AA12)),NOT(ISNUMBER($C$35))),"",AA12*$C$35) | AG12: =IF(OR(NOT(ISNUMBER(AA12)),NOT(ISNUMBER(AF12))),"",AA12+AF12) | AH12: =IF(OR(NOT(ISNUMBER(AA12)),NOT(ISNUMBER($H$33))),"",AA12*$H$33) | AI12: =IF(OR(NOT(ISNUMBER(AG12)),NOT(ISNUMBER(AH12))),"",MAX(0,AG12-AH12)) | AJ12: =IF(OR(NOT(ISNUMBER(AH12)),NOT(ISNUMBER(AA12))),"",AH12-AA12) | AL12: =IF(OR(NOT(ISNUMBER(MIETER!F17)),$G12="ja"),"",IF(NOT(ISNUMBER(MIETER!J17)),"",IF(ISNUMBER(AK12),MAX(MIETER!J17,AK12),MIETER!J17))) | AN12: =IF(OR(NOT(ISNUMBER(AL12)),NOT(ISNUMBER(AM12))),"",MAX(0,AM12-AL12)) | AR12: =IF(NOT(ISNUMBER(F12)),"",IF(AND(NOT(ISNUMBER(AL12)),NOT(ISNUMBER(AP12)),NOT(ISNUMBER(AQ12))),"",N(AL12)+N(AP12)+N(AQ12))) | AS12: =IF(OR($G12="ja",NOT(ISNUMBER(AL12)),NOT(ISNUMBER(AR12))),"",AR12+N(AN12)) | AT12: =IF(OR(NOT(ISNUMBER(AL12)),NOT(ISNUMBER(F12)),F12=0),"",AL12/F12) | AU12: =IF(OR(NOT(ISNUMBER(MIETER!F17)),NOT(ISNUMBER(MIETER!I17))),"",MIETER!I17) | AV12: =IF(OR(NOT(ISNUMBER(AU12)),$G12="ja",NOT(ISNUMBER($H$34))),"",EDATE(AU12,$H$34)) | AX12: =IF(NOT(ISNUMBER(F12)),"",IF(ISNUMBER(AW12),AW12,IF(NOT(ISNUMBER(AV12)),"",MAX(0,(YEAR(AV12)-YEAR(TODAY()))*12+MONTH(AV12)-MONTH(TODAY()))))) | AY12: =IF(NOT(ISNUMBER(AX12)),"",IF(ISNUMBER(AO12),AO12*AX12,IF(NOT(ISNUMBER(AN12)),"",AN12*AX12))) | AZ12: =IF(OR(NOT(ISNUMBER(AL12)),NOT(ISNUMBER(MIETER!$P$6))),"",ROUND(AL12*(1+MIETER!$P$6)^2,0)) | BC12: =IF(NOT(ISNUMBER(F12)),"",IF(ISNUMBER(BB12),BB12,IF(AND(ISNUMBER(BA12),ISNUMBER(AL12),AL12>0),AL12*BA12,IF(OR(NOT(ISNUMBER($C$62)),NOT(ISNUMBER($C$64))),"",$C$62+$C$64*F12/12)))) | BE12: =IF(NOT(ISNUMBER(BC12)),"",IF(ISNUMBER(BD12),MIN(BC12,BD12),IF(OR(NOT(ISNUMBER(F12)),NOT(ISNUMBER($C$64))),0,MIN(BC12,$C$64*F12/12)))) | BF12: =IF(OR(NOT(ISNUMBER(BC12)),NOT(ISNUMBER(AL12)),AL12=0),"",BC12/AL12) | BG12: =IF(NOT(ISNUMBER(AL12)),"",AL12*0.01) | BH12: =IF(OR(NOT(ISNUMBER(AL12)),NOT(ISNUMBER($C$28)),NOT(ISNUMBER(CD12)),CD12<=0),"",AL12*0.01*(1-$C$28)/CD12) | BI12: =IF(OR(NOT(ISNUMBER(K12)),NOT(ISNUMBER($H$30))),"",$H$30*K12) | BK12: =IF(OR(NOT(ISNUMBER(BI12)),NOT(ISNUMBER(AB12)),AB12<=0),"",1-BI12/AB12) | BL12: =IF(NOT(ISNUMBER(AB12)),"",IF(ISNUMBER(BJ12),BJ12,IF(AND(ISNUMBER(BI12),ISNUMBER(AE12),AE12>0),1-BI12/AE12,IF(NOT(ISNUMBER($C$31)),"",$C$31)))) | BM12: =IF(NOT(ISNUMBER(F12)),"",IF(ISNUMBER(BJ12),"vertrag",IF(ISNUMBER(BI12),"berechnet","standard"))) | BO12: =IF(NOT(ISNUMBER(F12)),"",IF(ISNUMBER(BN12),BN12,IF(NOT(ISNUMBER($C$30)),"",$C$30))) | BP12: =IF(OR(NOT(ISNUMBER(AE12)),NOT(ISNUMBER(BL12)),NOT(ISNUMBER($C$35))),"",AE12*(1+$C$35)*BL12) | BQ12: =IF(OR(NOT(ISNUMBER(BP12)),NOT(ISNUMBER(BO12)),NOT(ISNUMBER($C$35))),"",(BP12*BO12+N(U12)*(1+$C$35)*N($H$31)+N(V12)*(1+$C$35)*N($H$32))/12) | BR12: =IF(OR(NOT(ISNUMBER(AH12)),NOT(ISNUMBER($C$26))),"",AH12*$C$26/12) | BS12: =IF(OR(NOT(ISNUMBER(AH12)),NOT(ISNUMBER($C$26)),NOT(ISNUMBER($C$27))),"",ROUND(AH12*($C$26+$C$27)/12,0)) | BT12: =IF(OR(NOT(ISNUMBER(AS12)),NOT(ISNUMBER(BQ12)),NOT(ISNUMBER(BR12)),NOT(ISNUMBER(BC12))),"",AS12-BR12-BQ12-(BC12-N(BE12))) | BU12: =IF(OR(NOT(ISNUMBER(BT12)),NOT(ISNUMBER($C$28))),"",ROUND(-BT12*$C$28,0)) | BV12: =IF(OR(NOT(ISNUMBER(BE12)),NOT(ISNUMBER($C$28))),"",BE12*$C$28) | BW12: =IF(OR(NOT(ISNUMBER(AS12)),NOT(ISNUMBER(BS12)),NOT(ISNUMBER(BC12))),"",ROUND(AS12,0)-BS12-ROUND(BC12,0)) | BX12: =IF(OR(NOT(ISNUMBER(BW12)),NOT(ISNUMBER(BU12))),"",BW12+BU12) | BY12: =IF(OR(NOT(ISNUMBER(AR12)),NOT(ISNUMBER(BS12)),NOT(ISNUMBER(BC12)),NOT(ISNUMBER(BT12)),NOT(ISNUMBER($C$28))),"",ROUND(AR12,0)-BS12-ROUND(BC12,0)+ROUND(-(BT12-N(AN12))*$C$28,0)) | BZ12: =IF(OR(NOT(ISNUMBER(AA12)),NOT(ISNUMBER(AS12)),AS12=0),"",AA12/(AS12*12)) | CA12: =IF(OR(NOT(ISNUMBER(AA12)),NOT(ISNUMBER(AS12)),AA12=0),"",AS12*12/AA12) | CB12: =IF(OR(NOT(ISNUMBER(AS12)),NOT(ISNUMBER(BC12)),NOT(ISNUMBER(BO12)),NOT(ISNUMBER($C$28)),NOT(ISNUMBER($C$35))),"",(AS12-BC12)*(1-$C$28)-$C$28*N(BE12)-IF(BM12="berechnet",$C$28*(1+$C$35)*BO12*N(BI12)/12,0)) | CC12: =IF(OR(NOT(ISNUMBER(F12)),NOT(ISNUMBER($C$26)),NOT(ISNUMBER($C$27)),NOT(ISNUMBER($C$28)),NOT(ISNUMBER($C$35)),NOT(ISNUMBER($H$33))),"",($C$28*(1+$C$35)*(N(U12)*N($H$31)+N(V12)*N($H$32))-(N(U12)+N(V12))*$H$33*(($C$26+$C$27)-$C$28*$C$26))/12) | CD12: =IF(OR(NOT(ISNUMBER(BO12)),NOT(ISNUMBER($C$26)),NOT(ISNUMBER($C$27)),NOT(ISNUMBER($C$28)),NOT(ISNUMBER($C$35)),NOT(ISNUMBER($H$33)),BM12="",AND(BM12="standard",NOT(ISNUMBER($C$31)))),"",($H$33*(($C$26+$C$27)-$C$28*$C$26)-$C$28*(1+$C$35)*BO12*IF(BM12="berechnet",1,IF(BM12="vertrag",BJ12,$C$31)))/12) | CE12: =IF(NOT(ISNUMBER(F12)),"",IF(N($O$26)=2,IF(OR(NOT(ISNUMBER(AS12)),NOT(ISNUMBER(AN12)),IF(ISNUMBER(M12),M12,N($O$28))<=0),"",IF(AS12*12/IF(ISNUMBER(M12),M12,N($O$28))-N(U12)-N(V12)<=0,"",AS12*12/IF(ISNUMBER(M12),M12,N($O$28))-N(U12)-N(V12))),IF(N($O$26)=3,IF(OR(NOT(ISNUMBER(CB12)),NOT(ISNUMBER(CC12)),NOT(ISNUMBER(CD12)),N(CD12)<=0),"",IF((CB12+CC12+ROUND(AS12,0)-AS12-ROUND(BC12,0)+BC12-IF(ISNUMBER(N12),N12,N($O$29)))/CD12<=0,"",(CB12+CC12+ROUND(AS12,0)-AS12-ROUND(BC12,0)+BC12-IF(ISNUMBER(N12),N12,N($O$29)))/CD12)),"")))
A13: =IF(NOT(ISNUMBER(MIETER!F18)),"",ROW()-2) | B13: =IF(NOT(ISNUMBER(MIETER!F18)),"",IF(MIETER!A18="","",MIETER!A18)) | C13: =IF(NOT(ISNUMBER(MIETER!F18)),"",IF(MIETER!B18="","",MIETER!B18)) | D13: =IF(NOT(ISNUMBER(MIETER!F18)),"",IF(MIETER!C18="","",MIETER!C18)) | E13: =IF(NOT(ISNUMBER(MIETER!F18)),"",IF(MIETER!D18="","",MIETER!D18)) | F13: =IF(NOT(ISNUMBER(MIETER!F18)),"",MIETER!F18) | K13: =IF(OR(NOT(ISNUMBER(F13)),NOT(ISNUMBER(J13)),NOT(ISNUMBER($H$29)),$H$29=0),"",J13/$H$29) | O13: =IF(NOT(ISNUMBER(F13)),"",IF(NOT(ISNUMBER(T13)),"kein Preis",IF(ISNUMBER(CE13),IF(N($O$26)=2,"Rendite","Cashflow"),IF(OR(N($O$26)=2,N($O$26)=3),"Regler (Rückfall)","Regler")))) | P13: =IF(OR(NOT(ISNUMBER(T13)),NOT(ISNUMBER(F13)),F13=0),"",T13/F13) | Q13: =IF(OR(NOT(ISNUMBER(F13)),F13=0,NOT(ISNUMBER(VERKAUFSMATRIX!U16))),"",VERKAUFSMATRIX!U16/F13) | R13: =IF(OR(NOT(ISNUMBER(P13)),NOT(ISNUMBER(Q13)),Q13=0),"",P13/Q13-1) | T13: =IF(NOT(ISNUMBER(F13)),"",IF(ISNUMBER(CE13),IF(NOT(ISNUMBER(Y13)),"",(CE13+N(U13)+N(V13))/(1+Y13)-N(U13)-N(V13)),IF(NOT(ISNUMBER(L13)),"",F13*L13+N(S13)))) | W13: =IF(NOT(ISNUMBER(T13)),"",T13+N(U13)+N(V13)) | Y13: =IF(NOT(ISNUMBER(F13)),"",IF(ISNUMBER(X13),X13,IF(NOT(ISNUMBER($H$26)),"",$H$26))) | Z13: =IF(OR(NOT(ISNUMBER(W13)),NOT(ISNUMBER(Y13))),"",W13*Y13) | AA13: =IF(OR(NOT(ISNUMBER(W13)),NOT(ISNUMBER(Y13))),"",W13*(1+Y13)) | AB13: =IF(NOT(ISNUMBER(AA13)),"",AA13-N(U13)-N(V13)) | AC13: =IF(OR(NOT(ISNUMBER(W13)),NOT(ISNUMBER(F13)),F13=0),"",W13/F13) | AD13: =IF(OR(NOT(ISNUMBER(AB13)),NOT(ISNUMBER(F13)),F13=0),"",AB13/F13) | AE13: =IF(NOT(ISNUMBER(AB13)),"",AB13) | AF13: =IF(OR(NOT(ISNUMBER(AA13)),NOT(ISNUMBER($C$35))),"",AA13*$C$35) | AG13: =IF(OR(NOT(ISNUMBER(AA13)),NOT(ISNUMBER(AF13))),"",AA13+AF13) | AH13: =IF(OR(NOT(ISNUMBER(AA13)),NOT(ISNUMBER($H$33))),"",AA13*$H$33) | AI13: =IF(OR(NOT(ISNUMBER(AG13)),NOT(ISNUMBER(AH13))),"",MAX(0,AG13-AH13)) | AJ13: =IF(OR(NOT(ISNUMBER(AH13)),NOT(ISNUMBER(AA13))),"",AH13-AA13) | AL13: =IF(OR(NOT(ISNUMBER(MIETER!F18)),$G13="ja"),"",IF(NOT(ISNUMBER(MIETER!J18)),"",IF(ISNUMBER(AK13),MAX(MIETER!J18,AK13),MIETER!J18))) | AN13: =IF(OR(NOT(ISNUMBER(AL13)),NOT(ISNUMBER(AM13))),"",MAX(0,AM13-AL13)) | AR13: =IF(NOT(ISNUMBER(F13)),"",IF(AND(NOT(ISNUMBER(AL13)),NOT(ISNUMBER(AP13)),NOT(ISNUMBER(AQ13))),"",N(AL13)+N(AP13)+N(AQ13))) | AS13: =IF(OR($G13="ja",NOT(ISNUMBER(AL13)),NOT(ISNUMBER(AR13))),"",AR13+N(AN13)) | AT13: =IF(OR(NOT(ISNUMBER(AL13)),NOT(ISNUMBER(F13)),F13=0),"",AL13/F13) | AU13: =IF(OR(NOT(ISNUMBER(MIETER!F18)),NOT(ISNUMBER(MIETER!I18))),"",MIETER!I18) | AV13: =IF(OR(NOT(ISNUMBER(AU13)),$G13="ja",NOT(ISNUMBER($H$34))),"",EDATE(AU13,$H$34)) | AX13: =IF(NOT(ISNUMBER(F13)),"",IF(ISNUMBER(AW13),AW13,IF(NOT(ISNUMBER(AV13)),"",MAX(0,(YEAR(AV13)-YEAR(TODAY()))*12+MONTH(AV13)-MONTH(TODAY()))))) | AY13: =IF(NOT(ISNUMBER(AX13)),"",IF(ISNUMBER(AO13),AO13*AX13,IF(NOT(ISNUMBER(AN13)),"",AN13*AX13))) | AZ13: =IF(OR(NOT(ISNUMBER(AL13)),NOT(ISNUMBER(MIETER!$P$6))),"",ROUND(AL13*(1+MIETER!$P$6)^2,0)) | BC13: =IF(NOT(ISNUMBER(F13)),"",IF(ISNUMBER(BB13),BB13,IF(AND(ISNUMBER(BA13),ISNUMBER(AL13),AL13>0),AL13*BA13,IF(OR(NOT(ISNUMBER($C$62)),NOT(ISNUMBER($C$64))),"",$C$62+$C$64*F13/12)))) | BE13: =IF(NOT(ISNUMBER(BC13)),"",IF(ISNUMBER(BD13),MIN(BC13,BD13),IF(OR(NOT(ISNUMBER(F13)),NOT(ISNUMBER($C$64))),0,MIN(BC13,$C$64*F13/12)))) | BF13: =IF(OR(NOT(ISNUMBER(BC13)),NOT(ISNUMBER(AL13)),AL13=0),"",BC13/AL13) | BG13: =IF(NOT(ISNUMBER(AL13)),"",AL13*0.01) | BH13: =IF(OR(NOT(ISNUMBER(AL13)),NOT(ISNUMBER($C$28)),NOT(ISNUMBER(CD13)),CD13<=0),"",AL13*0.01*(1-$C$28)/CD13) | BI13: =IF(OR(NOT(ISNUMBER(K13)),NOT(ISNUMBER($H$30))),"",$H$30*K13) | BK13: =IF(OR(NOT(ISNUMBER(BI13)),NOT(ISNUMBER(AB13)),AB13<=0),"",1-BI13/AB13) | BL13: =IF(NOT(ISNUMBER(AB13)),"",IF(ISNUMBER(BJ13),BJ13,IF(AND(ISNUMBER(BI13),ISNUMBER(AE13),AE13>0),1-BI13/AE13,IF(NOT(ISNUMBER($C$31)),"",$C$31)))) | BM13: =IF(NOT(ISNUMBER(F13)),"",IF(ISNUMBER(BJ13),"vertrag",IF(ISNUMBER(BI13),"berechnet","standard"))) | BO13: =IF(NOT(ISNUMBER(F13)),"",IF(ISNUMBER(BN13),BN13,IF(NOT(ISNUMBER($C$30)),"",$C$30))) | BP13: =IF(OR(NOT(ISNUMBER(AE13)),NOT(ISNUMBER(BL13)),NOT(ISNUMBER($C$35))),"",AE13*(1+$C$35)*BL13) | BQ13: =IF(OR(NOT(ISNUMBER(BP13)),NOT(ISNUMBER(BO13)),NOT(ISNUMBER($C$35))),"",(BP13*BO13+N(U13)*(1+$C$35)*N($H$31)+N(V13)*(1+$C$35)*N($H$32))/12) | BR13: =IF(OR(NOT(ISNUMBER(AH13)),NOT(ISNUMBER($C$26))),"",AH13*$C$26/12) | BS13: =IF(OR(NOT(ISNUMBER(AH13)),NOT(ISNUMBER($C$26)),NOT(ISNUMBER($C$27))),"",ROUND(AH13*($C$26+$C$27)/12,0)) | BT13: =IF(OR(NOT(ISNUMBER(AS13)),NOT(ISNUMBER(BQ13)),NOT(ISNUMBER(BR13)),NOT(ISNUMBER(BC13))),"",AS13-BR13-BQ13-(BC13-N(BE13))) | BU13: =IF(OR(NOT(ISNUMBER(BT13)),NOT(ISNUMBER($C$28))),"",ROUND(-BT13*$C$28,0)) | BV13: =IF(OR(NOT(ISNUMBER(BE13)),NOT(ISNUMBER($C$28))),"",BE13*$C$28) | BW13: =IF(OR(NOT(ISNUMBER(AS13)),NOT(ISNUMBER(BS13)),NOT(ISNUMBER(BC13))),"",ROUND(AS13,0)-BS13-ROUND(BC13,0)) | BX13: =IF(OR(NOT(ISNUMBER(BW13)),NOT(ISNUMBER(BU13))),"",BW13+BU13) | BY13: =IF(OR(NOT(ISNUMBER(AR13)),NOT(ISNUMBER(BS13)),NOT(ISNUMBER(BC13)),NOT(ISNUMBER(BT13)),NOT(ISNUMBER($C$28))),"",ROUND(AR13,0)-BS13-ROUND(BC13,0)+ROUND(-(BT13-N(AN13))*$C$28,0)) | BZ13: =IF(OR(NOT(ISNUMBER(AA13)),NOT(ISNUMBER(AS13)),AS13=0),"",AA13/(AS13*12)) | CA13: =IF(OR(NOT(ISNUMBER(AA13)),NOT(ISNUMBER(AS13)),AA13=0),"",AS13*12/AA13) | CB13: =IF(OR(NOT(ISNUMBER(AS13)),NOT(ISNUMBER(BC13)),NOT(ISNUMBER(BO13)),NOT(ISNUMBER($C$28)),NOT(ISNUMBER($C$35))),"",(AS13-BC13)*(1-$C$28)-$C$28*N(BE13)-IF(BM13="berechnet",$C$28*(1+$C$35)*BO13*N(BI13)/12,0)) | CC13: =IF(OR(NOT(ISNUMBER(F13)),NOT(ISNUMBER($C$26)),NOT(ISNUMBER($C$27)),NOT(ISNUMBER($C$28)),NOT(ISNUMBER($C$35)),NOT(ISNUMBER($H$33))),"",($C$28*(1+$C$35)*(N(U13)*N($H$31)+N(V13)*N($H$32))-(N(U13)+N(V13))*$H$33*(($C$26+$C$27)-$C$28*$C$26))/12) | CD13: =IF(OR(NOT(ISNUMBER(BO13)),NOT(ISNUMBER($C$26)),NOT(ISNUMBER($C$27)),NOT(ISNUMBER($C$28)),NOT(ISNUMBER($C$35)),NOT(ISNUMBER($H$33)),BM13="",AND(BM13="standard",NOT(ISNUMBER($C$31)))),"",($H$33*(($C$26+$C$27)-$C$28*$C$26)-$C$28*(1+$C$35)*BO13*IF(BM13="berechnet",1,IF(BM13="vertrag",BJ13,$C$31)))/12) | CE13: =IF(NOT(ISNUMBER(F13)),"",IF(N($O$26)=2,IF(OR(NOT(ISNUMBER(AS13)),NOT(ISNUMBER(AN13)),IF(ISNUMBER(M13),M13,N($O$28))<=0),"",IF(AS13*12/IF(ISNUMBER(M13),M13,N($O$28))-N(U13)-N(V13)<=0,"",AS13*12/IF(ISNUMBER(M13),M13,N($O$28))-N(U13)-N(V13))),IF(N($O$26)=3,IF(OR(NOT(ISNUMBER(CB13)),NOT(ISNUMBER(CC13)),NOT(ISNUMBER(CD13)),N(CD13)<=0),"",IF((CB13+CC13+ROUND(AS13,0)-AS13-ROUND(BC13,0)+BC13-IF(ISNUMBER(N13),N13,N($O$29)))/CD13<=0,"",(CB13+CC13+ROUND(AS13,0)-AS13-ROUND(BC13,0)+BC13-IF(ISNUMBER(N13),N13,N($O$29)))/CD13)),"")))
A14: =IF(NOT(ISNUMBER(MIETER!F19)),"",ROW()-2) | B14: =IF(NOT(ISNUMBER(MIETER!F19)),"",IF(MIETER!A19="","",MIETER!A19)) | C14: =IF(NOT(ISNUMBER(MIETER!F19)),"",IF(MIETER!B19="","",MIETER!B19)) | D14: =IF(NOT(ISNUMBER(MIETER!F19)),"",IF(MIETER!C19="","",MIETER!C19)) | E14: =IF(NOT(ISNUMBER(MIETER!F19)),"",IF(MIETER!D19="","",MIETER!D19)) | F14: =IF(NOT(ISNUMBER(MIETER!F19)),"",MIETER!F19) | K14: =IF(OR(NOT(ISNUMBER(F14)),NOT(ISNUMBER(J14)),NOT(ISNUMBER($H$29)),$H$29=0),"",J14/$H$29) | O14: =IF(NOT(ISNUMBER(F14)),"",IF(NOT(ISNUMBER(T14)),"kein Preis",IF(ISNUMBER(CE14),IF(N($O$26)=2,"Rendite","Cashflow"),IF(OR(N($O$26)=2,N($O$26)=3),"Regler (Rückfall)","Regler")))) | P14: =IF(OR(NOT(ISNUMBER(T14)),NOT(ISNUMBER(F14)),F14=0),"",T14/F14) | Q14: =IF(OR(NOT(ISNUMBER(F14)),F14=0,NOT(ISNUMBER(VERKAUFSMATRIX!U17))),"",VERKAUFSMATRIX!U17/F14) | R14: =IF(OR(NOT(ISNUMBER(P14)),NOT(ISNUMBER(Q14)),Q14=0),"",P14/Q14-1) | T14: =IF(NOT(ISNUMBER(F14)),"",IF(ISNUMBER(CE14),IF(NOT(ISNUMBER(Y14)),"",(CE14+N(U14)+N(V14))/(1+Y14)-N(U14)-N(V14)),IF(NOT(ISNUMBER(L14)),"",F14*L14+N(S14)))) | W14: =IF(NOT(ISNUMBER(T14)),"",T14+N(U14)+N(V14)) | Y14: =IF(NOT(ISNUMBER(F14)),"",IF(ISNUMBER(X14),X14,IF(NOT(ISNUMBER($H$26)),"",$H$26))) | Z14: =IF(OR(NOT(ISNUMBER(W14)),NOT(ISNUMBER(Y14))),"",W14*Y14) | AA14: =IF(OR(NOT(ISNUMBER(W14)),NOT(ISNUMBER(Y14))),"",W14*(1+Y14)) | AB14: =IF(NOT(ISNUMBER(AA14)),"",AA14-N(U14)-N(V14)) | AC14: =IF(OR(NOT(ISNUMBER(W14)),NOT(ISNUMBER(F14)),F14=0),"",W14/F14) | AD14: =IF(OR(NOT(ISNUMBER(AB14)),NOT(ISNUMBER(F14)),F14=0),"",AB14/F14) | AE14: =IF(NOT(ISNUMBER(AB14)),"",AB14) | AF14: =IF(OR(NOT(ISNUMBER(AA14)),NOT(ISNUMBER($C$35))),"",AA14*$C$35) | AG14: =IF(OR(NOT(ISNUMBER(AA14)),NOT(ISNUMBER(AF14))),"",AA14+AF14) | AH14: =IF(OR(NOT(ISNUMBER(AA14)),NOT(ISNUMBER($H$33))),"",AA14*$H$33) | AI14: =IF(OR(NOT(ISNUMBER(AG14)),NOT(ISNUMBER(AH14))),"",MAX(0,AG14-AH14)) | AJ14: =IF(OR(NOT(ISNUMBER(AH14)),NOT(ISNUMBER(AA14))),"",AH14-AA14) | AL14: =IF(OR(NOT(ISNUMBER(MIETER!F19)),$G14="ja"),"",IF(NOT(ISNUMBER(MIETER!J19)),"",IF(ISNUMBER(AK14),MAX(MIETER!J19,AK14),MIETER!J19))) | AN14: =IF(OR(NOT(ISNUMBER(AL14)),NOT(ISNUMBER(AM14))),"",MAX(0,AM14-AL14)) | AR14: =IF(NOT(ISNUMBER(F14)),"",IF(AND(NOT(ISNUMBER(AL14)),NOT(ISNUMBER(AP14)),NOT(ISNUMBER(AQ14))),"",N(AL14)+N(AP14)+N(AQ14))) | AS14: =IF(OR($G14="ja",NOT(ISNUMBER(AL14)),NOT(ISNUMBER(AR14))),"",AR14+N(AN14)) | AT14: =IF(OR(NOT(ISNUMBER(AL14)),NOT(ISNUMBER(F14)),F14=0),"",AL14/F14) | AU14: =IF(OR(NOT(ISNUMBER(MIETER!F19)),NOT(ISNUMBER(MIETER!I19))),"",MIETER!I19) | AV14: =IF(OR(NOT(ISNUMBER(AU14)),$G14="ja",NOT(ISNUMBER($H$34))),"",EDATE(AU14,$H$34)) | AX14: =IF(NOT(ISNUMBER(F14)),"",IF(ISNUMBER(AW14),AW14,IF(NOT(ISNUMBER(AV14)),"",MAX(0,(YEAR(AV14)-YEAR(TODAY()))*12+MONTH(AV14)-MONTH(TODAY()))))) | AY14: =IF(NOT(ISNUMBER(AX14)),"",IF(ISNUMBER(AO14),AO14*AX14,IF(NOT(ISNUMBER(AN14)),"",AN14*AX14))) | AZ14: =IF(OR(NOT(ISNUMBER(AL14)),NOT(ISNUMBER(MIETER!$P$6))),"",ROUND(AL14*(1+MIETER!$P$6)^2,0)) | BC14: =IF(NOT(ISNUMBER(F14)),"",IF(ISNUMBER(BB14),BB14,IF(AND(ISNUMBER(BA14),ISNUMBER(AL14),AL14>0),AL14*BA14,IF(OR(NOT(ISNUMBER($C$62)),NOT(ISNUMBER($C$64))),"",$C$62+$C$64*F14/12)))) | BE14: =IF(NOT(ISNUMBER(BC14)),"",IF(ISNUMBER(BD14),MIN(BC14,BD14),IF(OR(NOT(ISNUMBER(F14)),NOT(ISNUMBER($C$64))),0,MIN(BC14,$C$64*F14/12)))) | BF14: =IF(OR(NOT(ISNUMBER(BC14)),NOT(ISNUMBER(AL14)),AL14=0),"",BC14/AL14) | BG14: =IF(NOT(ISNUMBER(AL14)),"",AL14*0.01) | BH14: =IF(OR(NOT(ISNUMBER(AL14)),NOT(ISNUMBER($C$28)),NOT(ISNUMBER(CD14)),CD14<=0),"",AL14*0.01*(1-$C$28)/CD14) | BI14: =IF(OR(NOT(ISNUMBER(K14)),NOT(ISNUMBER($H$30))),"",$H$30*K14) | BK14: =IF(OR(NOT(ISNUMBER(BI14)),NOT(ISNUMBER(AB14)),AB14<=0),"",1-BI14/AB14) | BL14: =IF(NOT(ISNUMBER(AB14)),"",IF(ISNUMBER(BJ14),BJ14,IF(AND(ISNUMBER(BI14),ISNUMBER(AE14),AE14>0),1-BI14/AE14,IF(NOT(ISNUMBER($C$31)),"",$C$31)))) | BM14: =IF(NOT(ISNUMBER(F14)),"",IF(ISNUMBER(BJ14),"vertrag",IF(ISNUMBER(BI14),"berechnet","standard"))) | BO14: =IF(NOT(ISNUMBER(F14)),"",IF(ISNUMBER(BN14),BN14,IF(NOT(ISNUMBER($C$30)),"",$C$30))) | BP14: =IF(OR(NOT(ISNUMBER(AE14)),NOT(ISNUMBER(BL14)),NOT(ISNUMBER($C$35))),"",AE14*(1+$C$35)*BL14) | BQ14: =IF(OR(NOT(ISNUMBER(BP14)),NOT(ISNUMBER(BO14)),NOT(ISNUMBER($C$35))),"",(BP14*BO14+N(U14)*(1+$C$35)*N($H$31)+N(V14)*(1+$C$35)*N($H$32))/12) | BR14: =IF(OR(NOT(ISNUMBER(AH14)),NOT(ISNUMBER($C$26))),"",AH14*$C$26/12) | BS14: =IF(OR(NOT(ISNUMBER(AH14)),NOT(ISNUMBER($C$26)),NOT(ISNUMBER($C$27))),"",ROUND(AH14*($C$26+$C$27)/12,0)) | BT14: =IF(OR(NOT(ISNUMBER(AS14)),NOT(ISNUMBER(BQ14)),NOT(ISNUMBER(BR14)),NOT(ISNUMBER(BC14))),"",AS14-BR14-BQ14-(BC14-N(BE14))) | BU14: =IF(OR(NOT(ISNUMBER(BT14)),NOT(ISNUMBER($C$28))),"",ROUND(-BT14*$C$28,0)) | BV14: =IF(OR(NOT(ISNUMBER(BE14)),NOT(ISNUMBER($C$28))),"",BE14*$C$28) | BW14: =IF(OR(NOT(ISNUMBER(AS14)),NOT(ISNUMBER(BS14)),NOT(ISNUMBER(BC14))),"",ROUND(AS14,0)-BS14-ROUND(BC14,0)) | BX14: =IF(OR(NOT(ISNUMBER(BW14)),NOT(ISNUMBER(BU14))),"",BW14+BU14) | BY14: =IF(OR(NOT(ISNUMBER(AR14)),NOT(ISNUMBER(BS14)),NOT(ISNUMBER(BC14)),NOT(ISNUMBER(BT14)),NOT(ISNUMBER($C$28))),"",ROUND(AR14,0)-BS14-ROUND(BC14,0)+ROUND(-(BT14-N(AN14))*$C$28,0)) | BZ14: =IF(OR(NOT(ISNUMBER(AA14)),NOT(ISNUMBER(AS14)),AS14=0),"",AA14/(AS14*12)) | CA14: =IF(OR(NOT(ISNUMBER(AA14)),NOT(ISNUMBER(AS14)),AA14=0),"",AS14*12/AA14) | CB14: =IF(OR(NOT(ISNUMBER(AS14)),NOT(ISNUMBER(BC14)),NOT(ISNUMBER(BO14)),NOT(ISNUMBER($C$28)),NOT(ISNUMBER($C$35))),"",(AS14-BC14)*(1-$C$28)-$C$28*N(BE14)-IF(BM14="berechnet",$C$28*(1+$C$35)*BO14*N(BI14)/12,0)) | CC14: =IF(OR(NOT(ISNUMBER(F14)),NOT(ISNUMBER($C$26)),NOT(ISNUMBER($C$27)),NOT(ISNUMBER($C$28)),NOT(ISNUMBER($C$35)),NOT(ISNUMBER($H$33))),"",($C$28*(1+$C$35)*(N(U14)*N($H$31)+N(V14)*N($H$32))-(N(U14)+N(V14))*$H$33*(($C$26+$C$27)-$C$28*$C$26))/12) | CD14: =IF(OR(NOT(ISNUMBER(BO14)),NOT(ISNUMBER($C$26)),NOT(ISNUMBER($C$27)),NOT(ISNUMBER($C$28)),NOT(ISNUMBER($C$35)),NOT(ISNUMBER($H$33)),BM14="",AND(BM14="standard",NOT(ISNUMBER($C$31)))),"",($H$33*(($C$26+$C$27)-$C$28*$C$26)-$C$28*(1+$C$35)*BO14*IF(BM14="berechnet",1,IF(BM14="vertrag",BJ14,$C$31)))/12) | CE14: =IF(NOT(ISNUMBER(F14)),"",IF(N($O$26)=2,IF(OR(NOT(ISNUMBER(AS14)),NOT(ISNUMBER(AN14)),IF(ISNUMBER(M14),M14,N($O$28))<=0),"",IF(AS14*12/IF(ISNUMBER(M14),M14,N($O$28))-N(U14)-N(V14)<=0,"",AS14*12/IF(ISNUMBER(M14),M14,N($O$28))-N(U14)-N(V14))),IF(N($O$26)=3,IF(OR(NOT(ISNUMBER(CB14)),NOT(ISNUMBER(CC14)),NOT(ISNUMBER(CD14)),N(CD14)<=0),"",IF((CB14+CC14+ROUND(AS14,0)-AS14-ROUND(BC14,0)+BC14-IF(ISNUMBER(N14),N14,N($O$29)))/CD14<=0,"",(CB14+CC14+ROUND(AS14,0)-AS14-ROUND(BC14,0)+BC14-IF(ISNUMBER(N14),N14,N($O$29)))/CD14)),"")))
A15: =IF(NOT(ISNUMBER(MIETER!F20)),"",ROW()-2) | B15: =IF(NOT(ISNUMBER(MIETER!F20)),"",IF(MIETER!A20="","",MIETER!A20)) | C15: =IF(NOT(ISNUMBER(MIETER!F20)),"",IF(MIETER!B20="","",MIETER!B20)) | D15: =IF(NOT(ISNUMBER(MIETER!F20)),"",IF(MIETER!C20="","",MIETER!C20)) | E15: =IF(NOT(ISNUMBER(MIETER!F20)),"",IF(MIETER!D20="","",MIETER!D20)) | F15: =IF(NOT(ISNUMBER(MIETER!F20)),"",MIETER!F20) | K15: =IF(OR(NOT(ISNUMBER(F15)),NOT(ISNUMBER(J15)),NOT(ISNUMBER($H$29)),$H$29=0),"",J15/$H$29) | O15: =IF(NOT(ISNUMBER(F15)),"",IF(NOT(ISNUMBER(T15)),"kein Preis",IF(ISNUMBER(CE15),IF(N($O$26)=2,"Rendite","Cashflow"),IF(OR(N($O$26)=2,N($O$26)=3),"Regler (Rückfall)","Regler")))) | P15: =IF(OR(NOT(ISNUMBER(T15)),NOT(ISNUMBER(F15)),F15=0),"",T15/F15) | Q15: =IF(OR(NOT(ISNUMBER(F15)),F15=0,NOT(ISNUMBER(VERKAUFSMATRIX!U18))),"",VERKAUFSMATRIX!U18/F15) | R15: =IF(OR(NOT(ISNUMBER(P15)),NOT(ISNUMBER(Q15)),Q15=0),"",P15/Q15-1) | T15: =IF(NOT(ISNUMBER(F15)),"",IF(ISNUMBER(CE15),IF(NOT(ISNUMBER(Y15)),"",(CE15+N(U15)+N(V15))/(1+Y15)-N(U15)-N(V15)),IF(NOT(ISNUMBER(L15)),"",F15*L15+N(S15)))) | W15: =IF(NOT(ISNUMBER(T15)),"",T15+N(U15)+N(V15)) | Y15: =IF(NOT(ISNUMBER(F15)),"",IF(ISNUMBER(X15),X15,IF(NOT(ISNUMBER($H$26)),"",$H$26))) | Z15: =IF(OR(NOT(ISNUMBER(W15)),NOT(ISNUMBER(Y15))),"",W15*Y15) | AA15: =IF(OR(NOT(ISNUMBER(W15)),NOT(ISNUMBER(Y15))),"",W15*(1+Y15)) | AB15: =IF(NOT(ISNUMBER(AA15)),"",AA15-N(U15)-N(V15)) | AC15: =IF(OR(NOT(ISNUMBER(W15)),NOT(ISNUMBER(F15)),F15=0),"",W15/F15) | AD15: =IF(OR(NOT(ISNUMBER(AB15)),NOT(ISNUMBER(F15)),F15=0),"",AB15/F15) | AE15: =IF(NOT(ISNUMBER(AB15)),"",AB15) | AF15: =IF(OR(NOT(ISNUMBER(AA15)),NOT(ISNUMBER($C$35))),"",AA15*$C$35) | AG15: =IF(OR(NOT(ISNUMBER(AA15)),NOT(ISNUMBER(AF15))),"",AA15+AF15) | AH15: =IF(OR(NOT(ISNUMBER(AA15)),NOT(ISNUMBER($H$33))),"",AA15*$H$33) | AI15: =IF(OR(NOT(ISNUMBER(AG15)),NOT(ISNUMBER(AH15))),"",MAX(0,AG15-AH15)) | AJ15: =IF(OR(NOT(ISNUMBER(AH15)),NOT(ISNUMBER(AA15))),"",AH15-AA15) | AL15: =IF(OR(NOT(ISNUMBER(MIETER!F20)),$G15="ja"),"",IF(NOT(ISNUMBER(MIETER!J20)),"",IF(ISNUMBER(AK15),MAX(MIETER!J20,AK15),MIETER!J20))) | AN15: =IF(OR(NOT(ISNUMBER(AL15)),NOT(ISNUMBER(AM15))),"",MAX(0,AM15-AL15)) | AR15: =IF(NOT(ISNUMBER(F15)),"",IF(AND(NOT(ISNUMBER(AL15)),NOT(ISNUMBER(AP15)),NOT(ISNUMBER(AQ15))),"",N(AL15)+N(AP15)+N(AQ15))) | AS15: =IF(OR($G15="ja",NOT(ISNUMBER(AL15)),NOT(ISNUMBER(AR15))),"",AR15+N(AN15)) | AT15: =IF(OR(NOT(ISNUMBER(AL15)),NOT(ISNUMBER(F15)),F15=0),"",AL15/F15) | AU15: =IF(OR(NOT(ISNUMBER(MIETER!F20)),NOT(ISNUMBER(MIETER!I20))),"",MIETER!I20) | AV15: =IF(OR(NOT(ISNUMBER(AU15)),$G15="ja",NOT(ISNUMBER($H$34))),"",EDATE(AU15,$H$34)) | AX15: =IF(NOT(ISNUMBER(F15)),"",IF(ISNUMBER(AW15),AW15,IF(NOT(ISNUMBER(AV15)),"",MAX(0,(YEAR(AV15)-YEAR(TODAY()))*12+MONTH(AV15)-MONTH(TODAY()))))) | AY15: =IF(NOT(ISNUMBER(AX15)),"",IF(ISNUMBER(AO15),AO15*AX15,IF(NOT(ISNUMBER(AN15)),"",AN15*AX15))) | AZ15: =IF(OR(NOT(ISNUMBER(AL15)),NOT(ISNUMBER(MIETER!$P$6))),"",ROUND(AL15*(1+MIETER!$P$6)^2,0)) | BC15: =IF(NOT(ISNUMBER(F15)),"",IF(ISNUMBER(BB15),BB15,IF(AND(ISNUMBER(BA15),ISNUMBER(AL15),AL15>0),AL15*BA15,IF(OR(NOT(ISNUMBER($C$62)),NOT(ISNUMBER($C$64))),"",$C$62+$C$64*F15/12)))) | BE15: =IF(NOT(ISNUMBER(BC15)),"",IF(ISNUMBER(BD15),MIN(BC15,BD15),IF(OR(NOT(ISNUMBER(F15)),NOT(ISNUMBER($C$64))),0,MIN(BC15,$C$64*F15/12)))) | BF15: =IF(OR(NOT(ISNUMBER(BC15)),NOT(ISNUMBER(AL15)),AL15=0),"",BC15/AL15) | BG15: =IF(NOT(ISNUMBER(AL15)),"",AL15*0.01) | BH15: =IF(OR(NOT(ISNUMBER(AL15)),NOT(ISNUMBER($C$28)),NOT(ISNUMBER(CD15)),CD15<=0),"",AL15*0.01*(1-$C$28)/CD15) | BI15: =IF(OR(NOT(ISNUMBER(K15)),NOT(ISNUMBER($H$30))),"",$H$30*K15) | BK15: =IF(OR(NOT(ISNUMBER(BI15)),NOT(ISNUMBER(AB15)),AB15<=0),"",1-BI15/AB15) | BL15: =IF(NOT(ISNUMBER(AB15)),"",IF(ISNUMBER(BJ15),BJ15,IF(AND(ISNUMBER(BI15),ISNUMBER(AE15),AE15>0),1-BI15/AE15,IF(NOT(ISNUMBER($C$31)),"",$C$31)))) | BM15: =IF(NOT(ISNUMBER(F15)),"",IF(ISNUMBER(BJ15),"vertrag",IF(ISNUMBER(BI15),"berechnet","standard"))) | BO15: =IF(NOT(ISNUMBER(F15)),"",IF(ISNUMBER(BN15),BN15,IF(NOT(ISNUMBER($C$30)),"",$C$30))) | BP15: =IF(OR(NOT(ISNUMBER(AE15)),NOT(ISNUMBER(BL15)),NOT(ISNUMBER($C$35))),"",AE15*(1+$C$35)*BL15) | BQ15: =IF(OR(NOT(ISNUMBER(BP15)),NOT(ISNUMBER(BO15)),NOT(ISNUMBER($C$35))),"",(BP15*BO15+N(U15)*(1+$C$35)*N($H$31)+N(V15)*(1+$C$35)*N($H$32))/12) | BR15: =IF(OR(NOT(ISNUMBER(AH15)),NOT(ISNUMBER($C$26))),"",AH15*$C$26/12) | BS15: =IF(OR(NOT(ISNUMBER(AH15)),NOT(ISNUMBER($C$26)),NOT(ISNUMBER($C$27))),"",ROUND(AH15*($C$26+$C$27)/12,0)) | BT15: =IF(OR(NOT(ISNUMBER(AS15)),NOT(ISNUMBER(BQ15)),NOT(ISNUMBER(BR15)),NOT(ISNUMBER(BC15))),"",AS15-BR15-BQ15-(BC15-N(BE15))) | BU15: =IF(OR(NOT(ISNUMBER(BT15)),NOT(ISNUMBER($C$28))),"",ROUND(-BT15*$C$28,0)) | BV15: =IF(OR(NOT(ISNUMBER(BE15)),NOT(ISNUMBER($C$28))),"",BE15*$C$28) | BW15: =IF(OR(NOT(ISNUMBER(AS15)),NOT(ISNUMBER(BS15)),NOT(ISNUMBER(BC15))),"",ROUND(AS15,0)-BS15-ROUND(BC15,0)) | BX15: =IF(OR(NOT(ISNUMBER(BW15)),NOT(ISNUMBER(BU15))),"",BW15+BU15) | BY15: =IF(OR(NOT(ISNUMBER(AR15)),NOT(ISNUMBER(BS15)),NOT(ISNUMBER(BC15)),NOT(ISNUMBER(BT15)),NOT(ISNUMBER($C$28))),"",ROUND(AR15,0)-BS15-ROUND(BC15,0)+ROUND(-(BT15-N(AN15))*$C$28,0)) | BZ15: =IF(OR(NOT(ISNUMBER(AA15)),NOT(ISNUMBER(AS15)),AS15=0),"",AA15/(AS15*12)) | CA15: =IF(OR(NOT(ISNUMBER(AA15)),NOT(ISNUMBER(AS15)),AA15=0),"",AS15*12/AA15) | CB15: =IF(OR(NOT(ISNUMBER(AS15)),NOT(ISNUMBER(BC15)),NOT(ISNUMBER(BO15)),NOT(ISNUMBER($C$28)),NOT(ISNUMBER($C$35))),"",(AS15-BC15)*(1-$C$28)-$C$28*N(BE15)-IF(BM15="berechnet",$C$28*(1+$C$35)*BO15*N(BI15)/12,0)) | CC15: =IF(OR(NOT(ISNUMBER(F15)),NOT(ISNUMBER($C$26)),NOT(ISNUMBER($C$27)),NOT(ISNUMBER($C$28)),NOT(ISNUMBER($C$35)),NOT(ISNUMBER($H$33))),"",($C$28*(1+$C$35)*(N(U15)*N($H$31)+N(V15)*N($H$32))-(N(U15)+N(V15))*$H$33*(($C$26+$C$27)-$C$28*$C$26))/12) | CD15: =IF(OR(NOT(ISNUMBER(BO15)),NOT(ISNUMBER($C$26)),NOT(ISNUMBER($C$27)),NOT(ISNUMBER($C$28)),NOT(ISNUMBER($C$35)),NOT(ISNUMBER($H$33)),BM15="",AND(BM15="standard",NOT(ISNUMBER($C$31)))),"",($H$33*(($C$26+$C$27)-$C$28*$C$26)-$C$28*(1+$C$35)*BO15*IF(BM15="berechnet",1,IF(BM15="vertrag",BJ15,$C$31)))/12) | CE15: =IF(NOT(ISNUMBER(F15)),"",IF(N($O$26)=2,IF(OR(NOT(ISNUMBER(AS15)),NOT(ISNUMBER(AN15)),IF(ISNUMBER(M15),M15,N($O$28))<=0),"",IF(AS15*12/IF(ISNUMBER(M15),M15,N($O$28))-N(U15)-N(V15)<=0,"",AS15*12/IF(ISNUMBER(M15),M15,N($O$28))-N(U15)-N(V15))),IF(N($O$26)=3,IF(OR(NOT(ISNUMBER(CB15)),NOT(ISNUMBER(CC15)),NOT(ISNUMBER(CD15)),N(CD15)<=0),"",IF((CB15+CC15+ROUND(AS15,0)-AS15-ROUND(BC15,0)+BC15-IF(ISNUMBER(N15),N15,N($O$29)))/CD15<=0,"",(CB15+CC15+ROUND(AS15,0)-AS15-ROUND(BC15,0)+BC15-IF(ISNUMBER(N15),N15,N($O$29)))/CD15)),"")))
... A22: =IF(NOT(ISNUMBER(MIETER!F27)),"",ROW()-2) | B22: =IF(NOT(ISNUMBER(MIETER!F27)),"",IF(MIETER!A27="","",MIETER!A27)) | C22: =IF(NOT(ISNUMBER(MIETER!F27)),"",IF(MIETER!B27="","",MIETER!B27)) | D22: =IF(NOT(ISNUMBER(MIETER!F27)),"",IF(MIETER!C27="","",MIETER!C27)) | E22: =IF(NOT(ISNUMBER(MIETER!F27)),"",IF(MIETER!D27="","",MIETER!D27)) | F22: =IF(NOT(ISNUMBER(MIETER!F27)),"",MIETER!F27) | K22: =IF(OR(NOT(ISNUMBER(F22)),NOT(ISNUMBER(J22)),NOT(ISNUMBER($H$29)),$H$29=0),"",J22/$H$29) | O22: =IF(NOT(ISNUMBER(F22)),"",IF(NOT(ISNUMBER(T22)),"kein Preis",IF(ISNUMBER(CE22),IF(N($O$26)=2,"Rendite","Cashflow"),IF(OR(N($O$26)=2,N($O$26)=3),"Regler (Rückfall)","Regler")))) | P22: =IF(OR(NOT(ISNUMBER(T22)),NOT(ISNUMBER(F22)),F22=0),"",T22/F22) | Q22: =IF(OR(NOT(ISNUMBER(F22)),F22=0,NOT(ISNUMBER(VERKAUFSMATRIX!U25))),"",VERKAUFSMATRIX!U25/F22) | R22: =IF(OR(NOT(ISNUMBER(P22)),NOT(ISNUMBER(Q22)),Q22=0),"",P22/Q22-1) | T22: =IF(NOT(ISNUMBER(F22)),"",IF(ISNUMBER(CE22),IF(NOT(ISNUMBER(Y22)),"",(CE22+N(U22)+N(V22))/(1+Y22)-N(U22)-N(V22)),IF(NOT(ISNUMBER(L22)),"",F22*L22+N(S22)))) | W22: =IF(NOT(ISNUMBER(T22)),"",T22+N(U22)+N(V22)) | Y22: =IF(NOT(ISNUMBER(F22)),"",IF(ISNUMBER(X22),X22,IF(NOT(ISNUMBER($H$26)),"",$H$26))) | Z22: =IF(OR(NOT(ISNUMBER(W22)),NOT(ISNUMBER(Y22))),"",W22*Y22) | AA22: =IF(OR(NOT(ISNUMBER(W22)),NOT(ISNUMBER(Y22))),"",W22*(1+Y22)) | AB22: =IF(NOT(ISNUMBER(AA22)),"",AA22-N(U22)-N(V22)) | AC22: =IF(OR(NOT(ISNUMBER(W22)),NOT(ISNUMBER(F22)),F22=0),"",W22/F22) | AD22: =IF(OR(NOT(ISNUMBER(AB22)),NOT(ISNUMBER(F22)),F22=0),"",AB22/F22) | AE22: =IF(NOT(ISNUMBER(AB22)),"",AB22) | AF22: =IF(OR(NOT(ISNUMBER(AA22)),NOT(ISNUMBER($C$35))),"",AA22*$C$35) | AG22: =IF(OR(NOT(ISNUMBER(AA22)),NOT(ISNUMBER(AF22))),"",AA22+AF22) | AH22: =IF(OR(NOT(ISNUMBER(AA22)),NOT(ISNUMBER($H$33))),"",AA22*$H$33) | AI22: =IF(OR(NOT(ISNUMBER(AG22)),NOT(ISNUMBER(AH22))),"",MAX(0,AG22-AH22)) | AJ22: =IF(OR(NOT(ISNUMBER(AH22)),NOT(ISNUMBER(AA22))),"",AH22-AA22) | AL22: =IF(OR(NOT(ISNUMBER(MIETER!F27)),$G22="ja"),"",IF(NOT(ISNUMBER(MIETER!J27)),"",IF(ISNUMBER(AK22),MAX(MIETER!J27,AK22),MIETER!J27))) | AN22: =IF(OR(NOT(ISNUMBER(AL22)),NOT(ISNUMBER(AM22))),"",MAX(0,AM22-AL22)) | AR22: =IF(NOT(ISNUMBER(F22)),"",IF(AND(NOT(ISNUMBER(AL22)),NOT(ISNUMBER(AP22)),NOT(ISNUMBER(AQ22))),"",N(AL22)+N(AP22)+N(AQ22))) | AS22: =IF(OR($G22="ja",NOT(ISNUMBER(AL22)),NOT(ISNUMBER(AR22))),"",AR22+N(AN22)) | AT22: =IF(OR(NOT(ISNUMBER(AL22)),NOT(ISNUMBER(F22)),F22=0),"",AL22/F22) | AU22: =IF(OR(NOT(ISNUMBER(MIETER!F27)),NOT(ISNUMBER(MIETER!I27))),"",MIETER!I27) | AV22: =IF(OR(NOT(ISNUMBER(AU22)),$G22="ja",NOT(ISNUMBER($H$34))),"",EDATE(AU22,$H$34)) | AX22: =IF(NOT(ISNUMBER(F22)),"",IF(ISNUMBER(AW22),AW22,IF(NOT(ISNUMBER(AV22)),"",MAX(0,(YEAR(AV22)-YEAR(TODAY()))*12+MONTH(AV22)-MONTH(TODAY()))))) | AY22: =IF(NOT(ISNUMBER(AX22)),"",IF(ISNUMBER(AO22),AO22*AX22,IF(NOT(ISNUMBER(AN22)),"",AN22*AX22))) | AZ22: =IF(OR(NOT(ISNUMBER(AL22)),NOT(ISNUMBER(MIETER!$P$6))),"",ROUND(AL22*(1+MIETER!$P$6)^2,0)) | BC22: =IF(NOT(ISNUMBER(F22)),"",IF(ISNUMBER(BB22),BB22,IF(AND(ISNUMBER(BA22),ISNUMBER(AL22),AL22>0),AL22*BA22,IF(OR(NOT(ISNUMBER($C$62)),NOT(ISNUMBER($C$64))),"",$C$62+$C$64*F22/12)))) | BE22: =IF(NOT(ISNUMBER(BC22)),"",IF(ISNUMBER(BD22),MIN(BC22,BD22),IF(OR(NOT(ISNUMBER(F22)),NOT(ISNUMBER($C$64))),0,MIN(BC22,$C$64*F22/12)))) | BF22: =IF(OR(NOT(ISNUMBER(BC22)),NOT(ISNUMBER(AL22)),AL22=0),"",BC22/AL22) | BG22: =IF(NOT(ISNUMBER(AL22)),"",AL22*0.01) | BH22: =IF(OR(NOT(ISNUMBER(AL22)),NOT(ISNUMBER($C$28)),NOT(ISNUMBER(CD22)),CD22<=0),"",AL22*0.01*(1-$C$28)/CD22) | BI22: =IF(OR(NOT(ISNUMBER(K22)),NOT(ISNUMBER($H$30))),"",$H$30*K22) | BK22: =IF(OR(NOT(ISNUMBER(BI22)),NOT(ISNUMBER(AB22)),AB22<=0),"",1-BI22/AB22) | BL22: =IF(NOT(ISNUMBER(AB22)),"",IF(ISNUMBER(BJ22),BJ22,IF(AND(ISNUMBER(BI22),ISNUMBER(AE22),AE22>0),1-BI22/AE22,IF(NOT(ISNUMBER($C$31)),"",$C$31)))) | BM22: =IF(NOT(ISNUMBER(F22)),"",IF(ISNUMBER(BJ22),"vertrag",IF(ISNUMBER(BI22),"berechnet","standard"))) | BO22: =IF(NOT(ISNUMBER(F22)),"",IF(ISNUMBER(BN22),BN22,IF(NOT(ISNUMBER($C$30)),"",$C$30))) | BP22: =IF(OR(NOT(ISNUMBER(AE22)),NOT(ISNUMBER(BL22)),NOT(ISNUMBER($C$35))),"",AE22*(1+$C$35)*BL22) | BQ22: =IF(OR(NOT(ISNUMBER(BP22)),NOT(ISNUMBER(BO22)),NOT(ISNUMBER($C$35))),"",(BP22*BO22+N(U22)*(1+$C$35)*N($H$31)+N(V22)*(1+$C$35)*N($H$32))/12) | BR22: =IF(OR(NOT(ISNUMBER(AH22)),NOT(ISNUMBER($C$26))),"",AH22*$C$26/12) | BS22: =IF(OR(NOT(ISNUMBER(AH22)),NOT(ISNUMBER($C$26)),NOT(ISNUMBER($C$27))),"",ROUND(AH22*($C$26+$C$27)/12,0)) | BT22: =IF(OR(NOT(ISNUMBER(AS22)),NOT(ISNUMBER(BQ22)),NOT(ISNUMBER(BR22)),NOT(ISNUMBER(BC22))),"",AS22-BR22-BQ22-(BC22-N(BE22))) | BU22: =IF(OR(NOT(ISNUMBER(BT22)),NOT(ISNUMBER($C$28))),"",ROUND(-BT22*$C$28,0)) | BV22: =IF(OR(NOT(ISNUMBER(BE22)),NOT(ISNUMBER($C$28))),"",BE22*$C$28) | BW22: =IF(OR(NOT(ISNUMBER(AS22)),NOT(ISNUMBER(BS22)),NOT(ISNUMBER(BC22))),"",ROUND(AS22,0)-BS22-ROUND(BC22,0)) | BX22: =IF(OR(NOT(ISNUMBER(BW22)),NOT(ISNUMBER(BU22))),"",BW22+BU22) | BY22: =IF(OR(NOT(ISNUMBER(AR22)),NOT(ISNUMBER(BS22)),NOT(ISNUMBER(BC22)),NOT(ISNUMBER(BT22)),NOT(ISNUMBER($C$28))),"",ROUND(AR22,0)-BS22-ROUND(BC22,0)+ROUND(-(BT22-N(AN22))*$C$28,0)) | BZ22: =IF(OR(NOT(ISNUMBER(AA22)),NOT(ISNUMBER(AS22)),AS22=0),"",AA22/(AS22*12)) | CA22: =IF(OR(NOT(ISNUMBER(AA22)),NOT(ISNUMBER(AS22)),AA22=0),"",AS22*12/AA22) | CB22: =IF(OR(NOT(ISNUMBER(AS22)),NOT(ISNUMBER(BC22)),NOT(ISNUMBER(BO22)),NOT(ISNUMBER($C$28)),NOT(ISNUMBER($C$35))),"",(AS22-BC22)*(1-$C$28)-$C$28*N(BE22)-IF(BM22="berechnet",$C$28*(1+$C$35)*BO22*N(BI22)/12,0)) | CC22: =IF(OR(NOT(ISNUMBER(F22)),NOT(ISNUMBER($C$26)),NOT(ISNUMBER($C$27)),NOT(ISNUMBER($C$28)),NOT(ISNUMBER($C$35)),NOT(ISNUMBER($H$33))),"",($C$28*(1+$C$35)*(N(U22)*N($H$31)+N(V22)*N($H$32))-(N(U22)+N(V22))*$H$33*(($C$26+$C$27)-$C$28*$C$26))/12) | CD22: =IF(OR(NOT(ISNUMBER(BO22)),NOT(ISNUMBER($C$26)),NOT(ISNUMBER($C$27)),NOT(ISNUMBER($C$28)),NOT(ISNUMBER($C$35)),NOT(ISNUMBER($H$33)),BM22="",AND(BM22="standard",NOT(ISNUMBER($C$31)))),"",($H$33*(($C$26+$C$27)-$C$28*$C$26)-$C$28*(1+$C$35)*BO22*IF(BM22="berechnet",1,IF(BM22="vertrag",BJ22,$C$31)))/12) | CE22: =IF(NOT(ISNUMBER(F22)),"",IF(N($O$26)=2,IF(OR(NOT(ISNUMBER(AS22)),NOT(ISNUMBER(AN22)),IF(ISNUMBER(M22),M22,N($O$28))<=0),"",IF(AS22*12/IF(ISNUMBER(M22),M22,N($O$28))-N(U22)-N(V22)<=0,"",AS22*12/IF(ISNUMBER(M22),M22,N($O$28))-N(U22)-N(V22))),IF(N($O$26)=3,IF(OR(NOT(ISNUMBER(CB22)),NOT(ISNUMBER(CC22)),NOT(ISNUMBER(CD22)),N(CD22)<=0),"",IF((CB22+CC22+ROUND(AS22,0)-AS22-ROUND(BC22,0)+BC22-IF(ISNUMBER(N22),N22,N($O$29)))/CD22<=0,"",(CB22+CC22+ROUND(AS22,0)-AS22-ROUND(BC22,0)+BC22-IF(ISNUMBER(N22),N22,N($O$29)))/CD22)),"")))
A23: SUMME / Ø | F23: =SUM(F3:F22) | G23: =COUNTIF(G3:G22,"ja") | H23: =SUM(H3:H22) | I23: =SUM(I3:I22) | J23: =SUM(J3:J22) | K23: =IF(OR(NOT(ISNUMBER(J23)),NOT(ISNUMBER($H$29)),$H$29=0),"",J23/$H$29) | L23: =IF(SUMIF(L3:L22,">0",F3:F22)=0,"",SUMPRODUCT(F3:F22,L3:L22)/SUMIF(L3:L22,">0",F3:F22)) | P23: =IF(SUMPRODUCT(--ISNUMBER(T3:T22),F3:F22)=0,"",T23/SUMPRODUCT(--ISNUMBER(T3:T22),F3:F22)) | Q23: =IF(OR(NOT(ISNUMBER(F23)),F23=0,NOT(ISNUMBER(VERKAUFSMATRIX!U28))),"",VERKAUFSMATRIX!U28/F23) | R23: =IF(OR(NOT(ISNUMBER(P23)),NOT(ISNUMBER(Q23)),Q23=0),"",P23/Q23-1) | S23: =SUM(S3:S22) | T23: =SUM(T3:T22) | U23: =SUM(U3:U22) | V23: =SUM(V3:V22) | W23: =SUM(W3:W22) | X23: =IF(OR(NOT(ISNUMBER(Z23)),NOT(ISNUMBER(W23)),W23=0),"",Z23/W23) | Z23: =SUM(Z3:Z22) | AA23: =SUM(AA3:AA22) | AB23: =SUM(AB3:AB22) | AC23: =IF(OR(NOT(ISNUMBER(W23)),NOT(ISNUMBER(F23)),F23=0),"",W23/F23) | AD23: =IF(OR(NOT(ISNUMBER(AB23)),NOT(ISNUMBER(F23)),F23=0),"",AB23/F23) | AE23: =SUM(AE3:AE22) | AF23: =SUM(AF3:AF22) | AG23: =SUM(AG3:AG22) | AH23: =SUM(AH3:AH22) | AI23: =SUM(AI3:AI22) | AJ23: =SUM(AJ3:AJ22) | AK23: =COUNT(AK3:AK22)&" WE manuell" | AL23: =SUM(AL3:AL22) | AM23: =SUM(AM3:AM22) | AN23: =SUM(AN3:AN22) | AO23: =SUM(AO3:AO22) | AP23: =SUM(AP3:AP22) | AQ23: =SUM(AQ3:AQ22) | AR23: =SUM(AR3:AR22) | AS23: =SUM(AS3:AS22) | AT23: =IF(SUMPRODUCT(--ISNUMBER(AL3:AL22),F3:F22)=0,"",AL23/SUMPRODUCT(--ISNUMBER(AL3:AL22),F3:F22)) | AU23: =IF(COUNT(AU3:AU22)=0,"",MIN(AU3:AU22)) | AV23: =IF(COUNT(AV3:AV22)=0,"",MAX(AV3:AV22)) | AX23: =IF(COUNT(AX3:AX22)=0,"",MAX(AX3:AX22)) | AY23: =SUM(AY3:AY22) | AZ23: =SUM(AZ3:AZ22) | BC23: =SUM(BC3:BC22) | BE23: =SUM(BE3:BE22) | BF23: =IF(OR(NOT(ISNUMBER(BC23)),NOT(ISNUMBER(AL23)),AL23=0),"",BC23/AL23) | BG23: =SUM(BG3:BG22) | BH23: =SUM(BH3:BH22) | BI23: =SUM(BI3:BI22) | BK23: =IF(OR(NOT(ISNUMBER(BI23)),NOT(ISNUMBER(AB23)),AB23=0),"",1-BI23/AB23) | BL23: =IF(OR(NOT(ISNUMBER(BI23)),NOT(ISNUMBER(AE23)),AE23=0),"",1-BI23/AE23) | BP23: =SUM(BP3:BP22) | BQ23: =SUM(BQ3:BQ22) | BR23: =SUM(BR3:BR22) | BS23: =SUM(BS3:BS22) | BT23: =SUM(BT3:BT22) | BU23: =SUM(BU3:BU22) | BV23: =SUM(BV3:BV22) | BW23: =SUM(BW3:BW22) | ... BY23: =SUM(BY3:BY22) | BZ23: =IF(SUMPRODUCT(--ISNUMBER(AS3:AS22),--ISNUMBER(AA3:AA22),AS3:AS22)=0,"",SUMPRODUCT(--ISNUMBER(AS3:AS22),--ISNUMBER(AA3:AA22),AA3:AA22)/(SUMPRODUCT(--ISNUMBER(AS3:AS22),--ISNUMBER(AA3:AA22),AS3:AS22)*12)) | CA23: =IF(SUMPRODUCT(--ISNUMBER(AS3:AS22),--ISNUMBER(AA3:AA22),AA3:AA22)=0,"",SUMPRODUCT(--ISNUMBER(AS3:AS22),--ISNUMBER(AA3:AA22),AS3:AS22)*12/SUMPRODUCT(--ISNUMBER(AS3:AS22),--ISNUMBER(AA3:AA22),AA3:AA22)) | CB23: =SUM(CB3:CB22) | CC23: =SUM(CC3:CC22) | CE23: =SUM(CE3:CE22)
A25: KÄUFER-PROFIL (Standard für alle Wohnungen) | E25: OBJEKT, ASSETS, STEUERUNG | J25: EINGABE-WEG (bestimmt den Verkaufspreis)
A26: Zins Käufer (p.a.) | C26: 0.048 | E26: Provision Standard (% vom Abgabepreis) | H26: 0.07 | J26: Eingabe-Weg: 1 = Regler €/m², 2 = Bruttomietrendite, 3 = Cashflow n. St. | O26: 1
A27: Tilgung Käufer (p.a.) | C27: 0.01 | E27: Grundstücksfläche gesamt (m²) | H27: 769 | J27: → aktiver Weg | O27: =IF(N($O$26)=2,"Bruttomietrendite",IF(N($O$26)=3,"Cashflow nach Steuern",IF(OR(N($O$26)=1,$O$26=""),"Regler €/m²","Regler €/m² (Schalter: 1, 2 oder 3)")))
A28: Grenzsteuersatz | C28: 0.42 | E28: Bodenrichtwert (€/m²) | H28: 240 | J28: Ziel-Bruttomietrendite (Soll-Miete inkl. Subvention) | O28: 0.05
A29: Bewirtschaftungsquote (Alt-Kontrolle) | C29: =IF(OR(NOT(ISNUMBER(C66)),NOT(ISNUMBER(C67)),NOT(ISNUMBER($C$69)),$C$69=0),"",(C66+C67)/$C$69) | E29: MEA-Nenner (Teilungserklärung) | H29: 895 | J29: Ziel-Cashflow nach Steuern mit Subvention (€/Mo) | O29: 0
A30: AfA-Satz Wohnung (Standard) | C30: 0.02 | E30: Bodenwert Haus gesamt (€) | H30: =IF(OR(NOT(ISNUMBER($H$27)),NOT(ISNUMBER($H$28))),"",$H$27*$H$28)
A31: Gebäudeanteil (Standard) | C31: 0.8 | E31: AfA-Satz Garage (p.a.) | H31: 0.02
A32: Finanzierung: 1 = 100 % KP, 2 = alles finanziert (108,5 %) | C32: 2 | E32: AfA-Satz Außenstellplatz (0 %) | H32: 0
A33: Loan-Faktor alles finanziert = 1 + KNK | C33: =IF(OR(NOT(ISNUMBER($C$35)),$C$35<0,$C$35>=1),"",1+$C$35) | E33: Loan-Faktor Vorwärtsrechnung (aus Finanzierung) | H33: =IF(NOT(ISNUMBER($C$32)),"",IF($C$32=1,1,IF(NOT(ISNUMBER($C$33)),"",$C$33)))
A34: k-Faktor global (Alt-Kontrolle) | C34: =IF(OR(NOT(ISNUMBER($H$33)),NOT(ISNUMBER($C$26)),NOT(ISNUMBER($C$27)),NOT(ISNUMBER($C$28)),NOT(ISNUMBER($C$30)),NOT(ISNUMBER($C$31)),NOT(ISNUMBER($C$35))),"",($H$33*(($C$26+$C$27)-$C$28*$C$26)-$C$28*$C$31*$C$30*(1+$C$35))/12) | E34: Sperrfrist Mieterhöhung (Monate) | H34: 36
A35: Kaufnebenkosten (GrESt 6,5 % + Notar/GB 2 %) | C35: 0.085
A36: Eingabe | B36: beschreibbares Feld - je Wohnung in der Tabelle oder oben im Parameterblock
A37: Annahme | B37: Eingabefeld je Wohnung leer = Standardwert aus dem Parameterblock greift (Provision, Hausgeld, AfA, Gebäudeanteil ...)
A38: Ergebnis | B38: Formel - nicht überschreiben; Hilfsspalten über die Schaltfläche + über der Tabelle aufklappen
A39: Aktiv | B39: bestimmt gerade den Preis (Eingabe-Weg rechts); grau = wirkt im gewählten Weg nicht
A40: Hinweis | B40: orange = Rückfall auf den Regler (keine Miete/kein Ziel) oder Miete angehoben; rot = Datenfehler
A41: VERGLEICH: MARKT-ANSATZ vs. VORWAERTS-ANSATZ
A43: VK Wohnungen MARKT-ANSATZ (VERKAUFSMATRIX!U28) | C43: =IFERROR(VERKAUFSMATRIX!U28,0)
A44: VK Wohnungen VORWAERTS-ANSATZ (Abgabepreis inkl. Aufschlag, ohne Garage/Provision) | C44: =T23
A45: Kaufpreis Garagen + Stellplätze gesamt (€) | C45: =IF(AND(NOT(ISNUMBER(U23)),NOT(ISNUMBER(V23))),"",N(U23)+N(V23))
A48: Delta (CF − Markt) in EUR | C48: =IFERROR(C44-C43,"")
A49: Delta (CF − Markt) in % | C49: =IFERROR((C44-C43)/C43,"")
A61: BEWIRTSCHAFTUNG (nicht umlagefaehig) - Standard fuer Wohnungen ohne Hausgeld-Angabe; speist die Alt-Kontrolle
A62: Verwaltung (EUR/WE/Monat) - Standardquelle Stufe 3 fuer AY | C62: 35
A63: Anzahl WE | C63: =COUNT(F3:F22)
A64: Laufende Rücklage (€/m²/Jahr) - Standard/Obergrenze fuer AY und BA | C64: 14
A65: Wohnfläche gesamt (m2) | C65: =F23
A66: Verwaltung gesamt (EUR/Jahr) | C66: =C62*C63*12
A67: Ruecklage gesamt (EUR/Jahr) | C67: =C64*C65
A68: Ruecklage ueber 10 Jahre (EUR) | C68: =C67*10
A69: Nettokaltmiete IST (€/Jahr) | C69: =IF(NOT(ISNUMBER(AL23)),"",AL23*12)
A70: -> Bewirtschaftungsquote C8 | C70: =$C$29
A73: RUECKLAGEN-TOPF -> Quote & max. Verkaufspreis (Alt-Kontrolle, globale Annahmen)
A74: Vorhandene WEG-Ruecklage (Referenz) | C74: =IFERROR(BESICHTIGUNG!B11,0)
A75: 10-Jahres-Bedarf (EUR) | C75: =C68
A76: Topf EUR | B76: Rueckl. EUR/m2 | C76: Rueckl. EUR/Jahr | D76: Quote C8 | E76: max. VK-Preis
A77: 0 | B77: =MAX(0,($C$75-A77)/10)/$C$65 | C77: =MAX(0,($C$75-A77)/10) | D77: =IF(OR(NOT(ISNUMBER($C$69)),$C$69=0),"",($C$66+C77)/$C$69) | E77: =(((1-$C$28)*(1-D77)*$AL$23)-$C$63*$O$29)/$C$34
A78: 5000 | B78: =MAX(0,($C$75-A78)/10)/$C$65 | C78: =MAX(0,($C$75-A78)/10) | D78: =IF(OR(NOT(ISNUMBER($C$69)),$C$69=0),"",($C$66+C78)/$C$69) | E78: =(((1-$C$28)*(1-D78)*$AL$23)-$C$63*$O$29)/$C$34
A79: 10000 | B79: =MAX(0,($C$75-A79)/10)/$C$65 | C79: =MAX(0,($C$75-A79)/10) | D79: =IF(OR(NOT(ISNUMBER($C$69)),$C$69=0),"",($C$66+C79)/$C$69) | E79: =(((1-$C$28)*(1-D79)*$AL$23)-$C$63*$O$29)/$C$34
A80: 15000 | B80: =MAX(0,($C$75-A80)/10)/$C$65 | C80: =MAX(0,($C$75-A80)/10) | D80: =IF(OR(NOT(ISNUMBER($C$69)),$C$69=0),"",($C$66+C80)/$C$69) | E80: =(((1-$C$28)*(1-D80)*$AL$23)-$C$63*$O$29)/$C$34
A81: 20000 | B81: =MAX(0,($C$75-A81)/10)/$C$65 | C81: =MAX(0,($C$75-A81)/10) | D81: =IF(OR(NOT(ISNUMBER($C$69)),$C$69=0),"",($C$66+C81)/$C$69) | E81: =(((1-$C$28)*(1-D81)*$AL$23)-$C$63*$O$29)/$C$34
A82: 25000 | B82: =MAX(0,($C$75-A82)/10)/$C$65 | C82: =MAX(0,($C$75-A82)/10) | D82: =IF(OR(NOT(ISNUMBER($C$69)),$C$69=0),"",($C$66+C82)/$C$69) | E82: =(((1-$C$28)*(1-D82)*$AL$23)-$C$63*$O$29)/$C$34
A83: 30000 | B83: =MAX(0,($C$75-A83)/10)/$C$65 | C83: =MAX(0,($C$75-A83)/10) | D83: =IF(OR(NOT(ISNUMBER($C$69)),$C$69=0),"",($C$66+C83)/$C$69) | E83: =(((1-$C$28)*(1-D83)*$AL$23)-$C$63*$O$29)/$C$34
A84: 35000 | B84: =MAX(0,($C$75-A84)/10)/$C$65 | C84: =MAX(0,($C$75-A84)/10) | D84: =IF(OR(NOT(ISNUMBER($C$69)),$C$69=0),"",($C$66+C84)/$C$69) | E84: =(((1-$C$28)*(1-D84)*$AL$23)-$C$63*$O$29)/$C$34
A85: 40000 | B85: =MAX(0,($C$75-A85)/10)/$C$65 | C85: =MAX(0,($C$75-A85)/10) | D85: =IF(OR(NOT(ISNUMBER($C$69)),$C$69=0),"",($C$66+C85)/$C$69) | E85: =(((1-$C$28)*(1-D85)*$AL$23)-$C$63*$O$29)/$C$34
A86: 45000 | B86: =MAX(0,($C$75-A86)/10)/$C$65 | C86: =MAX(0,($C$75-A86)/10) | D86: =IF(OR(NOT(ISNUMBER($C$69)),$C$69=0),"",($C$66+C86)/$C$69) | E86: =(((1-$C$28)*(1-D86)*$AL$23)-$C$63*$O$29)/$C$34
A87: 50000 | B87: =MAX(0,($C$75-A87)/10)/$C$65 | C87: =MAX(0,($C$75-A87)/10) | D87: =IF(OR(NOT(ISNUMBER($C$69)),$C$69=0),"",($C$66+C87)/$C$69) | E87: =(((1-$C$28)*(1-D87)*$AL$23)-$C$63*$O$29)/$C$34

Sheet Marktpreis Verifizierung
C2: Name | D2: Firma | F2: Telefon | G2: Worst-Case | H2: Best Case
B3: 1 | C3: Max Makler | D3: Homeday | F3: 0151/12626547 | G3: 2700 | H3: 3000
B4: 2
B5: 3
B6: 4
B7: 5
B8: 6
B9: 7
B10: 8
B11: 9
B12: 10
F14: Durschnitt | G14: =AVERAGE(G3:G12) | H14: =AVERAGE(H3:H12)
F15: Gesamt Durschnitt | G15: =AVERAGE(G14,H14)
B18: TEST BALLON 1 (leerstehend) | F18: TEST BALLON 2 (vermietet)
G19: Kaltmiete = | H19: 500
B20: Ballon Inseriert am | D20: 45485 | F20: Ballon Inseriert am
B21: Ballon war X Tage online | F21: Ballon war X Tage online
B22: Welches Bildmaterial wurde verwendet | F22: Welches Bildmaterial wurde verwendet
B23: Zustand der Wohnung | F23: Zustand der Wohnung
B24: Wie viele Anfragen? | F24: Wie viele Anfragen?
B25: Davon Makler Anfragen | F25: Davon Makler Anfragen
B26: Rest Anfragen | D26: =D24-D25 | F26: Rest Anfragen | H26: =H24-H25
B28: Link zum Inserat | F28: Link zum Inserat

Sheet Checkliste Objektprüfung
B2: OBJEKTUNTERLAGEN | G2: ZIELGRUPPE VERKAUF
B3: ERFORDERLICH FÜR OBJEKTPRÜFUNG | C3: VORHANDEN? | D3: GEPRÜFT? | E3: BESONDERHEITEN | G3: Beschreibung
B4: Expose/Bilder | C4: Ja | D4: Ja
B5: Grundbuch (nicht älter als 3 Monate) | C5: Ja | D5: Ja
B6: Grundrisse | C6: Ja | D6: Ja
B7: Wohnflächenberechnung | C7: Ja | D7: Ja | G7: STRATEGIE
C8: =IF(OR(COUNTIF(C4:C5,"Nein")>0, COUNTIF(C6:C7,"Nein")>0), "Objektunterlagen noch nicht vollständig!", "Objektunterlagen vollständig!") | D8: =IF(OR(COUNTIF(D4:D5,"Nein")>0, COUNTIF(D6:D7,"Nein")>0), "Objektunterlagen noch nicht vollständig!", "Objektunterlagen vollständig!") | E8: =IF(OR(COUNTIF(C4:C5,"Nein")>0, COUNTIF(C6:C7,"Nein")>0, COUNTIF(D4:D5,"Nein")>0, COUNTIF(D6:D7,"Nein")>0), "Objektunterlagen noch nicht vollständig/geprüft!", HYPERLINK("https://freiheit-mit-immobilien.mymemberspot.de/library/baGnXp5W4n1asNko0Rmx/4uzt76RlLRjCUoTXLc5B/6enCHKFepesO93y22M4v/details", "OBJEKTPRÜFUNG EINREICHEN")) | G8: Beschreibung
B10: ERFORDERLICH FÜR FINANZIERUNG | C10: VORHANDEN? | D10: GEPRÜFT? | E10: BESONDERHEITEN | G10: OBJEKTGESCHICHTE
B11: Energieausweis | C11: Ja | D11: Ja | G11: Lead Herkunft | H11: =BESICHTIGUNG!B3
B12: Nebenkostenabrechnung | C12: Ja | D12: Ja | G12: Wer ist der Eigentümer? | H12: =BESICHTIGUNG!B26
B13: Lageplan | C13: Ja | D13: Ja | G13: Warum wird das Objekt verkauft? | H13: =BESICHTIGUNG!B27
B14: Baulastenauskunft | C14: Ja | D14: Ja | G14: Schmerzgrenze Preis? | H14: =BESICHTIGUNG!B28
B15: Gebäudeversicherung | C15: Ja | D15: Ja | G15: Besonderheiten zum Haus / Erster Eindruck Umgebung | H15: =BESICHTIGUNG!B15
C16: =IF(COUNTIF(C11:C15,"Nein")>0, "Objektunterlagen noch nicht vollständig!", "Objektunterlagen vollständig!") | D16: =IF(COUNTIF(D11:D15,"Nein")>0, "Objektunterlagen noch nicht geprüft!", "Objektunterlagen geprüft!")
B18: FALLS VORHANDEN | C18: VORHANDEN? | D18: GEPRÜFT? | E18: BESONDERHEITEN
B19: Teilungserklärung | C19: Nein | D19: Nein
B20: Protokolle der Eigentümerversammlung | C20: Nein | D20: Nein
B21: Mietverträge (wenn vermietet) | C21: Ja | D21: Nein
G22: FINANZIERUNG
G23: =KALKU!M21 | I23: =KALKU!J39
B24: VERMIETUNG | G24: =KALKU!M22 | H24: =I24/I23 | I24: =KALKU!P22
B25: Wie viele Einheiten sind vermietet / leer? | C25: =BESICHTIGUNG!B31 | D25: =BESICHTIGUNG!B32 | G25: =KALKU!M23 | H25: =I25/I23 | I25: =KALKU!P23
B26: JNKM IST / Rendite IST | C26: =MIETER!J31 | D26: =MIETER!K32 | G26: =KALKU!M24 | I26: =KALKU!P24
B27: JNKM SOLL / Rendite SOLL | C27: =MIETER!N31 | D27: =MIETER!O32 | G27: Genügend EK für Deal vorhanden | H27: Ja
B28: JNKM Modernisierung / Rendite | C28: =MIETER!R31 | D28: =MIETER!S32 | G28: EK soll für diesen Deal verwendet werden | H28: Ja
G29: Kontakt zu Bank / Finanzierungsvermittler vorhanden? | H29: Ja
B30: KAUFPREIS HISTORIE | D30: SONSTIGE HINWEISE | G30: Notizen zur Finanzierung
B31: Inseratspreis | C31: =BESICHTIGUNG!B13 | D31: Hinweise
B32: Schmerzgrenze Preis | C32: =BESICHTIGUNG!B28
B33: Angebotspreis laut Kalkulation | C33: =KALKU!P37
B34: Schriftlich abgegebener Angebotspreis | C34: 800000
B35: Geeinigter Kaufpreis (geclosed) | C35: 900000
B37: GEPLANTE AUFWERTUNGSMAßNAHMEN
B38: Renovierung durch Fachmann verifiziert | C38: Ja | D38: Bemerkung | G38: =RENO!K6 | H38: =RENO!O6 | I38: =RENO!P6
A40: Nr | B40: Gewerk | C40: Maßnahme | E40: Menge | F40: Einheit | G40: Lohnkosten | H40: Materialkosten | I40: Gesamtkosten
A41: =IF(MAX(RENO!$C$12:$C$105)>0,1,"") | B41: =IF(A41<>"",IFERROR(VLOOKUP($A41,RENO!$C$12:$P$105,2,0),""),"") | C41: =IF(A41<>"",IFERROR(VLOOKUP($A41,RENO!$C$12:$P$105,4,0),""),"") | E41: =IF(A41<>"",IFERROR(VLOOKUP($A41,RENO!$C$12:$P$105,7,0),""),"") | F41: =IF(A41<>"",IFERROR(VLOOKUP($A41,RENO!$C$12:$P$105,8,0),""),"") | G41: =IF(A41<>"",IFERROR(VLOOKUP($A41,RENO!$C$12:$P$105,12,0),""),"") | H41: =IF(A41<>"",IFERROR(VLOOKUP($A41,RENO!$C$12:$P$105,13,0),""),"") | I41: =IF(A41<>"",IFERROR(VLOOKUP($A41,RENO!$C$12:$P$105,14,0),""),"")
A42: =IF(MAX(RENO!$C$12:$C$93)>A41,A41+1,"") | B42: =IF(A42<>"",IFERROR(VLOOKUP($A42,RENO!$C$12:$P$105,2,0),""),"") | C42: =IF(A42<>"",IFERROR(VLOOKUP($A42,RENO!$C$12:$P$105,4,0),""),"") | E42: =IF(A42<>"",IFERROR(VLOOKUP($A42,RENO!$C$12:$P$105,7,0),""),"") | F42: =IF(A42<>"",IFERROR(VLOOKUP($A42,RENO!$C$12:$P$105,8,0),""),"") | G42: =IF(A42<>"",IFERROR(VLOOKUP($A42,RENO!$C$12:$P$105,12,0),""),"") | H42: =IF(A42<>"",IFERROR(VLOOKUP($A42,RENO!$C$12:$P$105,13,0),""),"") | I42: =IF(A42<>"",IFERROR(VLOOKUP($A42,RENO!$C$12:$P$105,14,0),""),"")
A43: =IF(MAX(RENO!$C$12:$C$93)>A42,A42+1,"") | B43: =IF(A43<>"",IFERROR(VLOOKUP($A43,RENO!$C$12:$P$105,2,0),""),"") | C43: =IF(A43<>"",IFERROR(VLOOKUP($A43,RENO!$C$12:$P$105,4,0),""),"") | E43: =IF(A43<>"",IFERROR(VLOOKUP($A43,RENO!$C$12:$P$105,7,0),""),"") | F43: =IF(A43<>"",IFERROR(VLOOKUP($A43,RENO!$C$12:$P$105,8,0),""),"") | G43: =IF(A43<>"",IFERROR(VLOOKUP($A43,RENO!$C$12:$P$105,12,0),""),"") | H43: =IF(A43<>"",IFERROR(VLOOKUP($A43,RENO!$C$12:$P$105,13,0),""),"") | I43: =IF(A43<>"",IFERROR(VLOOKUP($A43,RENO!$C$12:$P$105,14,0),""),"")
A44: =IF(MAX(RENO!$C$12:$C$93)>A43,A43+1,"") | B44: =IF(A44<>"",IFERROR(VLOOKUP($A44,RENO!$C$12:$P$105,2,0),""),"") | C44: =IF(A44<>"",IFERROR(VLOOKUP($A44,RENO!$C$12:$P$105,4,0),""),"") | E44: =IF(A44<>"",IFERROR(VLOOKUP($A44,RENO!$C$12:$P$105,7,0),""),"") | F44: =IF(A44<>"",IFERROR(VLOOKUP($A44,RENO!$C$12:$P$105,8,0),""),"") | G44: =IF(A44<>"",IFERROR(VLOOKUP($A44,RENO!$C$12:$P$105,12,0),""),"") | H44: =IF(A44<>"",IFERROR(VLOOKUP($A44,RENO!$C$12:$P$105,13,0),""),"") | I44: =IF(A44<>"",IFERROR(VLOOKUP($A44,RENO!$C$12:$P$105,14,0),""),"")
A45: =IF(MAX(RENO!$C$12:$C$93)>A44,A44+1,"") | B45: =IF(A45<>"",IFERROR(VLOOKUP($A45,RENO!$C$12:$P$105,2,0),""),"") | C45: =IF(A45<>"",IFERROR(VLOOKUP($A45,RENO!$C$12:$P$105,4,0),""),"") | E45: =IF(A45<>"",IFERROR(VLOOKUP($A45,RENO!$C$12:$P$105,7,0),""),"") | F45: =IF(A45<>"",IFERROR(VLOOKUP($A45,RENO!$C$12:$P$105,8,0),""),"") | G45: =IF(A45<>"",IFERROR(VLOOKUP($A45,RENO!$C$12:$P$105,12,0),""),"") | H45: =IF(A45<>"",IFERROR(VLOOKUP($A45,RENO!$C$12:$P$105,13,0),""),"") | I45: =IF(A45<>"",IFERROR(VLOOKUP($A45,RENO!$C$12:$P$105,14,0),""),"")
A46: =IF(MAX(RENO!$C$12:$C$93)>A45,A45+1,"") | B46: =IF(A46<>"",IFERROR(VLOOKUP($A46,RENO!$C$12:$P$105,2,0),""),"") | C46: =IF(A46<>"",IFERROR(VLOOKUP($A46,RENO!$C$12:$P$105,4,0),""),"") | E46: =IF(A46<>"",IFERROR(VLOOKUP($A46,RENO!$C$12:$P$105,7,0),""),"") | F46: =IF(A46<>"",IFERROR(VLOOKUP($A46,RENO!$C$12:$P$105,8,0),""),"") | G46: =IF(A46<>"",IFERROR(VLOOKUP($A46,RENO!$C$12:$P$105,12,0),""),"") | H46: =IF(A46<>"",IFERROR(VLOOKUP($A46,RENO!$C$12:$P$105,13,0),""),"") | I46: =IF(A46<>"",IFERROR(VLOOKUP($A46,RENO!$C$12:$P$105,14,0),""),"")
A47: =IF(MAX(RENO!$C$12:$C$93)>A46,A46+1,"") | B47: =IF(A47<>"",IFERROR(VLOOKUP($A47,RENO!$C$12:$P$105,2,0),""),"") | C47: =IF(A47<>"",IFERROR(VLOOKUP($A47,RENO!$C$12:$P$105,4,0),""),"") | E47: =IF(A47<>"",IFERROR(VLOOKUP($A47,RENO!$C$12:$P$105,7,0),""),"") | F47: =IF(A47<>"",IFERROR(VLOOKUP($A47,RENO!$C$12:$P$105,8,0),""),"") | G47: =IF(A47<>"",IFERROR(VLOOKUP($A47,RENO!$C$12:$P$105,12,0),""),"") | H47: =IF(A47<>"",IFERROR(VLOOKUP($A47,RENO!$C$12:$P$105,13,0),""),"") | I47: =IF(A47<>"",IFERROR(VLOOKUP($A47,RENO!$C$12:$P$105,14,0),""),"")
A48: =IF(MAX(RENO!$C$12:$C$93)>A47,A47+1,"") | B48: =IF(A48<>"",IFERROR(VLOOKUP($A48,RENO!$C$12:$P$105,2,0),""),"") | C48: =IF(A48<>"",IFERROR(VLOOKUP($A48,RENO!$C$12:$P$105,4,0),""),"") | E48: =IF(A48<>"",IFERROR(VLOOKUP($A48,RENO!$C$12:$P$105,7,0),""),"") | F48: =IF(A48<>"",IFERROR(VLOOKUP($A48,RENO!$C$12:$P$105,8,0),""),"") | G48: =IF(A48<>"",IFERROR(VLOOKUP($A48,RENO!$C$12:$P$105,12,0),""),"") | H48: =IF(A48<>"",IFERROR(VLOOKUP($A48,RENO!$C$12:$P$105,13,0),""),"") | I48: =IF(A48<>"",IFERROR(VLOOKUP($A48,RENO!$C$12:$P$105,14,0),""),"")
A49: =IF(MAX(RENO!$C$12:$C$93)>A48,A48+1,"") | B49: =IF(A49<>"",IFERROR(VLOOKUP($A49,RENO!$C$12:$P$105,2,0),""),"") | C49: =IF(A49<>"",IFERROR(VLOOKUP($A49,RENO!$C$12:$P$105,4,0),""),"") | E49: =IF(A49<>"",IFERROR(VLOOKUP($A49,RENO!$C$12:$P$105,7,0),""),"") | F49: =IF(A49<>"",IFERROR(VLOOKUP($A49,RENO!$C$12:$P$105,8,0),""),"") | G49: =IF(A49<>"",IFERROR(VLOOKUP($A49,RENO!$C$12:$P$105,12,0),""),"") | H49: =IF(A49<>"",IFERROR(VLOOKUP($A49,RENO!$C$12:$P$105,13,0),""),"") | I49: =IF(A49<>"",IFERROR(VLOOKUP($A49,RENO!$C$12:$P$105,14,0),""),"")
A50: =IF(MAX(RENO!$C$12:$C$93)>A49,A49+1,"") | B50: =IF(A50<>"",IFERROR(VLOOKUP($A50,RENO!$C$12:$P$105,2,0),""),"") | C50: =IF(A50<>"",IFERROR(VLOOKUP($A50,RENO!$C$12:$P$105,4,0),""),"") | E50: =IF(A50<>"",IFERROR(VLOOKUP($A50,RENO!$C$12:$P$105,7,0),""),"") | F50: =IF(A50<>"",IFERROR(VLOOKUP($A50,RENO!$C$12:$P$105,8,0),""),"") | G50: =IF(A50<>"",IFERROR(VLOOKUP($A50,RENO!$C$12:$P$105,12,0),""),"") | H50: =IF(A50<>"",IFERROR(VLOOKUP($A50,RENO!$C$12:$P$105,13,0),""),"") | I50: =IF(A50<>"",IFERROR(VLOOKUP($A50,RENO!$C$12:$P$105,14,0),""),"")
A51: =IF(MAX(RENO!$C$12:$C$93)>A50,A50+1,"") | B51: =IF(A51<>"",IFERROR(VLOOKUP($A51,RENO!$C$12:$P$105,2,0),""),"") | C51: =IF(A51<>"",IFERROR(VLOOKUP($A51,RENO!$C$12:$P$105,4,0),""),"") | E51: =IF(A51<>"",IFERROR(VLOOKUP($A51,RENO!$C$12:$P$105,7,0),""),"") | F51: =IF(A51<>"",IFERROR(VLOOKUP($A51,RENO!$C$12:$P$105,8,0),""),"") | G51: =IF(A51<>"",IFERROR(VLOOKUP($A51,RENO!$C$12:$P$105,12,0),""),"") | H51: =IF(A51<>"",IFERROR(VLOOKUP($A51,RENO!$C$12:$P$105,13,0),""),"") | I51: =IF(A51<>"",IFERROR(VLOOKUP($A51,RENO!$C$12:$P$105,14,0),""),"")
A52: =IF(MAX(RENO!$C$12:$C$93)>A51,A51+1,"") | B52: =IF(A52<>"",IFERROR(VLOOKUP($A52,RENO!$C$12:$P$105,2,0),""),"") | C52: =IF(A52<>"",IFERROR(VLOOKUP($A52,RENO!$C$12:$P$105,4,0),""),"") | E52: =IF(A52<>"",IFERROR(VLOOKUP($A52,RENO!$C$12:$P$105,7,0),""),"") | F52: =IF(A52<>"",IFERROR(VLOOKUP($A52,RENO!$C$12:$P$105,8,0),""),"") | G52: =IF(A52<>"",IFERROR(VLOOKUP($A52,RENO!$C$12:$P$105,12,0),""),"") | H52: =IF(A52<>"",IFERROR(VLOOKUP($A52,RENO!$C$12:$P$105,13,0),""),"") | I52: =IF(A52<>"",IFERROR(VLOOKUP($A52,RENO!$C$12:$P$105,14,0),""),"")
A53: =IF(MAX(RENO!$C$12:$C$93)>A52,A52+1,"") | B53: =IF(A53<>"",IFERROR(VLOOKUP($A53,RENO!$C$12:$P$105,2,0),""),"") | C53: =IF(A53<>"",IFERROR(VLOOKUP($A53,RENO!$C$12:$P$105,4,0),""),"") | E53: =IF(A53<>"",IFERROR(VLOOKUP($A53,RENO!$C$12:$P$105,7,0),""),"") | F53: =IF(A53<>"",IFERROR(VLOOKUP($A53,RENO!$C$12:$P$105,8,0),""),"") | G53: =IF(A53<>"",IFERROR(VLOOKUP($A53,RENO!$C$12:$P$105,12,0),""),"") | H53: =IF(A53<>"",IFERROR(VLOOKUP($A53,RENO!$C$12:$P$105,13,0),""),"") | I53: =IF(A53<>"",IFERROR(VLOOKUP($A53,RENO!$C$12:$P$105,14,0),""),"")
... A132: =IF(MAX(RENO!$C$12:$C$93)>A131,A131+1,"") | B132: =IF(A132<>"",IFERROR(VLOOKUP($A132,RENO!$C$12:$P$105,2,0),""),"") | C132: =IF(A132<>"",IFERROR(VLOOKUP($A132,RENO!$C$12:$P$105,4,0),""),"") | E132: =IF(A132<>"",IFERROR(VLOOKUP($A132,RENO!$C$12:$P$105,7,0),""),"") | F132: =IF(A132<>"",IFERROR(VLOOKUP($A132,RENO!$C$12:$P$105,8,0),""),"") | G132: =IF(A132<>"",IFERROR(VLOOKUP($A132,RENO!$C$12:$P$105,12,0),""),"") | H132: =IF(A132<>"",IFERROR(VLOOKUP($A132,RENO!$C$12:$P$105,13,0),""),"") | I132: =IF(A132<>"",IFERROR(VLOOKUP($A132,RENO!$C$12:$P$105,14,0),""),"")
B133: =IF(A133<>"",IFERROR(VLOOKUP($A133,RENO!$C$12:$P$105,2,0),""),"") | C133: =IF(A133<>"",IFERROR(VLOOKUP($A133,RENO!$C$12:$P$105,4,0),""),"") | E133: =IF(A133<>"",IFERROR(VLOOKUP($A133,RENO!$C$12:$P$105,7,0),""),"") | F133: =IF(A133<>"",IFERROR(VLOOKUP($A133,RENO!$C$12:$P$105,8,0),""),"") | G133: =IF(A133<>"",IFERROR(VLOOKUP($A133,RENO!$C$12:$P$105,12,0),""),"") | H133: =IF(A133<>"",IFERROR(VLOOKUP($A133,RENO!$C$12:$P$105,13,0),""),"") | I133: =IF(A133<>"",IFERROR(VLOOKUP($A133,RENO!$C$12:$P$105,14,0),""),"")
B134: =IF(A134<>"",IFERROR(VLOOKUP($A134,RENO!$C$12:$P$105,2,0),""),"") | C134: =IF(A134<>"",IFERROR(VLOOKUP($A134,RENO!$C$12:$P$105,4,0),""),"") | E134: =IF(A134<>"",IFERROR(VLOOKUP($A134,RENO!$C$12:$P$105,7,0),""),"") | F134: =IF(A134<>"",IFERROR(VLOOKUP($A134,RENO!$C$12:$P$105,8,0),""),"") | G134: =IF(A134<>"",IFERROR(VLOOKUP($A134,RENO!$C$12:$P$105,12,0),""),"") | H134: =IF(A134<>"",IFERROR(VLOOKUP($A134,RENO!$C$12:$P$105,13,0),""),"") | I134: =IF(A134<>"",IFERROR(VLOOKUP($A134,RENO!$C$12:$P$105,14,0),""),"")
B135: =IF(A135<>"",IFERROR(VLOOKUP($A135,RENO!$C$12:$P$105,2,0),""),"") | C135: =IF(A135<>"",IFERROR(VLOOKUP($A135,RENO!$C$12:$P$105,4,0),""),"") | E135: =IF(A135<>"",IFERROR(VLOOKUP($A135,RENO!$C$12:$P$105,7,0),""),"") | F135: =IF(A135<>"",IFERROR(VLOOKUP($A135,RENO!$C$12:$P$105,8,0),""),"") | G135: =IF(A135<>"",IFERROR(VLOOKUP($A135,RENO!$C$12:$P$105,12,0),""),"") | H135: =IF(A135<>"",IFERROR(VLOOKUP($A135,RENO!$C$12:$P$105,13,0),""),"") | I135: =IF(A135<>"",IFERROR(VLOOKUP($A135,RENO!$C$12:$P$105,14,0),""),"")
B136: =IF(A136<>"",IFERROR(VLOOKUP($A136,RENO!$C$12:$P$105,2,0),""),"") | C136: =IF(A136<>"",IFERROR(VLOOKUP($A136,RENO!$C$12:$P$105,4,0),""),"") | E136: =IF(A136<>"",IFERROR(VLOOKUP($A136,RENO!$C$12:$P$105,7,0),""),"") | F136: =IF(A136<>"",IFERROR(VLOOKUP($A136,RENO!$C$12:$P$105,8,0),""),"") | G136: =IF(A136<>"",IFERROR(VLOOKUP($A136,RENO!$C$12:$P$105,12,0),""),"") | H136: =IF(A136<>"",IFERROR(VLOOKUP($A136,RENO!$C$12:$P$105,13,0),""),"") | I136: =IF(A136<>"",IFERROR(VLOOKUP($A136,RENO!$C$12:$P$105,14,0),""),"")
B137: =IF(A137<>"",IFERROR(VLOOKUP($A137,RENO!$C$12:$P$105,2,0),""),"") | C137: =IF(A137<>"",IFERROR(VLOOKUP($A137,RENO!$C$12:$P$105,4,0),""),"") | E137: =IF(A137<>"",IFERROR(VLOOKUP($A137,RENO!$C$12:$P$105,7,0),""),"") | F137: =IF(A137<>"",IFERROR(VLOOKUP($A137,RENO!$C$12:$P$105,8,0),""),"") | G137: =IF(A137<>"",IFERROR(VLOOKUP($A137,RENO!$C$12:$P$105,12,0),""),"") | H137: =IF(A137<>"",IFERROR(VLOOKUP($A137,RENO!$C$12:$P$105,13,0),""),"") | I137: =IF(A137<>"",IFERROR(VLOOKUP($A137,RENO!$C$12:$P$105,14,0),""),"")
B138: =IF(A138<>"",IFERROR(VLOOKUP($A138,RENO!$C$12:$P$105,2,0),""),"") | C138: =IF(A138<>"",IFERROR(VLOOKUP($A138,RENO!$C$12:$P$105,4,0),""),"") | E138: =IF(A138<>"",IFERROR(VLOOKUP($A138,RENO!$C$12:$P$105,7,0),""),"") | F138: =IF(A138<>"",IFERROR(VLOOKUP($A138,RENO!$C$12:$P$105,8,0),""),"") | G138: =IF(A138<>"",IFERROR(VLOOKUP($A138,RENO!$C$12:$P$105,12,0),""),"") | H138: =IF(A138<>"",IFERROR(VLOOKUP($A138,RENO!$C$12:$P$105,13,0),""),"") | I138: =IF(A138<>"",IFERROR(VLOOKUP($A138,RENO!$C$12:$P$105,14,0),""),"")
B139: =IF(A139<>"",IFERROR(VLOOKUP($A139,RENO!$C$12:$P$105,2,0),""),"") | C139: =IF(A139<>"",IFERROR(VLOOKUP($A139,RENO!$C$12:$P$105,4,0),""),"") | E139: =IF(A139<>"",IFERROR(VLOOKUP($A139,RENO!$C$12:$P$105,7,0),""),"") | F139: =IF(A139<>"",IFERROR(VLOOKUP($A139,RENO!$C$12:$P$105,8,0),""),"") | G139: =IF(A139<>"",IFERROR(VLOOKUP($A139,RENO!$C$12:$P$105,12,0),""),"") | H139: =IF(A139<>"",IFERROR(VLOOKUP($A139,RENO!$C$12:$P$105,13,0),""),"") | I139: =IF(A139<>"",IFERROR(VLOOKUP($A139,RENO!$C$12:$P$105,14,0),""),"")
B140: =IF(A140<>"",IFERROR(VLOOKUP($A140,RENO!$C$12:$P$105,2,0),""),"") | C140: =IF(A140<>"",IFERROR(VLOOKUP($A140,RENO!$C$12:$P$105,4,0),""),"") | E140: =IF(A140<>"",IFERROR(VLOOKUP($A140,RENO!$C$12:$P$105,7,0),""),"") | F140: =IF(A140<>"",IFERROR(VLOOKUP($A140,RENO!$C$12:$P$105,8,0),""),"") | G140: =IF(A140<>"",IFERROR(VLOOKUP($A140,RENO!$C$12:$P$105,12,0),""),"") | H140: =IF(A140<>"",IFERROR(VLOOKUP($A140,RENO!$C$12:$P$105,13,0),""),"") | I140: =IF(A140<>"",IFERROR(VLOOKUP($A140,RENO!$C$12:$P$105,14,0),""),"")
B141: =IF(A141<>"",IFERROR(VLOOKUP($A141,RENO!$C$12:$P$105,2,0),""),"") | C141: =IF(A141<>"",IFERROR(VLOOKUP($A141,RENO!$C$12:$P$105,4,0),""),"") | E141: =IF(A141<>"",IFERROR(VLOOKUP($A141,RENO!$C$12:$P$105,7,0),""),"") | F141: =IF(A141<>"",IFERROR(VLOOKUP($A141,RENO!$C$12:$P$105,8,0),""),"") | G141: =IF(A141<>"",IFERROR(VLOOKUP($A141,RENO!$C$12:$P$105,12,0),""),"") | H141: =IF(A141<>"",IFERROR(VLOOKUP($A141,RENO!$C$12:$P$105,13,0),""),"") | I141: =IF(A141<>"",IFERROR(VLOOKUP($A141,RENO!$C$12:$P$105,14,0),""),"")
B142: =IF(A142<>"",IFERROR(VLOOKUP($A142,RENO!$C$12:$P$105,2,0),""),"") | C142: =IF(A142<>"",IFERROR(VLOOKUP($A142,RENO!$C$12:$P$105,4,0),""),"") | E142: =IF(A142<>"",IFERROR(VLOOKUP($A142,RENO!$C$12:$P$105,7,0),""),"") | F142: =IF(A142<>"",IFERROR(VLOOKUP($A142,RENO!$C$12:$P$105,8,0),""),"") | G142: =IF(A142<>"",IFERROR(VLOOKUP($A142,RENO!$C$12:$P$105,12,0),""),"") | H142: =IF(A142<>"",IFERROR(VLOOKUP($A142,RENO!$C$12:$P$105,13,0),""),"") | I142: =IF(A142<>"",IFERROR(VLOOKUP($A142,RENO!$C$12:$P$105,14,0),""),"")
B143: =IF(A143<>"",IFERROR(VLOOKUP($A143,RENO!$C$12:$P$105,2,0),""),"") | C143: =IF(A143<>"",IFERROR(VLOOKUP($A143,RENO!$C$12:$P$105,4,0),""),"") | E143: =IF(A143<>"",IFERROR(VLOOKUP($A143,RENO!$C$12:$P$105,7,0),""),"") | F143: =IF(A143<>"",IFERROR(VLOOKUP($A143,RENO!$C$12:$P$105,8,0),""),"") | G143: =IF(A143<>"",IFERROR(VLOOKUP($A143,RENO!$C$12:$P$105,12,0),""),"") | H143: =IF(A143<>"",IFERROR(VLOOKUP($A143,RENO!$C$12:$P$105,13,0),""),"") | I143: =IF(A143<>"",IFERROR(VLOOKUP($A143,RENO!$C$12:$P$105,14,0),""),"")
B144: =IF(A144<>"",IFERROR(VLOOKUP($A144,RENO!$C$12:$P$105,2,0),""),"") | C144: =IF(A144<>"",IFERROR(VLOOKUP($A144,RENO!$C$12:$P$105,4,0),""),"") | E144: =IF(A144<>"",IFERROR(VLOOKUP($A144,RENO!$C$12:$P$105,7,0),""),"") | F144: =IF(A144<>"",IFERROR(VLOOKUP($A144,RENO!$C$12:$P$105,8,0),""),"") | G144: =IF(A144<>"",IFERROR(VLOOKUP($A144,RENO!$C$12:$P$105,12,0),""),"") | H144: =IF(A144<>"",IFERROR(VLOOKUP($A144,RENO!$C$12:$P$105,13,0),""),"") | I144: =IF(A144<>"",IFERROR(VLOOKUP($A144,RENO!$C$12:$P$105,14,0),""),"")
... B160: =IF(A160<>"",IFERROR(VLOOKUP($A160,RENO!$C$12:$P$105,2,0),""),"") | C160: =IF(A160<>"",IFERROR(VLOOKUP($A160,RENO!$C$12:$P$105,4,0),""),"") | E160: =IF(A160<>"",IFERROR(VLOOKUP($A160,RENO!$C$12:$P$105,7,0),""),"") | F160: =IF(A160<>"",IFERROR(VLOOKUP($A160,RENO!$C$12:$P$105,8,0),""),"") | G160: =IF(A160<>"",IFERROR(VLOOKUP($A160,RENO!$C$12:$P$105,12,0),""),"") | H160: =IF(A160<>"",IFERROR(VLOOKUP($A160,RENO!$C$12:$P$105,13,0),""),"") | I160: =IF(A160<>"",IFERROR(VLOOKUP($A160,RENO!$C$12:$P$105,14,0),""),"")

Sheet NK
A1: Bundesland | B1: Notar- und Grundbuchkosten | C1: Grunderwerbsteuer
A2: Baden-Württemberg | B2: 0.02 | C2: 0.05
A3: Bayern | B3: 0.02 | C3: 0.035
A4: Berlin | B4: 0.02 | C4: 0.06
A5: Brandenburg | B5: 0.02 | C5: 0.065
A6: Bremen | B6: 0.02 | C6: 0.05
A7: Hamburg | B7: 0.02 | C7: 0.045
A8: Hessen | B8: 0.02 | C8: 0.06
A9: Mecklenburg-Vorpommern | B9: 0.02 | C9: 0.06
A10: Niedersachsen | B10: 0.02 | C10: 0.05
A11: Nordrhein-Westfalen | B11: 0.02 | C11: 0.065
A12: Rheinland-Pfalz | B12: 0.02 | C12: 0.05
A13: Saarland | B13: 0.02 | C13: 0.065
... A17: Thüringen | B17: 0.02 | C17: 0.05
A36: DIAGRAMM-Daten für KALKU
A37: ANGEBOT | C37: =(KALKU!P37)
A38: NK | B38: =(+C37+B37) | C38: =(KALKU!J30)
A39: RENO | B39: =(+C38+B38) | C39: =(KALKU!J29+KALKU!J28)
A40: ZINS | B40: =(+C39+B39) | C40: =(KALKU!J27)
A41: GIK | C41: =(+B42)
A42: GEWINN | B42: =(C40+B40) | C42: =(KALKU!J40)
A43: VK | C43: =(KALKU!J37)
