Workbook
Name AUFTEILER_TPL_V2: 'Verkauf Cashflow'!$A$1
Name AUFTEILER_TPL_LAYOUT: 2

Sheet BESICHTIGUNG
A1: CHECKLISTE BESICHTIGUNG
A2: Datum Besichtigung
A3: Lead Herkunft
A5: EINKAUF
A6: Anschrift
A7: Wohnfläche in m²
A8: Baujahr
A9: Wohneinheiten im Haus
A10: Hausgeld pro Monat | B10: 0
A11: Rücklagen des Hauses | B11: 0
A12: Gewinn | B12: 0.3
A13: Inseratspreis
A14: Inseratspreis pro m² | B14: =B13/B7
A15: Besonderheiten Haus / Erster Eindruck Umgebung | B15: Text
A17: ZUSTAND (MIT BILDER DOKUMENTIEREN!)
A18: Dach | B18: Zustand?
A19: Fassade | B19: Zustand?
A20: Fenster | B20: Zustand?
A21: Stellplatz / Garage | B21: Vorhanden?
A22: Heizung | B22: Art? Baujahr?
A23: Elektrik | B23: Zustand?
A25: VERKÄUFER
A26: Wer ist der Eigentümer? | B26: Text
A27: Warum wird verkauft? | B27: Text
A28: Schmerzgrenze Preis?
A30: MIETSITUATION
A31: Wie viele Einheiten sind vermietet?
A32: Wie viele Einheiten stehen leer?
A33: IST Jahresnettokaltmiete? (JNKM)
A34: Kappungsgrenze? | B34: 0
A35: Wann waren die letzten Mieterhöhungen?
A36: SOLL Jahresnettokaltmiete? (JNKM)
A39: SONSTIGE NOTIZEN
A40: Text

Sheet KALKU
H2: HINWEISE ZUR KALKULATION / NOTIZEN
H3: =IF(AND(C13<250)," Wir empfehlen keine MFHs unter 250m²","")
H4: =IF(C14<1950," Achtung, Hinweis zum Baujahr!","")
B5: DATEN EINGABE → | C5: Wert eingeben | H5: =IF(AND(C15>1,C15<6)," Wir empfehlen Mehrfamilienhäuser ab 6 Einheiten","")
H6: =IF(((MIETER!L28/MIETER!M6)<0.6)," Achtung, Sehr geringe Miete!","")
B7: WERT WIRD BERECHNET → | C7: Wert wird berechnet | H7: =IF(J29>(600*C13)," Achtung, erhöhter Renovierungsaufwand!","")
B10: 1. EINKAUF | H10: 4. VORKALKULATION DER IMMOBILIE
B11: LINK ZU OBJEKTORDNER | C11: Drive Ordner | H11: PORTAL | I11: =" PORTALSPREIS (für ⌀"&TEXT(C13/C15,"#,##")&"m² Wohnfläche)" | K11: AUF- / ABSCHLÄGE | O11: VERKAUFSPREIS
B12: ANSCHRIFT | C12: =BESICHTIGUNG!B6 | K12: -0.05 | N12: =F41
B13: WOHNFLAECHE | C13: =BESICHTIGUNG!B7 | H13: Homeday Atlas | I13: 2800 | K13: =I13*(1+$K$12) | N13: =K13*(1+$F$41) | O13: =N13*$C$13
B14: BAUJAHR | C14: =BESICHTIGUNG!B8 | H14: IS24 Preisatlas | I14: 2900 | K14: =I14*(1+$K$12) | N14: =K14*(1+$F$41) | O14: =N14*$C$13
B15: WOHNEINHEITEN IM HAUS | C15: =BESICHTIGUNG!B9 | H15: Pricehubble / Check24 | I15: 2900 | K15: =I15*(1+$K$12) | N15: =K15*(1+$F$41) | O15: =N15*$C$13
B16: HAUSGELD PRO MONAT | C16: =1.5*C13 | H16: InterHyp | I16: 2700 | K16: =I16*(1+$K$12) | N16: =K16*(1+$F$41) | O16: =N16*$C$13
B17: RÜCKLAGEN DES HAUSES | C17: 0 | H17: Wohnungmarktbericht | I17: 2000 | K17: =IF(I17>0,I17*(1+$K$12),"") | N17: =IF(K17<>"",K17*(1+$F$41),"") | O17: =IF(N17<>"",N17*$C$13,"")
B18: GEWINN | C18: 0.35 | H18: ⌀ PORTALE | I18: =AVERAGE(I13:I17) | K18: =AVERAGE(K13:K17) | N18: =AVERAGE(N13:N17) | O18: =AVERAGE(O13:O17)
B19: SCHMERZGRENZE | C19: =BESICHTIGUNG!B28
B20: PREIS PRO m² | C20: =IFERROR(C19/C13,"") | H20: 5. BETEILIGUNG INVESTOR / DEALTRADER | M20: 9. FINANZIERUNG
B21: ZINSEN (variabel) | C21: 0.06 | D21: ZINSBINDUNG | F21: 12 | H21: GEWINNBETEILIGUNG DEALTRADER (%) | I21: 0 | J21: =I21*J40 | M21: GIK | P21: =J39
B22: EINMALKOSTEN FINANZIERUNG | C22: 0 | D22: =P24*C22 | H22: GEWINNBETEILIGUNG INVESTOR (%) | I22: 0 | J22: =I22*J40 | M22: - EK | P22: 0
B23: ZINS (B&H) | C23: 0.04 | H23: SONSTIGE BETEILIGUNG | I23: 0 | J23: 0 | M23: - Darlehen Investor | O23: 0 | P23: 0
B24: TILGUNG (B&H) | C24: 0.02 | H24: = RESTGEWINN HÄNDLER | I24: =J40-J21-J22 | M24: = Darlehen Bank | P24: =P21-P22-P23
B26: 2. NEBENKOSTENRECHNER | H26: 6. KOSTEN | M26: 10. WORST-CASE RECHNER (B&H)
B27: BUNDESLAND | D27: Nordrhein-Westfalen | H27: - FINANZIERUNGSKOSTEN | I27: =J27/C13 | J27: =(P23*(O23*(F21/12)))+(P24*(C21*(F21/12)))+D22 | M27: ZINSKOSTEN (pro Jahr B&H) | P27: =P24*(C23+C24)
B28: NOTAR- UND GRUNDBUCHKOSTEN | E28: =VLOOKUP(D27,NK!A2:C17,2,FALSE()) | F28: =E28*P37 | H28: =" - HAUSGELD ("&F21&" MONATE)" | I28: =J28/C13 | J28: =(C16*F21) | M28: HAUSGELD (pro Jahr B&H) | P28: =C16*12
B29: GRUNDERWERBSTEUER | E29: =VLOOKUP(D27,NK!A2:C17,3,FALSE()) | F29: =E29*P37 | H29: - AUFWERTUNGSKOSTEN (RENO BLATT) | I29: =J29/C13 | J29: =RENO!O8 | M29: JAHRESNETTOKALTMIETE SOLL | P29: =MIETER!N31
B30: MAKLERPROVISION | D30: 0.03 | E30: =D30*1.19 | F30: =E30*P37 | H30: - KAUFNEBENKOSTEN | I30: =J30/C13 | J30: =(J39-J27-J28-J29-J31)*(E31/(1+E31)) | M30: = CASHFLOW PRO JAHR | P30: =P29-P27-P28
B31: KAUFNEBENKOSTEN = | E31: =SUM(E28:E30) | F31: =SUM(F28:F30) | H31: =" - MIETEINNAHMEN IST ("&F21&" MONATE)" | J31: =(MIETER!J31*-1)*(F21/12) | M31: => RENDITE (JNKM zu KP+NK) Mietspiegel | P31: =P29/(P37+J30)
H32: = GESAMTKOSTEN | I32: =SUM(I27:I30) | J32: =SUM(J27:J31) | M32: => RENDITE (JNKM zu GIK) Modernisierung | P32: =MIETER!R31/J39
B34: 3. AUF-/ABSCHLAG | F34: =YEAR(TODAY()) | H34: 7. GEWINN & GIK | M34: 8. ANGEBOT
B35: ART DER HEIZUNG | C35: Zentral | E35: Elektro | F35: =IF(OR(E35="Öl", E35="Elektro"), -0.05, IF(E35="Gas", 0, IF(OR(E35="Pellet", E35="Wärmepumpe"), 0.05, ""))) | G35: =F34-E36 | H35: =" VERKAUFSPREIS aus VORKALKULATION (inkl. "&TEXT(C17-(20*C13),"#,##0 €")&" Rücklagen)" | I35: =J35/C13 | J35: =O18+C17-(50*C13) | M35: SCHMERZGRENZE | O35: =P35/C13 | P35: =C19
B36: BAUJAHR HEIZUNG | E36: 2024 | F36: =IF(ISBLANK(E36), 0, MAX(MIN(0.03 - 0.003 * (F34 - E36), 0.03), -0.09))
B37: FASSADE WIRD / IST GEDÄMMT? | E37: Ja | F37: =IF(E37="Nein",-0.04,0.04) | H37: VERKAUFSPREIS aus VERKAUFSMATRIX (Detailbetrachtung aller Wohnungen) | I37: =J37/C13 | J37: =VERKAUFSMATRIX!Y28 | M37: DEIN ANGEBOTSPREIS | O37: =P37/C13 | P37: =J39-J32
B38: ZÄHLERSCHRANK WIRD / WURDE ERNEUERT? | E38: 2024 | F38: =IF(ISBLANK(E38), 0, MAX(MIN(0.01 - 0.001 * (F34 - E38), 0.01), -0.02))
B39: TREPPENHAUS WIRD / WURDE RENOVIERT? | E39: Ja | F39: =IF(E39="Nein",-0.02,0.02) | H39: - GESAMTINVESTITIONSKOSTEN | I39: =J39/C13 | J39: =J37/(1+C18)
B40: INDIVIDUELLER AUF-/ABSCHLAG | F40: 0 | H40: =" = GEWINN "&TEXT(C18,"0%") | I40: =J40/C13 | J40: =J39*C18 | M40: DIFFERENZ (€) | O40: =P40/C13 | P40: =P37-P35
B41: AUF-/ABSCHLAG GESAMT = | F41: =SUM(F35:F40) | M41: DIFFERENZ (%) | O41: =IFERROR(1-(P37/P35),"")

Sheet RENO
B2: AUFWERTUNGSKALKULATION
B4: Anschrift | F4: =KALKU!C12 | K4: ="Kalkulierte Reno Kosten inkl. "&TEXT(I6,"0%")&" Puffer (Netto)" | O4: =P106*(1+I6) | P4: =IF(OR(F5=0,F5=""),"",O4/F5)
B5: Wohnfläche | F5: =KALKU!C13 | I5: 27
B6: Baujahr | F6: =KALKU!C14 | I6: 0.1 | K6: ="Kalkulierte Reno Kosten inkl. "&TEXT(I6,"0%")&" Puffer (Brutto)" | O6: =O4*(1+I7) | P6: =IF(OR(F5=0,F5=""),"",O6/F5)
B7: Marge Handwerker | F7: 0.3 | I7: 0.19
K8: Individueller Auf-/Abschlag | L8: 0 | M8: Meine Reno Kosten = | O8: =O6*(1+L8) | P8: =IF(OR(F5=0,F5=""),"",O8/F5) | R8: =SUM(R12:R105)
R10: ↑
B11: Gewerk | C11: Pos. | D11: Gewerk | E11: lfd. Nr. | F11: Maßnahmen | G11: Anteil Lohn- kosten in % | H11: Anteil Material in % | I11: Menge | J11: Einheit | K11: pschl. EP netto | L11: Zeit in h | M11: Zeit in Tagen | N11: Lohnkosten | O11: Materialkosten | P11: Gesamtkosten (Netto) | Q11: Summe pro Gewerk (Netto) | R11: Eingeholte Angebote von Handwerkern
B12: Entmietung | C12: =IF(I12>0,1,"") | D12: =B12 | E12: 1 | F12: Entmietung (Anwaltskosten, Umzugskosten etc.) | J12: Stk | K12: 4000 | L12: 0 | M12: 0 | N12: 0 | O12: 0 | P12: =I12*K12 | Q12: =P12
B13: Entrümpelung Entsorgung | C13: =IF(I13>0,MAX($C$12:C12)+1,"") | D13: =IF(ISBLANK(B13),D12,B13) | E13: 2 | F13: Entrümplung (ohne Entsorgungskosten) | G13: 0.8 | H13: 0.2 | J13: m² | K13: 40 | L13: =(N13/$I$5)/(1+$F$7) | M13: =L13/8 | N13: =P13*G13 | O13: =P13*H13 | P13: =I13*K13 | Q13: =SUM(P13:P14)
C14: =IF(I14>0,MAX($C$12:C13)+1,"") | D14: =IF(ISBLANK(B14),D13,B14) | E14: 3 | F14: Entkernung (Wohn- und Nutzfläche) | G14: 0.9 | H14: 0.1 | J14: m² Wfl. | K14: 55 | L14: =(N14/$I$5)/(1+$F$7) | M14: =L14/8 | N14: =P14*G14 | O14: =P14*H14 | P14: =I14*K14
B15: Fassade | C15: =IF(I15>0,MAX($C$12:C14)+1,"") | D15: =IF(ISBLANK(B15),D14,B15) | E15: 4 | F15: Gerüstkosten Auf-/Abbau (Einrüstung der Fassade) | G15: 0.9 | H15: 0.1 | J15: m² | K15: 8 | L15: =(N15/$I$5)/(1+$F$7) | M15: =L15/8 | N15: =P15*G15 | O15: =P15*H15 | P15: =I15*K15 | Q15: =SUM(P15:P22)
C16: =IF(I16>0,MAX($C$12:C15)+1,"") | D16: =IF(ISBLANK(B16),D15,B16) | E16: 5 | F16: Fassade reinigen | J16: m² | K16: 2.5 | L16: =(N16/$I$5)/(1+$F$7) | M16: =L16/8 | N16: =P16*G16 | O16: =P16*H16 | P16: =I16*K16
C17: =IF(I17>0,MAX($C$12:C16)+1,"") | D17: =IF(ISBLANK(B17),D16,B17) | E17: 6 | F17: Sockel Fassade aufarbeiten | J17: m² | K17: 15 | L17: =(N17/$I$5)/(1+$F$7) | M17: =L17/8 | N17: =P17*G17 | O17: =P17*H17 | P17: =I17*K17
C18: =IF(I18>0,MAX($C$12:C17)+1,"") | D18: =IF(ISBLANK(B18),D17,B18) | E18: 7 | F18: Dämmung WDVS (16mm) | J18: m² | K18: 45 | L18: =(N18/$I$5)/(1+$F$7) | M18: =L18/8 | N18: =P18*G18 | O18: =P18*H18 | P18: =I18*K18
C19: =IF(I19>0,MAX($C$12:C18)+1,"") | D19: =IF(ISBLANK(B19),D18,B19) | E19: 8 | F19: Gewebespachtel | J19: m² | K19: 20 | L19: =(N19/$I$5)/(1+$F$7) | M19: =L19/8 | N19: =P19*G19 | O19: =P19*H19 | P19: =I19*K19
C20: =IF(I20>0,MAX($C$12:C19)+1,"") | D20: =IF(ISBLANK(B20),D19,B20) | E20: 9 | F20: Fassade verputzen | G20: 0.7 | H20: 0.3 | J20: m² | K20: 20 | L20: =(N20/$I$5)/(1+$F$7) | M20: =L20/8 | N20: =P20*G20 | O20: =P20*H20 | P20: =I20*K20
C21: =IF(I21>0,MAX($C$12:C20)+1,"") | D21: =IF(ISBLANK(B21),D20,B21) | E21: 10 | F21: Fenster ausspitzen | J21: Stk | K21: 25 | L21: =(N21/$I$5)/(1+$F$7) | M21: =L21/8 | N21: =P21*G21 | O21: =P21*H21 | P21: =I21*K21
C22: =IF(I22>0,MAX($C$12:C21)+1,"") | D22: =IF(ISBLANK(B22),D20,B22) | E22: 11 | F22: Fassade neu streichen (zweifach) | G22: 0.75 | H22: 0.25 | J22: m² | K22: 12.5 | L22: =(N22/$I$5)/(1+$F$7) | M22: =L22/8 | N22: =P22*G22 | O22: =P22*H22 | P22: =I22*K22
B23: Dach | C23: =IF(I23>0,MAX($C$12:C22)+1,"") | D23: =IF(ISBLANK(B23),D22,B23) | E23: 12 | F23: Dachreinigung | G23: 0.8 | H23: 0.2 | J23: m² | K23: 5 | L23: =(N23/$I$5)/(1+$F$7) | M23: =L23/8 | N23: =P23*G23 | O23: =P23*H23 | P23: =I23*K23 | Q23: =SUM(P23:P27)
C24: =IF(I24>0,MAX($C$12:C23)+1,"") | D24: =IF(ISBLANK(B24),D22,B24) | E24: 13 | F24: Dachbeschichtung / Versiegelung (zweifach) | J24: m² | K24: 25 | L24: =(N24/$I$5)/(1+$F$7) | M24: =L24/8 | N24: =P24*G24 | O24: =P24*H24 | P24: =I24*K24
C25: =IF(I25>0,MAX($C$12:C24)+1,"") | D25: =IF(ISBLANK(B25),D23,B25) | E25: 14 | F25: Dach neu decken | G25: 0.8 | H25: 0.2 | J25: m² | K25: 95 | L25: =(N25/$I$5)/(1+$F$7) | M25: =L25/8 | N25: =P25*G25 | O25: =P25*H25 | P25: =I25*K25
C26: =IF(I26>0,MAX($C$12:C25)+1,"") | D26: =IF(ISBLANK(B26),D25,B26) | E26: 15 | F26: Dachrinne & Fallrohre erneuern | G26: 0.8 | H26: 0.2 | J26: lfd.m | K26: 50 | L26: =(N26/$I$5)/(1+$F$7) | M26: =L26/8 | N26: =P26*G26 | O26: =P26*H26 | P26: =I26*K26
C27: =IF(I27>0,MAX($C$12:C26)+1,"") | D27: =IF(ISBLANK(B27),D26,B27) | E27: 16 | F27: Dachdämmung (inkl. Dampfsperre) | G27: 0.6 | H27: 0.4 | J27: m² | K27: 90 | L27: =(N27/$I$5)/(1+$F$7) | M27: =L27/8 | N27: =P27*G27 | O27: =P27*H27 | P27: =I27*K27
B28: Wände und Decken | C28: =IF(I28>0,MAX($C$12:C27)+1,"") | D28: =IF(ISBLANK(B28),D27,B28) | E28: 17 | F28: Wände und Decken neu tapezieren und streichen | G28: 0.8 | H28: 0.2 | J28: m² Wfl. | K28: =18 | L28: =(N28/$I$5)/(1+$F$7) | M28: =L28/8 | N28: =P28*G28 | O28: =P28*H28 | P28: =I28*K28 | Q28: =SUM(P28:P33)
C29: =IF(I29>0,MAX($C$12:C28)+1,"") | D29: =IF(ISBLANK(B29),D28,B29) | E29: 18 | F29: Wände verputzen | G29: 0.7 | H29: 0.3 | J29: m² Wfl. | K29: 17 | L29: =(N29/$I$5)/(1+$F$7) | M29: =L29/8 | N29: =P29*G29 | O29: =P29*H29 | P29: =I29*K29
C30: =IF(I30>0,MAX($C$12:C29)+1,"") | D30: =IF(ISBLANK(B30),D29,B30) | E30: 19 | F30: Wand einziehen (Trockenbau) | G30: 0.7 | H30: 0.3 | J30: m² | K30: 60 | L30: =(N30/$I$5)/(1+$F$7) | M30: =L30/8 | N30: =P30*G30 | O30: =P30*H30 | P30: =I30*K30
C31: =IF(I31>0,MAX($C$12:C30)+1,"") | D31: =IF(ISBLANK(B31),D30,B31) | E31: 20 | F31: Decke abhängen (Trockenbau) | G31: 0.7 | H31: 0.3 | J31: m² | K31: 44 | L31: =(N31/$I$5)/(1+$F$7) | M31: =L31/8 | N31: =P31*G31 | O31: =P31*H31 | P31: =I31*K31
C32: =IF(I32>0,MAX($C$12:C31)+1,"") | D32: =IF(ISBLANK(B32),D31,B32) | E32: 21 | F32: Tapete entfernen | G32: 0.95 | H32: 0.05 | J32: m² Wfl. | K32: 7 | L32: =(N32/$I$5)/(1+$F$7) | M32: =L32/8 | N32: =P32*G32 | O32: =P32*H32 | P32: =I32*K32
C33: =IF(I33>0,MAX($C$12:C32)+1,"") | D33: =IF(ISBLANK(B33),D32,B33) | E33: 22 | F33: Wände und Decken streichen | G33: 0.8 | H33: 0.2 | J33: m² Wfl. | K33: 8.95 | L33: =(N33/$I$5)/(1+$F$7) | M33: =L33/8 | N33: =P33*G33 | O33: =P33*H33 | P33: =I33*K33
B34: Fussböden | C34: =IF(I34>0,MAX($C$12:C33)+1,"") | D34: =IF(ISBLANK(B34),D33,B34) | E34: 23 | F34: Alten Bodenbelag entfernen | G34: 0.9 | H34: 0.1 | J34: m² | K34: 5.2 | L34: =(N34/$I$5)/(1+$F$7) | M34: =L34/8 | N34: =P34*G34 | O34: =P34*H34 | P34: =I34*K34 | Q34: =SUM(P34:P39)
C35: =IF(I35>0,MAX($C$12:C34)+1,"") | D35: =IF(ISBLANK(B35),D34,B35) | E35: 24 | F35: Balkonfußboden beschichten | G35: 0.8 | H35: 0.2 | J35: Stk | K35: 350 | L35: =(N35/$I$5)/(1+$F$7) | M35: =L35/8 | N35: =P35*G35 | O35: =P35*H35 | P35: =I35*K35
C36: =IF(I36>0,MAX($C$12:C35)+1,"") | D36: =IF(ISBLANK(B36),D35,B36) | E36: 25 | F36: Sockelleisten erneuern pauschal pro Raum | G36: 0.8 | H36: 0.2 | J36: Raum | K36: 78 | L36: =(N36/$I$5)/(1+$F$7) | M36: =L36/8 | N36: =P36*G36 | O36: =P36*H36 | P36: =I36*K36
C37: =IF(I37>0,MAX($C$12:C36)+1,"") | D37: =IF(ISBLANK(B37),D36,B37) | E37: 26 | F37: Laminat / Vinyl verlegen | G37: 0.6 | H37: 0.4 | J37: m² Wfl. | K37: 38 | L37: =(N37/$I$5)/(1+$F$7) | M37: =L37/8 | N37: =P37*G37 | O37: =P37*H37 | P37: =I37*K37
C38: =IF(I38>0,MAX($C$12:C37)+1,"") | D38: =IF(ISBLANK(B38),D37,B38) | E38: 27 | F38: Laminat / Vinyl verlegen (mit Trittschalldämmung) | G38: 0.6 | H38: 0.4 | J38: m² Wfl. | K38: 50 | L38: =(N38/$I$5)/(1+$F$7) | M38: =L38/8 | N38: =P38*G38 | O38: =P38*H38 | P38: =I38*K38
C39: =IF(I39>0,MAX($C$12:C38)+1,"") | D39: =IF(ISBLANK(B39),D38,B39) | E39: 28 | F39: Parkett schleifen und lackieren | G39: 0.7 | H39: 0.3 | J39: m² Wfl. | K39: 80 | L39: =(N39/$I$5)/(1+$F$7) | M39: =L39/8 | N39: =P39*G39 | O39: =P39*H39 | P39: =I39*K39
B40: Fenster und Türen | C40: =IF(I40>0,MAX($C$12:C39)+1,"") | D40: =IF(ISBLANK(B40),D39,B40) | E40: 29 | F40: Geländer entrosten und streichen | G40: 0.85 | H40: 0.15 | J40: lfd.m | K40: 45 | L40: =(N40/$I$5)/(1+$F$7) | M40: =L40/8 | N40: =P40*G40 | O40: =P40*H40 | P40: =I40*K40 | Q40: =SUM(P40:P54)
C41: =IF(I41>0,MAX($C$12:C40)+1,"") | D41: =IF(ISBLANK(B41),D40,B41) | E41: 30 | F41: Holzfenster lackieren | G41: 0.8 | H41: 0.2 | J41: Stk | K41: 120 | L41: =(N41/$I$5)/(1+$F$7) | M41: =L41/8 | N41: =P41*G41 | O41: =P41*H41 | P41: =I41*K41
C42: =IF(I42>0,MAX($C$12:C41)+1,"") | D42: =IF(ISBLANK(B42),D41,B42) | E42: 31 | F42: Tür und Zarge lackieren | G42: 0.7 | H42: 0.3 | J42: Stk | K42: 180 | L42: =(N42/$I$5)/(1+$F$7) | M42: =L42/8 | N42: =P42*G42 | O42: =P42*H42 | P42: =I42*K42
C43: =IF(I43>0,MAX($C$12:C42)+1,"") | D43: =IF(ISBLANK(B43),D42,B43) | E43: 32 | F43: Zarge lackieren | G43: 0.7 | H43: 0.3 | J43: Stk | K43: 80 | L43: =(N43/$I$5)/(1+$F$7) | M43: =L43/8 | N43: =P43*G43 | O43: =P43*H43 | P43: =I43*K43
C44: =IF(I44>0,MAX($C$12:C43)+1,"") | D44: =IF(ISBLANK(B44),D43,B44) | E44: 33 | F44: Innentür mit Türzarge erneuern | G44: 0.2 | H44: 0.8 | J44: Stk | K44: 280 | L44: =(N44/$I$5)/(1+$F$7) | M44: =L44/8 | N44: =P44*G44 | O44: =P44*H44 | P44: =I44*K44
C45: =IF(I45>0,MAX($C$12:C44)+1,"") | D45: =IF(ISBLANK(B45),D44,B45) | E45: 34 | F45: Innentürblatt erneuern | G45: 0.1 | H45: 0.9 | J45: Stk | K45: 140 | L45: =(N45/$I$5)/(1+$F$7) | M45: =L45/8 | N45: =P45*G45 | O45: =P45*H45 | P45: =I45*K45
C46: =IF(I46>0,MAX($C$12:C45)+1,"") | D46: =IF(ISBLANK(B46),D45,B46) | E46: 35 | F46: Türbeschläge Innentür erneuern | G46: 0.2 | H46: 0.8 | J46: Stk | K46: 35 | L46: =(N46/$I$5)/(1+$F$7) | M46: =L46/8 | N46: =P46*G46 | O46: =P46*H46 | P46: =I46*K46
C47: =IF(I47>0,MAX($C$12:C46)+1,"") | D47: =IF(ISBLANK(B47),D46,B47) | E47: 36 | F47: Wohnungstür erneuern | G47: 0.3 | H47: 0.7 | J47: Stk | K47: 1400 | L47: =(N47/$I$5)/(1+$F$7) | M47: =L47/8 | N47: =P47*G47 | O47: =P47*H47 | P47: =I47*K47
C48: =IF(I48>0,MAX($C$12:C47)+1,"") | D48: =IF(ISBLANK(B48),D47,B48) | E48: 37 | F48: Hauseingangstür erneuern | G48: 0.25 | H48: 0.75 | J48: Stk | K48: 2750 | L48: =(N48/$I$5)/(1+$F$7) | M48: =L48/8 | N48: =P48*G48 | O48: =P48*H48 | P48: =I48*K48
C49: =IF(I49>0,MAX($C$12:C48)+1,"") | D49: =IF(ISBLANK(B49),D48,B49) | E49: 38 | F49: Fenster einstellen | G49: 1 | H49: 0 | J49: Stk | K49: 15 | L49: =(N49/$I$5)/(1+$F$7) | M49: =L49/8 | N49: =P49*G49 | O49: =P49*H49 | P49: =I49*K49
C50: =IF(I50>0,MAX($C$12:C49)+1,"") | D50: =IF(ISBLANK(B50),D49,B50) | E50: 39 | F50: Fenster erneuern (komplett) | G50: 0.5 | H50: 0.5 | J50: Stk | K50: 800 | L50: =(N50/$I$5)/(1+$F$7) | M50: =L50/8 | N50: =P50*G50 | O50: =P50*H50 | P50: =I50*K50
C51: =IF(I51>0,MAX($C$12:C50)+1,"") | D51: =IF(ISBLANK(B51),D50,B51) | E51: 40 | F51: Balkontür erneuern | G51: 0.2 | H51: 0.8 | J51: Stk. | K51: 900 | L51: =(N51/$I$5)/(1+$F$7) | M51: =L51/8 | N51: =P51*G51 | O51: =P51*H51 | P51: =I51*K51
C52: =IF(I52>0,MAX($C$12:C51)+1,"") | D52: =IF(ISBLANK(B52),D51,B52) | E52: 41 | F52: Fensterbänke | G52: 0.35 | H52: 0.65 | J52: Stk | K52: 75 | L52: =(N52/$I$5)/(1+$F$7) | M52: =L52/8 | N52: =P52*G52 | O52: =P52*H52 | P52: =I52*K52
... C54: =IF(I54>0,MAX($C$12:C53)+1,"") | D54: =IF(ISBLANK(B54),D53,B54) | E54: 43 | F54: Dachflächenfenster erneuern | G54: 0.3 | H54: 0.7 | J54: Stk | K54: 1000 | L54: =(N54/$I$5)/(1+$F$7) | M54: =L54/8 | N54: =P54*G54 | O54: =P54*H54 | P54: =I54*K54
B55: Fliesen | C55: =IF(I55>0,MAX($C$12:C54)+1,"") | D55: =IF(ISBLANK(B55),D54,B55) | E55: 44 | F55: Fliesenspiegel Küche lackieren | G55: 0.7 | H55: 0.3 | J55: psch | K55: 120 | L55: =(N55/$I$5)/(1+$F$7) | M55: =L55/8 | N55: =P55*G55 | O55: =P55*H55 | P55: =I55*K55 | Q55: =SUM(P55:P60)
C56: =IF(I56>0,MAX($C$12:C55)+1,"") | D56: =IF(ISBLANK(B56),D55,B56) | E56: 45 | F56: Wandfliesen erneuern | G56: 0.75 | H56: 0.25 | J56: m² | K56: 70 | L56: =(N56/$I$5)/(1+$F$7) | M56: =L56/8 | N56: =P56*G56 | O56: =P56*H56 | P56: =I56*K56
C57: =IF(I57>0,MAX($C$12:C56)+1,"") | D57: =IF(ISBLANK(B57),D56,B57) | E57: 46 | F57: Bodenfliesen erneuern | G57: 0.75 | H57: 0.25 | J57: m² | K57: 80 | L57: =(N57/$I$5)/(1+$F$7) | M57: =L57/8 | N57: =P57*G57 | O57: =P57*H57 | P57: =I57*K57
C58: =IF(I58>0,MAX($C$12:C57)+1,"") | D58: =IF(ISBLANK(B58),D57,B58) | E58: 47 | F58: Fliesenspiegel in Küche erneuern | G58: 0.75 | H58: 0.25 | J58: psch | K58: 250 | L58: =(N58/$I$5)/(1+$F$7) | M58: =L58/8 | N58: =P58*G58 | O58: =P58*H58 | P58: =I58*K58
C59: =IF(I59>0,MAX($C$12:C58)+1,"") | D59: =IF(ISBLANK(B59),D58,B59) | E59: 48 | F59: Silikonfugen im Bad erneuern | G59: 0.9 | H59: 0.1 | J59: psch | K59: 250 | L59: =(N59/$I$5)/(1+$F$7) | M59: =L59/8 | N59: =P59*G59 | O59: =P59*H59 | P59: =I59*K59
C60: =IF(I60>0,MAX($C$12:C59)+1,"") | D60: =IF(ISBLANK(B60),D59,B60) | E60: 49 | F60: Wandfliesen lackieren Bad | G60: 0.8 | H60: 0.2 | J60: psch | K60: 450 | L60: =(N60/$I$5)/(1+$F$7) | M60: =L60/8 | N60: =P60*G60 | O60: =P60*H60 | P60: =I60*K60
B61: Elektro | C61: =IF(I61>0,MAX($C$12:C60)+1,"") | D61: =IF(ISBLANK(B61),D60,B61) | E61: 50 | F61: E-Check in Wohnung | G61: 0.95 | H61: 0.05 | J61: Stk | K61: 500 | L61: =(N61/$I$5)/(1+$F$7) | M61: =L61/8 | N61: =P61*G61 | O61: =P61*H61 | P61: =I61*K61 | Q61: =SUM(P61:P69)
C62: =IF(I62>0,MAX($C$12:C61)+1,"") | D62: =IF(ISBLANK(B62),D61,B62) | E62: 51 | F62: Taster und Steckdosen austauschen | G62: 0.65 | H62: 0.35 | J62: Stk | K62: 30 | L62: =(N62/$I$5)/(1+$F$7) | M62: =L62/8 | N62: =P62*G62 | O62: =P62*H62 | P62: =I62*K62
C63: =IF(I63>0,MAX($C$12:C62)+1,"") | D63: =IF(ISBLANK(B63),D62,B63) | E63: 52 | F63: LED-Spots | G63: 0.5 | H63: 0.5 | J63: Stk | K63: 30 | L63: =(N63/$I$5)/(1+$F$7) | M63: =L63/8 | N63: =P63*G63 | O63: =P63*H63 | P63: =I63*K63
C64: =IF(I64>0,MAX($C$12:C63)+1,"") | D64: =IF(ISBLANK(B64),D63,B64) | E64: 53 | F64: Nachrüstung FI-Schutzschalter | G64: 0.85 | H64: 0.15 | J64: Stk | K64: 500 | L64: =(N64/$I$5)/(1+$F$7) | M64: =L64/8 | N64: =P64*G64 | O64: =P64*H64 | P64: =I64*K64
C65: =IF(I65>0,MAX($C$12:C64)+1,"") | D65: =IF(ISBLANK(B65),D64,B65) | E65: 54 | F65: Sprechanlage | J65: Stk | K65: 300 | L65: =(N65/$I$5)/(1+$F$7) | M65: =L65/8 | N65: =P65*G65 | O65: =P65*H65 | P65: =I65*K65
C66: =IF(I66>0,MAX($C$12:C65)+1,"") | D66: =IF(ISBLANK(B66),D65,B66) | E66: 55 | F66: Lampen erneuern (Treppenhaus, Keller, Hof, Eingang) | G66: 0.5 | H66: 0.5 | J66: Stk | K66: 50 | L66: =(N66/$I$5)/(1+$F$7) | M66: =L66/8 | N66: =P66*G66 | O66: =P66*H66 | P66: =I66*K66
C67: =IF(I67>0,MAX($C$12:C66)+1,"") | D67: =IF(ISBLANK(B67),D66,B67) | E67: 56 | F67: Unterverteilung Wohnung komplett erneuern | G67: 0.65 | H67: 0.35 | J67: Stk | K67: 600 | L67: =(N67/$I$5)/(1+$F$7) | M67: =L67/8 | N67: =P67*G67 | O67: =P67*H67 | P67: =I67*K67
C68: =IF(I68>0,MAX($C$12:C67)+1,"") | D68: =IF(ISBLANK(B68),D67,B68) | E68: 57 | F68: Neuer Zählerschrank für MFH | J68: WE | K68: 1000 | L68: =(N68/$I$5)/(1+$F$7) | M68: =L68/8 | N68: =P68*G68 | O68: =P68*H68 | P68: =I68*K68
C69: =IF(I69>0,MAX($C$12:C68)+1,"") | D69: =IF(ISBLANK(B69),D67,B69) | E69: 58 | F69: Elektroinstallation neu pro qm Wohnfläche | G69: 0.65 | H69: 0.35 | J69: m² | K69: 80 | L69: =(N69/$I$5)/(1+$F$7) | M69: =L69/8 | N69: =P69*G69 | O69: =P69*H69 | P69: =I69*K69
B70: Heizung / Heizkörper | C70: =IF(I70>0,MAX($C$12:C69)+1,"") | D70: =IF(ISBLANK(B70),D69,B70) | E70: 59 | F70: Heizkörper lackieren | G70: 0.75 | H70: 0.25 | J70: Stk | K70: 65 | L70: =(N70/$I$5)/(1+$F$7) | M70: =L70/8 | N70: =P70*G70 | O70: =P70*H70 | P70: =I70*K70 | Q70: =SUM(P70:P83)
C71: =IF(I71>0,MAX($C$12:C70)+1,"") | D71: =IF(ISBLANK(B71),D70,B71) | E71: 60 | F71: Thermostatkopfwechsel | G71: 0.3 | H71: 0.7 | J71: Stk | K71: 40 | L71: =(N71/$I$5)/(1+$F$7) | M71: =L71/8 | N71: =P71*G71 | O71: =P71*H71 | P71: =I71*K71
C72: =IF(I72>0,MAX($C$12:C71)+1,"") | D72: =IF(ISBLANK(B72),D71,B72) | E72: 61 | F72: Heizkörper überprüfen in Wohnung | G72: 1 | H72: 0 | J72: Stk | K72: 145 | L72: =(N72/$I$5)/(1+$F$7) | M72: =L72/8 | N72: =P72*G72 | O72: =P72*H72 | P72: =I72*K72
C73: =IF(I73>0,MAX($C$12:C72)+1,"") | D73: =IF(ISBLANK(B73),D72,B73) | E73: 62 | F73: Heizkörper mit Thermostat erneuern | G73: 0 | H73: 1 | J73: Stk | K73: 240 | L73: =(N73/$I$5)/(1+$F$7) | M73: =L73/8 | N73: =P73*G73 | O73: =P73*H73 | P73: =I73*K73
C74: =IF(I74>0,MAX($C$12:C73)+1,"") | D74: =IF(ISBLANK(B74),D73,B74) | E74: 63 | F74: Elekrodurchlauferhitzer erneuern | G74: 0.3 | H74: 0.7 | J74: Stk | K74: 750 | L74: =(N74/$I$5)/(1+$F$7) | M74: =L74/8 | N74: =P74*G74 | O74: =P74*H74 | P74: =I74*K74
C75: =IF(I75>0,MAX($C$12:C74)+1,"") | D75: =IF(ISBLANK(B75),D74,B75) | E75: 64 | F75: Heizleitungen erneuern pro qm Wfl. | G75: 0.7 | H75: 0.3 | J75: m² | K75: 40 | L75: =(N75/$I$5)/(1+$F$7) | M75: =L75/8 | N75: =P75*G75 | O75: =P75*H75 | P75: =I75*K75
C76: =IF(I76>0,MAX($C$12:C75)+1,"") | D76: =IF(ISBLANK(B76),D75,B76) | E76: 65 | F76: Badlüfter tauschen | G76: 0.35 | H76: 0.65 | J76: Stk | K76: 105 | L76: =(N76/$I$5)/(1+$F$7) | M76: =L76/8 | N76: =P76*G76 | O76: =P76*H76 | P76: =I76*K76
C77: =IF(I77>0,MAX($C$12:C76)+1,"") | D77: =IF(ISBLANK(B77),D76,B77) | E77: 66 | F77: Pelletheizung einbauen (ohne Leitungen & Heizkörper) | J77: WE | K77: 6500 | L77: =(N77/$I$5)/(1+$F$7) | M77: =L77/8 | N77: =P77*G77 | O77: =P77*H77 | P77: =I77*K77
C78: =IF(I78>0,MAX($C$12:C77)+1,"") | D78: =IF(ISBLANK(B78),D77,B78) | E78: 67 | F78: Gaszentralheizung erneuern | J78: WE
C79: =IF(I79>0,MAX($C$12:C78)+1,"") | D79: =IF(ISBLANK(B79),D78,B79) | E79: 68 | F79: Luft-Wärmepumpe erneuern | J79: WE
C80: =IF(I80>0,MAX($C$12:C79)+1,"") | D80: =IF(ISBLANK(B80),D76,B80) | E80: 69 | F80: Elektroheizung - Einbau Stromleitungen | G80: 0.4 | H80: 0.6 | J80: m² | K80: 10 | L80: =(N80/$I$5)/(1+$F$7) | M80: =L80/8 | N80: =P80*G80 | O80: =P80*H80 | P80: =I80*K80
C81: =IF(I81>0,MAX($C$12:C80)+1,"") | D81: =IF(ISBLANK(B81),D80,B81) | E81: 70 | F81: Elektroheizung | G81: 0.4 | H81: 0.6 | J81: m² | K81: 30 | L81: =(N81/$I$5)/(1+$F$7) | M81: =L81/8 | N81: =P81*G81 | O81: =P81*H81 | P81: =I81*K81
C82: =IF(I82>0,MAX($C$12:C81)+1,"") | D82: =IF(ISBLANK(B82),D81,B82) | E82: 71 | F82: Gastherme überprüfen | G82: 1 | H82: 0 | J82: Stk | K82: 200 | L82: =(N82/$I$5)/(1+$F$7) | M82: =L82/8 | N82: =P82*G82 | O82: =P82*H82 | P82: =I82*K82
C83: =IF(I83>0,MAX($C$12:C82)+1,"") | D83: =IF(ISBLANK(B83),D82,B83) | E83: 72 | F83: Gastherme erneuern | G83: 0.4 | H83: 0.6 | J83: Stk | K83: 4750 | L83: =(N83/$I$5)/(1+$F$7) | M83: =L83/8 | N83: =P83*G83 | O83: =P83*H83 | P83: =I83*K83
B84: Bad / Sanitär | C84: =IF(I84>0,MAX($C$12:C83)+1,"") | D84: =IF(ISBLANK(B84),D83,B84) | E84: 73 | F84: Badewanne erneuern | G84: 0.4 | H84: 0.6 | J84: Stk. | K84: 800 | L84: =(N84/$I$5)/(1+$F$7) | M84: =L84/8 | N84: =P84*G84 | O84: =P84*H84 | P84: =I84*K84 | Q84: =SUM(P84:P96)
C85: =IF(I85>0,MAX($C$12:C84)+1,"") | D85: =IF(ISBLANK(B85),D84,B85) | E85: 74 | F85: Armatur Badewanne inkl. Duschstange erneuern | G85: 0.4 | H85: 0.6 | J85: Stk. | K85: 250 | L85: =(N85/$I$5)/(1+$F$7) | M85: =L85/8 | N85: =P85*G85 | O85: =P85*H85 | P85: =I85*K85
C86: =IF(I86>0,MAX($C$12:C85)+1,"") | D86: =IF(ISBLANK(B86),D85,B86) | E86: 75 | F86: Duschwanne erneuern | G86: 0.4 | H86: 0.6 | J86: Stk. | K86: 600 | L86: =(N86/$I$5)/(1+$F$7) | M86: =L86/8 | N86: =P86*G86 | O86: =P86*H86 | P86: =I86*K86
C87: =IF(I87>0,MAX($C$12:C86)+1,"") | D87: =IF(ISBLANK(B87),D86,B87) | E87: 76 | F87: Handbrause mit Schlauch erneuern | G87: 0.3 | H87: 0.7 | J87: Stk. | K87: 70 | L87: =(N87/$I$5)/(1+$F$7) | M87: =L87/8 | N87: =P87*G87 | O87: =P87*H87 | P87: =I87*K87
C88: =IF(I88>0,MAX($C$12:C87)+1,"") | D88: =IF(ISBLANK(B88),D87,B88) | E88: 77 | F88: Waschbecken erneuern | G88: 0.6 | H88: 0.4 | J88: Stk. | K88: 280 | L88: =(N88/$I$5)/(1+$F$7) | M88: =L88/8 | N88: =P88*G88 | O88: =P88*H88 | P88: =I88*K88
C89: =IF(I89>0,MAX($C$12:C88)+1,"") | D89: =IF(ISBLANK(B89),D88,B89) | E89: 78 | F89: Armatur Waschbecken erneuern | G89: 0.4 | H89: 0.6 | J89: Stk. | K89: 120 | L89: =(N89/$I$5)/(1+$F$7) | M89: =L89/8 | N89: =P89*G89 | O89: =P89*H89 | P89: =I89*K89
C90: =IF(I90>0,MAX($C$12:C89)+1,"") | D90: =IF(ISBLANK(B90),D89,B90) | E90: 79 | F90: WC erneuern | G90: 0.4 | H90: 0.6 | J90: Stk. | K90: 220 | L90: =(N90/$I$5)/(1+$F$7) | M90: =L90/8 | N90: =P90*G90 | O90: =P90*H90 | P90: =I90*K90
C91: =IF(I91>0,MAX($C$12:C90)+1,"") | D91: =IF(ISBLANK(B91),D90,B91) | E91: 80 | F91: WC Sitz + Deckel erneuern | G91: 0.2 | H91: 0.8 | J91: Stk. | K91: 60 | L91: =(N91/$I$5)/(1+$F$7) | M91: =L91/8 | N91: =P91*G91 | O91: =P91*H91 | P91: =I91*K91
C92: =IF(I92>0,MAX($C$12:C91)+1,"") | D92: =IF(ISBLANK(B92),D91,B92) | E92: 81 | F92: WC Spülkasten erneuern | G92: 0.3 | H92: 0.7 | J92: Stk. | K92: 100 | L92: =(N92/$I$5)/(1+$F$7) | M92: =L92/8 | N92: =P92*G92 | O92: =P92*H92 | P92: =I92*K92
C93: =IF(I93>0,MAX($C$12:C92)+1,"") | D93: =IF(ISBLANK(B93),D92,B93) | E93: 82 | F93: Bad Komplettsanierung ohne Leitungen | G93: 0.7 | H93: 0.3 | J93: m² Wfl. | K93: 750 | L93: =(N93/$I$5)/(1+$F$7) | M93: =L93/8 | N93: =P93*G93 | O93: =P93*H93 | P93: =I93*K93
C94: =IF(I94>0,MAX($C$12:C93)+1,"") | D94: =IF(ISBLANK(B94),D93,B94) | E94: 83 | F94: Wasserleitungen erneuern | G94: 0.7 | H94: 0.3 | J94: m² | K94: 70 | L94: =(N94/$I$5)/(1+$F$7) | M94: =L94/8 | N94: =P94*G94 | O94: =P94*H94 | P94: =I94*K94
C95: =IF(I95>0,MAX($C$12:C94)+1,"") | D95: =IF(ISBLANK(B95),D94,B95) | E95: 84 | F95: Wasserzähler einbauen | G95: 0.4 | H95: 0.6 | J95: Stk. | K95: 350 | L95: =(N95/$I$5)/(1+$F$7) | M95: =L95/8 | N95: =P95*G95 | O95: =P95*H95 | P95: =I95*K95
C96: =IF(I96>0,MAX($C$12:C95)+1,"") | D96: =IF(ISBLANK(B96),D95,B96) | E96: 85 | F96: Waschmaschienen Anschluss herstellen | G96: 0.8 | H96: 0.2 | J96: Stk | K96: 300 | L96: =(N96/$I$5)/(1+$F$7) | M96: =L96/8 | N96: =P96*G96 | O96: =P96*H96 | P96: =I96*K96
B97: Außenanlage | C97: =IF(I97>0,MAX($C$12:C96)+1,"") | D97: =IF(ISBLANK(B97),D96,B97) | E97: 86 | F97: Gartenarbeiten | G97: 0.85 | H97: 0.15 | J97: Std | K97: 35 | L97: =(N97/$I$5)/(1+$F$7) | M97: =L97/8 | N97: =P97*G97 | O97: =P97*H97 | P97: =I97*K97 | Q97: =SUM(P97:P99)
C98: =IF(I98>0,MAX($C$12:C97)+1,"") | D98: =IF(ISBLANK(B98),D97,B98) | E98: 87 | F98: Asphalt / Betondecke abbrechen und entsorgen | J98: m² | K98: 25 | L98: =(N98/$I$5)/(1+$F$7) | M98: =L98/8 | N98: =P98*G98 | O98: =P98*H98 | P98: =I98*K98
C99: =IF(I99>0,MAX($C$12:C98)+1,"") | D99: =IF(ISBLANK(B99),D98,B99) | E99: 88 | F99: Hof pflastern (inkl. Steine) | J99: m² | K99: 80 | L99: =(N99/$I$5)/(1+$F$7) | M99: =L99/8 | N99: =P99*G99 | O99: =P99*H99 | P99: =I99*K99
B100: Reinigung | C100: =IF(I100>0,MAX($C$12:C99)+1,"") | D100: =IF(ISBLANK(B100),D99,B100) | E100: 89 | F100: Grundreinigung Wohnung / Bauendreinigung | G100: 1 | H100: 0 | J100: Stk | K100: 500 | L100: =(N100/$I$5)/(1+$F$7) | M100: =L100/8 | N100: =P100*G100 | O100: =P100*H100 | P100: =I100*K100 | Q100: =P100
B101: Home Staging | C101: =IF(I101>0,MAX($C$12:C100)+1,"") | D101: =IF(ISBLANK(B101),D100,B101) | E101: 90 | F101: Home Staging (Beispieleinrichtung für den Verkauf) | J101: m² | K101: 50 | L101: =(N101/$I$5)/(1+$F$7) | M101: =L101/8 | N101: =P101*G101 | O101: =P101*H101 | P101: =I101*K101 | Q101: =P101
B102: Sonstiges | C102: =IF(I102>0,MAX($C$12:C101)+1,"") | D102: =IF(ISBLANK(B102),D101,B102) | E102: 91 | F102: Einbauküche (inkl. Montage) | G102: 0.5 | H102: 0.5 | J102: Stk | K102: 3000 | L102: =(N102/$I$5)/(1+$F$7) | M102: =L102/8 | N102: =P102*G102 | O102: =P102*H102 | P102: =I102*K102 | Q102: =SUM(P102:P105)
C103: =IF(I103>0,MAX($C$12:C102)+1,"") | D103: =IF(ISBLANK(B103),D102,B103) | E103: 92 | F103: Scheune abreißen (inkl. Entsorgung) | G103: 0.5 | H103: 0.5 | J103: psch | K103: 10000 | L103: =(N103/$I$5)/(1+$F$7) | M103: =L103/8 | N103: =P103*G103 | O103: =P103*H103 | P103: =I103*K103
C104: =IF(I104>0,MAX($C$12:C103)+1,"") | D104: =IF(ISBLANK(B104),D103,B104) | E104: 93 | F104: WEG Aufteilung | G104: 0.5 | H104: 0.5 | J104: psch | K104: 12000 | L104: =(N104/$I$5)/(1+$F$7) | M104: =L104/8 | N104: =P104*G104 | O104: =P104*H104 | P104: =I104*K104
...

Sheet MIETER
A1: MIETAUFSTELLUNG
R3: § 559 BGB (Modernisierung)
N4: =TODAY() | R4: Modernisierungskosten =
N5: § 558 BGB (Mietspiegel) | R5: Davon 8% umlegbar auf JNKM = | T5: =T4*8%
L6: Mietspiegel → | M6: 10 | N6: Kappungsgrenze = | P6: 0.2 | R6: Erhöhung pro Monat pro qm WFL = | T6: =T5/12/F28 | U6: Tagesaktuelle Mietsituation während dem Projekt | Y6: Modul 4 Output
A7: Haus Nr. | B7: WHG Nr | C7: Etage | D7: Lage | E7: Zimmer | F7: Wohnfläche | G7: Name Mieter | H7: Beginn Miete | I7: letz. Erhöhung | J7: Kaltmiete IST | K7: Garagen-/Stellpl.- miete | L7: IST KM/qm | M7: Δ zu Mietspiegel | N7: Kaltmiete NEU | O7: Stellplätze | P7: NEU KM/qm | Q7: Δ zu Mietspiegel | R7: Kaltmiete SOLL | S7: Stellplätze | T7: SOLL KM/qm | U7: Kaltmiete | V7: Stellplätze | W7: IST KM/qm | X7: Notiz | Y7: Mietspiegel-Obergrenze EUR/m² (per WE)
K8: =IF(AND(NOT(ISNUMBER('Verkauf Cashflow'!AL3)),NOT(ISNUMBER('Verkauf Cashflow'!AM3))),"",N('Verkauf Cashflow'!AL3)+N('Verkauf Cashflow'!AM3)) | L8: =IFERROR(J8/F8,"") | M8: =IF(L8="", "", L8-$M$6) | N8: =IFERROR(IF(J8/F8>(Y8+$M$6)/2,J8,IF(I8<EDATE($N$4,-36),IF(J8*(1+$P$6)/F8<=(Y8+$M$6)/2,J8*(1+$P$6),F8*(Y8+$M$6)/2),J8)),"") | P8: =IFERROR(N8/F8,"") | Q8: =IF(P8="", "", P8-$M$6) | R8: =IF(Y8="","",IFERROR(MAX(J8,(Y8+$T$6)*F8),"")) | T8: =IFERROR(R8/F8,"") | W8: =IFERROR(U8/F8,"")
K9: =IF(AND(NOT(ISNUMBER('Verkauf Cashflow'!AL4)),NOT(ISNUMBER('Verkauf Cashflow'!AM4))),"",N('Verkauf Cashflow'!AL4)+N('Verkauf Cashflow'!AM4)) | L9: =IFERROR(J9/F9,"") | M9: =IF(L9="", "", L9-$M$6) | N9: =IFERROR(IF(J9/F9>(Y9+$M$6)/2,J9,IF(I9<EDATE($N$4,-36),IF(J9*(1+$P$6)/F9<=(Y9+$M$6)/2,J9*(1+$P$6),F9*(Y9+$M$6)/2),J9)),"") | P9: =IFERROR(N9/F9,"") | Q9: =IF(P9="", "", P9-$M$6) | R9: =IF(Y9="","",IFERROR(MAX(J9,(Y9+$T$6)*F9),"")) | T9: =IFERROR(R9/F9,"") | W9: =IFERROR(U9/F9,"")
K10: =IF(AND(NOT(ISNUMBER('Verkauf Cashflow'!AL5)),NOT(ISNUMBER('Verkauf Cashflow'!AM5))),"",N('Verkauf Cashflow'!AL5)+N('Verkauf Cashflow'!AM5)) | L10: =IFERROR(J10/F10,"") | M10: =IF(L10="", "", L10-$M$6) | N10: =IFERROR(IF(J10/F10>(Y10+$M$6)/2,J10,IF(I10<EDATE($N$4,-36),IF(J10*(1+$P$6)/F10<=(Y10+$M$6)/2,J10*(1+$P$6),F10*(Y10+$M$6)/2),J10)),"") | P10: =IFERROR(N10/F10,"") | Q10: =IF(P10="", "", P10-$M$6) | R10: =IF(Y10="","",IFERROR(MAX(J10,(Y10+$T$6)*F10),"")) | T10: =IFERROR(R10/F10,"") | W10: =IFERROR(U10/F10,"")
K11: =IF(AND(NOT(ISNUMBER('Verkauf Cashflow'!AL6)),NOT(ISNUMBER('Verkauf Cashflow'!AM6))),"",N('Verkauf Cashflow'!AL6)+N('Verkauf Cashflow'!AM6)) | L11: =IFERROR(J11/F11,"") | M11: =IF(L11="", "", L11-$M$6) | N11: =IFERROR(IF(J11/F11>(Y11+$M$6)/2,J11,IF(I11<EDATE($N$4,-36),IF(J11*(1+$P$6)/F11<=(Y11+$M$6)/2,J11*(1+$P$6),F11*(Y11+$M$6)/2),J11)),"") | P11: =IFERROR(N11/F11,"") | Q11: =IF(P11="", "", P11-$M$6) | R11: =IF(Y11="","",IFERROR(MAX(J11,(Y11+$T$6)*F11),"")) | T11: =IFERROR(R11/F11,"") | W11: =IFERROR(U11/F11,"")
K12: =IF(AND(NOT(ISNUMBER('Verkauf Cashflow'!AL7)),NOT(ISNUMBER('Verkauf Cashflow'!AM7))),"",N('Verkauf Cashflow'!AL7)+N('Verkauf Cashflow'!AM7)) | L12: =IFERROR(J12/F12,"") | M12: =IF(L12="", "", L12-$M$6) | N12: =IFERROR(IF(J12/F12>(Y12+$M$6)/2,J12,IF(I12<EDATE($N$4,-36),IF(J12*(1+$P$6)/F12<=(Y12+$M$6)/2,J12*(1+$P$6),F12*(Y12+$M$6)/2),J12)),"") | P12: =IFERROR(N12/F12,"") | Q12: =IF(P12="", "", P12-$M$6) | R12: =IF(Y12="","",IFERROR(MAX(J12,(Y12+$T$6)*F12),"")) | T12: =IFERROR(R12/F12,"") | W12: =IFERROR(U12/F12,"")
K13: =IF(AND(NOT(ISNUMBER('Verkauf Cashflow'!AL8)),NOT(ISNUMBER('Verkauf Cashflow'!AM8))),"",N('Verkauf Cashflow'!AL8)+N('Verkauf Cashflow'!AM8)) | L13: =IFERROR(J13/F13,"") | M13: =IF(L13="", "", L13-$M$6) | N13: =IFERROR(IF(J13/F13>(Y13+$M$6)/2,J13,IF(I13<EDATE($N$4,-36),IF(J13*(1+$P$6)/F13<=(Y13+$M$6)/2,J13*(1+$P$6),F13*(Y13+$M$6)/2),J13)),"") | P13: =IFERROR(N13/F13,"") | Q13: =IF(P13="", "", P13-$M$6) | R13: =IF(Y13="","",IFERROR(MAX(J13,(Y13+$T$6)*F13),"")) | T13: =IFERROR(R13/F13,"") | W13: =IFERROR(U13/F13,"")
K14: =IF(AND(NOT(ISNUMBER('Verkauf Cashflow'!AL9)),NOT(ISNUMBER('Verkauf Cashflow'!AM9))),"",N('Verkauf Cashflow'!AL9)+N('Verkauf Cashflow'!AM9)) | L14: =IFERROR(J14/F14,"") | M14: =IF(L14="", "", L14-$M$6) | N14: =IFERROR(IF(J14/F14>(Y14+$M$6)/2,J14,IF(I14<EDATE($N$4,-36),IF(J14*(1+$P$6)/F14<=(Y14+$M$6)/2,J14*(1+$P$6),F14*(Y14+$M$6)/2),J14)),"") | P14: =IFERROR(N14/F14,"") | Q14: =IF(P14="", "", P14-$M$6) | R14: =IF(Y14="","",IFERROR(MAX(J14,(Y14+$T$6)*F14),"")) | T14: =IFERROR(R14/F14,"") | W14: =IFERROR(U14/F14,"")
K15: =IF(AND(NOT(ISNUMBER('Verkauf Cashflow'!AL10)),NOT(ISNUMBER('Verkauf Cashflow'!AM10))),"",N('Verkauf Cashflow'!AL10)+N('Verkauf Cashflow'!AM10)) | L15: =IFERROR(J15/F15,"") | M15: =IF(L15="", "", L15-$M$6) | N15: =IFERROR(IF(J15/F15>(Y15+$M$6)/2,J15,IF(I15<EDATE($N$4,-36),IF(J15*(1+$P$6)/F15<=(Y15+$M$6)/2,J15*(1+$P$6),F15*(Y15+$M$6)/2),J15)),"") | P15: =IFERROR(N15/F15,"") | Q15: =IF(P15="", "", P15-$M$6) | R15: =IF(Y15="","",IFERROR(MAX(J15,(Y15+$T$6)*F15),"")) | T15: =IFERROR(R15/F15,"") | W15: =IFERROR(U15/F15,"")
K16: =IF(AND(NOT(ISNUMBER('Verkauf Cashflow'!AL11)),NOT(ISNUMBER('Verkauf Cashflow'!AM11))),"",N('Verkauf Cashflow'!AL11)+N('Verkauf Cashflow'!AM11)) | L16: =IFERROR(J16/F16,"") | M16: =IF(L16="", "", L16-$M$6) | N16: =IFERROR(IF(J16/F16>(Y16+$M$6)/2,J16,IF(I16<EDATE($N$4,-36),IF(J16*(1+$P$6)/F16<=(Y16+$M$6)/2,J16*(1+$P$6),F16*(Y16+$M$6)/2),J16)),"") | P16: =IFERROR(N16/F16,"") | Q16: =IF(P16="", "", P16-$M$6) | R16: =IF(Y16="","",IFERROR(MAX(J16,(Y16+$T$6)*F16),"")) | T16: =IFERROR(R16/F16,"") | W16: =IFERROR(U16/F16,"")
K17: =IF(AND(NOT(ISNUMBER('Verkauf Cashflow'!AL12)),NOT(ISNUMBER('Verkauf Cashflow'!AM12))),"",N('Verkauf Cashflow'!AL12)+N('Verkauf Cashflow'!AM12)) | L17: =IFERROR(J17/F17,"") | M17: =IF(L17="", "", L17-$M$6) | N17: =IFERROR(IF(J17/F17>(Y17+$M$6)/2,J17,IF(I17<EDATE($N$4,-36),IF(J17*(1+$P$6)/F17<=(Y17+$M$6)/2,J17*(1+$P$6),F17*(Y17+$M$6)/2),J17)),"") | P17: =IFERROR(N17/F17,"") | Q17: =IF(P17="", "", P17-$M$6) | R17: =IF(Y17="","",IFERROR(MAX(J17,(Y17+$T$6)*F17),"")) | T17: =IFERROR(R17/F17,"") | W17: =IFERROR(U17/F17,"")
K18: =IF(AND(NOT(ISNUMBER('Verkauf Cashflow'!AL13)),NOT(ISNUMBER('Verkauf Cashflow'!AM13))),"",N('Verkauf Cashflow'!AL13)+N('Verkauf Cashflow'!AM13)) | L18: =IFERROR(J18/F18,"") | M18: =IF(L18="", "", L18-$M$6) | N18: =IFERROR(IF(J18/F18>(Y18+$M$6)/2,J18,IF(I18<EDATE($N$4,-36),IF(J18*(1+$P$6)/F18<=(Y18+$M$6)/2,J18*(1+$P$6),F18*(Y18+$M$6)/2),J18)),"") | P18: =IFERROR(N18/F18,"") | Q18: =IF(P18="", "", P18-$M$6) | R18: =IF(Y18="","",IFERROR(MAX(J18,(Y18+$T$6)*F18),"")) | T18: =IFERROR(R18/F18,"") | W18: =IFERROR(U18/F18,"")
K19: =IF(AND(NOT(ISNUMBER('Verkauf Cashflow'!AL14)),NOT(ISNUMBER('Verkauf Cashflow'!AM14))),"",N('Verkauf Cashflow'!AL14)+N('Verkauf Cashflow'!AM14)) | L19: =IFERROR(J19/F19,"") | M19: =IF(L19="", "", L19-$M$6) | N19: =IFERROR(IF(J19/F19>(Y19+$M$6)/2,J19,IF(I19<EDATE($N$4,-36),IF(J19*(1+$P$6)/F19<=(Y19+$M$6)/2,J19*(1+$P$6),F19*(Y19+$M$6)/2),J19)),"") | P19: =IFERROR(N19/F19,"") | Q19: =IF(P19="", "", P19-$M$6) | R19: =IF(Y19="","",IFERROR(MAX(J19,(Y19+$T$6)*F19),"")) | T19: =IFERROR(R19/F19,"") | W19: =IFERROR(U19/F19,"")
... K27: =IF(AND(NOT(ISNUMBER('Verkauf Cashflow'!AL22)),NOT(ISNUMBER('Verkauf Cashflow'!AM22))),"",N('Verkauf Cashflow'!AL22)+N('Verkauf Cashflow'!AM22)) | L27: =IFERROR(J27/F27,"") | M27: =IF(L27="", "", L27-$M$6) | N27: =IFERROR(IF(J27/F27>(Y27+$M$6)/2,J27,IF(I27<EDATE($N$4,-36),IF(J27*(1+$P$6)/F27<=(Y27+$M$6)/2,J27*(1+$P$6),F27*(Y27+$M$6)/2),J27)),"") | P27: =IFERROR(N27/F27,"") | Q27: =IF(P27="", "", P27-$M$6) | R27: =IF(Y27="","",IFERROR(MAX(J27,(Y27+$T$6)*F27),"")) | T27: =IFERROR(R27/F27,"") | W27: =IFERROR(U27/F27,"")
F28: =SUM(F8:F27) | J28: =SUM(J8:J27) | K28: =SUM(K8:K27) | L28: =AVERAGE(L8:L27) | N28: =SUM(N8:N27) | O28: =SUM(O8:O27) | P28: =AVERAGE(P8:P27) | R28: =SUM(R8:R27) | S28: =SUM(S8:S27) | T28: =AVERAGE(T8:T27) | U28: =SUM(U8:U27) | V28: =SUM(V8:V27) | W28: =IFERROR(AVERAGE(W8:W27),"")
J29: ↓ | K29: ↓ | N29: ↓ | O29: ↓ | R29: ↓ | S29: ↓
I30: pro Jahr = | J30: =J28*12 | K30: =K28*12 | N30: =N28*12 | O30: =O28*12 | R30: =R28*12 | S30: =S28*12
I31: JNKM = | J31: =J30+K30 | N31: =N30+O30 | R31: =R30+S30
J32: Rendite Einkauf (KP+NK) | K32: =J31/(KALKU!P37+KALKU!J30) | N32: Rendite Einkauf (KP+NK) | O32: =N31/(KALKU!P37+KALKU!J30) | R32: Rendite Einkauf (GIK) | S32: =R31/KALKU!J39

Sheet VERKAUFSMATRIX
A1: VERKAUFSMATRIX
A5: HAUS NR. | B5: WHG NR. | C5: ETAGE | D5: LAGE | E5: ZIMMER | F5: WOHN- FLÄCHE | G5: €/qm PORTALPREISE | H5: €/qm AUF/ABSCHLAG | I5: MIETSITUATION (- 10%) | J5: Auf-/Abschlag Mietsituation | K5: Δ zu Mietspiegel | L5: =MIETER!M6 | M5: BALKON (- 5%) | N5: Auf-/Abschlag Balkon | O5: Baujahr Etagenheizung | P5: Auf-/Abschlag Etagenheizung | Q5: ZUSTAND RENOVIERUNG IM VERKAUF (+5%/- 5%) | R5: Auf-/Abschlag Renovierung | S5: ETAGE / LAGE (- 5%) | T5: ETAGE / LAGE (- 5%) | U5: VERKAUFSPREIS WOHNUNG | V5: PREIS GARAGE / STELLPLATZ | W5: VORSCHLAG VERKAUFSPREIS | X5: INDIVIDUELLER AUF-/ABSCHLAG | Y5: MEIN VERKAUFSPREIS | Z5: VK / qm | AA5: % RENDITE MEIN PREIS
A6: =IF(ISNUMBER(MIETER!F8),IFERROR(MIETER!A8,""),"") | B6: =IF(ISNUMBER(MIETER!F8),IFERROR(MIETER!B8,""),"") | C6: =IF(ISNUMBER(MIETER!F8),IFERROR(MIETER!C8,""),"") | D6: =IF(ISNUMBER(MIETER!F8),IFERROR(MIETER!D8,""),"") | E6: =IF(ISNUMBER(MIETER!F8),IFERROR(MIETER!E8,""),"") | F6: =IF(ISNUMBER(MIETER!F8),IFERROR(MIETER!F8,""),"") | G6: =IF(ISNUMBER(MIETER!F8),KALKU!$I$18,"") | H6: =IF(ISNUMBER(MIETER!F8),KALKU!$N$18,"") | J6: =IF(ISNUMBER(MIETER!F8),IF(I6="vermietet",H6*(-0.1),H6*0),"") | K6: =IF(ISNUMBER(MIETER!F8),IFERROR(MIETER!Q8/MIETER!$M$6,""),"") | L6: =IF(ISNUMBER(MIETER!F8),IF(K6 >= 0%,H6*(0.01), IF(K6 >= -5%,H6*(-0.01), IF(K6 >= -10%,H6*(-0.02), IF(K6 >= -15%,H6*(-0.03), IF(K6 >= -20%,H6*(-0.04), IF(K6 >= -25%,H6*(-0.05), IF(K6 >= -30%,H6*(-0.06), IF(K6 >= -35%,H6*(-0.07), IF(K6 >= -40%,H6*(-0.08), IF(K6 >= -45%,H6*(-0.09), IF(K6 >= -50%, H6*(-0.1), H6*0 ) )))))))))),"") | N6: =IF(NOT(ISNUMBER(H6)),"",IF(M6="Kein Balkon",H6*(-0.05),H6*0)) | P6: =IF(NOT(ISNUMBER(H6)),"",IF(ISBLANK(O6),0,H6*MIN((YEAR(TODAY())-O6)*0.003,0.09)*-1)) | R6: =IF(ISNUMBER(MIETER!F8),IF(Q6="renoviert",H6*0.05,IF(Q6="teilweise renoviert",H6*0,IF(Q6="unrenoviert",H6*-0.05,0))),"") | S6: =IF(ISNUMBER(MIETER!F8),C6,"") | T6: =IF(ISNUMBER(MIETER!F8),IF(OR(S6="EG",S6="1.OG",S6="2.OG",S6="OG",S6="über 2.OG mit Aufzug"),H6*0,IF(OR(S6="UG",S6="über 2.OG ohne Aufzug"),H6*(-0.05),0)),"") | U6: =IF(ISNUMBER(MIETER!F8),IFERROR(F6*(H6+J6+L6+N6+P6+R6+T6),""),"") | V6: =IF(NOT(ISNUMBER(MIETER!F8)),"",N('Verkauf Cashflow'!Q3)+N('Verkauf Cashflow'!R3)) | W6: =IF(ISNUMBER(MIETER!F8),U6+V6,"") | X6: =IF(ISNUMBER('Verkauf Cashflow'!O3),'Verkauf Cashflow'!O3,"") | Y6: =IF(ISNUMBER('Verkauf Cashflow'!S3),'Verkauf Cashflow'!S3,"") | Z6: =IF(ISNUMBER(MIETER!F8),IFERROR(Y6/F6,""),"") | AA6: =IF(ISNUMBER('Verkauf Cashflow'!CF3),'Verkauf Cashflow'!CF3,"")
A7: =IF(ISNUMBER(MIETER!F9),IFERROR(MIETER!A9,""),"") | B7: =IF(ISNUMBER(MIETER!F9),IFERROR(MIETER!B9,""),"") | C7: =IF(ISNUMBER(MIETER!F9),IFERROR(MIETER!C9,""),"") | D7: =IF(ISNUMBER(MIETER!F9),IFERROR(MIETER!D9,""),"") | E7: =IF(ISNUMBER(MIETER!F9),IFERROR(MIETER!E9,""),"") | F7: =IF(ISNUMBER(MIETER!F9),IFERROR(MIETER!F9,""),"") | G7: =IF(ISNUMBER(MIETER!F9),KALKU!$I$18,"") | H7: =IF(ISNUMBER(MIETER!F9),KALKU!$N$18,"") | J7: =IF(ISNUMBER(MIETER!F9),IF(I7="vermietet",H7*(-0.1),H7*0),"") | K7: =IF(ISNUMBER(MIETER!F9),IFERROR(MIETER!Q9/MIETER!$M$6,""),"") | L7: =IF(ISNUMBER(MIETER!F9),IF(K7 >= 0%,H7*(0.01), IF(K7 >= -5%,H7*(-0.01), IF(K7 >= -10%,H7*(-0.02), IF(K7 >= -15%,H7*(-0.03), IF(K7 >= -20%,H7*(-0.04), IF(K7 >= -25%,H7*(-0.05), IF(K7 >= -30%,H7*(-0.06), IF(K7 >= -35%,H7*(-0.07), IF(K7 >= -40%,H7*(-0.08), IF(K7 >= -45%,H7*(-0.09), IF(K7 >= -50%, H7*(-0.1), H7* 0) )))))))))),"") | N7: =IF(NOT(ISNUMBER(H7)),"",IF(M7="Kein Balkon",H7*(-0.05),H7*0)) | P7: =IF(NOT(ISNUMBER(H7)),"",IF(ISBLANK(O7),0,H7*MIN((YEAR(TODAY())-O7)*0.003,0.09)*-1)) | R7: =IF(ISNUMBER(MIETER!F9),IF(Q7="renoviert",H7*0.05,IF(Q7="teilweise renoviert",H7*0,IF(Q7="unrenoviert",H7*-0.05,0))),"") | S7: =IF(ISNUMBER(MIETER!F9),C7,"") | T7: =IF(ISNUMBER(MIETER!F9),IF(OR(S7="EG",S7="1.OG",S7="2.OG",S7="OG",S7="über 2.OG mit Aufzug"),H7*0,IF(OR(S7="UG",S7="über 2.OG ohne Aufzug"),H7*(-0.05),0)),"") | U7: =IF(ISNUMBER(MIETER!F9),IFERROR(F7*(H7+J7+L7+N7+P7+R7+T7),""),"") | V7: =IF(NOT(ISNUMBER(MIETER!F9)),"",N('Verkauf Cashflow'!Q4)+N('Verkauf Cashflow'!R4)) | W7: =IF(ISNUMBER(MIETER!F9),U7+V7,"") | X7: =IF(ISNUMBER('Verkauf Cashflow'!O4),'Verkauf Cashflow'!O4,"") | Y7: =IF(ISNUMBER('Verkauf Cashflow'!S4),'Verkauf Cashflow'!S4,"") | Z7: =IF(ISNUMBER(MIETER!F9),IFERROR(Y7/F7,""),"") | AA7: =IF(ISNUMBER('Verkauf Cashflow'!CF4),'Verkauf Cashflow'!CF4,"")
A8: =IF(ISNUMBER(MIETER!F10),IFERROR(MIETER!A10,""),"") | B8: =IF(ISNUMBER(MIETER!F10),IFERROR(MIETER!B10,""),"") | C8: =IF(ISNUMBER(MIETER!F10),IFERROR(MIETER!C10,""),"") | D8: =IF(ISNUMBER(MIETER!F10),IFERROR(MIETER!D10,""),"") | E8: =IF(ISNUMBER(MIETER!F10),IFERROR(MIETER!E10,""),"") | F8: =IF(ISNUMBER(MIETER!F10),IFERROR(MIETER!F10,""),"") | G8: =IF(ISNUMBER(MIETER!F10),KALKU!$I$18,"") | H8: =IF(ISNUMBER(MIETER!F10),KALKU!$N$18,"") | J8: =IF(ISNUMBER(MIETER!F10),IF(I8="vermietet",H8*(-0.1),H8*0),"") | K8: =IF(ISNUMBER(MIETER!F10),IFERROR(MIETER!Q10/MIETER!$M$6,""),"") | L8: =IF(ISNUMBER(MIETER!F10),IF(K8 >= 0%,H8*(0.01), IF(K8 >= -5%,H8*(-0.01), IF(K8 >= -10%,H8*(-0.02), IF(K8 >= -15%,H8*(-0.03), IF(K8 >= -20%,H8*(-0.04), IF(K8 >= -25%,H8*(-0.05), IF(K8 >= -30%,H8*(-0.06), IF(K8 >= -35%,H8*(-0.07), IF(K8 >= -40%,H8*(-0.08), IF(K8 >= -45%,H8*(-0.09), IF(K8 >= -50%, H8*(-0.1), H8* 0) )))))))))),"") | N8: =IF(NOT(ISNUMBER(H8)),"",IF(M8="Kein Balkon",H8*(-0.05),H8*0)) | P8: =IF(NOT(ISNUMBER(H8)),"",IF(ISBLANK(O8),0,H8*MIN((YEAR(TODAY())-O8)*0.003,0.09)*-1)) | R8: =IF(ISNUMBER(MIETER!F10),IF(Q8="renoviert",H8*0.05,IF(Q8="teilweise renoviert",H8*0,IF(Q8="unrenoviert",H8*-0.05,0))),"") | S8: =IF(ISNUMBER(MIETER!F10),C8,"") | T8: =IF(ISNUMBER(MIETER!F10),IF(OR(S8="EG",S8="1.OG",S8="2.OG",S8="OG",S8="über 2.OG mit Aufzug"),H8*0,IF(OR(S8="UG",S8="über 2.OG ohne Aufzug"),H8*(-0.05),0)),"") | U8: =IF(ISNUMBER(MIETER!F10),IFERROR(F8*(H8+J8+L8+N8+P8+R8+T8),""),"") | V8: =IF(NOT(ISNUMBER(MIETER!F10)),"",N('Verkauf Cashflow'!Q5)+N('Verkauf Cashflow'!R5)) | W8: =IF(ISNUMBER(MIETER!F10),U8+V8,"") | X8: =IF(ISNUMBER('Verkauf Cashflow'!O5),'Verkauf Cashflow'!O5,"") | Y8: =IF(ISNUMBER('Verkauf Cashflow'!S5),'Verkauf Cashflow'!S5,"") | Z8: =IF(ISNUMBER(MIETER!F10),IFERROR(Y8/F8,""),"") | AA8: =IF(ISNUMBER('Verkauf Cashflow'!CF5),'Verkauf Cashflow'!CF5,"")
A9: =IF(ISNUMBER(MIETER!F11),IFERROR(MIETER!A11,""),"") | B9: =IF(ISNUMBER(MIETER!F11),IFERROR(MIETER!B11,""),"") | C9: =IF(ISNUMBER(MIETER!F11),IFERROR(MIETER!C11,""),"") | D9: =IF(ISNUMBER(MIETER!F11),IFERROR(MIETER!D11,""),"") | E9: =IF(ISNUMBER(MIETER!F11),IFERROR(MIETER!E11,""),"") | F9: =IF(ISNUMBER(MIETER!F11),IFERROR(MIETER!F11,""),"") | G9: =IF(ISNUMBER(MIETER!F11),KALKU!$I$18,"") | H9: =IF(ISNUMBER(MIETER!F11),KALKU!$N$18,"") | J9: =IF(ISNUMBER(MIETER!F11),IF(I9="vermietet",H9*(-0.1),H9*0),"") | K9: =IF(ISNUMBER(MIETER!F11),IFERROR(MIETER!Q11/MIETER!$M$6,""),"") | L9: =IF(ISNUMBER(MIETER!F11),IF(K9 >= 0%,H9*(0.01), IF(K9 >= -5%,H9*(-0.01), IF(K9 >= -10%,H9*(-0.02), IF(K9 >= -15%,H9*(-0.03), IF(K9 >= -20%,H9*(-0.04), IF(K9 >= -25%,H9*(-0.05), IF(K9 >= -30%,H9*(-0.06), IF(K9 >= -35%,H9*(-0.07), IF(K9 >= -40%,H9*(-0.08), IF(K9 >= -45%,H9*(-0.09), IF(K9 >= -50%, H9*(-0.1), H9* 0) )))))))))),"") | N9: =IF(NOT(ISNUMBER(H9)),"",IF(M9="Kein Balkon",H9*(-0.05),H9*0)) | P9: =IF(NOT(ISNUMBER(H9)),"",IF(ISBLANK(O9),0,H9*MIN((YEAR(TODAY())-O9)*0.003,0.09)*-1)) | R9: =IF(ISNUMBER(MIETER!F11),IF(Q9="renoviert",H9*0.05,IF(Q9="teilweise renoviert",H9*0,IF(Q9="unrenoviert",H9*-0.05,0))),"") | S9: =IF(ISNUMBER(MIETER!F11),C9,"") | T9: =IF(ISNUMBER(MIETER!F11),IF(OR(S9="EG",S9="1.OG",S9="2.OG",S9="OG",S9="über 2.OG mit Aufzug"),H9*0,IF(OR(S9="UG",S9="über 2.OG ohne Aufzug"),H9*(-0.05),0)),"") | U9: =IF(ISNUMBER(MIETER!F11),IFERROR(F9*(H9+J9+L9+N9+P9+R9+T9),""),"") | V9: =IF(NOT(ISNUMBER(MIETER!F11)),"",N('Verkauf Cashflow'!Q6)+N('Verkauf Cashflow'!R6)) | W9: =IF(ISNUMBER(MIETER!F11),U9+V9,"") | X9: =IF(ISNUMBER('Verkauf Cashflow'!O6),'Verkauf Cashflow'!O6,"") | Y9: =IF(ISNUMBER('Verkauf Cashflow'!S6),'Verkauf Cashflow'!S6,"") | Z9: =IF(ISNUMBER(MIETER!F11),IFERROR(Y9/F9,""),"") | AA9: =IF(ISNUMBER('Verkauf Cashflow'!CF6),'Verkauf Cashflow'!CF6,"")
A10: =IF(ISNUMBER(MIETER!F12),IFERROR(MIETER!A12,""),"") | B10: =IF(ISNUMBER(MIETER!F12),IFERROR(MIETER!B12,""),"") | C10: =IF(ISNUMBER(MIETER!F12),IFERROR(MIETER!C12,""),"") | D10: =IF(ISNUMBER(MIETER!F12),IFERROR(MIETER!D12,""),"") | E10: =IF(ISNUMBER(MIETER!F12),IFERROR(MIETER!E12,""),"") | F10: =IF(ISNUMBER(MIETER!F12),IFERROR(MIETER!F12,""),"") | G10: =IF(ISNUMBER(MIETER!F12),KALKU!$I$18,"") | H10: =IF(ISNUMBER(MIETER!F12),KALKU!$N$18,"") | J10: =IF(ISNUMBER(MIETER!F12),IF(I10="vermietet",H10*(-0.1),H10*0),"") | K10: =IF(ISNUMBER(MIETER!F12),IFERROR(MIETER!Q12/MIETER!$M$6,""),"") | L10: =IF(ISNUMBER(MIETER!F12),IF(K10 >= 0%,H10*(0.01), IF(K10 >= -5%,H10*(-0.01), IF(K10 >= -10%,H10*(-0.02), IF(K10 >= -15%,H10*(-0.03), IF(K10 >= -20%,H10*(-0.04), IF(K10 >= -25%,H10*(-0.05), IF(K10 >= -30%,H10*(-0.06), IF(K10 >= -35%,H10*(-0.07), IF(K10 >= -40%,H10*(-0.08), IF(K10 >= -45%,H10*(-0.09), IF(K10 >= -50%, H10*(-0.1), H10* 0) )))))))))),"") | N10: =IF(NOT(ISNUMBER(H10)),"",IF(M10="Kein Balkon",H10*(-0.05),H10*0)) | P10: =IF(NOT(ISNUMBER(H10)),"",IF(ISBLANK(O10),0,H10*MIN((YEAR(TODAY())-O10)*0.003,0.09)*-1)) | R10: =IF(ISNUMBER(MIETER!F12),IF(Q10="renoviert",H10*0.05,IF(Q10="teilweise renoviert",H10*0,IF(Q10="unrenoviert",H10*-0.05,0))),"") | S10: =IF(ISNUMBER(MIETER!F12),C10,"") | T10: =IF(ISNUMBER(MIETER!F12),IF(OR(S10="EG",S10="1.OG",S10="2.OG",S10="OG",S10="über 2.OG mit Aufzug"),H10*0,IF(OR(S10="UG",S10="über 2.OG ohne Aufzug"),H10*(-0.05),0)),"") | U10: =IF(ISNUMBER(MIETER!F12),IFERROR(F10*(H10+J10+L10+N10+P10+R10+T10),""),"") | V10: =IF(NOT(ISNUMBER(MIETER!F12)),"",N('Verkauf Cashflow'!Q7)+N('Verkauf Cashflow'!R7)) | W10: =IF(ISNUMBER(MIETER!F12),U10+V10,"") | X10: =IF(ISNUMBER('Verkauf Cashflow'!O7),'Verkauf Cashflow'!O7,"") | Y10: =IF(ISNUMBER('Verkauf Cashflow'!S7),'Verkauf Cashflow'!S7,"") | Z10: =IF(ISNUMBER(MIETER!F12),IFERROR(Y10/F10,""),"") | AA10: =IF(ISNUMBER('Verkauf Cashflow'!CF7),'Verkauf Cashflow'!CF7,"")
A11: =IF(ISNUMBER(MIETER!F13),IFERROR(MIETER!A13,""),"") | B11: =IF(ISNUMBER(MIETER!F13),IFERROR(MIETER!B13,""),"") | C11: =IF(ISNUMBER(MIETER!F13),IFERROR(MIETER!C13,""),"") | D11: =IF(ISNUMBER(MIETER!F13),IFERROR(MIETER!D13,""),"") | E11: =IF(ISNUMBER(MIETER!F13),IFERROR(MIETER!E13,""),"") | F11: =IF(ISNUMBER(MIETER!F13),IFERROR(MIETER!F13,""),"") | G11: =IF(ISNUMBER(MIETER!F13),KALKU!$I$18,"") | H11: =IF(ISNUMBER(MIETER!F13),KALKU!$N$18,"") | J11: =IF(ISNUMBER(MIETER!F13),IF(I11="vermietet",H11*(-0.1),H11*0),"") | K11: =IF(ISNUMBER(MIETER!F13),IFERROR(MIETER!Q13/MIETER!$M$6,""),"") | L11: =IF(ISNUMBER(MIETER!F13),IF(K11 >= 0%,H11*(0.01), IF(K11 >= -5%,H11*(-0.01), IF(K11 >= -10%,H11*(-0.02), IF(K11 >= -15%,H11*(-0.03), IF(K11 >= -20%,H11*(-0.04), IF(K11 >= -25%,H11*(-0.05), IF(K11 >= -30%,H11*(-0.06), IF(K11 >= -35%,H11*(-0.07), IF(K11 >= -40%,H11*(-0.08), IF(K11 >= -45%,H11*(-0.09), IF(K11 >= -50%, H11*(-0.1), H11* 0) )))))))))),"") | N11: =IF(NOT(ISNUMBER(H11)),"",IF(M11="Kein Balkon",H11*(-0.05),H11*0)) | P11: =IF(NOT(ISNUMBER(H11)),"",IF(ISBLANK(O11),0,H11*MIN((YEAR(TODAY())-O11)*0.003,0.09)*-1)) | R11: =IF(ISNUMBER(MIETER!F13),IF(Q11="renoviert",H11*0.05,IF(Q11="teilweise renoviert",H11*0,IF(Q11="unrenoviert",H11*-0.05,0))),"") | S11: =IF(ISNUMBER(MIETER!F13),C11,"") | T11: =IF(ISNUMBER(MIETER!F13),IF(OR(S11="EG",S11="1.OG",S11="2.OG",S11="OG",S11="über 2.OG mit Aufzug"),H11*0,IF(OR(S11="UG",S11="über 2.OG ohne Aufzug"),H11*(-0.05),0)),"") | U11: =IF(ISNUMBER(MIETER!F13),IFERROR(F11*(H11+J11+L11+N11+P11+R11+T11),""),"") | V11: =IF(NOT(ISNUMBER(MIETER!F13)),"",N('Verkauf Cashflow'!Q8)+N('Verkauf Cashflow'!R8)) | W11: =IF(ISNUMBER(MIETER!F13),U11+V11,"") | X11: =IF(ISNUMBER('Verkauf Cashflow'!O8),'Verkauf Cashflow'!O8,"") | Y11: =IF(ISNUMBER('Verkauf Cashflow'!S8),'Verkauf Cashflow'!S8,"") | Z11: =IF(ISNUMBER(MIETER!F13),IFERROR(Y11/F11,""),"") | AA11: =IF(ISNUMBER('Verkauf Cashflow'!CF8),'Verkauf Cashflow'!CF8,"")
A12: =IF(ISNUMBER(MIETER!F14),IFERROR(MIETER!A14,""),"") | B12: =IF(ISNUMBER(MIETER!F14),IFERROR(MIETER!B14,""),"") | C12: =IF(ISNUMBER(MIETER!F14),IFERROR(MIETER!C14,""),"") | D12: =IF(ISNUMBER(MIETER!F14),IFERROR(MIETER!D14,""),"") | E12: =IF(ISNUMBER(MIETER!F14),IFERROR(MIETER!E14,""),"") | F12: =IF(ISNUMBER(MIETER!F14),IFERROR(MIETER!F14,""),"") | G12: =IF(ISNUMBER(MIETER!F14),KALKU!$I$18,"") | H12: =IF(ISNUMBER(MIETER!F14),KALKU!$N$18,"") | J12: =IF(ISNUMBER(MIETER!F14),IF(I12="vermietet",H12*(-0.1),H12*0),"") | K12: =IF(ISNUMBER(MIETER!F14),IFERROR(MIETER!Q14/MIETER!$M$6,""),"") | L12: =IF(ISNUMBER(MIETER!F14),IF(K12 >= 0%,H12*(0.01), IF(K12 >= -5%,H12*(-0.01), IF(K12 >= -10%,H12*(-0.02), IF(K12 >= -15%,H12*(-0.03), IF(K12 >= -20%,H12*(-0.04), IF(K12 >= -25%,H12*(-0.05), IF(K12 >= -30%,H12*(-0.06), IF(K12 >= -35%,H12*(-0.07), IF(K12 >= -40%,H12*(-0.08), IF(K12 >= -45%,H12*(-0.09), IF(K12 >= -50%, H12*(-0.1), H12* 0) )))))))))),"") | N12: =IF(NOT(ISNUMBER(H12)),"",IF(M12="Kein Balkon",H12*(-0.05),H12*0)) | P12: =IF(NOT(ISNUMBER(H12)),"",IF(ISBLANK(O12),0,H12*MIN((YEAR(TODAY())-O12)*0.003,0.09)*-1)) | R12: =IF(ISNUMBER(MIETER!F14),IF(Q12="renoviert",H12*0.05,IF(Q12="teilweise renoviert",H12*0,IF(Q12="unrenoviert",H12*-0.05,0))),"") | S12: =IF(ISNUMBER(MIETER!F14),C12,"") | T12: =IF(ISNUMBER(MIETER!F14),IF(OR(S12="EG",S12="1.OG",S12="2.OG",S12="OG",S12="über 2.OG mit Aufzug"),H12*0,IF(OR(S12="UG",S12="über 2.OG ohne Aufzug"),H12*(-0.05),0)),"") | U12: =IF(ISNUMBER(MIETER!F14),IFERROR(F12*(H12+J12+L12+N12+P12+R12+T12),""),"") | V12: =IF(NOT(ISNUMBER(MIETER!F14)),"",N('Verkauf Cashflow'!Q9)+N('Verkauf Cashflow'!R9)) | W12: =IF(ISNUMBER(MIETER!F14),U12+V12,"") | X12: =IF(ISNUMBER('Verkauf Cashflow'!O9),'Verkauf Cashflow'!O9,"") | Y12: =IF(ISNUMBER('Verkauf Cashflow'!S9),'Verkauf Cashflow'!S9,"") | Z12: =IF(ISNUMBER(MIETER!F14),IFERROR(Y12/F12,""),"") | AA12: =IF(ISNUMBER('Verkauf Cashflow'!CF9),'Verkauf Cashflow'!CF9,"")
A13: =IF(ISNUMBER(MIETER!F15),IFERROR(MIETER!A15,""),"") | B13: =IF(ISNUMBER(MIETER!F15),IFERROR(MIETER!B15,""),"") | C13: =IF(ISNUMBER(MIETER!F15),IFERROR(MIETER!C15,""),"") | D13: =IF(ISNUMBER(MIETER!F15),IFERROR(MIETER!D15,""),"") | E13: =IF(ISNUMBER(MIETER!F15),IFERROR(MIETER!E15,""),"") | F13: =IF(ISNUMBER(MIETER!F15),IFERROR(MIETER!F15,""),"") | G13: =IF(ISNUMBER(MIETER!F15),KALKU!$I$18,"") | H13: =IF(ISNUMBER(MIETER!F15),KALKU!$N$18,"") | J13: =IF(ISNUMBER(MIETER!F15),IF(I13="vermietet",H13*(-0.1),H13*0),"") | K13: =IF(ISNUMBER(MIETER!F15),IFERROR(MIETER!Q15/MIETER!$M$6,""),"") | L13: =IF(ISNUMBER(MIETER!F15),IF(K13 >= 0%,H13*(0.01), IF(K13 >= -5%,H13*(-0.01), IF(K13 >= -10%,H13*(-0.02), IF(K13 >= -15%,H13*(-0.03), IF(K13 >= -20%,H13*(-0.04), IF(K13 >= -25%,H13*(-0.05), IF(K13 >= -30%,H13*(-0.06), IF(K13 >= -35%,H13*(-0.07), IF(K13 >= -40%,H13*(-0.08), IF(K13 >= -45%,H13*(-0.09), IF(K13 >= -50%, H13*(-0.1), H13* 0) )))))))))),"") | N13: =IF(NOT(ISNUMBER(H13)),"",IF(M13="Kein Balkon",H13*(-0.05),H13*0)) | P13: =IF(NOT(ISNUMBER(H13)),"",IF(ISBLANK(O13),0,H13*MIN((YEAR(TODAY())-O13)*0.003,0.09)*-1)) | R13: =IF(ISNUMBER(MIETER!F15),IF(Q13="renoviert",H13*0.05,IF(Q13="teilweise renoviert",H13*0,IF(Q13="unrenoviert",H13*-0.05,0))),"") | S13: =IF(ISNUMBER(MIETER!F15),C13,"") | T13: =IF(ISNUMBER(MIETER!F15),IF(OR(S13="EG",S13="1.OG",S13="2.OG",S13="OG",S13="über 2.OG mit Aufzug"),H13*0,IF(OR(S13="UG",S13="über 2.OG ohne Aufzug"),H13*(-0.05),0)),"") | U13: =IF(ISNUMBER(MIETER!F15),IFERROR(F13*(H13+J13+L13+N13+P13+R13+T13),""),"") | V13: =IF(NOT(ISNUMBER(MIETER!F15)),"",N('Verkauf Cashflow'!Q10)+N('Verkauf Cashflow'!R10)) | W13: =IF(ISNUMBER(MIETER!F15),U13+V13,"") | X13: =IF(ISNUMBER('Verkauf Cashflow'!O10),'Verkauf Cashflow'!O10,"") | Y13: =IF(ISNUMBER('Verkauf Cashflow'!S10),'Verkauf Cashflow'!S10,"") | Z13: =IF(ISNUMBER(MIETER!F15),IFERROR(Y13/F13,""),"") | AA13: =IF(ISNUMBER('Verkauf Cashflow'!CF10),'Verkauf Cashflow'!CF10,"")
A14: =IF(ISNUMBER(MIETER!F16),IFERROR(MIETER!A16,""),"") | B14: =IF(ISNUMBER(MIETER!F16),IFERROR(MIETER!B16,""),"") | C14: =IF(ISNUMBER(MIETER!F16),IFERROR(MIETER!C16,""),"") | D14: =IF(ISNUMBER(MIETER!F16),IFERROR(MIETER!D16,""),"") | E14: =IF(ISNUMBER(MIETER!F16),IFERROR(MIETER!E16,""),"") | F14: =IF(ISNUMBER(MIETER!F16),IFERROR(MIETER!F16,""),"") | G14: =IF(ISNUMBER(MIETER!F16),KALKU!$I$18,"") | H14: =IF(ISNUMBER(MIETER!F16),KALKU!$N$18,"") | J14: =IF(ISNUMBER(MIETER!F16),IF(I14="vermietet",H14*(-0.1),H14*0),"") | K14: =IF(ISNUMBER(MIETER!F16),IFERROR(MIETER!Q16/MIETER!$M$6,""),"") | L14: =IF(ISNUMBER(MIETER!F16),IF(K14 >= 0%,H14*(0.01), IF(K14 >= -5%,H14*(-0.01), IF(K14 >= -10%,H14*(-0.02), IF(K14 >= -15%,H14*(-0.03), IF(K14 >= -20%,H14*(-0.04), IF(K14 >= -25%,H14*(-0.05), IF(K14 >= -30%,H14*(-0.06), IF(K14 >= -35%,H14*(-0.07), IF(K14 >= -40%,H14*(-0.08), IF(K14 >= -45%,H14*(-0.09), IF(K14 >= -50%, H14*(-0.1), H14* 0) )))))))))),"") | N14: =IF(NOT(ISNUMBER(H14)),"",IF(M14="Kein Balkon",H14*(-0.05),H14*0)) | P14: =IF(NOT(ISNUMBER(H14)),"",IF(ISBLANK(O14),0,H14*MIN((YEAR(TODAY())-O14)*0.003,0.09)*-1)) | R14: =IF(ISNUMBER(MIETER!F16),IF(Q14="renoviert",H14*0.05,IF(Q14="teilweise renoviert",H14*0,IF(Q14="unrenoviert",H14*-0.05,0))),"") | S14: =IF(ISNUMBER(MIETER!F16),C14,"") | T14: =IF(ISNUMBER(MIETER!F16),IF(OR(S14="EG",S14="1.OG",S14="2.OG",S14="OG",S14="über 2.OG mit Aufzug"),H14*0,IF(OR(S14="UG",S14="über 2.OG ohne Aufzug"),H14*(-0.05),0)),"") | U14: =IF(ISNUMBER(MIETER!F16),IFERROR(F14*(H14+J14+L14+N14+P14+R14+T14),""),"") | V14: =IF(NOT(ISNUMBER(MIETER!F16)),"",N('Verkauf Cashflow'!Q11)+N('Verkauf Cashflow'!R11)) | W14: =IF(ISNUMBER(MIETER!F16),U14+V14,"") | X14: =IF(ISNUMBER('Verkauf Cashflow'!O11),'Verkauf Cashflow'!O11,"") | Y14: =IF(ISNUMBER('Verkauf Cashflow'!S11),'Verkauf Cashflow'!S11,"") | Z14: =IF(ISNUMBER(MIETER!F16),IFERROR(Y14/F14,""),"") | AA14: =IF(ISNUMBER('Verkauf Cashflow'!CF11),'Verkauf Cashflow'!CF11,"")
A15: =IF(ISNUMBER(MIETER!F17),IFERROR(MIETER!A17,""),"") | B15: =IF(ISNUMBER(MIETER!F17),IFERROR(MIETER!B17,""),"") | C15: =IF(ISNUMBER(MIETER!F17),IFERROR(MIETER!C17,""),"") | D15: =IF(ISNUMBER(MIETER!F17),IFERROR(MIETER!D17,""),"") | E15: =IF(ISNUMBER(MIETER!F17),IFERROR(MIETER!E17,""),"") | F15: =IF(ISNUMBER(MIETER!F17),IFERROR(MIETER!F17,""),"") | G15: =IF(ISNUMBER(MIETER!F17),KALKU!$I$18,"") | H15: =IF(ISNUMBER(MIETER!F17),KALKU!$N$18,"") | J15: =IF(ISNUMBER(MIETER!F17),IF(I15="vermietet",H15*(-0.1),H15*0),"") | K15: =IF(ISNUMBER(MIETER!F17),IFERROR(MIETER!Q17/MIETER!$M$6,""),"") | L15: =IF(ISNUMBER(MIETER!F17),IF(K15 >= 0%,H15*(0.01), IF(K15 >= -5%,H15*(-0.01), IF(K15 >= -10%,H15*(-0.02), IF(K15 >= -15%,H15*(-0.03), IF(K15 >= -20%,H15*(-0.04), IF(K15 >= -25%,H15*(-0.05), IF(K15 >= -30%,H15*(-0.06), IF(K15 >= -35%,H15*(-0.07), IF(K15 >= -40%,H15*(-0.08), IF(K15 >= -45%,H15*(-0.09), IF(K15 >= -50%, H15*(-0.1), H15* 0) )))))))))),"") | N15: =IF(NOT(ISNUMBER(H15)),"",IF(M15="Kein Balkon",H15*(-0.05),H15*0)) | P15: =IF(NOT(ISNUMBER(H15)),"",IF(ISBLANK(O15),0,H15*MIN((YEAR(TODAY())-O15)*0.003,0.09)*-1)) | R15: =IF(ISNUMBER(MIETER!F17),IF(Q15="renoviert",H15*0.05,IF(Q15="teilweise renoviert",H15*0,IF(Q15="unrenoviert",H15*-0.05,0))),"") | S15: =IF(ISNUMBER(MIETER!F17),C15,"") | T15: =IF(ISNUMBER(MIETER!F17),IF(OR(S15="EG",S15="1.OG",S15="2.OG",S15="OG",S15="über 2.OG mit Aufzug"),H15*0,IF(OR(S15="UG",S15="über 2.OG ohne Aufzug"),H15*(-0.05),0)),"") | U15: =IF(ISNUMBER(MIETER!F17),IFERROR(F15*(H15+J15+L15+N15+P15+R15+T15),""),"") | V15: =IF(NOT(ISNUMBER(MIETER!F17)),"",N('Verkauf Cashflow'!Q12)+N('Verkauf Cashflow'!R12)) | W15: =IF(ISNUMBER(MIETER!F17),U15+V15,"") | X15: =IF(ISNUMBER('Verkauf Cashflow'!O12),'Verkauf Cashflow'!O12,"") | Y15: =IF(ISNUMBER('Verkauf Cashflow'!S12),'Verkauf Cashflow'!S12,"") | Z15: =IF(ISNUMBER(MIETER!F17),IFERROR(Y15/F15,""),"") | AA15: =IF(ISNUMBER('Verkauf Cashflow'!CF12),'Verkauf Cashflow'!CF12,"")
A16: =IF(ISNUMBER(MIETER!F18),IFERROR(MIETER!A18,""),"") | B16: =IF(ISNUMBER(MIETER!F18),IFERROR(MIETER!B18,""),"") | C16: =IF(ISNUMBER(MIETER!F18),IFERROR(MIETER!C18,""),"") | D16: =IF(ISNUMBER(MIETER!F18),IFERROR(MIETER!D18,""),"") | E16: =IF(ISNUMBER(MIETER!F18),IFERROR(MIETER!E18,""),"") | F16: =IF(ISNUMBER(MIETER!F18),IFERROR(MIETER!F18,""),"") | G16: =IF(ISNUMBER(MIETER!F18),KALKU!$I$18,"") | H16: =IF(ISNUMBER(MIETER!F18),KALKU!$N$18,"") | J16: =IF(ISNUMBER(MIETER!F18),IF(I16="vermietet",H16*(-0.1),H16*0),"") | K16: =IF(ISNUMBER(MIETER!F18),IFERROR(MIETER!Q18/MIETER!$M$6,""),"") | L16: =IF(ISNUMBER(MIETER!F18),IF(K16 >= 0%,H16*(0.01), IF(K16 >= -5%,H16*(-0.01), IF(K16 >= -10%,H16*(-0.02), IF(K16 >= -15%,H16*(-0.03), IF(K16 >= -20%,H16*(-0.04), IF(K16 >= -25%,H16*(-0.05), IF(K16 >= -30%,H16*(-0.06), IF(K16 >= -35%,H16*(-0.07), IF(K16 >= -40%,H16*(-0.08), IF(K16 >= -45%,H16*(-0.09), IF(K16 >= -50%, H16*(-0.1), H16* 0) )))))))))),"") | N16: =IF(NOT(ISNUMBER(H16)),"",IF(M16="Kein Balkon",H16*(-0.05),H16*0)) | P16: =IF(NOT(ISNUMBER(H16)),"",IF(ISBLANK(O16),0,H16*MIN((YEAR(TODAY())-O16)*0.003,0.09)*-1)) | R16: =IF(ISNUMBER(MIETER!F18),IF(Q16="renoviert",H16*0.05,IF(Q16="teilweise renoviert",H16*0,IF(Q16="unrenoviert",H16*-0.05,0))),"") | S16: =IF(ISNUMBER(MIETER!F18),C16,"") | T16: =IF(ISNUMBER(MIETER!F18),IF(OR(S16="EG",S16="1.OG",S16="2.OG",S16="OG",S16="über 2.OG mit Aufzug"),H16*0,IF(OR(S16="UG",S16="über 2.OG ohne Aufzug"),H16*(-0.05),0)),"") | U16: =IF(ISNUMBER(MIETER!F18),IFERROR(F16*(H16+J16+L16+N16+P16+R16+T16),""),"") | V16: =IF(NOT(ISNUMBER(MIETER!F18)),"",N('Verkauf Cashflow'!Q13)+N('Verkauf Cashflow'!R13)) | W16: =IF(ISNUMBER(MIETER!F18),U16+V16,"") | X16: =IF(ISNUMBER('Verkauf Cashflow'!O13),'Verkauf Cashflow'!O13,"") | Y16: =IF(ISNUMBER('Verkauf Cashflow'!S13),'Verkauf Cashflow'!S13,"") | Z16: =IF(ISNUMBER(MIETER!F18),IFERROR(Y16/F16,""),"") | AA16: =IF(ISNUMBER('Verkauf Cashflow'!CF13),'Verkauf Cashflow'!CF13,"")
A17: =IF(ISNUMBER(MIETER!F19),IFERROR(MIETER!A19,""),"") | B17: =IF(ISNUMBER(MIETER!F19),IFERROR(MIETER!B19,""),"") | C17: =IF(ISNUMBER(MIETER!F19),IFERROR(MIETER!C19,""),"") | D17: =IF(ISNUMBER(MIETER!F19),IFERROR(MIETER!D19,""),"") | E17: =IF(ISNUMBER(MIETER!F19),IFERROR(MIETER!E19,""),"") | F17: =IF(ISNUMBER(MIETER!F19),IFERROR(MIETER!F19,""),"") | G17: =IF(ISNUMBER(MIETER!F19),KALKU!$I$18,"") | H17: =IF(ISNUMBER(MIETER!F19),KALKU!$N$18,"") | J17: =IF(ISNUMBER(MIETER!F19),IF(I17="vermietet",H17*(-0.1),H17*0),"") | K17: =IF(ISNUMBER(MIETER!F19),IFERROR(MIETER!Q19/MIETER!$M$6,""),"") | L17: =IF(ISNUMBER(MIETER!F19),IF(K17 >= 0%,H17*(0.01), IF(K17 >= -5%,H17*(-0.01), IF(K17 >= -10%,H17*(-0.02), IF(K17 >= -15%,H17*(-0.03), IF(K17 >= -20%,H17*(-0.04), IF(K17 >= -25%,H17*(-0.05), IF(K17 >= -30%,H17*(-0.06), IF(K17 >= -35%,H17*(-0.07), IF(K17 >= -40%,H17*(-0.08), IF(K17 >= -45%,H17*(-0.09), IF(K17 >= -50%, H17*(-0.1), H17* 0) )))))))))),"") | N17: =IF(NOT(ISNUMBER(H17)),"",IF(M17="Kein Balkon",H17*(-0.05),H17*0)) | P17: =IF(NOT(ISNUMBER(H17)),"",IF(ISBLANK(O17),0,H17*MIN((YEAR(TODAY())-O17)*0.003,0.09)*-1)) | R17: =IF(ISNUMBER(MIETER!F19),IF(Q17="renoviert",H17*0.05,IF(Q17="teilweise renoviert",H17*0,IF(Q17="unrenoviert",H17*-0.05,0))),"") | S17: =IF(ISNUMBER(MIETER!F19),C17,"") | T17: =IF(ISNUMBER(MIETER!F19),IF(OR(S17="EG",S17="1.OG",S17="2.OG",S17="OG",S17="über 2.OG mit Aufzug"),H17*0,IF(OR(S17="UG",S17="über 2.OG ohne Aufzug"),H17*(-0.05),0)),"") | U17: =IF(ISNUMBER(MIETER!F19),IFERROR(F17*(H17+J17+L17+N17+P17+R17+T17),""),"") | V17: =IF(NOT(ISNUMBER(MIETER!F19)),"",N('Verkauf Cashflow'!Q14)+N('Verkauf Cashflow'!R14)) | W17: =IF(ISNUMBER(MIETER!F19),U17+V17,"") | X17: =IF(ISNUMBER('Verkauf Cashflow'!O14),'Verkauf Cashflow'!O14,"") | Y17: =IF(ISNUMBER('Verkauf Cashflow'!S14),'Verkauf Cashflow'!S14,"") | Z17: =IF(ISNUMBER(MIETER!F19),IFERROR(Y17/F17,""),"") | AA17: =IF(ISNUMBER('Verkauf Cashflow'!CF14),'Verkauf Cashflow'!CF14,"")
A18: =IF(ISNUMBER(MIETER!F20),IFERROR(MIETER!A20,""),"") | B18: =IF(ISNUMBER(MIETER!F20),IFERROR(MIETER!B20,""),"") | C18: =IF(ISNUMBER(MIETER!F20),IFERROR(MIETER!C20,""),"") | D18: =IF(ISNUMBER(MIETER!F20),IFERROR(MIETER!D20,""),"") | E18: =IF(ISNUMBER(MIETER!F20),IFERROR(MIETER!E20,""),"") | F18: =IF(ISNUMBER(MIETER!F20),IFERROR(MIETER!F20,""),"") | G18: =IF(ISNUMBER(MIETER!F20),KALKU!$I$18,"") | H18: =IF(ISNUMBER(MIETER!F20),KALKU!$N$18,"") | J18: =IF(ISNUMBER(MIETER!F20),IF(I18="vermietet",H18*(-0.1),H18*0),"") | K18: =IF(ISNUMBER(MIETER!F20),IFERROR(MIETER!Q20/MIETER!$M$6,""),"") | L18: =IF(ISNUMBER(MIETER!F20),IF(K18 >= 0%,H18*(0.01), IF(K18 >= -5%,H18*(-0.01), IF(K18 >= -10%,H18*(-0.02), IF(K18 >= -15%,H18*(-0.03), IF(K18 >= -20%,H18*(-0.04), IF(K18 >= -25%,H18*(-0.05), IF(K18 >= -30%,H18*(-0.06), IF(K18 >= -35%,H18*(-0.07), IF(K18 >= -40%,H18*(-0.08), IF(K18 >= -45%,H18*(-0.09), IF(K18 >= -50%, H18*(-0.1), H18* 0) )))))))))),"") | N18: =IF(NOT(ISNUMBER(H18)),"",IF(M18="Kein Balkon",H18*(-0.05),H18*0)) | P18: =IF(NOT(ISNUMBER(H18)),"",IF(ISBLANK(O18),0,H18*MIN((YEAR(TODAY())-O18)*0.003,0.09)*-1)) | R18: =IF(ISNUMBER(MIETER!F20),IF(Q18="renoviert",H18*0.05,IF(Q18="teilweise renoviert",H18*0,IF(Q18="unrenoviert",H18*-0.05,0))),"") | S18: =IF(ISNUMBER(MIETER!F20),C18,"") | T18: =IF(ISNUMBER(MIETER!F20),IF(OR(S18="EG",S18="1.OG",S18="2.OG",S18="OG",S18="über 2.OG mit Aufzug"),H18*0,IF(OR(S18="UG",S18="über 2.OG ohne Aufzug"),H18*(-0.05),0)),"") | U18: =IF(ISNUMBER(MIETER!F20),IFERROR(F18*(H18+J18+L18+N18+P18+R18+T18),""),"") | V18: =IF(NOT(ISNUMBER(MIETER!F20)),"",N('Verkauf Cashflow'!Q15)+N('Verkauf Cashflow'!R15)) | W18: =IF(ISNUMBER(MIETER!F20),U18+V18,"") | X18: =IF(ISNUMBER('Verkauf Cashflow'!O15),'Verkauf Cashflow'!O15,"") | Y18: =IF(ISNUMBER('Verkauf Cashflow'!S15),'Verkauf Cashflow'!S15,"") | Z18: =IF(ISNUMBER(MIETER!F20),IFERROR(Y18/F18,""),"") | AA18: =IF(ISNUMBER('Verkauf Cashflow'!CF15),'Verkauf Cashflow'!CF15,"")
... A25: =IF(ISNUMBER(MIETER!F27),IFERROR(MIETER!A27,""),"") | B25: =IF(ISNUMBER(MIETER!F27),IFERROR(MIETER!B27,""),"") | C25: =IF(ISNUMBER(MIETER!F27),IFERROR(MIETER!C27,""),"") | D25: =IF(ISNUMBER(MIETER!F27),IFERROR(MIETER!D27,""),"") | E25: =IF(ISNUMBER(MIETER!F27),IFERROR(MIETER!E27,""),"") | F25: =IF(ISNUMBER(MIETER!F27),IFERROR(MIETER!F27,""),"") | G25: =IF(ISNUMBER(MIETER!F27),KALKU!$I$18,"") | H25: =IF(ISNUMBER(MIETER!F27),KALKU!$N$18,"") | J25: =IF(ISNUMBER(MIETER!F27),IF(I25="vermietet",H25*(-0.1),H25*0),"") | K25: =IF(ISNUMBER(MIETER!F27),IFERROR(MIETER!Q27/MIETER!$M$6,""),"") | L25: =IF(ISNUMBER(MIETER!F27),IF(K25 >= 0%,H25*(0.01), IF(K25 >= -5%,H25*(-0.01), IF(K25 >= -10%,H25*(-0.02), IF(K25 >= -15%,H25*(-0.03), IF(K25 >= -20%,H25*(-0.04), IF(K25 >= -25%,H25*(-0.05), IF(K25 >= -30%,H25*(-0.06), IF(K25 >= -35%,H25*(-0.07), IF(K25 >= -40%,H25*(-0.08), IF(K25 >= -45%,H25*(-0.09), IF(K25 >= -50%, H25*(-0.1), H25* 0) )))))))))),"") | N25: =IF(NOT(ISNUMBER(H25)),"",IF(M25="Kein Balkon",H25*(-0.05),H25*0)) | P25: =IF(NOT(ISNUMBER(H25)),"",IF(ISBLANK(O25),0,H25*MIN((YEAR(TODAY())-O25)*0.003,0.09)*-1)) | R25: =IF(ISNUMBER(MIETER!F27),IF(Q25="renoviert",H25*0.05,IF(Q25="teilweise renoviert",H25*0,IF(Q25="unrenoviert",H25*-0.05,0))),"") | S25: =IF(ISNUMBER(MIETER!F27),C25,"") | T25: =IF(ISNUMBER(MIETER!F27),IF(OR(S25="EG",S25="1.OG",S25="2.OG",S25="OG",S25="über 2.OG mit Aufzug"),H25*0,IF(OR(S25="UG",S25="über 2.OG ohne Aufzug"),H25*(-0.05),0)),"") | U25: =IF(ISNUMBER(MIETER!F27),IFERROR(F25*(H25+J25+L25+N25+P25+R25+T25),""),"") | V25: =IF(NOT(ISNUMBER(MIETER!F27)),"",N('Verkauf Cashflow'!Q22)+N('Verkauf Cashflow'!R22)) | W25: =IF(ISNUMBER(MIETER!F27),U25+V25,"") | X25: =IF(ISNUMBER('Verkauf Cashflow'!O22),'Verkauf Cashflow'!O22,"") | Y25: =IF(ISNUMBER('Verkauf Cashflow'!S22),'Verkauf Cashflow'!S22,"") | Z25: =IF(ISNUMBER(MIETER!F27),IFERROR(Y25/F25,""),"") | AA25: =IF(ISNUMBER('Verkauf Cashflow'!CF22),'Verkauf Cashflow'!CF22,"")
C26: Rücklage
C27: Subventionskosten
C28: Summe | F28: =SUM(F6:F25) | G28: =AVERAGEIF(G6:G25, ">0") | H28: =AVERAGEIF(H6:H25, ">0") | U28: =SUM(U6:U25) | V28: =SUM(V6:V25) | W28: =SUM(W6:W25) | X28: =SUM(X6:X25) | Y28: =SUM(Y6:Y27) | Z28: =IFERROR(AVERAGEIF(Z6:Z25, ">0"),"") | AA28: =IFERROR(AVERAGE(AA6:AA25),"")

Sheet Verkauf Cashflow
A1: STAMM | L1: PREIS | AG1: MIETE | AW1: BEWIRTSCHAFTUNG | BE1: STEUER | BS1: ERGEBNIS
A2: WE | B2: Haus | C2: WHG | D2: Etage | E2: Lage | F2: Wohnfläche m2 | G2: Leer- stand | H2: Gar. Anz. | I2: Stpl. Anz. | J2: MEA Zähler | K2: MEA- Anteil | L2: REGLER Abgabe €/m² | M2: Markt €/m² | N2: Delta zu Markt | O2: Indiv. Auf-/ Abschlag € | P2: Abgabepreis Wohnung | Q2: Abgabepreis Garage | R2: Abgabepreis Stellplatz | S2: Abgabepreis gesamt | T2: Provision % (leer=Std.) | U2: Provision effektiv | V2: Provision EUR | W2: Kaufpreis gesamt | X2: Kaufpreis Wohnung | Y2: Abgabe ges. €/m² (CRM) | Z2: Kaufpreis Whg €/m² | AA2: Beurkundeter KP Wohnung | AB2: Kauf- nebenkosten | AC2: Kapital- bedarf | AD2: Darlehen (Annahme C12) | AE2: Eigen- kapital | AF2: Aufschlag Beurkundung | AG2: Kaltmiete manuell €/Mo | AH2: Kaltmiete IST €/Mo | AI2: Soll-/Zielmiete €/Mo | AJ2: Subvention Tag 1 €/Mo | AK2: Subvention Ø Modul 5 €/Mo | AL2: Miete Garage | AM2: Miete Stellplatz | AN2: Miete gesamt ohne Subv. | AO2: Einnahmen CF (inkl. Subv.) | AP2: Kaltmiete €/m² | AQ2: letzte Erhöhung | AR2: nächste Erhöhung ab | AS2: Reach-Time Mo (Modul 5) | AT2: Rest- monate | AU2: Subvention gesamt € | AV2: Soll-Vorschlag 2 Kappungen | AW2: Bewirt. % (Schaetzung) | AX2: Hausgeld n.u. (leer=Std.) | AY2: Hausgeld n.u. €/Mo | AZ2: davon Rücklage (leer=Std.) | BA2: davon Rücklage €/Mo | BB2: Bewirt.quote % v. NKM IST | BC2: 1 % Bewirt. €/Mo v. NKM | BD2: 1 %-Pkt Bewirt. = € Kaufpreis | BE2: Bodenwert WE € | BF2: Gebäudeanteil lt. Vertrag | BG2: Gebäudeanteil aus BRW (100 %) | BH2: Gebäudeanteil effektiv (Quote) | BI2: Anteil- Quelle | BJ2: AfA-Satz WE (leer=C9) | BK2: AfA-Satz effektiv | BL2: AfA-Basis Wohnung | BM2: AfA €/Mo | BN2: Zinsen €/Mo | BO2: Annuitaet €/Mo | BP2: Steuerbasis €/Mo | BQ2: Erstattung (+) Steuer (-) | BR2: Rücklage spaeter abziehbar €/Mo | BS2: CF vor Steuern €/Mo | BT2: CF nach Steuern €/Mo | BU2: CF n.St. ohne Subvention | BV2: Rechenhilfe: Ertrag n.St. o. Fin. | BW2: Rechenhilfe: Garage/Stpl. netto 100 % | BX2: Rechenhilfe: k bei 100 % | BY2: Rechenhilfe: k bei 109,3 % | BZ2: max. tragbar KP Wohnung 100 % | CA2: max. tragbar KP Wohnung 109,3 % | CB2: max. tragbar 109,3 % OHNE Subvention | CC2: max. tragbar Regler €/m² | CD2: Delta Regler zu max. tragbar | CE2: Faktor | CF2: Brutto- mietrendite | CG2: Ampel Fall 100 % KP | CH2: Ampel Fall 109,3 %
A3: =IF(NOT(ISNUMBER(MIETER!F8)),"",ROW()-2) | B3: =IF(NOT(ISNUMBER(MIETER!F8)),"",IF(MIETER!A8="","",MIETER!A8)) | C3: =IF(NOT(ISNUMBER(MIETER!F8)),"",IF(MIETER!B8="","",MIETER!B8)) | D3: =IF(NOT(ISNUMBER(MIETER!F8)),"",IF(MIETER!C8="","",MIETER!C8)) | E3: =IF(NOT(ISNUMBER(MIETER!F8)),"",IF(MIETER!D8="","",MIETER!D8)) | F3: =IF(NOT(ISNUMBER(MIETER!F8)),"",MIETER!F8) | K3: =IF(OR(NOT(ISNUMBER(F3)),NOT(ISNUMBER(J3)),NOT(ISNUMBER($H$29)),$H$29=0),"",J3/$H$29) | M3: =IF(OR(NOT(ISNUMBER(F3)),F3=0,NOT(ISNUMBER(VERKAUFSMATRIX!U6))),"",VERKAUFSMATRIX!U6/F3) | N3: =IF(OR(NOT(ISNUMBER(L3)),NOT(ISNUMBER(M3)),M3=0),"",L3/M3-1) | P3: =IF(OR(NOT(ISNUMBER(F3)),NOT(ISNUMBER(L3))),"",F3*L3+N(O3)) | S3: =IF(NOT(ISNUMBER(P3)),"",P3+N(Q3)+N(R3)) | U3: =IF(NOT(ISNUMBER(F3)),"",IF(ISNUMBER(T3),T3,IF(NOT(ISNUMBER($H$26)),"",$H$26))) | V3: =IF(OR(NOT(ISNUMBER(S3)),NOT(ISNUMBER(U3))),"",S3*U3) | W3: =IF(OR(NOT(ISNUMBER(S3)),NOT(ISNUMBER(U3))),"",S3*(1+U3)) | X3: =IF(NOT(ISNUMBER(W3)),"",W3-N(Q3)-N(R3)) | Y3: =IF(OR(NOT(ISNUMBER(S3)),NOT(ISNUMBER(F3)),F3=0),"",S3/F3) | Z3: =IF(OR(NOT(ISNUMBER(X3)),NOT(ISNUMBER(F3)),F3=0),"",X3/F3) | AA3: =IF(OR(NOT(ISNUMBER(X3)),NOT(ISNUMBER($H$34))),"",X3*MAX(1,$H$34)) | AB3: =IF(OR(NOT(ISNUMBER(W3)),NOT(ISNUMBER($H$34)),NOT(ISNUMBER($C$36))),"",W3*MAX(1,$H$34)*$C$36) | AC3: =IF(OR(NOT(ISNUMBER(W3)),NOT(ISNUMBER(AB3))),"",W3+AB3) | AD3: =IF(OR(NOT(ISNUMBER(W3)),NOT(ISNUMBER($H$34))),"",W3*$H$34) | AE3: =IF(OR(NOT(ISNUMBER(AC3)),NOT(ISNUMBER(AD3))),"",MAX(0,AC3-AD3)) | AF3: =IF(OR(NOT(ISNUMBER(AD3)),NOT(ISNUMBER(W3))),"",AD3-W3) | AH3: =IF(OR(NOT(ISNUMBER(MIETER!F8)),$G3="ja"),"",IF(NOT(ISNUMBER(MIETER!J8)),"",IF(ISNUMBER(AG3),MAX(MIETER!J8,AG3),MIETER!J8))) | AJ3: =IF(OR(NOT(ISNUMBER(AH3)),NOT(ISNUMBER(AI3))),"",MAX(0,AI3-AH3)) | AN3: =IF(NOT(ISNUMBER(F3)),"",IF(AND(NOT(ISNUMBER(AH3)),NOT(ISNUMBER(AL3)),NOT(ISNUMBER(AM3))),"",N(AH3)+N(AL3)+N(AM3))) | AO3: =IF(OR($G3="ja",NOT(ISNUMBER(AH3)),NOT(ISNUMBER(AN3))),"",AN3+N(AJ3)) | AP3: =IF(OR(NOT(ISNUMBER(AH3)),NOT(ISNUMBER(F3)),F3=0),"",AH3/F3) | AQ3: =IF(OR(NOT(ISNUMBER(MIETER!F8)),NOT(ISNUMBER(MIETER!I8))),"",MIETER!I8) | AR3: =IF(OR(NOT(ISNUMBER(AQ3)),$G3="ja",NOT(ISNUMBER($H$35))),"",EDATE(AQ3,$H$35)) | AT3: =IF(NOT(ISNUMBER(F3)),"",IF(ISNUMBER(AS3),AS3,IF(NOT(ISNUMBER(AR3)),"",MAX(0,(YEAR(AR3)-YEAR(TODAY()))*12+MONTH(AR3)-MONTH(TODAY()))))) | AU3: =IF(NOT(ISNUMBER(AT3)),"",IF(ISNUMBER(AK3),AK3*AT3,IF(NOT(ISNUMBER(AJ3)),"",AJ3*AT3))) | AV3: =IF(OR(NOT(ISNUMBER(AH3)),NOT(ISNUMBER(MIETER!$P$6))),"",ROUND(AH3*(1+MIETER!$P$6)^2,0)) | AY3: =IF(NOT(ISNUMBER(F3)),"",IF(ISNUMBER(AX3),AX3,IF(AND(ISNUMBER(AW3),ISNUMBER(AH3),AH3>0),AH3*AW3,IF(OR(NOT(ISNUMBER($C$62)),NOT(ISNUMBER($C$64))),"",$C$62+$C$64*F3/12)))) | BA3: =IF(NOT(ISNUMBER(AY3)),"",IF(ISNUMBER(AZ3),MIN(AY3,AZ3),IF(OR(NOT(ISNUMBER(F3)),NOT(ISNUMBER($C$64))),0,MIN(AY3,$C$64*F3/12)))) | BB3: =IF(OR(NOT(ISNUMBER(AY3)),NOT(ISNUMBER(AH3)),AH3=0),"",AY3/AH3) | BC3: =IF(NOT(ISNUMBER(AH3)),"",AH3*0.01) | BD3: =IF(OR(NOT(ISNUMBER(AH3)),NOT(ISNUMBER($C$28)),NOT(ISNUMBER(BY3)),BY3<=0),"",AH3*0.01*(1-$C$28)/BY3) | BE3: =IF(OR(NOT(ISNUMBER(K3)),NOT(ISNUMBER($H$30))),"",$H$30*K3) | BG3: =IF(OR(NOT(ISNUMBER(BE3)),NOT(ISNUMBER(X3)),X3<=0),"",1-BE3/X3) | BH3: =IF(NOT(ISNUMBER(X3)),"",IF(ISNUMBER(BF3),BF3,IF(AND(ISNUMBER(BE3),ISNUMBER(AA3),AA3>0),1-BE3/AA3,IF(NOT(ISNUMBER($C$31)),"",$C$31)))) | BI3: =IF(NOT(ISNUMBER(F3)),"",IF(ISNUMBER(BF3),"vertrag",IF(ISNUMBER(BE3),"berechnet","standard"))) | BK3: =IF(NOT(ISNUMBER(F3)),"",IF(ISNUMBER(BJ3),BJ3,IF(NOT(ISNUMBER($C$30)),"",$C$30))) | BL3: =IF(OR(NOT(ISNUMBER(AA3)),NOT(ISNUMBER(BH3)),NOT(ISNUMBER($C$36))),"",AA3*(1+$C$36)*BH3) | BM3: =IF(OR(NOT(ISNUMBER(BL3)),NOT(ISNUMBER(BK3)),NOT(ISNUMBER($C$36)),NOT(ISNUMBER($H$34))),"",(BL3*BK3+N(Q3)*MAX(1,$H$34)*(1+$C$36)*N($H$31)+N(R3)*MAX(1,$H$34)*(1+$C$36)*N($H$32))/12) | BN3: =IF(OR(NOT(ISNUMBER(AD3)),NOT(ISNUMBER($C$26))),"",AD3*$C$26/12) | BO3: =IF(OR(NOT(ISNUMBER(AD3)),NOT(ISNUMBER($C$26)),NOT(ISNUMBER($C$27))),"",ROUND(AD3*($C$26+$C$27)/12,0)) | BP3: =IF(OR(NOT(ISNUMBER(AO3)),NOT(ISNUMBER(BM3)),NOT(ISNUMBER(BN3)),NOT(ISNUMBER(AY3))),"",AO3-BN3-BM3-(AY3-N(BA3))) | BQ3: =IF(OR(NOT(ISNUMBER(BP3)),NOT(ISNUMBER($C$28))),"",ROUND(-BP3*$C$28,0)) | BR3: =IF(OR(NOT(ISNUMBER(BA3)),NOT(ISNUMBER($C$28))),"",BA3*$C$28) | BS3: =IF(OR(NOT(ISNUMBER(AO3)),NOT(ISNUMBER(BO3)),NOT(ISNUMBER(AY3))),"",ROUND(AO3,0)-BO3-ROUND(AY3,0)) | BT3: =IF(OR(NOT(ISNUMBER(BS3)),NOT(ISNUMBER(BQ3))),"",BS3+BQ3) | BU3: =IF(OR(NOT(ISNUMBER(AN3)),NOT(ISNUMBER(BO3)),NOT(ISNUMBER(AY3)),NOT(ISNUMBER(BP3)),NOT(ISNUMBER($C$28))),"",ROUND(AN3,0)-BO3-ROUND(AY3,0)+ROUND(-(BP3-N(AJ3))*$C$28,0)) | BV3: =IF(OR(NOT(ISNUMBER(AO3)),NOT(ISNUMBER(AY3)),NOT(ISNUMBER(BK3)),NOT(ISNUMBER($C$28)),NOT(ISNUMBER($C$36))),"",(AO3-AY3)*(1-$C$28)-$C$28*N(BA3)-IF(BI3="berechnet",$C$28*(1+$C$36)*BK3*N(BE3)/12,0)) | BW3: =IF(OR(NOT(ISNUMBER(F3)),NOT(ISNUMBER($C$26)),NOT(ISNUMBER($C$27)),NOT(ISNUMBER($C$28)),NOT(ISNUMBER($C$36))),"",($C$28*(1+$C$36)*(N(Q3)*N($H$31)+N(R3)*N($H$32))-(N(Q3)+N(R3))*(($C$26+$C$27)-$C$28*$C$26))/12) | BX3: =IF(OR(NOT(ISNUMBER(BK3)),NOT(ISNUMBER($C$26)),NOT(ISNUMBER($C$27)),NOT(ISNUMBER($C$28)),NOT(ISNUMBER($C$36)),BI3=""),"",(($C$26+$C$27)-$C$28*$C$26-$C$28*(1+$C$36)*BK3*IF(BI3="berechnet",1,IF(BI3="vertrag",BF3,$C$31)))/12) | BY3: =IF(OR(NOT(ISNUMBER(BX3)),NOT(ISNUMBER($C$34))),"",$C$34*BX3) | BZ3: =IF(OR($G3="ja",NOT(ISNUMBER(AH3)),NOT(ISNUMBER(BV3)),NOT(ISNUMBER(BW3)),NOT(ISNUMBER(BX3)),BX3<=0),"",(BV3-N($C$32)+BW3)/BX3) | CA3: =IF(OR($G3="ja",NOT(ISNUMBER(AH3)),NOT(ISNUMBER(BV3)),NOT(ISNUMBER(BW3)),NOT(ISNUMBER(BY3)),BY3<=0,NOT(ISNUMBER($C$34))),"",(BV3-N($C$32)+BW3*$C$34)/BY3) | CB3: =IF(OR(NOT(ISNUMBER(CA3)),NOT(ISNUMBER($C$28))),"",CA3-N(AJ3)*(1-$C$28)/BY3) | CC3: =IF(OR(NOT(ISNUMBER(CA3)),NOT(ISNUMBER(U3)),U3<=-1,NOT(ISNUMBER(F3)),F3=0),"",((CA3+N(Q3)+N(R3))/(1+U3)-N(Q3)-N(R3)-N(O3))/F3) | CD3: =IF(OR(NOT(ISNUMBER(L3)),NOT(ISNUMBER(CC3))),"",L3-CC3) | CE3: =IF(OR(NOT(ISNUMBER(W3)),NOT(ISNUMBER(AN3)),AN3=0),"",W3/(AN3*12)) | CF3: =IF(OR(NOT(ISNUMBER(W3)),NOT(ISNUMBER(AN3)),W3=0),"",AN3*12/W3) | CG3: =IF(NOT(ISNUMBER(F3)),"",IF($G3="ja","GRAU: Leerstand - keine Mietbasis",IF(AND(ISNUMBER(AH3),AH3=0),"GRAU: Ist-Miete 0 - Leerstand pruefen",IF(NOT(ISNUMBER(AH3)),"GRAU: Wohnungsmiete fehlt",IF(NOT(ISNUMBER(AJ3)),"GRAU: keine Sollmiete/Mietspiegel",IF(AND(ISNUMBER(AW3),ISNUMBER(AX3)),"GRAU: zwei Hausgeld-Quellen gesetzt",IF(AND(OR(ISNUMBER(AX3),ISNUMBER(AW3)),NOT(ISNUMBER(AZ3))),"GRAU: Ruecklagenanteil fehlt",IF(AND(AJ3>0,NOT(ISNUMBER(AT3))),"GRAU: Subventionsdauer unbekannt",IF(AND(ISNUMBER(BH3),BH3<=0),"ROT: Bodenwert uebersteigt Kaufpreis - Daten pruefen",IF(NOT(ISNUMBER(BT3)),"GRAU: Cashflow nicht rechenbar",IF(NOT(ISNUMBER(BZ3)),"GRAU: max. tragbar nicht rechenbar",IF(BZ3<=0,"ROT: kein tragbarer Preis bei diesem Ziel-Cashflow",IF(AND(BI3="berechnet",BZ3<BE3),"ROT: max. tragbar unter Bodenwert - Modell nicht gueltig",IF(X3<=BZ3-N(AJ3)*(1-$C$28)/BX3,"GRUEN: Preis unter max. tragbar (auch ohne Subvention)",IF(X3<=BZ3,"GELB: nur mit Subvention tragbar",IF(X3<=BZ3*(1+N($H$33)),"GELB: bis Toleranz darueber","ROT: deutlich ueber max. tragbar")))))))))))))))) | CH3: =IF(NOT(ISNUMBER(F3)),"",IF($G3="ja","GRAU: Leerstand - keine Mietbasis",IF(AND(ISNUMBER(AH3),AH3=0),"GRAU: Ist-Miete 0 - Leerstand pruefen",IF(NOT(ISNUMBER(AH3)),"GRAU: Wohnungsmiete fehlt",IF(NOT(ISNUMBER(AJ3)),"GRAU: keine Sollmiete/Mietspiegel",IF(AND(ISNUMBER(AW3),ISNUMBER(AX3)),"GRAU: zwei Hausgeld-Quellen gesetzt",IF(AND(OR(ISNUMBER(AX3),ISNUMBER(AW3)),NOT(ISNUMBER(AZ3))),"GRAU: Ruecklagenanteil fehlt",IF(AND(AJ3>0,NOT(ISNUMBER(AT3))),"GRAU: Subventionsdauer unbekannt",IF(AND(ISNUMBER(BH3),BH3<=0),"ROT: Bodenwert uebersteigt Kaufpreis - Daten pruefen",IF(NOT(ISNUMBER(BT3)),"GRAU: Cashflow nicht rechenbar",IF(NOT(ISNUMBER(CA3)),"GRAU: max. tragbar nicht rechenbar",IF(CA3<=0,"ROT: kein tragbarer Preis bei diesem Ziel-Cashflow",IF(AND(BI3="berechnet",CA3<BE3),"ROT: max. tragbar unter Bodenwert - Modell nicht gueltig",IF(X3<=CB3,"GRUEN: Preis unter max. tragbar (auch ohne Subvention)",IF(X3<=CA3,"GELB: nur mit Subvention tragbar",IF(X3<=CA3*(1+N($H$33)),"GELB: bis Toleranz darueber","ROT: deutlich ueber max. tragbar"))))))))))))))))
A4: =IF(NOT(ISNUMBER(MIETER!F9)),"",ROW()-2) | B4: =IF(NOT(ISNUMBER(MIETER!F9)),"",IF(MIETER!A9="","",MIETER!A9)) | C4: =IF(NOT(ISNUMBER(MIETER!F9)),"",IF(MIETER!B9="","",MIETER!B9)) | D4: =IF(NOT(ISNUMBER(MIETER!F9)),"",IF(MIETER!C9="","",MIETER!C9)) | E4: =IF(NOT(ISNUMBER(MIETER!F9)),"",IF(MIETER!D9="","",MIETER!D9)) | F4: =IF(NOT(ISNUMBER(MIETER!F9)),"",MIETER!F9) | K4: =IF(OR(NOT(ISNUMBER(F4)),NOT(ISNUMBER(J4)),NOT(ISNUMBER($H$29)),$H$29=0),"",J4/$H$29) | M4: =IF(OR(NOT(ISNUMBER(F4)),F4=0,NOT(ISNUMBER(VERKAUFSMATRIX!U7))),"",VERKAUFSMATRIX!U7/F4) | N4: =IF(OR(NOT(ISNUMBER(L4)),NOT(ISNUMBER(M4)),M4=0),"",L4/M4-1) | P4: =IF(OR(NOT(ISNUMBER(F4)),NOT(ISNUMBER(L4))),"",F4*L4+N(O4)) | S4: =IF(NOT(ISNUMBER(P4)),"",P4+N(Q4)+N(R4)) | U4: =IF(NOT(ISNUMBER(F4)),"",IF(ISNUMBER(T4),T4,IF(NOT(ISNUMBER($H$26)),"",$H$26))) | V4: =IF(OR(NOT(ISNUMBER(S4)),NOT(ISNUMBER(U4))),"",S4*U4) | W4: =IF(OR(NOT(ISNUMBER(S4)),NOT(ISNUMBER(U4))),"",S4*(1+U4)) | X4: =IF(NOT(ISNUMBER(W4)),"",W4-N(Q4)-N(R4)) | Y4: =IF(OR(NOT(ISNUMBER(S4)),NOT(ISNUMBER(F4)),F4=0),"",S4/F4) | Z4: =IF(OR(NOT(ISNUMBER(X4)),NOT(ISNUMBER(F4)),F4=0),"",X4/F4) | AA4: =IF(OR(NOT(ISNUMBER(X4)),NOT(ISNUMBER($H$34))),"",X4*MAX(1,$H$34)) | AB4: =IF(OR(NOT(ISNUMBER(W4)),NOT(ISNUMBER($H$34)),NOT(ISNUMBER($C$36))),"",W4*MAX(1,$H$34)*$C$36) | AC4: =IF(OR(NOT(ISNUMBER(W4)),NOT(ISNUMBER(AB4))),"",W4+AB4) | AD4: =IF(OR(NOT(ISNUMBER(W4)),NOT(ISNUMBER($H$34))),"",W4*$H$34) | AE4: =IF(OR(NOT(ISNUMBER(AC4)),NOT(ISNUMBER(AD4))),"",MAX(0,AC4-AD4)) | AF4: =IF(OR(NOT(ISNUMBER(AD4)),NOT(ISNUMBER(W4))),"",AD4-W4) | AH4: =IF(OR(NOT(ISNUMBER(MIETER!F9)),$G4="ja"),"",IF(NOT(ISNUMBER(MIETER!J9)),"",IF(ISNUMBER(AG4),MAX(MIETER!J9,AG4),MIETER!J9))) | AJ4: =IF(OR(NOT(ISNUMBER(AH4)),NOT(ISNUMBER(AI4))),"",MAX(0,AI4-AH4)) | AN4: =IF(NOT(ISNUMBER(F4)),"",IF(AND(NOT(ISNUMBER(AH4)),NOT(ISNUMBER(AL4)),NOT(ISNUMBER(AM4))),"",N(AH4)+N(AL4)+N(AM4))) | AO4: =IF(OR($G4="ja",NOT(ISNUMBER(AH4)),NOT(ISNUMBER(AN4))),"",AN4+N(AJ4)) | AP4: =IF(OR(NOT(ISNUMBER(AH4)),NOT(ISNUMBER(F4)),F4=0),"",AH4/F4) | AQ4: =IF(OR(NOT(ISNUMBER(MIETER!F9)),NOT(ISNUMBER(MIETER!I9))),"",MIETER!I9) | AR4: =IF(OR(NOT(ISNUMBER(AQ4)),$G4="ja",NOT(ISNUMBER($H$35))),"",EDATE(AQ4,$H$35)) | AT4: =IF(NOT(ISNUMBER(F4)),"",IF(ISNUMBER(AS4),AS4,IF(NOT(ISNUMBER(AR4)),"",MAX(0,(YEAR(AR4)-YEAR(TODAY()))*12+MONTH(AR4)-MONTH(TODAY()))))) | AU4: =IF(NOT(ISNUMBER(AT4)),"",IF(ISNUMBER(AK4),AK4*AT4,IF(NOT(ISNUMBER(AJ4)),"",AJ4*AT4))) | AV4: =IF(OR(NOT(ISNUMBER(AH4)),NOT(ISNUMBER(MIETER!$P$6))),"",ROUND(AH4*(1+MIETER!$P$6)^2,0)) | AY4: =IF(NOT(ISNUMBER(F4)),"",IF(ISNUMBER(AX4),AX4,IF(AND(ISNUMBER(AW4),ISNUMBER(AH4),AH4>0),AH4*AW4,IF(OR(NOT(ISNUMBER($C$62)),NOT(ISNUMBER($C$64))),"",$C$62+$C$64*F4/12)))) | BA4: =IF(NOT(ISNUMBER(AY4)),"",IF(ISNUMBER(AZ4),MIN(AY4,AZ4),IF(OR(NOT(ISNUMBER(F4)),NOT(ISNUMBER($C$64))),0,MIN(AY4,$C$64*F4/12)))) | BB4: =IF(OR(NOT(ISNUMBER(AY4)),NOT(ISNUMBER(AH4)),AH4=0),"",AY4/AH4) | BC4: =IF(NOT(ISNUMBER(AH4)),"",AH4*0.01) | BD4: =IF(OR(NOT(ISNUMBER(AH4)),NOT(ISNUMBER($C$28)),NOT(ISNUMBER(BY4)),BY4<=0),"",AH4*0.01*(1-$C$28)/BY4) | BE4: =IF(OR(NOT(ISNUMBER(K4)),NOT(ISNUMBER($H$30))),"",$H$30*K4) | BG4: =IF(OR(NOT(ISNUMBER(BE4)),NOT(ISNUMBER(X4)),X4<=0),"",1-BE4/X4) | BH4: =IF(NOT(ISNUMBER(X4)),"",IF(ISNUMBER(BF4),BF4,IF(AND(ISNUMBER(BE4),ISNUMBER(AA4),AA4>0),1-BE4/AA4,IF(NOT(ISNUMBER($C$31)),"",$C$31)))) | BI4: =IF(NOT(ISNUMBER(F4)),"",IF(ISNUMBER(BF4),"vertrag",IF(ISNUMBER(BE4),"berechnet","standard"))) | BK4: =IF(NOT(ISNUMBER(F4)),"",IF(ISNUMBER(BJ4),BJ4,IF(NOT(ISNUMBER($C$30)),"",$C$30))) | BL4: =IF(OR(NOT(ISNUMBER(AA4)),NOT(ISNUMBER(BH4)),NOT(ISNUMBER($C$36))),"",AA4*(1+$C$36)*BH4) | BM4: =IF(OR(NOT(ISNUMBER(BL4)),NOT(ISNUMBER(BK4)),NOT(ISNUMBER($C$36)),NOT(ISNUMBER($H$34))),"",(BL4*BK4+N(Q4)*MAX(1,$H$34)*(1+$C$36)*N($H$31)+N(R4)*MAX(1,$H$34)*(1+$C$36)*N($H$32))/12) | BN4: =IF(OR(NOT(ISNUMBER(AD4)),NOT(ISNUMBER($C$26))),"",AD4*$C$26/12) | BO4: =IF(OR(NOT(ISNUMBER(AD4)),NOT(ISNUMBER($C$26)),NOT(ISNUMBER($C$27))),"",ROUND(AD4*($C$26+$C$27)/12,0)) | BP4: =IF(OR(NOT(ISNUMBER(AO4)),NOT(ISNUMBER(BM4)),NOT(ISNUMBER(BN4)),NOT(ISNUMBER(AY4))),"",AO4-BN4-BM4-(AY4-N(BA4))) | BQ4: =IF(OR(NOT(ISNUMBER(BP4)),NOT(ISNUMBER($C$28))),"",ROUND(-BP4*$C$28,0)) | BR4: =IF(OR(NOT(ISNUMBER(BA4)),NOT(ISNUMBER($C$28))),"",BA4*$C$28) | BS4: =IF(OR(NOT(ISNUMBER(AO4)),NOT(ISNUMBER(BO4)),NOT(ISNUMBER(AY4))),"",ROUND(AO4,0)-BO4-ROUND(AY4,0)) | BT4: =IF(OR(NOT(ISNUMBER(BS4)),NOT(ISNUMBER(BQ4))),"",BS4+BQ4) | BU4: =IF(OR(NOT(ISNUMBER(AN4)),NOT(ISNUMBER(BO4)),NOT(ISNUMBER(AY4)),NOT(ISNUMBER(BP4)),NOT(ISNUMBER($C$28))),"",ROUND(AN4,0)-BO4-ROUND(AY4,0)+ROUND(-(BP4-N(AJ4))*$C$28,0)) | BV4: =IF(OR(NOT(ISNUMBER(AO4)),NOT(ISNUMBER(AY4)),NOT(ISNUMBER(BK4)),NOT(ISNUMBER($C$28)),NOT(ISNUMBER($C$36))),"",(AO4-AY4)*(1-$C$28)-$C$28*N(BA4)-IF(BI4="berechnet",$C$28*(1+$C$36)*BK4*N(BE4)/12,0)) | BW4: =IF(OR(NOT(ISNUMBER(F4)),NOT(ISNUMBER($C$26)),NOT(ISNUMBER($C$27)),NOT(ISNUMBER($C$28)),NOT(ISNUMBER($C$36))),"",($C$28*(1+$C$36)*(N(Q4)*N($H$31)+N(R4)*N($H$32))-(N(Q4)+N(R4))*(($C$26+$C$27)-$C$28*$C$26))/12) | BX4: =IF(OR(NOT(ISNUMBER(BK4)),NOT(ISNUMBER($C$26)),NOT(ISNUMBER($C$27)),NOT(ISNUMBER($C$28)),NOT(ISNUMBER($C$36)),BI4=""),"",(($C$26+$C$27)-$C$28*$C$26-$C$28*(1+$C$36)*BK4*IF(BI4="berechnet",1,IF(BI4="vertrag",BF4,$C$31)))/12) | BY4: =IF(OR(NOT(ISNUMBER(BX4)),NOT(ISNUMBER($C$34))),"",$C$34*BX4) | BZ4: =IF(OR($G4="ja",NOT(ISNUMBER(AH4)),NOT(ISNUMBER(BV4)),NOT(ISNUMBER(BW4)),NOT(ISNUMBER(BX4)),BX4<=0),"",(BV4-N($C$32)+BW4)/BX4) | CA4: =IF(OR($G4="ja",NOT(ISNUMBER(AH4)),NOT(ISNUMBER(BV4)),NOT(ISNUMBER(BW4)),NOT(ISNUMBER(BY4)),BY4<=0,NOT(ISNUMBER($C$34))),"",(BV4-N($C$32)+BW4*$C$34)/BY4) | CB4: =IF(OR(NOT(ISNUMBER(CA4)),NOT(ISNUMBER($C$28))),"",CA4-N(AJ4)*(1-$C$28)/BY4) | CC4: =IF(OR(NOT(ISNUMBER(CA4)),NOT(ISNUMBER(U4)),U4<=-1,NOT(ISNUMBER(F4)),F4=0),"",((CA4+N(Q4)+N(R4))/(1+U4)-N(Q4)-N(R4)-N(O4))/F4) | CD4: =IF(OR(NOT(ISNUMBER(L4)),NOT(ISNUMBER(CC4))),"",L4-CC4) | CE4: =IF(OR(NOT(ISNUMBER(W4)),NOT(ISNUMBER(AN4)),AN4=0),"",W4/(AN4*12)) | CF4: =IF(OR(NOT(ISNUMBER(W4)),NOT(ISNUMBER(AN4)),W4=0),"",AN4*12/W4) | CG4: =IF(NOT(ISNUMBER(F4)),"",IF($G4="ja","GRAU: Leerstand - keine Mietbasis",IF(AND(ISNUMBER(AH4),AH4=0),"GRAU: Ist-Miete 0 - Leerstand pruefen",IF(NOT(ISNUMBER(AH4)),"GRAU: Wohnungsmiete fehlt",IF(NOT(ISNUMBER(AJ4)),"GRAU: keine Sollmiete/Mietspiegel",IF(AND(ISNUMBER(AW4),ISNUMBER(AX4)),"GRAU: zwei Hausgeld-Quellen gesetzt",IF(AND(OR(ISNUMBER(AX4),ISNUMBER(AW4)),NOT(ISNUMBER(AZ4))),"GRAU: Ruecklagenanteil fehlt",IF(AND(AJ4>0,NOT(ISNUMBER(AT4))),"GRAU: Subventionsdauer unbekannt",IF(AND(ISNUMBER(BH4),BH4<=0),"ROT: Bodenwert uebersteigt Kaufpreis - Daten pruefen",IF(NOT(ISNUMBER(BT4)),"GRAU: Cashflow nicht rechenbar",IF(NOT(ISNUMBER(BZ4)),"GRAU: max. tragbar nicht rechenbar",IF(BZ4<=0,"ROT: kein tragbarer Preis bei diesem Ziel-Cashflow",IF(AND(BI4="berechnet",BZ4<BE4),"ROT: max. tragbar unter Bodenwert - Modell nicht gueltig",IF(X4<=BZ4-N(AJ4)*(1-$C$28)/BX4,"GRUEN: Preis unter max. tragbar (auch ohne Subvention)",IF(X4<=BZ4,"GELB: nur mit Subvention tragbar",IF(X4<=BZ4*(1+N($H$33)),"GELB: bis Toleranz darueber","ROT: deutlich ueber max. tragbar")))))))))))))))) | CH4: =IF(NOT(ISNUMBER(F4)),"",IF($G4="ja","GRAU: Leerstand - keine Mietbasis",IF(AND(ISNUMBER(AH4),AH4=0),"GRAU: Ist-Miete 0 - Leerstand pruefen",IF(NOT(ISNUMBER(AH4)),"GRAU: Wohnungsmiete fehlt",IF(NOT(ISNUMBER(AJ4)),"GRAU: keine Sollmiete/Mietspiegel",IF(AND(ISNUMBER(AW4),ISNUMBER(AX4)),"GRAU: zwei Hausgeld-Quellen gesetzt",IF(AND(OR(ISNUMBER(AX4),ISNUMBER(AW4)),NOT(ISNUMBER(AZ4))),"GRAU: Ruecklagenanteil fehlt",IF(AND(AJ4>0,NOT(ISNUMBER(AT4))),"GRAU: Subventionsdauer unbekannt",IF(AND(ISNUMBER(BH4),BH4<=0),"ROT: Bodenwert uebersteigt Kaufpreis - Daten pruefen",IF(NOT(ISNUMBER(BT4)),"GRAU: Cashflow nicht rechenbar",IF(NOT(ISNUMBER(CA4)),"GRAU: max. tragbar nicht rechenbar",IF(CA4<=0,"ROT: kein tragbarer Preis bei diesem Ziel-Cashflow",IF(AND(BI4="berechnet",CA4<BE4),"ROT: max. tragbar unter Bodenwert - Modell nicht gueltig",IF(X4<=CB4,"GRUEN: Preis unter max. tragbar (auch ohne Subvention)",IF(X4<=CA4,"GELB: nur mit Subvention tragbar",IF(X4<=CA4*(1+N($H$33)),"GELB: bis Toleranz darueber","ROT: deutlich ueber max. tragbar"))))))))))))))))
A5: =IF(NOT(ISNUMBER(MIETER!F10)),"",ROW()-2) | B5: =IF(NOT(ISNUMBER(MIETER!F10)),"",IF(MIETER!A10="","",MIETER!A10)) | C5: =IF(NOT(ISNUMBER(MIETER!F10)),"",IF(MIETER!B10="","",MIETER!B10)) | D5: =IF(NOT(ISNUMBER(MIETER!F10)),"",IF(MIETER!C10="","",MIETER!C10)) | E5: =IF(NOT(ISNUMBER(MIETER!F10)),"",IF(MIETER!D10="","",MIETER!D10)) | F5: =IF(NOT(ISNUMBER(MIETER!F10)),"",MIETER!F10) | K5: =IF(OR(NOT(ISNUMBER(F5)),NOT(ISNUMBER(J5)),NOT(ISNUMBER($H$29)),$H$29=0),"",J5/$H$29) | M5: =IF(OR(NOT(ISNUMBER(F5)),F5=0,NOT(ISNUMBER(VERKAUFSMATRIX!U8))),"",VERKAUFSMATRIX!U8/F5) | N5: =IF(OR(NOT(ISNUMBER(L5)),NOT(ISNUMBER(M5)),M5=0),"",L5/M5-1) | P5: =IF(OR(NOT(ISNUMBER(F5)),NOT(ISNUMBER(L5))),"",F5*L5+N(O5)) | S5: =IF(NOT(ISNUMBER(P5)),"",P5+N(Q5)+N(R5)) | U5: =IF(NOT(ISNUMBER(F5)),"",IF(ISNUMBER(T5),T5,IF(NOT(ISNUMBER($H$26)),"",$H$26))) | V5: =IF(OR(NOT(ISNUMBER(S5)),NOT(ISNUMBER(U5))),"",S5*U5) | W5: =IF(OR(NOT(ISNUMBER(S5)),NOT(ISNUMBER(U5))),"",S5*(1+U5)) | X5: =IF(NOT(ISNUMBER(W5)),"",W5-N(Q5)-N(R5)) | Y5: =IF(OR(NOT(ISNUMBER(S5)),NOT(ISNUMBER(F5)),F5=0),"",S5/F5) | Z5: =IF(OR(NOT(ISNUMBER(X5)),NOT(ISNUMBER(F5)),F5=0),"",X5/F5) | AA5: =IF(OR(NOT(ISNUMBER(X5)),NOT(ISNUMBER($H$34))),"",X5*MAX(1,$H$34)) | AB5: =IF(OR(NOT(ISNUMBER(W5)),NOT(ISNUMBER($H$34)),NOT(ISNUMBER($C$36))),"",W5*MAX(1,$H$34)*$C$36) | AC5: =IF(OR(NOT(ISNUMBER(W5)),NOT(ISNUMBER(AB5))),"",W5+AB5) | AD5: =IF(OR(NOT(ISNUMBER(W5)),NOT(ISNUMBER($H$34))),"",W5*$H$34) | AE5: =IF(OR(NOT(ISNUMBER(AC5)),NOT(ISNUMBER(AD5))),"",MAX(0,AC5-AD5)) | AF5: =IF(OR(NOT(ISNUMBER(AD5)),NOT(ISNUMBER(W5))),"",AD5-W5) | AH5: =IF(OR(NOT(ISNUMBER(MIETER!F10)),$G5="ja"),"",IF(NOT(ISNUMBER(MIETER!J10)),"",IF(ISNUMBER(AG5),MAX(MIETER!J10,AG5),MIETER!J10))) | AJ5: =IF(OR(NOT(ISNUMBER(AH5)),NOT(ISNUMBER(AI5))),"",MAX(0,AI5-AH5)) | AN5: =IF(NOT(ISNUMBER(F5)),"",IF(AND(NOT(ISNUMBER(AH5)),NOT(ISNUMBER(AL5)),NOT(ISNUMBER(AM5))),"",N(AH5)+N(AL5)+N(AM5))) | AO5: =IF(OR($G5="ja",NOT(ISNUMBER(AH5)),NOT(ISNUMBER(AN5))),"",AN5+N(AJ5)) | AP5: =IF(OR(NOT(ISNUMBER(AH5)),NOT(ISNUMBER(F5)),F5=0),"",AH5/F5) | AQ5: =IF(OR(NOT(ISNUMBER(MIETER!F10)),NOT(ISNUMBER(MIETER!I10))),"",MIETER!I10) | AR5: =IF(OR(NOT(ISNUMBER(AQ5)),$G5="ja",NOT(ISNUMBER($H$35))),"",EDATE(AQ5,$H$35)) | AT5: =IF(NOT(ISNUMBER(F5)),"",IF(ISNUMBER(AS5),AS5,IF(NOT(ISNUMBER(AR5)),"",MAX(0,(YEAR(AR5)-YEAR(TODAY()))*12+MONTH(AR5)-MONTH(TODAY()))))) | AU5: =IF(NOT(ISNUMBER(AT5)),"",IF(ISNUMBER(AK5),AK5*AT5,IF(NOT(ISNUMBER(AJ5)),"",AJ5*AT5))) | AV5: =IF(OR(NOT(ISNUMBER(AH5)),NOT(ISNUMBER(MIETER!$P$6))),"",ROUND(AH5*(1+MIETER!$P$6)^2,0)) | AY5: =IF(NOT(ISNUMBER(F5)),"",IF(ISNUMBER(AX5),AX5,IF(AND(ISNUMBER(AW5),ISNUMBER(AH5),AH5>0),AH5*AW5,IF(OR(NOT(ISNUMBER($C$62)),NOT(ISNUMBER($C$64))),"",$C$62+$C$64*F5/12)))) | BA5: =IF(NOT(ISNUMBER(AY5)),"",IF(ISNUMBER(AZ5),MIN(AY5,AZ5),IF(OR(NOT(ISNUMBER(F5)),NOT(ISNUMBER($C$64))),0,MIN(AY5,$C$64*F5/12)))) | BB5: =IF(OR(NOT(ISNUMBER(AY5)),NOT(ISNUMBER(AH5)),AH5=0),"",AY5/AH5) | BC5: =IF(NOT(ISNUMBER(AH5)),"",AH5*0.01) | BD5: =IF(OR(NOT(ISNUMBER(AH5)),NOT(ISNUMBER($C$28)),NOT(ISNUMBER(BY5)),BY5<=0),"",AH5*0.01*(1-$C$28)/BY5) | BE5: =IF(OR(NOT(ISNUMBER(K5)),NOT(ISNUMBER($H$30))),"",$H$30*K5) | BG5: =IF(OR(NOT(ISNUMBER(BE5)),NOT(ISNUMBER(X5)),X5<=0),"",1-BE5/X5) | BH5: =IF(NOT(ISNUMBER(X5)),"",IF(ISNUMBER(BF5),BF5,IF(AND(ISNUMBER(BE5),ISNUMBER(AA5),AA5>0),1-BE5/AA5,IF(NOT(ISNUMBER($C$31)),"",$C$31)))) | BI5: =IF(NOT(ISNUMBER(F5)),"",IF(ISNUMBER(BF5),"vertrag",IF(ISNUMBER(BE5),"berechnet","standard"))) | BK5: =IF(NOT(ISNUMBER(F5)),"",IF(ISNUMBER(BJ5),BJ5,IF(NOT(ISNUMBER($C$30)),"",$C$30))) | BL5: =IF(OR(NOT(ISNUMBER(AA5)),NOT(ISNUMBER(BH5)),NOT(ISNUMBER($C$36))),"",AA5*(1+$C$36)*BH5) | BM5: =IF(OR(NOT(ISNUMBER(BL5)),NOT(ISNUMBER(BK5)),NOT(ISNUMBER($C$36)),NOT(ISNUMBER($H$34))),"",(BL5*BK5+N(Q5)*MAX(1,$H$34)*(1+$C$36)*N($H$31)+N(R5)*MAX(1,$H$34)*(1+$C$36)*N($H$32))/12) | BN5: =IF(OR(NOT(ISNUMBER(AD5)),NOT(ISNUMBER($C$26))),"",AD5*$C$26/12) | BO5: =IF(OR(NOT(ISNUMBER(AD5)),NOT(ISNUMBER($C$26)),NOT(ISNUMBER($C$27))),"",ROUND(AD5*($C$26+$C$27)/12,0)) | BP5: =IF(OR(NOT(ISNUMBER(AO5)),NOT(ISNUMBER(BM5)),NOT(ISNUMBER(BN5)),NOT(ISNUMBER(AY5))),"",AO5-BN5-BM5-(AY5-N(BA5))) | BQ5: =IF(OR(NOT(ISNUMBER(BP5)),NOT(ISNUMBER($C$28))),"",ROUND(-BP5*$C$28,0)) | BR5: =IF(OR(NOT(ISNUMBER(BA5)),NOT(ISNUMBER($C$28))),"",BA5*$C$28) | BS5: =IF(OR(NOT(ISNUMBER(AO5)),NOT(ISNUMBER(BO5)),NOT(ISNUMBER(AY5))),"",ROUND(AO5,0)-BO5-ROUND(AY5,0)) | BT5: =IF(OR(NOT(ISNUMBER(BS5)),NOT(ISNUMBER(BQ5))),"",BS5+BQ5) | BU5: =IF(OR(NOT(ISNUMBER(AN5)),NOT(ISNUMBER(BO5)),NOT(ISNUMBER(AY5)),NOT(ISNUMBER(BP5)),NOT(ISNUMBER($C$28))),"",ROUND(AN5,0)-BO5-ROUND(AY5,0)+ROUND(-(BP5-N(AJ5))*$C$28,0)) | BV5: =IF(OR(NOT(ISNUMBER(AO5)),NOT(ISNUMBER(AY5)),NOT(ISNUMBER(BK5)),NOT(ISNUMBER($C$28)),NOT(ISNUMBER($C$36))),"",(AO5-AY5)*(1-$C$28)-$C$28*N(BA5)-IF(BI5="berechnet",$C$28*(1+$C$36)*BK5*N(BE5)/12,0)) | BW5: =IF(OR(NOT(ISNUMBER(F5)),NOT(ISNUMBER($C$26)),NOT(ISNUMBER($C$27)),NOT(ISNUMBER($C$28)),NOT(ISNUMBER($C$36))),"",($C$28*(1+$C$36)*(N(Q5)*N($H$31)+N(R5)*N($H$32))-(N(Q5)+N(R5))*(($C$26+$C$27)-$C$28*$C$26))/12) | BX5: =IF(OR(NOT(ISNUMBER(BK5)),NOT(ISNUMBER($C$26)),NOT(ISNUMBER($C$27)),NOT(ISNUMBER($C$28)),NOT(ISNUMBER($C$36)),BI5=""),"",(($C$26+$C$27)-$C$28*$C$26-$C$28*(1+$C$36)*BK5*IF(BI5="berechnet",1,IF(BI5="vertrag",BF5,$C$31)))/12) | BY5: =IF(OR(NOT(ISNUMBER(BX5)),NOT(ISNUMBER($C$34))),"",$C$34*BX5) | BZ5: =IF(OR($G5="ja",NOT(ISNUMBER(AH5)),NOT(ISNUMBER(BV5)),NOT(ISNUMBER(BW5)),NOT(ISNUMBER(BX5)),BX5<=0),"",(BV5-N($C$32)+BW5)/BX5) | CA5: =IF(OR($G5="ja",NOT(ISNUMBER(AH5)),NOT(ISNUMBER(BV5)),NOT(ISNUMBER(BW5)),NOT(ISNUMBER(BY5)),BY5<=0,NOT(ISNUMBER($C$34))),"",(BV5-N($C$32)+BW5*$C$34)/BY5) | CB5: =IF(OR(NOT(ISNUMBER(CA5)),NOT(ISNUMBER($C$28))),"",CA5-N(AJ5)*(1-$C$28)/BY5) | CC5: =IF(OR(NOT(ISNUMBER(CA5)),NOT(ISNUMBER(U5)),U5<=-1,NOT(ISNUMBER(F5)),F5=0),"",((CA5+N(Q5)+N(R5))/(1+U5)-N(Q5)-N(R5)-N(O5))/F5) | CD5: =IF(OR(NOT(ISNUMBER(L5)),NOT(ISNUMBER(CC5))),"",L5-CC5) | CE5: =IF(OR(NOT(ISNUMBER(W5)),NOT(ISNUMBER(AN5)),AN5=0),"",W5/(AN5*12)) | CF5: =IF(OR(NOT(ISNUMBER(W5)),NOT(ISNUMBER(AN5)),W5=0),"",AN5*12/W5) | CG5: =IF(NOT(ISNUMBER(F5)),"",IF($G5="ja","GRAU: Leerstand - keine Mietbasis",IF(AND(ISNUMBER(AH5),AH5=0),"GRAU: Ist-Miete 0 - Leerstand pruefen",IF(NOT(ISNUMBER(AH5)),"GRAU: Wohnungsmiete fehlt",IF(NOT(ISNUMBER(AJ5)),"GRAU: keine Sollmiete/Mietspiegel",IF(AND(ISNUMBER(AW5),ISNUMBER(AX5)),"GRAU: zwei Hausgeld-Quellen gesetzt",IF(AND(OR(ISNUMBER(AX5),ISNUMBER(AW5)),NOT(ISNUMBER(AZ5))),"GRAU: Ruecklagenanteil fehlt",IF(AND(AJ5>0,NOT(ISNUMBER(AT5))),"GRAU: Subventionsdauer unbekannt",IF(AND(ISNUMBER(BH5),BH5<=0),"ROT: Bodenwert uebersteigt Kaufpreis - Daten pruefen",IF(NOT(ISNUMBER(BT5)),"GRAU: Cashflow nicht rechenbar",IF(NOT(ISNUMBER(BZ5)),"GRAU: max. tragbar nicht rechenbar",IF(BZ5<=0,"ROT: kein tragbarer Preis bei diesem Ziel-Cashflow",IF(AND(BI5="berechnet",BZ5<BE5),"ROT: max. tragbar unter Bodenwert - Modell nicht gueltig",IF(X5<=BZ5-N(AJ5)*(1-$C$28)/BX5,"GRUEN: Preis unter max. tragbar (auch ohne Subvention)",IF(X5<=BZ5,"GELB: nur mit Subvention tragbar",IF(X5<=BZ5*(1+N($H$33)),"GELB: bis Toleranz darueber","ROT: deutlich ueber max. tragbar")))))))))))))))) | CH5: =IF(NOT(ISNUMBER(F5)),"",IF($G5="ja","GRAU: Leerstand - keine Mietbasis",IF(AND(ISNUMBER(AH5),AH5=0),"GRAU: Ist-Miete 0 - Leerstand pruefen",IF(NOT(ISNUMBER(AH5)),"GRAU: Wohnungsmiete fehlt",IF(NOT(ISNUMBER(AJ5)),"GRAU: keine Sollmiete/Mietspiegel",IF(AND(ISNUMBER(AW5),ISNUMBER(AX5)),"GRAU: zwei Hausgeld-Quellen gesetzt",IF(AND(OR(ISNUMBER(AX5),ISNUMBER(AW5)),NOT(ISNUMBER(AZ5))),"GRAU: Ruecklagenanteil fehlt",IF(AND(AJ5>0,NOT(ISNUMBER(AT5))),"GRAU: Subventionsdauer unbekannt",IF(AND(ISNUMBER(BH5),BH5<=0),"ROT: Bodenwert uebersteigt Kaufpreis - Daten pruefen",IF(NOT(ISNUMBER(BT5)),"GRAU: Cashflow nicht rechenbar",IF(NOT(ISNUMBER(CA5)),"GRAU: max. tragbar nicht rechenbar",IF(CA5<=0,"ROT: kein tragbarer Preis bei diesem Ziel-Cashflow",IF(AND(BI5="berechnet",CA5<BE5),"ROT: max. tragbar unter Bodenwert - Modell nicht gueltig",IF(X5<=CB5,"GRUEN: Preis unter max. tragbar (auch ohne Subvention)",IF(X5<=CA5,"GELB: nur mit Subvention tragbar",IF(X5<=CA5*(1+N($H$33)),"GELB: bis Toleranz darueber","ROT: deutlich ueber max. tragbar"))))))))))))))))
A6: =IF(NOT(ISNUMBER(MIETER!F11)),"",ROW()-2) | B6: =IF(NOT(ISNUMBER(MIETER!F11)),"",IF(MIETER!A11="","",MIETER!A11)) | C6: =IF(NOT(ISNUMBER(MIETER!F11)),"",IF(MIETER!B11="","",MIETER!B11)) | D6: =IF(NOT(ISNUMBER(MIETER!F11)),"",IF(MIETER!C11="","",MIETER!C11)) | E6: =IF(NOT(ISNUMBER(MIETER!F11)),"",IF(MIETER!D11="","",MIETER!D11)) | F6: =IF(NOT(ISNUMBER(MIETER!F11)),"",MIETER!F11) | K6: =IF(OR(NOT(ISNUMBER(F6)),NOT(ISNUMBER(J6)),NOT(ISNUMBER($H$29)),$H$29=0),"",J6/$H$29) | M6: =IF(OR(NOT(ISNUMBER(F6)),F6=0,NOT(ISNUMBER(VERKAUFSMATRIX!U9))),"",VERKAUFSMATRIX!U9/F6) | N6: =IF(OR(NOT(ISNUMBER(L6)),NOT(ISNUMBER(M6)),M6=0),"",L6/M6-1) | P6: =IF(OR(NOT(ISNUMBER(F6)),NOT(ISNUMBER(L6))),"",F6*L6+N(O6)) | S6: =IF(NOT(ISNUMBER(P6)),"",P6+N(Q6)+N(R6)) | U6: =IF(NOT(ISNUMBER(F6)),"",IF(ISNUMBER(T6),T6,IF(NOT(ISNUMBER($H$26)),"",$H$26))) | V6: =IF(OR(NOT(ISNUMBER(S6)),NOT(ISNUMBER(U6))),"",S6*U6) | W6: =IF(OR(NOT(ISNUMBER(S6)),NOT(ISNUMBER(U6))),"",S6*(1+U6)) | X6: =IF(NOT(ISNUMBER(W6)),"",W6-N(Q6)-N(R6)) | Y6: =IF(OR(NOT(ISNUMBER(S6)),NOT(ISNUMBER(F6)),F6=0),"",S6/F6) | Z6: =IF(OR(NOT(ISNUMBER(X6)),NOT(ISNUMBER(F6)),F6=0),"",X6/F6) | AA6: =IF(OR(NOT(ISNUMBER(X6)),NOT(ISNUMBER($H$34))),"",X6*MAX(1,$H$34)) | AB6: =IF(OR(NOT(ISNUMBER(W6)),NOT(ISNUMBER($H$34)),NOT(ISNUMBER($C$36))),"",W6*MAX(1,$H$34)*$C$36) | AC6: =IF(OR(NOT(ISNUMBER(W6)),NOT(ISNUMBER(AB6))),"",W6+AB6) | AD6: =IF(OR(NOT(ISNUMBER(W6)),NOT(ISNUMBER($H$34))),"",W6*$H$34) | AE6: =IF(OR(NOT(ISNUMBER(AC6)),NOT(ISNUMBER(AD6))),"",MAX(0,AC6-AD6)) | AF6: =IF(OR(NOT(ISNUMBER(AD6)),NOT(ISNUMBER(W6))),"",AD6-W6) | AH6: =IF(OR(NOT(ISNUMBER(MIETER!F11)),$G6="ja"),"",IF(NOT(ISNUMBER(MIETER!J11)),"",IF(ISNUMBER(AG6),MAX(MIETER!J11,AG6),MIETER!J11))) | AJ6: =IF(OR(NOT(ISNUMBER(AH6)),NOT(ISNUMBER(AI6))),"",MAX(0,AI6-AH6)) | AN6: =IF(NOT(ISNUMBER(F6)),"",IF(AND(NOT(ISNUMBER(AH6)),NOT(ISNUMBER(AL6)),NOT(ISNUMBER(AM6))),"",N(AH6)+N(AL6)+N(AM6))) | AO6: =IF(OR($G6="ja",NOT(ISNUMBER(AH6)),NOT(ISNUMBER(AN6))),"",AN6+N(AJ6)) | AP6: =IF(OR(NOT(ISNUMBER(AH6)),NOT(ISNUMBER(F6)),F6=0),"",AH6/F6) | AQ6: =IF(OR(NOT(ISNUMBER(MIETER!F11)),NOT(ISNUMBER(MIETER!I11))),"",MIETER!I11) | AR6: =IF(OR(NOT(ISNUMBER(AQ6)),$G6="ja",NOT(ISNUMBER($H$35))),"",EDATE(AQ6,$H$35)) | AT6: =IF(NOT(ISNUMBER(F6)),"",IF(ISNUMBER(AS6),AS6,IF(NOT(ISNUMBER(AR6)),"",MAX(0,(YEAR(AR6)-YEAR(TODAY()))*12+MONTH(AR6)-MONTH(TODAY()))))) | AU6: =IF(NOT(ISNUMBER(AT6)),"",IF(ISNUMBER(AK6),AK6*AT6,IF(NOT(ISNUMBER(AJ6)),"",AJ6*AT6))) | AV6: =IF(OR(NOT(ISNUMBER(AH6)),NOT(ISNUMBER(MIETER!$P$6))),"",ROUND(AH6*(1+MIETER!$P$6)^2,0)) | AY6: =IF(NOT(ISNUMBER(F6)),"",IF(ISNUMBER(AX6),AX6,IF(AND(ISNUMBER(AW6),ISNUMBER(AH6),AH6>0),AH6*AW6,IF(OR(NOT(ISNUMBER($C$62)),NOT(ISNUMBER($C$64))),"",$C$62+$C$64*F6/12)))) | BA6: =IF(NOT(ISNUMBER(AY6)),"",IF(ISNUMBER(AZ6),MIN(AY6,AZ6),IF(OR(NOT(ISNUMBER(F6)),NOT(ISNUMBER($C$64))),0,MIN(AY6,$C$64*F6/12)))) | BB6: =IF(OR(NOT(ISNUMBER(AY6)),NOT(ISNUMBER(AH6)),AH6=0),"",AY6/AH6) | BC6: =IF(NOT(ISNUMBER(AH6)),"",AH6*0.01) | BD6: =IF(OR(NOT(ISNUMBER(AH6)),NOT(ISNUMBER($C$28)),NOT(ISNUMBER(BY6)),BY6<=0),"",AH6*0.01*(1-$C$28)/BY6) | BE6: =IF(OR(NOT(ISNUMBER(K6)),NOT(ISNUMBER($H$30))),"",$H$30*K6) | BG6: =IF(OR(NOT(ISNUMBER(BE6)),NOT(ISNUMBER(X6)),X6<=0),"",1-BE6/X6) | BH6: =IF(NOT(ISNUMBER(X6)),"",IF(ISNUMBER(BF6),BF6,IF(AND(ISNUMBER(BE6),ISNUMBER(AA6),AA6>0),1-BE6/AA6,IF(NOT(ISNUMBER($C$31)),"",$C$31)))) | BI6: =IF(NOT(ISNUMBER(F6)),"",IF(ISNUMBER(BF6),"vertrag",IF(ISNUMBER(BE6),"berechnet","standard"))) | BK6: =IF(NOT(ISNUMBER(F6)),"",IF(ISNUMBER(BJ6),BJ6,IF(NOT(ISNUMBER($C$30)),"",$C$30))) | BL6: =IF(OR(NOT(ISNUMBER(AA6)),NOT(ISNUMBER(BH6)),NOT(ISNUMBER($C$36))),"",AA6*(1+$C$36)*BH6) | BM6: =IF(OR(NOT(ISNUMBER(BL6)),NOT(ISNUMBER(BK6)),NOT(ISNUMBER($C$36)),NOT(ISNUMBER($H$34))),"",(BL6*BK6+N(Q6)*MAX(1,$H$34)*(1+$C$36)*N($H$31)+N(R6)*MAX(1,$H$34)*(1+$C$36)*N($H$32))/12) | BN6: =IF(OR(NOT(ISNUMBER(AD6)),NOT(ISNUMBER($C$26))),"",AD6*$C$26/12) | BO6: =IF(OR(NOT(ISNUMBER(AD6)),NOT(ISNUMBER($C$26)),NOT(ISNUMBER($C$27))),"",ROUND(AD6*($C$26+$C$27)/12,0)) | BP6: =IF(OR(NOT(ISNUMBER(AO6)),NOT(ISNUMBER(BM6)),NOT(ISNUMBER(BN6)),NOT(ISNUMBER(AY6))),"",AO6-BN6-BM6-(AY6-N(BA6))) | BQ6: =IF(OR(NOT(ISNUMBER(BP6)),NOT(ISNUMBER($C$28))),"",ROUND(-BP6*$C$28,0)) | BR6: =IF(OR(NOT(ISNUMBER(BA6)),NOT(ISNUMBER($C$28))),"",BA6*$C$28) | BS6: =IF(OR(NOT(ISNUMBER(AO6)),NOT(ISNUMBER(BO6)),NOT(ISNUMBER(AY6))),"",ROUND(AO6,0)-BO6-ROUND(AY6,0)) | BT6: =IF(OR(NOT(ISNUMBER(BS6)),NOT(ISNUMBER(BQ6))),"",BS6+BQ6) | BU6: =IF(OR(NOT(ISNUMBER(AN6)),NOT(ISNUMBER(BO6)),NOT(ISNUMBER(AY6)),NOT(ISNUMBER(BP6)),NOT(ISNUMBER($C$28))),"",ROUND(AN6,0)-BO6-ROUND(AY6,0)+ROUND(-(BP6-N(AJ6))*$C$28,0)) | BV6: =IF(OR(NOT(ISNUMBER(AO6)),NOT(ISNUMBER(AY6)),NOT(ISNUMBER(BK6)),NOT(ISNUMBER($C$28)),NOT(ISNUMBER($C$36))),"",(AO6-AY6)*(1-$C$28)-$C$28*N(BA6)-IF(BI6="berechnet",$C$28*(1+$C$36)*BK6*N(BE6)/12,0)) | BW6: =IF(OR(NOT(ISNUMBER(F6)),NOT(ISNUMBER($C$26)),NOT(ISNUMBER($C$27)),NOT(ISNUMBER($C$28)),NOT(ISNUMBER($C$36))),"",($C$28*(1+$C$36)*(N(Q6)*N($H$31)+N(R6)*N($H$32))-(N(Q6)+N(R6))*(($C$26+$C$27)-$C$28*$C$26))/12) | BX6: =IF(OR(NOT(ISNUMBER(BK6)),NOT(ISNUMBER($C$26)),NOT(ISNUMBER($C$27)),NOT(ISNUMBER($C$28)),NOT(ISNUMBER($C$36)),BI6=""),"",(($C$26+$C$27)-$C$28*$C$26-$C$28*(1+$C$36)*BK6*IF(BI6="berechnet",1,IF(BI6="vertrag",BF6,$C$31)))/12) | BY6: =IF(OR(NOT(ISNUMBER(BX6)),NOT(ISNUMBER($C$34))),"",$C$34*BX6) | BZ6: =IF(OR($G6="ja",NOT(ISNUMBER(AH6)),NOT(ISNUMBER(BV6)),NOT(ISNUMBER(BW6)),NOT(ISNUMBER(BX6)),BX6<=0),"",(BV6-N($C$32)+BW6)/BX6) | CA6: =IF(OR($G6="ja",NOT(ISNUMBER(AH6)),NOT(ISNUMBER(BV6)),NOT(ISNUMBER(BW6)),NOT(ISNUMBER(BY6)),BY6<=0,NOT(ISNUMBER($C$34))),"",(BV6-N($C$32)+BW6*$C$34)/BY6) | CB6: =IF(OR(NOT(ISNUMBER(CA6)),NOT(ISNUMBER($C$28))),"",CA6-N(AJ6)*(1-$C$28)/BY6) | CC6: =IF(OR(NOT(ISNUMBER(CA6)),NOT(ISNUMBER(U6)),U6<=-1,NOT(ISNUMBER(F6)),F6=0),"",((CA6+N(Q6)+N(R6))/(1+U6)-N(Q6)-N(R6)-N(O6))/F6) | CD6: =IF(OR(NOT(ISNUMBER(L6)),NOT(ISNUMBER(CC6))),"",L6-CC6) | CE6: =IF(OR(NOT(ISNUMBER(W6)),NOT(ISNUMBER(AN6)),AN6=0),"",W6/(AN6*12)) | CF6: =IF(OR(NOT(ISNUMBER(W6)),NOT(ISNUMBER(AN6)),W6=0),"",AN6*12/W6) | CG6: =IF(NOT(ISNUMBER(F6)),"",IF($G6="ja","GRAU: Leerstand - keine Mietbasis",IF(AND(ISNUMBER(AH6),AH6=0),"GRAU: Ist-Miete 0 - Leerstand pruefen",IF(NOT(ISNUMBER(AH6)),"GRAU: Wohnungsmiete fehlt",IF(NOT(ISNUMBER(AJ6)),"GRAU: keine Sollmiete/Mietspiegel",IF(AND(ISNUMBER(AW6),ISNUMBER(AX6)),"GRAU: zwei Hausgeld-Quellen gesetzt",IF(AND(OR(ISNUMBER(AX6),ISNUMBER(AW6)),NOT(ISNUMBER(AZ6))),"GRAU: Ruecklagenanteil fehlt",IF(AND(AJ6>0,NOT(ISNUMBER(AT6))),"GRAU: Subventionsdauer unbekannt",IF(AND(ISNUMBER(BH6),BH6<=0),"ROT: Bodenwert uebersteigt Kaufpreis - Daten pruefen",IF(NOT(ISNUMBER(BT6)),"GRAU: Cashflow nicht rechenbar",IF(NOT(ISNUMBER(BZ6)),"GRAU: max. tragbar nicht rechenbar",IF(BZ6<=0,"ROT: kein tragbarer Preis bei diesem Ziel-Cashflow",IF(AND(BI6="berechnet",BZ6<BE6),"ROT: max. tragbar unter Bodenwert - Modell nicht gueltig",IF(X6<=BZ6-N(AJ6)*(1-$C$28)/BX6,"GRUEN: Preis unter max. tragbar (auch ohne Subvention)",IF(X6<=BZ6,"GELB: nur mit Subvention tragbar",IF(X6<=BZ6*(1+N($H$33)),"GELB: bis Toleranz darueber","ROT: deutlich ueber max. tragbar")))))))))))))))) | CH6: =IF(NOT(ISNUMBER(F6)),"",IF($G6="ja","GRAU: Leerstand - keine Mietbasis",IF(AND(ISNUMBER(AH6),AH6=0),"GRAU: Ist-Miete 0 - Leerstand pruefen",IF(NOT(ISNUMBER(AH6)),"GRAU: Wohnungsmiete fehlt",IF(NOT(ISNUMBER(AJ6)),"GRAU: keine Sollmiete/Mietspiegel",IF(AND(ISNUMBER(AW6),ISNUMBER(AX6)),"GRAU: zwei Hausgeld-Quellen gesetzt",IF(AND(OR(ISNUMBER(AX6),ISNUMBER(AW6)),NOT(ISNUMBER(AZ6))),"GRAU: Ruecklagenanteil fehlt",IF(AND(AJ6>0,NOT(ISNUMBER(AT6))),"GRAU: Subventionsdauer unbekannt",IF(AND(ISNUMBER(BH6),BH6<=0),"ROT: Bodenwert uebersteigt Kaufpreis - Daten pruefen",IF(NOT(ISNUMBER(BT6)),"GRAU: Cashflow nicht rechenbar",IF(NOT(ISNUMBER(CA6)),"GRAU: max. tragbar nicht rechenbar",IF(CA6<=0,"ROT: kein tragbarer Preis bei diesem Ziel-Cashflow",IF(AND(BI6="berechnet",CA6<BE6),"ROT: max. tragbar unter Bodenwert - Modell nicht gueltig",IF(X6<=CB6,"GRUEN: Preis unter max. tragbar (auch ohne Subvention)",IF(X6<=CA6,"GELB: nur mit Subvention tragbar",IF(X6<=CA6*(1+N($H$33)),"GELB: bis Toleranz darueber","ROT: deutlich ueber max. tragbar"))))))))))))))))
A7: =IF(NOT(ISNUMBER(MIETER!F12)),"",ROW()-2) | B7: =IF(NOT(ISNUMBER(MIETER!F12)),"",IF(MIETER!A12="","",MIETER!A12)) | C7: =IF(NOT(ISNUMBER(MIETER!F12)),"",IF(MIETER!B12="","",MIETER!B12)) | D7: =IF(NOT(ISNUMBER(MIETER!F12)),"",IF(MIETER!C12="","",MIETER!C12)) | E7: =IF(NOT(ISNUMBER(MIETER!F12)),"",IF(MIETER!D12="","",MIETER!D12)) | F7: =IF(NOT(ISNUMBER(MIETER!F12)),"",MIETER!F12) | K7: =IF(OR(NOT(ISNUMBER(F7)),NOT(ISNUMBER(J7)),NOT(ISNUMBER($H$29)),$H$29=0),"",J7/$H$29) | M7: =IF(OR(NOT(ISNUMBER(F7)),F7=0,NOT(ISNUMBER(VERKAUFSMATRIX!U10))),"",VERKAUFSMATRIX!U10/F7) | N7: =IF(OR(NOT(ISNUMBER(L7)),NOT(ISNUMBER(M7)),M7=0),"",L7/M7-1) | P7: =IF(OR(NOT(ISNUMBER(F7)),NOT(ISNUMBER(L7))),"",F7*L7+N(O7)) | S7: =IF(NOT(ISNUMBER(P7)),"",P7+N(Q7)+N(R7)) | U7: =IF(NOT(ISNUMBER(F7)),"",IF(ISNUMBER(T7),T7,IF(NOT(ISNUMBER($H$26)),"",$H$26))) | V7: =IF(OR(NOT(ISNUMBER(S7)),NOT(ISNUMBER(U7))),"",S7*U7) | W7: =IF(OR(NOT(ISNUMBER(S7)),NOT(ISNUMBER(U7))),"",S7*(1+U7)) | X7: =IF(NOT(ISNUMBER(W7)),"",W7-N(Q7)-N(R7)) | Y7: =IF(OR(NOT(ISNUMBER(S7)),NOT(ISNUMBER(F7)),F7=0),"",S7/F7) | Z7: =IF(OR(NOT(ISNUMBER(X7)),NOT(ISNUMBER(F7)),F7=0),"",X7/F7) | AA7: =IF(OR(NOT(ISNUMBER(X7)),NOT(ISNUMBER($H$34))),"",X7*MAX(1,$H$34)) | AB7: =IF(OR(NOT(ISNUMBER(W7)),NOT(ISNUMBER($H$34)),NOT(ISNUMBER($C$36))),"",W7*MAX(1,$H$34)*$C$36) | AC7: =IF(OR(NOT(ISNUMBER(W7)),NOT(ISNUMBER(AB7))),"",W7+AB7) | AD7: =IF(OR(NOT(ISNUMBER(W7)),NOT(ISNUMBER($H$34))),"",W7*$H$34) | AE7: =IF(OR(NOT(ISNUMBER(AC7)),NOT(ISNUMBER(AD7))),"",MAX(0,AC7-AD7)) | AF7: =IF(OR(NOT(ISNUMBER(AD7)),NOT(ISNUMBER(W7))),"",AD7-W7) | AH7: =IF(OR(NOT(ISNUMBER(MIETER!F12)),$G7="ja"),"",IF(NOT(ISNUMBER(MIETER!J12)),"",IF(ISNUMBER(AG7),MAX(MIETER!J12,AG7),MIETER!J12))) | AJ7: =IF(OR(NOT(ISNUMBER(AH7)),NOT(ISNUMBER(AI7))),"",MAX(0,AI7-AH7)) | AN7: =IF(NOT(ISNUMBER(F7)),"",IF(AND(NOT(ISNUMBER(AH7)),NOT(ISNUMBER(AL7)),NOT(ISNUMBER(AM7))),"",N(AH7)+N(AL7)+N(AM7))) | AO7: =IF(OR($G7="ja",NOT(ISNUMBER(AH7)),NOT(ISNUMBER(AN7))),"",AN7+N(AJ7)) | AP7: =IF(OR(NOT(ISNUMBER(AH7)),NOT(ISNUMBER(F7)),F7=0),"",AH7/F7) | AQ7: =IF(OR(NOT(ISNUMBER(MIETER!F12)),NOT(ISNUMBER(MIETER!I12))),"",MIETER!I12) | AR7: =IF(OR(NOT(ISNUMBER(AQ7)),$G7="ja",NOT(ISNUMBER($H$35))),"",EDATE(AQ7,$H$35)) | AT7: =IF(NOT(ISNUMBER(F7)),"",IF(ISNUMBER(AS7),AS7,IF(NOT(ISNUMBER(AR7)),"",MAX(0,(YEAR(AR7)-YEAR(TODAY()))*12+MONTH(AR7)-MONTH(TODAY()))))) | AU7: =IF(NOT(ISNUMBER(AT7)),"",IF(ISNUMBER(AK7),AK7*AT7,IF(NOT(ISNUMBER(AJ7)),"",AJ7*AT7))) | AV7: =IF(OR(NOT(ISNUMBER(AH7)),NOT(ISNUMBER(MIETER!$P$6))),"",ROUND(AH7*(1+MIETER!$P$6)^2,0)) | AY7: =IF(NOT(ISNUMBER(F7)),"",IF(ISNUMBER(AX7),AX7,IF(AND(ISNUMBER(AW7),ISNUMBER(AH7),AH7>0),AH7*AW7,IF(OR(NOT(ISNUMBER($C$62)),NOT(ISNUMBER($C$64))),"",$C$62+$C$64*F7/12)))) | BA7: =IF(NOT(ISNUMBER(AY7)),"",IF(ISNUMBER(AZ7),MIN(AY7,AZ7),IF(OR(NOT(ISNUMBER(F7)),NOT(ISNUMBER($C$64))),0,MIN(AY7,$C$64*F7/12)))) | BB7: =IF(OR(NOT(ISNUMBER(AY7)),NOT(ISNUMBER(AH7)),AH7=0),"",AY7/AH7) | BC7: =IF(NOT(ISNUMBER(AH7)),"",AH7*0.01) | BD7: =IF(OR(NOT(ISNUMBER(AH7)),NOT(ISNUMBER($C$28)),NOT(ISNUMBER(BY7)),BY7<=0),"",AH7*0.01*(1-$C$28)/BY7) | BE7: =IF(OR(NOT(ISNUMBER(K7)),NOT(ISNUMBER($H$30))),"",$H$30*K7) | BG7: =IF(OR(NOT(ISNUMBER(BE7)),NOT(ISNUMBER(X7)),X7<=0),"",1-BE7/X7) | BH7: =IF(NOT(ISNUMBER(X7)),"",IF(ISNUMBER(BF7),BF7,IF(AND(ISNUMBER(BE7),ISNUMBER(AA7),AA7>0),1-BE7/AA7,IF(NOT(ISNUMBER($C$31)),"",$C$31)))) | BI7: =IF(NOT(ISNUMBER(F7)),"",IF(ISNUMBER(BF7),"vertrag",IF(ISNUMBER(BE7),"berechnet","standard"))) | BK7: =IF(NOT(ISNUMBER(F7)),"",IF(ISNUMBER(BJ7),BJ7,IF(NOT(ISNUMBER($C$30)),"",$C$30))) | BL7: =IF(OR(NOT(ISNUMBER(AA7)),NOT(ISNUMBER(BH7)),NOT(ISNUMBER($C$36))),"",AA7*(1+$C$36)*BH7) | BM7: =IF(OR(NOT(ISNUMBER(BL7)),NOT(ISNUMBER(BK7)),NOT(ISNUMBER($C$36)),NOT(ISNUMBER($H$34))),"",(BL7*BK7+N(Q7)*MAX(1,$H$34)*(1+$C$36)*N($H$31)+N(R7)*MAX(1,$H$34)*(1+$C$36)*N($H$32))/12) | BN7: =IF(OR(NOT(ISNUMBER(AD7)),NOT(ISNUMBER($C$26))),"",AD7*$C$26/12) | BO7: =IF(OR(NOT(ISNUMBER(AD7)),NOT(ISNUMBER($C$26)),NOT(ISNUMBER($C$27))),"",ROUND(AD7*($C$26+$C$27)/12,0)) | BP7: =IF(OR(NOT(ISNUMBER(AO7)),NOT(ISNUMBER(BM7)),NOT(ISNUMBER(BN7)),NOT(ISNUMBER(AY7))),"",AO7-BN7-BM7-(AY7-N(BA7))) | BQ7: =IF(OR(NOT(ISNUMBER(BP7)),NOT(ISNUMBER($C$28))),"",ROUND(-BP7*$C$28,0)) | BR7: =IF(OR(NOT(ISNUMBER(BA7)),NOT(ISNUMBER($C$28))),"",BA7*$C$28) | BS7: =IF(OR(NOT(ISNUMBER(AO7)),NOT(ISNUMBER(BO7)),NOT(ISNUMBER(AY7))),"",ROUND(AO7,0)-BO7-ROUND(AY7,0)) | BT7: =IF(OR(NOT(ISNUMBER(BS7)),NOT(ISNUMBER(BQ7))),"",BS7+BQ7) | BU7: =IF(OR(NOT(ISNUMBER(AN7)),NOT(ISNUMBER(BO7)),NOT(ISNUMBER(AY7)),NOT(ISNUMBER(BP7)),NOT(ISNUMBER($C$28))),"",ROUND(AN7,0)-BO7-ROUND(AY7,0)+ROUND(-(BP7-N(AJ7))*$C$28,0)) | BV7: =IF(OR(NOT(ISNUMBER(AO7)),NOT(ISNUMBER(AY7)),NOT(ISNUMBER(BK7)),NOT(ISNUMBER($C$28)),NOT(ISNUMBER($C$36))),"",(AO7-AY7)*(1-$C$28)-$C$28*N(BA7)-IF(BI7="berechnet",$C$28*(1+$C$36)*BK7*N(BE7)/12,0)) | BW7: =IF(OR(NOT(ISNUMBER(F7)),NOT(ISNUMBER($C$26)),NOT(ISNUMBER($C$27)),NOT(ISNUMBER($C$28)),NOT(ISNUMBER($C$36))),"",($C$28*(1+$C$36)*(N(Q7)*N($H$31)+N(R7)*N($H$32))-(N(Q7)+N(R7))*(($C$26+$C$27)-$C$28*$C$26))/12) | BX7: =IF(OR(NOT(ISNUMBER(BK7)),NOT(ISNUMBER($C$26)),NOT(ISNUMBER($C$27)),NOT(ISNUMBER($C$28)),NOT(ISNUMBER($C$36)),BI7=""),"",(($C$26+$C$27)-$C$28*$C$26-$C$28*(1+$C$36)*BK7*IF(BI7="berechnet",1,IF(BI7="vertrag",BF7,$C$31)))/12) | BY7: =IF(OR(NOT(ISNUMBER(BX7)),NOT(ISNUMBER($C$34))),"",$C$34*BX7) | BZ7: =IF(OR($G7="ja",NOT(ISNUMBER(AH7)),NOT(ISNUMBER(BV7)),NOT(ISNUMBER(BW7)),NOT(ISNUMBER(BX7)),BX7<=0),"",(BV7-N($C$32)+BW7)/BX7) | CA7: =IF(OR($G7="ja",NOT(ISNUMBER(AH7)),NOT(ISNUMBER(BV7)),NOT(ISNUMBER(BW7)),NOT(ISNUMBER(BY7)),BY7<=0,NOT(ISNUMBER($C$34))),"",(BV7-N($C$32)+BW7*$C$34)/BY7) | CB7: =IF(OR(NOT(ISNUMBER(CA7)),NOT(ISNUMBER($C$28))),"",CA7-N(AJ7)*(1-$C$28)/BY7) | CC7: =IF(OR(NOT(ISNUMBER(CA7)),NOT(ISNUMBER(U7)),U7<=-1,NOT(ISNUMBER(F7)),F7=0),"",((CA7+N(Q7)+N(R7))/(1+U7)-N(Q7)-N(R7)-N(O7))/F7) | CD7: =IF(OR(NOT(ISNUMBER(L7)),NOT(ISNUMBER(CC7))),"",L7-CC7) | CE7: =IF(OR(NOT(ISNUMBER(W7)),NOT(ISNUMBER(AN7)),AN7=0),"",W7/(AN7*12)) | CF7: =IF(OR(NOT(ISNUMBER(W7)),NOT(ISNUMBER(AN7)),W7=0),"",AN7*12/W7) | CG7: =IF(NOT(ISNUMBER(F7)),"",IF($G7="ja","GRAU: Leerstand - keine Mietbasis",IF(AND(ISNUMBER(AH7),AH7=0),"GRAU: Ist-Miete 0 - Leerstand pruefen",IF(NOT(ISNUMBER(AH7)),"GRAU: Wohnungsmiete fehlt",IF(NOT(ISNUMBER(AJ7)),"GRAU: keine Sollmiete/Mietspiegel",IF(AND(ISNUMBER(AW7),ISNUMBER(AX7)),"GRAU: zwei Hausgeld-Quellen gesetzt",IF(AND(OR(ISNUMBER(AX7),ISNUMBER(AW7)),NOT(ISNUMBER(AZ7))),"GRAU: Ruecklagenanteil fehlt",IF(AND(AJ7>0,NOT(ISNUMBER(AT7))),"GRAU: Subventionsdauer unbekannt",IF(AND(ISNUMBER(BH7),BH7<=0),"ROT: Bodenwert uebersteigt Kaufpreis - Daten pruefen",IF(NOT(ISNUMBER(BT7)),"GRAU: Cashflow nicht rechenbar",IF(NOT(ISNUMBER(BZ7)),"GRAU: max. tragbar nicht rechenbar",IF(BZ7<=0,"ROT: kein tragbarer Preis bei diesem Ziel-Cashflow",IF(AND(BI7="berechnet",BZ7<BE7),"ROT: max. tragbar unter Bodenwert - Modell nicht gueltig",IF(X7<=BZ7-N(AJ7)*(1-$C$28)/BX7,"GRUEN: Preis unter max. tragbar (auch ohne Subvention)",IF(X7<=BZ7,"GELB: nur mit Subvention tragbar",IF(X7<=BZ7*(1+N($H$33)),"GELB: bis Toleranz darueber","ROT: deutlich ueber max. tragbar")))))))))))))))) | CH7: =IF(NOT(ISNUMBER(F7)),"",IF($G7="ja","GRAU: Leerstand - keine Mietbasis",IF(AND(ISNUMBER(AH7),AH7=0),"GRAU: Ist-Miete 0 - Leerstand pruefen",IF(NOT(ISNUMBER(AH7)),"GRAU: Wohnungsmiete fehlt",IF(NOT(ISNUMBER(AJ7)),"GRAU: keine Sollmiete/Mietspiegel",IF(AND(ISNUMBER(AW7),ISNUMBER(AX7)),"GRAU: zwei Hausgeld-Quellen gesetzt",IF(AND(OR(ISNUMBER(AX7),ISNUMBER(AW7)),NOT(ISNUMBER(AZ7))),"GRAU: Ruecklagenanteil fehlt",IF(AND(AJ7>0,NOT(ISNUMBER(AT7))),"GRAU: Subventionsdauer unbekannt",IF(AND(ISNUMBER(BH7),BH7<=0),"ROT: Bodenwert uebersteigt Kaufpreis - Daten pruefen",IF(NOT(ISNUMBER(BT7)),"GRAU: Cashflow nicht rechenbar",IF(NOT(ISNUMBER(CA7)),"GRAU: max. tragbar nicht rechenbar",IF(CA7<=0,"ROT: kein tragbarer Preis bei diesem Ziel-Cashflow",IF(AND(BI7="berechnet",CA7<BE7),"ROT: max. tragbar unter Bodenwert - Modell nicht gueltig",IF(X7<=CB7,"GRUEN: Preis unter max. tragbar (auch ohne Subvention)",IF(X7<=CA7,"GELB: nur mit Subvention tragbar",IF(X7<=CA7*(1+N($H$33)),"GELB: bis Toleranz darueber","ROT: deutlich ueber max. tragbar"))))))))))))))))
A8: =IF(NOT(ISNUMBER(MIETER!F13)),"",ROW()-2) | B8: =IF(NOT(ISNUMBER(MIETER!F13)),"",IF(MIETER!A13="","",MIETER!A13)) | C8: =IF(NOT(ISNUMBER(MIETER!F13)),"",IF(MIETER!B13="","",MIETER!B13)) | D8: =IF(NOT(ISNUMBER(MIETER!F13)),"",IF(MIETER!C13="","",MIETER!C13)) | E8: =IF(NOT(ISNUMBER(MIETER!F13)),"",IF(MIETER!D13="","",MIETER!D13)) | F8: =IF(NOT(ISNUMBER(MIETER!F13)),"",MIETER!F13) | K8: =IF(OR(NOT(ISNUMBER(F8)),NOT(ISNUMBER(J8)),NOT(ISNUMBER($H$29)),$H$29=0),"",J8/$H$29) | M8: =IF(OR(NOT(ISNUMBER(F8)),F8=0,NOT(ISNUMBER(VERKAUFSMATRIX!U11))),"",VERKAUFSMATRIX!U11/F8) | N8: =IF(OR(NOT(ISNUMBER(L8)),NOT(ISNUMBER(M8)),M8=0),"",L8/M8-1) | P8: =IF(OR(NOT(ISNUMBER(F8)),NOT(ISNUMBER(L8))),"",F8*L8+N(O8)) | S8: =IF(NOT(ISNUMBER(P8)),"",P8+N(Q8)+N(R8)) | U8: =IF(NOT(ISNUMBER(F8)),"",IF(ISNUMBER(T8),T8,IF(NOT(ISNUMBER($H$26)),"",$H$26))) | V8: =IF(OR(NOT(ISNUMBER(S8)),NOT(ISNUMBER(U8))),"",S8*U8) | W8: =IF(OR(NOT(ISNUMBER(S8)),NOT(ISNUMBER(U8))),"",S8*(1+U8)) | X8: =IF(NOT(ISNUMBER(W8)),"",W8-N(Q8)-N(R8)) | Y8: =IF(OR(NOT(ISNUMBER(S8)),NOT(ISNUMBER(F8)),F8=0),"",S8/F8) | Z8: =IF(OR(NOT(ISNUMBER(X8)),NOT(ISNUMBER(F8)),F8=0),"",X8/F8) | AA8: =IF(OR(NOT(ISNUMBER(X8)),NOT(ISNUMBER($H$34))),"",X8*MAX(1,$H$34)) | AB8: =IF(OR(NOT(ISNUMBER(W8)),NOT(ISNUMBER($H$34)),NOT(ISNUMBER($C$36))),"",W8*MAX(1,$H$34)*$C$36) | AC8: =IF(OR(NOT(ISNUMBER(W8)),NOT(ISNUMBER(AB8))),"",W8+AB8) | AD8: =IF(OR(NOT(ISNUMBER(W8)),NOT(ISNUMBER($H$34))),"",W8*$H$34) | AE8: =IF(OR(NOT(ISNUMBER(AC8)),NOT(ISNUMBER(AD8))),"",MAX(0,AC8-AD8)) | AF8: =IF(OR(NOT(ISNUMBER(AD8)),NOT(ISNUMBER(W8))),"",AD8-W8) | AH8: =IF(OR(NOT(ISNUMBER(MIETER!F13)),$G8="ja"),"",IF(NOT(ISNUMBER(MIETER!J13)),"",IF(ISNUMBER(AG8),MAX(MIETER!J13,AG8),MIETER!J13))) | AJ8: =IF(OR(NOT(ISNUMBER(AH8)),NOT(ISNUMBER(AI8))),"",MAX(0,AI8-AH8)) | AN8: =IF(NOT(ISNUMBER(F8)),"",IF(AND(NOT(ISNUMBER(AH8)),NOT(ISNUMBER(AL8)),NOT(ISNUMBER(AM8))),"",N(AH8)+N(AL8)+N(AM8))) | AO8: =IF(OR($G8="ja",NOT(ISNUMBER(AH8)),NOT(ISNUMBER(AN8))),"",AN8+N(AJ8)) | AP8: =IF(OR(NOT(ISNUMBER(AH8)),NOT(ISNUMBER(F8)),F8=0),"",AH8/F8) | AQ8: =IF(OR(NOT(ISNUMBER(MIETER!F13)),NOT(ISNUMBER(MIETER!I13))),"",MIETER!I13) | AR8: =IF(OR(NOT(ISNUMBER(AQ8)),$G8="ja",NOT(ISNUMBER($H$35))),"",EDATE(AQ8,$H$35)) | AT8: =IF(NOT(ISNUMBER(F8)),"",IF(ISNUMBER(AS8),AS8,IF(NOT(ISNUMBER(AR8)),"",MAX(0,(YEAR(AR8)-YEAR(TODAY()))*12+MONTH(AR8)-MONTH(TODAY()))))) | AU8: =IF(NOT(ISNUMBER(AT8)),"",IF(ISNUMBER(AK8),AK8*AT8,IF(NOT(ISNUMBER(AJ8)),"",AJ8*AT8))) | AV8: =IF(OR(NOT(ISNUMBER(AH8)),NOT(ISNUMBER(MIETER!$P$6))),"",ROUND(AH8*(1+MIETER!$P$6)^2,0)) | AY8: =IF(NOT(ISNUMBER(F8)),"",IF(ISNUMBER(AX8),AX8,IF(AND(ISNUMBER(AW8),ISNUMBER(AH8),AH8>0),AH8*AW8,IF(OR(NOT(ISNUMBER($C$62)),NOT(ISNUMBER($C$64))),"",$C$62+$C$64*F8/12)))) | BA8: =IF(NOT(ISNUMBER(AY8)),"",IF(ISNUMBER(AZ8),MIN(AY8,AZ8),IF(OR(NOT(ISNUMBER(F8)),NOT(ISNUMBER($C$64))),0,MIN(AY8,$C$64*F8/12)))) | BB8: =IF(OR(NOT(ISNUMBER(AY8)),NOT(ISNUMBER(AH8)),AH8=0),"",AY8/AH8) | BC8: =IF(NOT(ISNUMBER(AH8)),"",AH8*0.01) | BD8: =IF(OR(NOT(ISNUMBER(AH8)),NOT(ISNUMBER($C$28)),NOT(ISNUMBER(BY8)),BY8<=0),"",AH8*0.01*(1-$C$28)/BY8) | BE8: =IF(OR(NOT(ISNUMBER(K8)),NOT(ISNUMBER($H$30))),"",$H$30*K8) | BG8: =IF(OR(NOT(ISNUMBER(BE8)),NOT(ISNUMBER(X8)),X8<=0),"",1-BE8/X8) | BH8: =IF(NOT(ISNUMBER(X8)),"",IF(ISNUMBER(BF8),BF8,IF(AND(ISNUMBER(BE8),ISNUMBER(AA8),AA8>0),1-BE8/AA8,IF(NOT(ISNUMBER($C$31)),"",$C$31)))) | BI8: =IF(NOT(ISNUMBER(F8)),"",IF(ISNUMBER(BF8),"vertrag",IF(ISNUMBER(BE8),"berechnet","standard"))) | BK8: =IF(NOT(ISNUMBER(F8)),"",IF(ISNUMBER(BJ8),BJ8,IF(NOT(ISNUMBER($C$30)),"",$C$30))) | BL8: =IF(OR(NOT(ISNUMBER(AA8)),NOT(ISNUMBER(BH8)),NOT(ISNUMBER($C$36))),"",AA8*(1+$C$36)*BH8) | BM8: =IF(OR(NOT(ISNUMBER(BL8)),NOT(ISNUMBER(BK8)),NOT(ISNUMBER($C$36)),NOT(ISNUMBER($H$34))),"",(BL8*BK8+N(Q8)*MAX(1,$H$34)*(1+$C$36)*N($H$31)+N(R8)*MAX(1,$H$34)*(1+$C$36)*N($H$32))/12) | BN8: =IF(OR(NOT(ISNUMBER(AD8)),NOT(ISNUMBER($C$26))),"",AD8*$C$26/12) | BO8: =IF(OR(NOT(ISNUMBER(AD8)),NOT(ISNUMBER($C$26)),NOT(ISNUMBER($C$27))),"",ROUND(AD8*($C$26+$C$27)/12,0)) | BP8: =IF(OR(NOT(ISNUMBER(AO8)),NOT(ISNUMBER(BM8)),NOT(ISNUMBER(BN8)),NOT(ISNUMBER(AY8))),"",AO8-BN8-BM8-(AY8-N(BA8))) | BQ8: =IF(OR(NOT(ISNUMBER(BP8)),NOT(ISNUMBER($C$28))),"",ROUND(-BP8*$C$28,0)) | BR8: =IF(OR(NOT(ISNUMBER(BA8)),NOT(ISNUMBER($C$28))),"",BA8*$C$28) | BS8: =IF(OR(NOT(ISNUMBER(AO8)),NOT(ISNUMBER(BO8)),NOT(ISNUMBER(AY8))),"",ROUND(AO8,0)-BO8-ROUND(AY8,0)) | BT8: =IF(OR(NOT(ISNUMBER(BS8)),NOT(ISNUMBER(BQ8))),"",BS8+BQ8) | BU8: =IF(OR(NOT(ISNUMBER(AN8)),NOT(ISNUMBER(BO8)),NOT(ISNUMBER(AY8)),NOT(ISNUMBER(BP8)),NOT(ISNUMBER($C$28))),"",ROUND(AN8,0)-BO8-ROUND(AY8,0)+ROUND(-(BP8-N(AJ8))*$C$28,0)) | BV8: =IF(OR(NOT(ISNUMBER(AO8)),NOT(ISNUMBER(AY8)),NOT(ISNUMBER(BK8)),NOT(ISNUMBER($C$28)),NOT(ISNUMBER($C$36))),"",(AO8-AY8)*(1-$C$28)-$C$28*N(BA8)-IF(BI8="berechnet",$C$28*(1+$C$36)*BK8*N(BE8)/12,0)) | BW8: =IF(OR(NOT(ISNUMBER(F8)),NOT(ISNUMBER($C$26)),NOT(ISNUMBER($C$27)),NOT(ISNUMBER($C$28)),NOT(ISNUMBER($C$36))),"",($C$28*(1+$C$36)*(N(Q8)*N($H$31)+N(R8)*N($H$32))-(N(Q8)+N(R8))*(($C$26+$C$27)-$C$28*$C$26))/12) | BX8: =IF(OR(NOT(ISNUMBER(BK8)),NOT(ISNUMBER($C$26)),NOT(ISNUMBER($C$27)),NOT(ISNUMBER($C$28)),NOT(ISNUMBER($C$36)),BI8=""),"",(($C$26+$C$27)-$C$28*$C$26-$C$28*(1+$C$36)*BK8*IF(BI8="berechnet",1,IF(BI8="vertrag",BF8,$C$31)))/12) | BY8: =IF(OR(NOT(ISNUMBER(BX8)),NOT(ISNUMBER($C$34))),"",$C$34*BX8) | BZ8: =IF(OR($G8="ja",NOT(ISNUMBER(AH8)),NOT(ISNUMBER(BV8)),NOT(ISNUMBER(BW8)),NOT(ISNUMBER(BX8)),BX8<=0),"",(BV8-N($C$32)+BW8)/BX8) | CA8: =IF(OR($G8="ja",NOT(ISNUMBER(AH8)),NOT(ISNUMBER(BV8)),NOT(ISNUMBER(BW8)),NOT(ISNUMBER(BY8)),BY8<=0,NOT(ISNUMBER($C$34))),"",(BV8-N($C$32)+BW8*$C$34)/BY8) | CB8: =IF(OR(NOT(ISNUMBER(CA8)),NOT(ISNUMBER($C$28))),"",CA8-N(AJ8)*(1-$C$28)/BY8) | CC8: =IF(OR(NOT(ISNUMBER(CA8)),NOT(ISNUMBER(U8)),U8<=-1,NOT(ISNUMBER(F8)),F8=0),"",((CA8+N(Q8)+N(R8))/(1+U8)-N(Q8)-N(R8)-N(O8))/F8) | CD8: =IF(OR(NOT(ISNUMBER(L8)),NOT(ISNUMBER(CC8))),"",L8-CC8) | CE8: =IF(OR(NOT(ISNUMBER(W8)),NOT(ISNUMBER(AN8)),AN8=0),"",W8/(AN8*12)) | CF8: =IF(OR(NOT(ISNUMBER(W8)),NOT(ISNUMBER(AN8)),W8=0),"",AN8*12/W8) | CG8: =IF(NOT(ISNUMBER(F8)),"",IF($G8="ja","GRAU: Leerstand - keine Mietbasis",IF(AND(ISNUMBER(AH8),AH8=0),"GRAU: Ist-Miete 0 - Leerstand pruefen",IF(NOT(ISNUMBER(AH8)),"GRAU: Wohnungsmiete fehlt",IF(NOT(ISNUMBER(AJ8)),"GRAU: keine Sollmiete/Mietspiegel",IF(AND(ISNUMBER(AW8),ISNUMBER(AX8)),"GRAU: zwei Hausgeld-Quellen gesetzt",IF(AND(OR(ISNUMBER(AX8),ISNUMBER(AW8)),NOT(ISNUMBER(AZ8))),"GRAU: Ruecklagenanteil fehlt",IF(AND(AJ8>0,NOT(ISNUMBER(AT8))),"GRAU: Subventionsdauer unbekannt",IF(AND(ISNUMBER(BH8),BH8<=0),"ROT: Bodenwert uebersteigt Kaufpreis - Daten pruefen",IF(NOT(ISNUMBER(BT8)),"GRAU: Cashflow nicht rechenbar",IF(NOT(ISNUMBER(BZ8)),"GRAU: max. tragbar nicht rechenbar",IF(BZ8<=0,"ROT: kein tragbarer Preis bei diesem Ziel-Cashflow",IF(AND(BI8="berechnet",BZ8<BE8),"ROT: max. tragbar unter Bodenwert - Modell nicht gueltig",IF(X8<=BZ8-N(AJ8)*(1-$C$28)/BX8,"GRUEN: Preis unter max. tragbar (auch ohne Subvention)",IF(X8<=BZ8,"GELB: nur mit Subvention tragbar",IF(X8<=BZ8*(1+N($H$33)),"GELB: bis Toleranz darueber","ROT: deutlich ueber max. tragbar")))))))))))))))) | CH8: =IF(NOT(ISNUMBER(F8)),"",IF($G8="ja","GRAU: Leerstand - keine Mietbasis",IF(AND(ISNUMBER(AH8),AH8=0),"GRAU: Ist-Miete 0 - Leerstand pruefen",IF(NOT(ISNUMBER(AH8)),"GRAU: Wohnungsmiete fehlt",IF(NOT(ISNUMBER(AJ8)),"GRAU: keine Sollmiete/Mietspiegel",IF(AND(ISNUMBER(AW8),ISNUMBER(AX8)),"GRAU: zwei Hausgeld-Quellen gesetzt",IF(AND(OR(ISNUMBER(AX8),ISNUMBER(AW8)),NOT(ISNUMBER(AZ8))),"GRAU: Ruecklagenanteil fehlt",IF(AND(AJ8>0,NOT(ISNUMBER(AT8))),"GRAU: Subventionsdauer unbekannt",IF(AND(ISNUMBER(BH8),BH8<=0),"ROT: Bodenwert uebersteigt Kaufpreis - Daten pruefen",IF(NOT(ISNUMBER(BT8)),"GRAU: Cashflow nicht rechenbar",IF(NOT(ISNUMBER(CA8)),"GRAU: max. tragbar nicht rechenbar",IF(CA8<=0,"ROT: kein tragbarer Preis bei diesem Ziel-Cashflow",IF(AND(BI8="berechnet",CA8<BE8),"ROT: max. tragbar unter Bodenwert - Modell nicht gueltig",IF(X8<=CB8,"GRUEN: Preis unter max. tragbar (auch ohne Subvention)",IF(X8<=CA8,"GELB: nur mit Subvention tragbar",IF(X8<=CA8*(1+N($H$33)),"GELB: bis Toleranz darueber","ROT: deutlich ueber max. tragbar"))))))))))))))))
A9: =IF(NOT(ISNUMBER(MIETER!F14)),"",ROW()-2) | B9: =IF(NOT(ISNUMBER(MIETER!F14)),"",IF(MIETER!A14="","",MIETER!A14)) | C9: =IF(NOT(ISNUMBER(MIETER!F14)),"",IF(MIETER!B14="","",MIETER!B14)) | D9: =IF(NOT(ISNUMBER(MIETER!F14)),"",IF(MIETER!C14="","",MIETER!C14)) | E9: =IF(NOT(ISNUMBER(MIETER!F14)),"",IF(MIETER!D14="","",MIETER!D14)) | F9: =IF(NOT(ISNUMBER(MIETER!F14)),"",MIETER!F14) | K9: =IF(OR(NOT(ISNUMBER(F9)),NOT(ISNUMBER(J9)),NOT(ISNUMBER($H$29)),$H$29=0),"",J9/$H$29) | M9: =IF(OR(NOT(ISNUMBER(F9)),F9=0,NOT(ISNUMBER(VERKAUFSMATRIX!U12))),"",VERKAUFSMATRIX!U12/F9) | N9: =IF(OR(NOT(ISNUMBER(L9)),NOT(ISNUMBER(M9)),M9=0),"",L9/M9-1) | P9: =IF(OR(NOT(ISNUMBER(F9)),NOT(ISNUMBER(L9))),"",F9*L9+N(O9)) | S9: =IF(NOT(ISNUMBER(P9)),"",P9+N(Q9)+N(R9)) | U9: =IF(NOT(ISNUMBER(F9)),"",IF(ISNUMBER(T9),T9,IF(NOT(ISNUMBER($H$26)),"",$H$26))) | V9: =IF(OR(NOT(ISNUMBER(S9)),NOT(ISNUMBER(U9))),"",S9*U9) | W9: =IF(OR(NOT(ISNUMBER(S9)),NOT(ISNUMBER(U9))),"",S9*(1+U9)) | X9: =IF(NOT(ISNUMBER(W9)),"",W9-N(Q9)-N(R9)) | Y9: =IF(OR(NOT(ISNUMBER(S9)),NOT(ISNUMBER(F9)),F9=0),"",S9/F9) | Z9: =IF(OR(NOT(ISNUMBER(X9)),NOT(ISNUMBER(F9)),F9=0),"",X9/F9) | AA9: =IF(OR(NOT(ISNUMBER(X9)),NOT(ISNUMBER($H$34))),"",X9*MAX(1,$H$34)) | AB9: =IF(OR(NOT(ISNUMBER(W9)),NOT(ISNUMBER($H$34)),NOT(ISNUMBER($C$36))),"",W9*MAX(1,$H$34)*$C$36) | AC9: =IF(OR(NOT(ISNUMBER(W9)),NOT(ISNUMBER(AB9))),"",W9+AB9) | AD9: =IF(OR(NOT(ISNUMBER(W9)),NOT(ISNUMBER($H$34))),"",W9*$H$34) | AE9: =IF(OR(NOT(ISNUMBER(AC9)),NOT(ISNUMBER(AD9))),"",MAX(0,AC9-AD9)) | AF9: =IF(OR(NOT(ISNUMBER(AD9)),NOT(ISNUMBER(W9))),"",AD9-W9) | AH9: =IF(OR(NOT(ISNUMBER(MIETER!F14)),$G9="ja"),"",IF(NOT(ISNUMBER(MIETER!J14)),"",IF(ISNUMBER(AG9),MAX(MIETER!J14,AG9),MIETER!J14))) | AJ9: =IF(OR(NOT(ISNUMBER(AH9)),NOT(ISNUMBER(AI9))),"",MAX(0,AI9-AH9)) | AN9: =IF(NOT(ISNUMBER(F9)),"",IF(AND(NOT(ISNUMBER(AH9)),NOT(ISNUMBER(AL9)),NOT(ISNUMBER(AM9))),"",N(AH9)+N(AL9)+N(AM9))) | AO9: =IF(OR($G9="ja",NOT(ISNUMBER(AH9)),NOT(ISNUMBER(AN9))),"",AN9+N(AJ9)) | AP9: =IF(OR(NOT(ISNUMBER(AH9)),NOT(ISNUMBER(F9)),F9=0),"",AH9/F9) | AQ9: =IF(OR(NOT(ISNUMBER(MIETER!F14)),NOT(ISNUMBER(MIETER!I14))),"",MIETER!I14) | AR9: =IF(OR(NOT(ISNUMBER(AQ9)),$G9="ja",NOT(ISNUMBER($H$35))),"",EDATE(AQ9,$H$35)) | AT9: =IF(NOT(ISNUMBER(F9)),"",IF(ISNUMBER(AS9),AS9,IF(NOT(ISNUMBER(AR9)),"",MAX(0,(YEAR(AR9)-YEAR(TODAY()))*12+MONTH(AR9)-MONTH(TODAY()))))) | AU9: =IF(NOT(ISNUMBER(AT9)),"",IF(ISNUMBER(AK9),AK9*AT9,IF(NOT(ISNUMBER(AJ9)),"",AJ9*AT9))) | AV9: =IF(OR(NOT(ISNUMBER(AH9)),NOT(ISNUMBER(MIETER!$P$6))),"",ROUND(AH9*(1+MIETER!$P$6)^2,0)) | AY9: =IF(NOT(ISNUMBER(F9)),"",IF(ISNUMBER(AX9),AX9,IF(AND(ISNUMBER(AW9),ISNUMBER(AH9),AH9>0),AH9*AW9,IF(OR(NOT(ISNUMBER($C$62)),NOT(ISNUMBER($C$64))),"",$C$62+$C$64*F9/12)))) | BA9: =IF(NOT(ISNUMBER(AY9)),"",IF(ISNUMBER(AZ9),MIN(AY9,AZ9),IF(OR(NOT(ISNUMBER(F9)),NOT(ISNUMBER($C$64))),0,MIN(AY9,$C$64*F9/12)))) | BB9: =IF(OR(NOT(ISNUMBER(AY9)),NOT(ISNUMBER(AH9)),AH9=0),"",AY9/AH9) | BC9: =IF(NOT(ISNUMBER(AH9)),"",AH9*0.01) | BD9: =IF(OR(NOT(ISNUMBER(AH9)),NOT(ISNUMBER($C$28)),NOT(ISNUMBER(BY9)),BY9<=0),"",AH9*0.01*(1-$C$28)/BY9) | BE9: =IF(OR(NOT(ISNUMBER(K9)),NOT(ISNUMBER($H$30))),"",$H$30*K9) | BG9: =IF(OR(NOT(ISNUMBER(BE9)),NOT(ISNUMBER(X9)),X9<=0),"",1-BE9/X9) | BH9: =IF(NOT(ISNUMBER(X9)),"",IF(ISNUMBER(BF9),BF9,IF(AND(ISNUMBER(BE9),ISNUMBER(AA9),AA9>0),1-BE9/AA9,IF(NOT(ISNUMBER($C$31)),"",$C$31)))) | BI9: =IF(NOT(ISNUMBER(F9)),"",IF(ISNUMBER(BF9),"vertrag",IF(ISNUMBER(BE9),"berechnet","standard"))) | BK9: =IF(NOT(ISNUMBER(F9)),"",IF(ISNUMBER(BJ9),BJ9,IF(NOT(ISNUMBER($C$30)),"",$C$30))) | BL9: =IF(OR(NOT(ISNUMBER(AA9)),NOT(ISNUMBER(BH9)),NOT(ISNUMBER($C$36))),"",AA9*(1+$C$36)*BH9) | BM9: =IF(OR(NOT(ISNUMBER(BL9)),NOT(ISNUMBER(BK9)),NOT(ISNUMBER($C$36)),NOT(ISNUMBER($H$34))),"",(BL9*BK9+N(Q9)*MAX(1,$H$34)*(1+$C$36)*N($H$31)+N(R9)*MAX(1,$H$34)*(1+$C$36)*N($H$32))/12) | BN9: =IF(OR(NOT(ISNUMBER(AD9)),NOT(ISNUMBER($C$26))),"",AD9*$C$26/12) | BO9: =IF(OR(NOT(ISNUMBER(AD9)),NOT(ISNUMBER($C$26)),NOT(ISNUMBER($C$27))),"",ROUND(AD9*($C$26+$C$27)/12,0)) | BP9: =IF(OR(NOT(ISNUMBER(AO9)),NOT(ISNUMBER(BM9)),NOT(ISNUMBER(BN9)),NOT(ISNUMBER(AY9))),"",AO9-BN9-BM9-(AY9-N(BA9))) | BQ9: =IF(OR(NOT(ISNUMBER(BP9)),NOT(ISNUMBER($C$28))),"",ROUND(-BP9*$C$28,0)) | BR9: =IF(OR(NOT(ISNUMBER(BA9)),NOT(ISNUMBER($C$28))),"",BA9*$C$28) | BS9: =IF(OR(NOT(ISNUMBER(AO9)),NOT(ISNUMBER(BO9)),NOT(ISNUMBER(AY9))),"",ROUND(AO9,0)-BO9-ROUND(AY9,0)) | BT9: =IF(OR(NOT(ISNUMBER(BS9)),NOT(ISNUMBER(BQ9))),"",BS9+BQ9) | BU9: =IF(OR(NOT(ISNUMBER(AN9)),NOT(ISNUMBER(BO9)),NOT(ISNUMBER(AY9)),NOT(ISNUMBER(BP9)),NOT(ISNUMBER($C$28))),"",ROUND(AN9,0)-BO9-ROUND(AY9,0)+ROUND(-(BP9-N(AJ9))*$C$28,0)) | BV9: =IF(OR(NOT(ISNUMBER(AO9)),NOT(ISNUMBER(AY9)),NOT(ISNUMBER(BK9)),NOT(ISNUMBER($C$28)),NOT(ISNUMBER($C$36))),"",(AO9-AY9)*(1-$C$28)-$C$28*N(BA9)-IF(BI9="berechnet",$C$28*(1+$C$36)*BK9*N(BE9)/12,0)) | BW9: =IF(OR(NOT(ISNUMBER(F9)),NOT(ISNUMBER($C$26)),NOT(ISNUMBER($C$27)),NOT(ISNUMBER($C$28)),NOT(ISNUMBER($C$36))),"",($C$28*(1+$C$36)*(N(Q9)*N($H$31)+N(R9)*N($H$32))-(N(Q9)+N(R9))*(($C$26+$C$27)-$C$28*$C$26))/12) | BX9: =IF(OR(NOT(ISNUMBER(BK9)),NOT(ISNUMBER($C$26)),NOT(ISNUMBER($C$27)),NOT(ISNUMBER($C$28)),NOT(ISNUMBER($C$36)),BI9=""),"",(($C$26+$C$27)-$C$28*$C$26-$C$28*(1+$C$36)*BK9*IF(BI9="berechnet",1,IF(BI9="vertrag",BF9,$C$31)))/12) | BY9: =IF(OR(NOT(ISNUMBER(BX9)),NOT(ISNUMBER($C$34))),"",$C$34*BX9) | BZ9: =IF(OR($G9="ja",NOT(ISNUMBER(AH9)),NOT(ISNUMBER(BV9)),NOT(ISNUMBER(BW9)),NOT(ISNUMBER(BX9)),BX9<=0),"",(BV9-N($C$32)+BW9)/BX9) | CA9: =IF(OR($G9="ja",NOT(ISNUMBER(AH9)),NOT(ISNUMBER(BV9)),NOT(ISNUMBER(BW9)),NOT(ISNUMBER(BY9)),BY9<=0,NOT(ISNUMBER($C$34))),"",(BV9-N($C$32)+BW9*$C$34)/BY9) | CB9: =IF(OR(NOT(ISNUMBER(CA9)),NOT(ISNUMBER($C$28))),"",CA9-N(AJ9)*(1-$C$28)/BY9) | CC9: =IF(OR(NOT(ISNUMBER(CA9)),NOT(ISNUMBER(U9)),U9<=-1,NOT(ISNUMBER(F9)),F9=0),"",((CA9+N(Q9)+N(R9))/(1+U9)-N(Q9)-N(R9)-N(O9))/F9) | CD9: =IF(OR(NOT(ISNUMBER(L9)),NOT(ISNUMBER(CC9))),"",L9-CC9) | CE9: =IF(OR(NOT(ISNUMBER(W9)),NOT(ISNUMBER(AN9)),AN9=0),"",W9/(AN9*12)) | CF9: =IF(OR(NOT(ISNUMBER(W9)),NOT(ISNUMBER(AN9)),W9=0),"",AN9*12/W9) | CG9: =IF(NOT(ISNUMBER(F9)),"",IF($G9="ja","GRAU: Leerstand - keine Mietbasis",IF(AND(ISNUMBER(AH9),AH9=0),"GRAU: Ist-Miete 0 - Leerstand pruefen",IF(NOT(ISNUMBER(AH9)),"GRAU: Wohnungsmiete fehlt",IF(NOT(ISNUMBER(AJ9)),"GRAU: keine Sollmiete/Mietspiegel",IF(AND(ISNUMBER(AW9),ISNUMBER(AX9)),"GRAU: zwei Hausgeld-Quellen gesetzt",IF(AND(OR(ISNUMBER(AX9),ISNUMBER(AW9)),NOT(ISNUMBER(AZ9))),"GRAU: Ruecklagenanteil fehlt",IF(AND(AJ9>0,NOT(ISNUMBER(AT9))),"GRAU: Subventionsdauer unbekannt",IF(AND(ISNUMBER(BH9),BH9<=0),"ROT: Bodenwert uebersteigt Kaufpreis - Daten pruefen",IF(NOT(ISNUMBER(BT9)),"GRAU: Cashflow nicht rechenbar",IF(NOT(ISNUMBER(BZ9)),"GRAU: max. tragbar nicht rechenbar",IF(BZ9<=0,"ROT: kein tragbarer Preis bei diesem Ziel-Cashflow",IF(AND(BI9="berechnet",BZ9<BE9),"ROT: max. tragbar unter Bodenwert - Modell nicht gueltig",IF(X9<=BZ9-N(AJ9)*(1-$C$28)/BX9,"GRUEN: Preis unter max. tragbar (auch ohne Subvention)",IF(X9<=BZ9,"GELB: nur mit Subvention tragbar",IF(X9<=BZ9*(1+N($H$33)),"GELB: bis Toleranz darueber","ROT: deutlich ueber max. tragbar")))))))))))))))) | CH9: =IF(NOT(ISNUMBER(F9)),"",IF($G9="ja","GRAU: Leerstand - keine Mietbasis",IF(AND(ISNUMBER(AH9),AH9=0),"GRAU: Ist-Miete 0 - Leerstand pruefen",IF(NOT(ISNUMBER(AH9)),"GRAU: Wohnungsmiete fehlt",IF(NOT(ISNUMBER(AJ9)),"GRAU: keine Sollmiete/Mietspiegel",IF(AND(ISNUMBER(AW9),ISNUMBER(AX9)),"GRAU: zwei Hausgeld-Quellen gesetzt",IF(AND(OR(ISNUMBER(AX9),ISNUMBER(AW9)),NOT(ISNUMBER(AZ9))),"GRAU: Ruecklagenanteil fehlt",IF(AND(AJ9>0,NOT(ISNUMBER(AT9))),"GRAU: Subventionsdauer unbekannt",IF(AND(ISNUMBER(BH9),BH9<=0),"ROT: Bodenwert uebersteigt Kaufpreis - Daten pruefen",IF(NOT(ISNUMBER(BT9)),"GRAU: Cashflow nicht rechenbar",IF(NOT(ISNUMBER(CA9)),"GRAU: max. tragbar nicht rechenbar",IF(CA9<=0,"ROT: kein tragbarer Preis bei diesem Ziel-Cashflow",IF(AND(BI9="berechnet",CA9<BE9),"ROT: max. tragbar unter Bodenwert - Modell nicht gueltig",IF(X9<=CB9,"GRUEN: Preis unter max. tragbar (auch ohne Subvention)",IF(X9<=CA9,"GELB: nur mit Subvention tragbar",IF(X9<=CA9*(1+N($H$33)),"GELB: bis Toleranz darueber","ROT: deutlich ueber max. tragbar"))))))))))))))))
A10: =IF(NOT(ISNUMBER(MIETER!F15)),"",ROW()-2) | B10: =IF(NOT(ISNUMBER(MIETER!F15)),"",IF(MIETER!A15="","",MIETER!A15)) | C10: =IF(NOT(ISNUMBER(MIETER!F15)),"",IF(MIETER!B15="","",MIETER!B15)) | D10: =IF(NOT(ISNUMBER(MIETER!F15)),"",IF(MIETER!C15="","",MIETER!C15)) | E10: =IF(NOT(ISNUMBER(MIETER!F15)),"",IF(MIETER!D15="","",MIETER!D15)) | F10: =IF(NOT(ISNUMBER(MIETER!F15)),"",MIETER!F15) | K10: =IF(OR(NOT(ISNUMBER(F10)),NOT(ISNUMBER(J10)),NOT(ISNUMBER($H$29)),$H$29=0),"",J10/$H$29) | M10: =IF(OR(NOT(ISNUMBER(F10)),F10=0,NOT(ISNUMBER(VERKAUFSMATRIX!U13))),"",VERKAUFSMATRIX!U13/F10) | N10: =IF(OR(NOT(ISNUMBER(L10)),NOT(ISNUMBER(M10)),M10=0),"",L10/M10-1) | P10: =IF(OR(NOT(ISNUMBER(F10)),NOT(ISNUMBER(L10))),"",F10*L10+N(O10)) | S10: =IF(NOT(ISNUMBER(P10)),"",P10+N(Q10)+N(R10)) | U10: =IF(NOT(ISNUMBER(F10)),"",IF(ISNUMBER(T10),T10,IF(NOT(ISNUMBER($H$26)),"",$H$26))) | V10: =IF(OR(NOT(ISNUMBER(S10)),NOT(ISNUMBER(U10))),"",S10*U10) | W10: =IF(OR(NOT(ISNUMBER(S10)),NOT(ISNUMBER(U10))),"",S10*(1+U10)) | X10: =IF(NOT(ISNUMBER(W10)),"",W10-N(Q10)-N(R10)) | Y10: =IF(OR(NOT(ISNUMBER(S10)),NOT(ISNUMBER(F10)),F10=0),"",S10/F10) | Z10: =IF(OR(NOT(ISNUMBER(X10)),NOT(ISNUMBER(F10)),F10=0),"",X10/F10) | AA10: =IF(OR(NOT(ISNUMBER(X10)),NOT(ISNUMBER($H$34))),"",X10*MAX(1,$H$34)) | AB10: =IF(OR(NOT(ISNUMBER(W10)),NOT(ISNUMBER($H$34)),NOT(ISNUMBER($C$36))),"",W10*MAX(1,$H$34)*$C$36) | AC10: =IF(OR(NOT(ISNUMBER(W10)),NOT(ISNUMBER(AB10))),"",W10+AB10) | AD10: =IF(OR(NOT(ISNUMBER(W10)),NOT(ISNUMBER($H$34))),"",W10*$H$34) | AE10: =IF(OR(NOT(ISNUMBER(AC10)),NOT(ISNUMBER(AD10))),"",MAX(0,AC10-AD10)) | AF10: =IF(OR(NOT(ISNUMBER(AD10)),NOT(ISNUMBER(W10))),"",AD10-W10) | AH10: =IF(OR(NOT(ISNUMBER(MIETER!F15)),$G10="ja"),"",IF(NOT(ISNUMBER(MIETER!J15)),"",IF(ISNUMBER(AG10),MAX(MIETER!J15,AG10),MIETER!J15))) | AJ10: =IF(OR(NOT(ISNUMBER(AH10)),NOT(ISNUMBER(AI10))),"",MAX(0,AI10-AH10)) | AN10: =IF(NOT(ISNUMBER(F10)),"",IF(AND(NOT(ISNUMBER(AH10)),NOT(ISNUMBER(AL10)),NOT(ISNUMBER(AM10))),"",N(AH10)+N(AL10)+N(AM10))) | AO10: =IF(OR($G10="ja",NOT(ISNUMBER(AH10)),NOT(ISNUMBER(AN10))),"",AN10+N(AJ10)) | AP10: =IF(OR(NOT(ISNUMBER(AH10)),NOT(ISNUMBER(F10)),F10=0),"",AH10/F10) | AQ10: =IF(OR(NOT(ISNUMBER(MIETER!F15)),NOT(ISNUMBER(MIETER!I15))),"",MIETER!I15) | AR10: =IF(OR(NOT(ISNUMBER(AQ10)),$G10="ja",NOT(ISNUMBER($H$35))),"",EDATE(AQ10,$H$35)) | AT10: =IF(NOT(ISNUMBER(F10)),"",IF(ISNUMBER(AS10),AS10,IF(NOT(ISNUMBER(AR10)),"",MAX(0,(YEAR(AR10)-YEAR(TODAY()))*12+MONTH(AR10)-MONTH(TODAY()))))) | AU10: =IF(NOT(ISNUMBER(AT10)),"",IF(ISNUMBER(AK10),AK10*AT10,IF(NOT(ISNUMBER(AJ10)),"",AJ10*AT10))) | AV10: =IF(OR(NOT(ISNUMBER(AH10)),NOT(ISNUMBER(MIETER!$P$6))),"",ROUND(AH10*(1+MIETER!$P$6)^2,0)) | AY10: =IF(NOT(ISNUMBER(F10)),"",IF(ISNUMBER(AX10),AX10,IF(AND(ISNUMBER(AW10),ISNUMBER(AH10),AH10>0),AH10*AW10,IF(OR(NOT(ISNUMBER($C$62)),NOT(ISNUMBER($C$64))),"",$C$62+$C$64*F10/12)))) | BA10: =IF(NOT(ISNUMBER(AY10)),"",IF(ISNUMBER(AZ10),MIN(AY10,AZ10),IF(OR(NOT(ISNUMBER(F10)),NOT(ISNUMBER($C$64))),0,MIN(AY10,$C$64*F10/12)))) | BB10: =IF(OR(NOT(ISNUMBER(AY10)),NOT(ISNUMBER(AH10)),AH10=0),"",AY10/AH10) | BC10: =IF(NOT(ISNUMBER(AH10)),"",AH10*0.01) | BD10: =IF(OR(NOT(ISNUMBER(AH10)),NOT(ISNUMBER($C$28)),NOT(ISNUMBER(BY10)),BY10<=0),"",AH10*0.01*(1-$C$28)/BY10) | BE10: =IF(OR(NOT(ISNUMBER(K10)),NOT(ISNUMBER($H$30))),"",$H$30*K10) | BG10: =IF(OR(NOT(ISNUMBER(BE10)),NOT(ISNUMBER(X10)),X10<=0),"",1-BE10/X10) | BH10: =IF(NOT(ISNUMBER(X10)),"",IF(ISNUMBER(BF10),BF10,IF(AND(ISNUMBER(BE10),ISNUMBER(AA10),AA10>0),1-BE10/AA10,IF(NOT(ISNUMBER($C$31)),"",$C$31)))) | BI10: =IF(NOT(ISNUMBER(F10)),"",IF(ISNUMBER(BF10),"vertrag",IF(ISNUMBER(BE10),"berechnet","standard"))) | BK10: =IF(NOT(ISNUMBER(F10)),"",IF(ISNUMBER(BJ10),BJ10,IF(NOT(ISNUMBER($C$30)),"",$C$30))) | BL10: =IF(OR(NOT(ISNUMBER(AA10)),NOT(ISNUMBER(BH10)),NOT(ISNUMBER($C$36))),"",AA10*(1+$C$36)*BH10) | BM10: =IF(OR(NOT(ISNUMBER(BL10)),NOT(ISNUMBER(BK10)),NOT(ISNUMBER($C$36)),NOT(ISNUMBER($H$34))),"",(BL10*BK10+N(Q10)*MAX(1,$H$34)*(1+$C$36)*N($H$31)+N(R10)*MAX(1,$H$34)*(1+$C$36)*N($H$32))/12) | BN10: =IF(OR(NOT(ISNUMBER(AD10)),NOT(ISNUMBER($C$26))),"",AD10*$C$26/12) | BO10: =IF(OR(NOT(ISNUMBER(AD10)),NOT(ISNUMBER($C$26)),NOT(ISNUMBER($C$27))),"",ROUND(AD10*($C$26+$C$27)/12,0)) | BP10: =IF(OR(NOT(ISNUMBER(AO10)),NOT(ISNUMBER(BM10)),NOT(ISNUMBER(BN10)),NOT(ISNUMBER(AY10))),"",AO10-BN10-BM10-(AY10-N(BA10))) | BQ10: =IF(OR(NOT(ISNUMBER(BP10)),NOT(ISNUMBER($C$28))),"",ROUND(-BP10*$C$28,0)) | BR10: =IF(OR(NOT(ISNUMBER(BA10)),NOT(ISNUMBER($C$28))),"",BA10*$C$28) | BS10: =IF(OR(NOT(ISNUMBER(AO10)),NOT(ISNUMBER(BO10)),NOT(ISNUMBER(AY10))),"",ROUND(AO10,0)-BO10-ROUND(AY10,0)) | BT10: =IF(OR(NOT(ISNUMBER(BS10)),NOT(ISNUMBER(BQ10))),"",BS10+BQ10) | BU10: =IF(OR(NOT(ISNUMBER(AN10)),NOT(ISNUMBER(BO10)),NOT(ISNUMBER(AY10)),NOT(ISNUMBER(BP10)),NOT(ISNUMBER($C$28))),"",ROUND(AN10,0)-BO10-ROUND(AY10,0)+ROUND(-(BP10-N(AJ10))*$C$28,0)) | BV10: =IF(OR(NOT(ISNUMBER(AO10)),NOT(ISNUMBER(AY10)),NOT(ISNUMBER(BK10)),NOT(ISNUMBER($C$28)),NOT(ISNUMBER($C$36))),"",(AO10-AY10)*(1-$C$28)-$C$28*N(BA10)-IF(BI10="berechnet",$C$28*(1+$C$36)*BK10*N(BE10)/12,0)) | BW10: =IF(OR(NOT(ISNUMBER(F10)),NOT(ISNUMBER($C$26)),NOT(ISNUMBER($C$27)),NOT(ISNUMBER($C$28)),NOT(ISNUMBER($C$36))),"",($C$28*(1+$C$36)*(N(Q10)*N($H$31)+N(R10)*N($H$32))-(N(Q10)+N(R10))*(($C$26+$C$27)-$C$28*$C$26))/12) | BX10: =IF(OR(NOT(ISNUMBER(BK10)),NOT(ISNUMBER($C$26)),NOT(ISNUMBER($C$27)),NOT(ISNUMBER($C$28)),NOT(ISNUMBER($C$36)),BI10=""),"",(($C$26+$C$27)-$C$28*$C$26-$C$28*(1+$C$36)*BK10*IF(BI10="berechnet",1,IF(BI10="vertrag",BF10,$C$31)))/12) | BY10: =IF(OR(NOT(ISNUMBER(BX10)),NOT(ISNUMBER($C$34))),"",$C$34*BX10) | BZ10: =IF(OR($G10="ja",NOT(ISNUMBER(AH10)),NOT(ISNUMBER(BV10)),NOT(ISNUMBER(BW10)),NOT(ISNUMBER(BX10)),BX10<=0),"",(BV10-N($C$32)+BW10)/BX10) | CA10: =IF(OR($G10="ja",NOT(ISNUMBER(AH10)),NOT(ISNUMBER(BV10)),NOT(ISNUMBER(BW10)),NOT(ISNUMBER(BY10)),BY10<=0,NOT(ISNUMBER($C$34))),"",(BV10-N($C$32)+BW10*$C$34)/BY10) | CB10: =IF(OR(NOT(ISNUMBER(CA10)),NOT(ISNUMBER($C$28))),"",CA10-N(AJ10)*(1-$C$28)/BY10) | CC10: =IF(OR(NOT(ISNUMBER(CA10)),NOT(ISNUMBER(U10)),U10<=-1,NOT(ISNUMBER(F10)),F10=0),"",((CA10+N(Q10)+N(R10))/(1+U10)-N(Q10)-N(R10)-N(O10))/F10) | CD10: =IF(OR(NOT(ISNUMBER(L10)),NOT(ISNUMBER(CC10))),"",L10-CC10) | CE10: =IF(OR(NOT(ISNUMBER(W10)),NOT(ISNUMBER(AN10)),AN10=0),"",W10/(AN10*12)) | CF10: =IF(OR(NOT(ISNUMBER(W10)),NOT(ISNUMBER(AN10)),W10=0),"",AN10*12/W10) | CG10: =IF(NOT(ISNUMBER(F10)),"",IF($G10="ja","GRAU: Leerstand - keine Mietbasis",IF(AND(ISNUMBER(AH10),AH10=0),"GRAU: Ist-Miete 0 - Leerstand pruefen",IF(NOT(ISNUMBER(AH10)),"GRAU: Wohnungsmiete fehlt",IF(NOT(ISNUMBER(AJ10)),"GRAU: keine Sollmiete/Mietspiegel",IF(AND(ISNUMBER(AW10),ISNUMBER(AX10)),"GRAU: zwei Hausgeld-Quellen gesetzt",IF(AND(OR(ISNUMBER(AX10),ISNUMBER(AW10)),NOT(ISNUMBER(AZ10))),"GRAU: Ruecklagenanteil fehlt",IF(AND(AJ10>0,NOT(ISNUMBER(AT10))),"GRAU: Subventionsdauer unbekannt",IF(AND(ISNUMBER(BH10),BH10<=0),"ROT: Bodenwert uebersteigt Kaufpreis - Daten pruefen",IF(NOT(ISNUMBER(BT10)),"GRAU: Cashflow nicht rechenbar",IF(NOT(ISNUMBER(BZ10)),"GRAU: max. tragbar nicht rechenbar",IF(BZ10<=0,"ROT: kein tragbarer Preis bei diesem Ziel-Cashflow",IF(AND(BI10="berechnet",BZ10<BE10),"ROT: max. tragbar unter Bodenwert - Modell nicht gueltig",IF(X10<=BZ10-N(AJ10)*(1-$C$28)/BX10,"GRUEN: Preis unter max. tragbar (auch ohne Subvention)",IF(X10<=BZ10,"GELB: nur mit Subvention tragbar",IF(X10<=BZ10*(1+N($H$33)),"GELB: bis Toleranz darueber","ROT: deutlich ueber max. tragbar")))))))))))))))) | CH10: =IF(NOT(ISNUMBER(F10)),"",IF($G10="ja","GRAU: Leerstand - keine Mietbasis",IF(AND(ISNUMBER(AH10),AH10=0),"GRAU: Ist-Miete 0 - Leerstand pruefen",IF(NOT(ISNUMBER(AH10)),"GRAU: Wohnungsmiete fehlt",IF(NOT(ISNUMBER(AJ10)),"GRAU: keine Sollmiete/Mietspiegel",IF(AND(ISNUMBER(AW10),ISNUMBER(AX10)),"GRAU: zwei Hausgeld-Quellen gesetzt",IF(AND(OR(ISNUMBER(AX10),ISNUMBER(AW10)),NOT(ISNUMBER(AZ10))),"GRAU: Ruecklagenanteil fehlt",IF(AND(AJ10>0,NOT(ISNUMBER(AT10))),"GRAU: Subventionsdauer unbekannt",IF(AND(ISNUMBER(BH10),BH10<=0),"ROT: Bodenwert uebersteigt Kaufpreis - Daten pruefen",IF(NOT(ISNUMBER(BT10)),"GRAU: Cashflow nicht rechenbar",IF(NOT(ISNUMBER(CA10)),"GRAU: max. tragbar nicht rechenbar",IF(CA10<=0,"ROT: kein tragbarer Preis bei diesem Ziel-Cashflow",IF(AND(BI10="berechnet",CA10<BE10),"ROT: max. tragbar unter Bodenwert - Modell nicht gueltig",IF(X10<=CB10,"GRUEN: Preis unter max. tragbar (auch ohne Subvention)",IF(X10<=CA10,"GELB: nur mit Subvention tragbar",IF(X10<=CA10*(1+N($H$33)),"GELB: bis Toleranz darueber","ROT: deutlich ueber max. tragbar"))))))))))))))))
A11: =IF(NOT(ISNUMBER(MIETER!F16)),"",ROW()-2) | B11: =IF(NOT(ISNUMBER(MIETER!F16)),"",IF(MIETER!A16="","",MIETER!A16)) | C11: =IF(NOT(ISNUMBER(MIETER!F16)),"",IF(MIETER!B16="","",MIETER!B16)) | D11: =IF(NOT(ISNUMBER(MIETER!F16)),"",IF(MIETER!C16="","",MIETER!C16)) | E11: =IF(NOT(ISNUMBER(MIETER!F16)),"",IF(MIETER!D16="","",MIETER!D16)) | F11: =IF(NOT(ISNUMBER(MIETER!F16)),"",MIETER!F16) | K11: =IF(OR(NOT(ISNUMBER(F11)),NOT(ISNUMBER(J11)),NOT(ISNUMBER($H$29)),$H$29=0),"",J11/$H$29) | M11: =IF(OR(NOT(ISNUMBER(F11)),F11=0,NOT(ISNUMBER(VERKAUFSMATRIX!U14))),"",VERKAUFSMATRIX!U14/F11) | N11: =IF(OR(NOT(ISNUMBER(L11)),NOT(ISNUMBER(M11)),M11=0),"",L11/M11-1) | P11: =IF(OR(NOT(ISNUMBER(F11)),NOT(ISNUMBER(L11))),"",F11*L11+N(O11)) | S11: =IF(NOT(ISNUMBER(P11)),"",P11+N(Q11)+N(R11)) | U11: =IF(NOT(ISNUMBER(F11)),"",IF(ISNUMBER(T11),T11,IF(NOT(ISNUMBER($H$26)),"",$H$26))) | V11: =IF(OR(NOT(ISNUMBER(S11)),NOT(ISNUMBER(U11))),"",S11*U11) | W11: =IF(OR(NOT(ISNUMBER(S11)),NOT(ISNUMBER(U11))),"",S11*(1+U11)) | X11: =IF(NOT(ISNUMBER(W11)),"",W11-N(Q11)-N(R11)) | Y11: =IF(OR(NOT(ISNUMBER(S11)),NOT(ISNUMBER(F11)),F11=0),"",S11/F11) | Z11: =IF(OR(NOT(ISNUMBER(X11)),NOT(ISNUMBER(F11)),F11=0),"",X11/F11) | AA11: =IF(OR(NOT(ISNUMBER(X11)),NOT(ISNUMBER($H$34))),"",X11*MAX(1,$H$34)) | AB11: =IF(OR(NOT(ISNUMBER(W11)),NOT(ISNUMBER($H$34)),NOT(ISNUMBER($C$36))),"",W11*MAX(1,$H$34)*$C$36) | AC11: =IF(OR(NOT(ISNUMBER(W11)),NOT(ISNUMBER(AB11))),"",W11+AB11) | AD11: =IF(OR(NOT(ISNUMBER(W11)),NOT(ISNUMBER($H$34))),"",W11*$H$34) | AE11: =IF(OR(NOT(ISNUMBER(AC11)),NOT(ISNUMBER(AD11))),"",MAX(0,AC11-AD11)) | AF11: =IF(OR(NOT(ISNUMBER(AD11)),NOT(ISNUMBER(W11))),"",AD11-W11) | AH11: =IF(OR(NOT(ISNUMBER(MIETER!F16)),$G11="ja"),"",IF(NOT(ISNUMBER(MIETER!J16)),"",IF(ISNUMBER(AG11),MAX(MIETER!J16,AG11),MIETER!J16))) | AJ11: =IF(OR(NOT(ISNUMBER(AH11)),NOT(ISNUMBER(AI11))),"",MAX(0,AI11-AH11)) | AN11: =IF(NOT(ISNUMBER(F11)),"",IF(AND(NOT(ISNUMBER(AH11)),NOT(ISNUMBER(AL11)),NOT(ISNUMBER(AM11))),"",N(AH11)+N(AL11)+N(AM11))) | AO11: =IF(OR($G11="ja",NOT(ISNUMBER(AH11)),NOT(ISNUMBER(AN11))),"",AN11+N(AJ11)) | AP11: =IF(OR(NOT(ISNUMBER(AH11)),NOT(ISNUMBER(F11)),F11=0),"",AH11/F11) | AQ11: =IF(OR(NOT(ISNUMBER(MIETER!F16)),NOT(ISNUMBER(MIETER!I16))),"",MIETER!I16) | AR11: =IF(OR(NOT(ISNUMBER(AQ11)),$G11="ja",NOT(ISNUMBER($H$35))),"",EDATE(AQ11,$H$35)) | AT11: =IF(NOT(ISNUMBER(F11)),"",IF(ISNUMBER(AS11),AS11,IF(NOT(ISNUMBER(AR11)),"",MAX(0,(YEAR(AR11)-YEAR(TODAY()))*12+MONTH(AR11)-MONTH(TODAY()))))) | AU11: =IF(NOT(ISNUMBER(AT11)),"",IF(ISNUMBER(AK11),AK11*AT11,IF(NOT(ISNUMBER(AJ11)),"",AJ11*AT11))) | AV11: =IF(OR(NOT(ISNUMBER(AH11)),NOT(ISNUMBER(MIETER!$P$6))),"",ROUND(AH11*(1+MIETER!$P$6)^2,0)) | AY11: =IF(NOT(ISNUMBER(F11)),"",IF(ISNUMBER(AX11),AX11,IF(AND(ISNUMBER(AW11),ISNUMBER(AH11),AH11>0),AH11*AW11,IF(OR(NOT(ISNUMBER($C$62)),NOT(ISNUMBER($C$64))),"",$C$62+$C$64*F11/12)))) | BA11: =IF(NOT(ISNUMBER(AY11)),"",IF(ISNUMBER(AZ11),MIN(AY11,AZ11),IF(OR(NOT(ISNUMBER(F11)),NOT(ISNUMBER($C$64))),0,MIN(AY11,$C$64*F11/12)))) | BB11: =IF(OR(NOT(ISNUMBER(AY11)),NOT(ISNUMBER(AH11)),AH11=0),"",AY11/AH11) | BC11: =IF(NOT(ISNUMBER(AH11)),"",AH11*0.01) | BD11: =IF(OR(NOT(ISNUMBER(AH11)),NOT(ISNUMBER($C$28)),NOT(ISNUMBER(BY11)),BY11<=0),"",AH11*0.01*(1-$C$28)/BY11) | BE11: =IF(OR(NOT(ISNUMBER(K11)),NOT(ISNUMBER($H$30))),"",$H$30*K11) | BG11: =IF(OR(NOT(ISNUMBER(BE11)),NOT(ISNUMBER(X11)),X11<=0),"",1-BE11/X11) | BH11: =IF(NOT(ISNUMBER(X11)),"",IF(ISNUMBER(BF11),BF11,IF(AND(ISNUMBER(BE11),ISNUMBER(AA11),AA11>0),1-BE11/AA11,IF(NOT(ISNUMBER($C$31)),"",$C$31)))) | BI11: =IF(NOT(ISNUMBER(F11)),"",IF(ISNUMBER(BF11),"vertrag",IF(ISNUMBER(BE11),"berechnet","standard"))) | BK11: =IF(NOT(ISNUMBER(F11)),"",IF(ISNUMBER(BJ11),BJ11,IF(NOT(ISNUMBER($C$30)),"",$C$30))) | BL11: =IF(OR(NOT(ISNUMBER(AA11)),NOT(ISNUMBER(BH11)),NOT(ISNUMBER($C$36))),"",AA11*(1+$C$36)*BH11) | BM11: =IF(OR(NOT(ISNUMBER(BL11)),NOT(ISNUMBER(BK11)),NOT(ISNUMBER($C$36)),NOT(ISNUMBER($H$34))),"",(BL11*BK11+N(Q11)*MAX(1,$H$34)*(1+$C$36)*N($H$31)+N(R11)*MAX(1,$H$34)*(1+$C$36)*N($H$32))/12) | BN11: =IF(OR(NOT(ISNUMBER(AD11)),NOT(ISNUMBER($C$26))),"",AD11*$C$26/12) | BO11: =IF(OR(NOT(ISNUMBER(AD11)),NOT(ISNUMBER($C$26)),NOT(ISNUMBER($C$27))),"",ROUND(AD11*($C$26+$C$27)/12,0)) | BP11: =IF(OR(NOT(ISNUMBER(AO11)),NOT(ISNUMBER(BM11)),NOT(ISNUMBER(BN11)),NOT(ISNUMBER(AY11))),"",AO11-BN11-BM11-(AY11-N(BA11))) | BQ11: =IF(OR(NOT(ISNUMBER(BP11)),NOT(ISNUMBER($C$28))),"",ROUND(-BP11*$C$28,0)) | BR11: =IF(OR(NOT(ISNUMBER(BA11)),NOT(ISNUMBER($C$28))),"",BA11*$C$28) | BS11: =IF(OR(NOT(ISNUMBER(AO11)),NOT(ISNUMBER(BO11)),NOT(ISNUMBER(AY11))),"",ROUND(AO11,0)-BO11-ROUND(AY11,0)) | BT11: =IF(OR(NOT(ISNUMBER(BS11)),NOT(ISNUMBER(BQ11))),"",BS11+BQ11) | BU11: =IF(OR(NOT(ISNUMBER(AN11)),NOT(ISNUMBER(BO11)),NOT(ISNUMBER(AY11)),NOT(ISNUMBER(BP11)),NOT(ISNUMBER($C$28))),"",ROUND(AN11,0)-BO11-ROUND(AY11,0)+ROUND(-(BP11-N(AJ11))*$C$28,0)) | BV11: =IF(OR(NOT(ISNUMBER(AO11)),NOT(ISNUMBER(AY11)),NOT(ISNUMBER(BK11)),NOT(ISNUMBER($C$28)),NOT(ISNUMBER($C$36))),"",(AO11-AY11)*(1-$C$28)-$C$28*N(BA11)-IF(BI11="berechnet",$C$28*(1+$C$36)*BK11*N(BE11)/12,0)) | BW11: =IF(OR(NOT(ISNUMBER(F11)),NOT(ISNUMBER($C$26)),NOT(ISNUMBER($C$27)),NOT(ISNUMBER($C$28)),NOT(ISNUMBER($C$36))),"",($C$28*(1+$C$36)*(N(Q11)*N($H$31)+N(R11)*N($H$32))-(N(Q11)+N(R11))*(($C$26+$C$27)-$C$28*$C$26))/12) | BX11: =IF(OR(NOT(ISNUMBER(BK11)),NOT(ISNUMBER($C$26)),NOT(ISNUMBER($C$27)),NOT(ISNUMBER($C$28)),NOT(ISNUMBER($C$36)),BI11=""),"",(($C$26+$C$27)-$C$28*$C$26-$C$28*(1+$C$36)*BK11*IF(BI11="berechnet",1,IF(BI11="vertrag",BF11,$C$31)))/12) | BY11: =IF(OR(NOT(ISNUMBER(BX11)),NOT(ISNUMBER($C$34))),"",$C$34*BX11) | BZ11: =IF(OR($G11="ja",NOT(ISNUMBER(AH11)),NOT(ISNUMBER(BV11)),NOT(ISNUMBER(BW11)),NOT(ISNUMBER(BX11)),BX11<=0),"",(BV11-N($C$32)+BW11)/BX11) | CA11: =IF(OR($G11="ja",NOT(ISNUMBER(AH11)),NOT(ISNUMBER(BV11)),NOT(ISNUMBER(BW11)),NOT(ISNUMBER(BY11)),BY11<=0,NOT(ISNUMBER($C$34))),"",(BV11-N($C$32)+BW11*$C$34)/BY11) | CB11: =IF(OR(NOT(ISNUMBER(CA11)),NOT(ISNUMBER($C$28))),"",CA11-N(AJ11)*(1-$C$28)/BY11) | CC11: =IF(OR(NOT(ISNUMBER(CA11)),NOT(ISNUMBER(U11)),U11<=-1,NOT(ISNUMBER(F11)),F11=0),"",((CA11+N(Q11)+N(R11))/(1+U11)-N(Q11)-N(R11)-N(O11))/F11) | CD11: =IF(OR(NOT(ISNUMBER(L11)),NOT(ISNUMBER(CC11))),"",L11-CC11) | CE11: =IF(OR(NOT(ISNUMBER(W11)),NOT(ISNUMBER(AN11)),AN11=0),"",W11/(AN11*12)) | CF11: =IF(OR(NOT(ISNUMBER(W11)),NOT(ISNUMBER(AN11)),W11=0),"",AN11*12/W11) | CG11: =IF(NOT(ISNUMBER(F11)),"",IF($G11="ja","GRAU: Leerstand - keine Mietbasis",IF(AND(ISNUMBER(AH11),AH11=0),"GRAU: Ist-Miete 0 - Leerstand pruefen",IF(NOT(ISNUMBER(AH11)),"GRAU: Wohnungsmiete fehlt",IF(NOT(ISNUMBER(AJ11)),"GRAU: keine Sollmiete/Mietspiegel",IF(AND(ISNUMBER(AW11),ISNUMBER(AX11)),"GRAU: zwei Hausgeld-Quellen gesetzt",IF(AND(OR(ISNUMBER(AX11),ISNUMBER(AW11)),NOT(ISNUMBER(AZ11))),"GRAU: Ruecklagenanteil fehlt",IF(AND(AJ11>0,NOT(ISNUMBER(AT11))),"GRAU: Subventionsdauer unbekannt",IF(AND(ISNUMBER(BH11),BH11<=0),"ROT: Bodenwert uebersteigt Kaufpreis - Daten pruefen",IF(NOT(ISNUMBER(BT11)),"GRAU: Cashflow nicht rechenbar",IF(NOT(ISNUMBER(BZ11)),"GRAU: max. tragbar nicht rechenbar",IF(BZ11<=0,"ROT: kein tragbarer Preis bei diesem Ziel-Cashflow",IF(AND(BI11="berechnet",BZ11<BE11),"ROT: max. tragbar unter Bodenwert - Modell nicht gueltig",IF(X11<=BZ11-N(AJ11)*(1-$C$28)/BX11,"GRUEN: Preis unter max. tragbar (auch ohne Subvention)",IF(X11<=BZ11,"GELB: nur mit Subvention tragbar",IF(X11<=BZ11*(1+N($H$33)),"GELB: bis Toleranz darueber","ROT: deutlich ueber max. tragbar")))))))))))))))) | CH11: =IF(NOT(ISNUMBER(F11)),"",IF($G11="ja","GRAU: Leerstand - keine Mietbasis",IF(AND(ISNUMBER(AH11),AH11=0),"GRAU: Ist-Miete 0 - Leerstand pruefen",IF(NOT(ISNUMBER(AH11)),"GRAU: Wohnungsmiete fehlt",IF(NOT(ISNUMBER(AJ11)),"GRAU: keine Sollmiete/Mietspiegel",IF(AND(ISNUMBER(AW11),ISNUMBER(AX11)),"GRAU: zwei Hausgeld-Quellen gesetzt",IF(AND(OR(ISNUMBER(AX11),ISNUMBER(AW11)),NOT(ISNUMBER(AZ11))),"GRAU: Ruecklagenanteil fehlt",IF(AND(AJ11>0,NOT(ISNUMBER(AT11))),"GRAU: Subventionsdauer unbekannt",IF(AND(ISNUMBER(BH11),BH11<=0),"ROT: Bodenwert uebersteigt Kaufpreis - Daten pruefen",IF(NOT(ISNUMBER(BT11)),"GRAU: Cashflow nicht rechenbar",IF(NOT(ISNUMBER(CA11)),"GRAU: max. tragbar nicht rechenbar",IF(CA11<=0,"ROT: kein tragbarer Preis bei diesem Ziel-Cashflow",IF(AND(BI11="berechnet",CA11<BE11),"ROT: max. tragbar unter Bodenwert - Modell nicht gueltig",IF(X11<=CB11,"GRUEN: Preis unter max. tragbar (auch ohne Subvention)",IF(X11<=CA11,"GELB: nur mit Subvention tragbar",IF(X11<=CA11*(1+N($H$33)),"GELB: bis Toleranz darueber","ROT: deutlich ueber max. tragbar"))))))))))))))))
A12: =IF(NOT(ISNUMBER(MIETER!F17)),"",ROW()-2) | B12: =IF(NOT(ISNUMBER(MIETER!F17)),"",IF(MIETER!A17="","",MIETER!A17)) | C12: =IF(NOT(ISNUMBER(MIETER!F17)),"",IF(MIETER!B17="","",MIETER!B17)) | D12: =IF(NOT(ISNUMBER(MIETER!F17)),"",IF(MIETER!C17="","",MIETER!C17)) | E12: =IF(NOT(ISNUMBER(MIETER!F17)),"",IF(MIETER!D17="","",MIETER!D17)) | F12: =IF(NOT(ISNUMBER(MIETER!F17)),"",MIETER!F17) | K12: =IF(OR(NOT(ISNUMBER(F12)),NOT(ISNUMBER(J12)),NOT(ISNUMBER($H$29)),$H$29=0),"",J12/$H$29) | M12: =IF(OR(NOT(ISNUMBER(F12)),F12=0,NOT(ISNUMBER(VERKAUFSMATRIX!U15))),"",VERKAUFSMATRIX!U15/F12) | N12: =IF(OR(NOT(ISNUMBER(L12)),NOT(ISNUMBER(M12)),M12=0),"",L12/M12-1) | P12: =IF(OR(NOT(ISNUMBER(F12)),NOT(ISNUMBER(L12))),"",F12*L12+N(O12)) | S12: =IF(NOT(ISNUMBER(P12)),"",P12+N(Q12)+N(R12)) | U12: =IF(NOT(ISNUMBER(F12)),"",IF(ISNUMBER(T12),T12,IF(NOT(ISNUMBER($H$26)),"",$H$26))) | V12: =IF(OR(NOT(ISNUMBER(S12)),NOT(ISNUMBER(U12))),"",S12*U12) | W12: =IF(OR(NOT(ISNUMBER(S12)),NOT(ISNUMBER(U12))),"",S12*(1+U12)) | X12: =IF(NOT(ISNUMBER(W12)),"",W12-N(Q12)-N(R12)) | Y12: =IF(OR(NOT(ISNUMBER(S12)),NOT(ISNUMBER(F12)),F12=0),"",S12/F12) | Z12: =IF(OR(NOT(ISNUMBER(X12)),NOT(ISNUMBER(F12)),F12=0),"",X12/F12) | AA12: =IF(OR(NOT(ISNUMBER(X12)),NOT(ISNUMBER($H$34))),"",X12*MAX(1,$H$34)) | AB12: =IF(OR(NOT(ISNUMBER(W12)),NOT(ISNUMBER($H$34)),NOT(ISNUMBER($C$36))),"",W12*MAX(1,$H$34)*$C$36) | AC12: =IF(OR(NOT(ISNUMBER(W12)),NOT(ISNUMBER(AB12))),"",W12+AB12) | AD12: =IF(OR(NOT(ISNUMBER(W12)),NOT(ISNUMBER($H$34))),"",W12*$H$34) | AE12: =IF(OR(NOT(ISNUMBER(AC12)),NOT(ISNUMBER(AD12))),"",MAX(0,AC12-AD12)) | AF12: =IF(OR(NOT(ISNUMBER(AD12)),NOT(ISNUMBER(W12))),"",AD12-W12) | AH12: =IF(OR(NOT(ISNUMBER(MIETER!F17)),$G12="ja"),"",IF(NOT(ISNUMBER(MIETER!J17)),"",IF(ISNUMBER(AG12),MAX(MIETER!J17,AG12),MIETER!J17))) | AJ12: =IF(OR(NOT(ISNUMBER(AH12)),NOT(ISNUMBER(AI12))),"",MAX(0,AI12-AH12)) | AN12: =IF(NOT(ISNUMBER(F12)),"",IF(AND(NOT(ISNUMBER(AH12)),NOT(ISNUMBER(AL12)),NOT(ISNUMBER(AM12))),"",N(AH12)+N(AL12)+N(AM12))) | AO12: =IF(OR($G12="ja",NOT(ISNUMBER(AH12)),NOT(ISNUMBER(AN12))),"",AN12+N(AJ12)) | AP12: =IF(OR(NOT(ISNUMBER(AH12)),NOT(ISNUMBER(F12)),F12=0),"",AH12/F12) | AQ12: =IF(OR(NOT(ISNUMBER(MIETER!F17)),NOT(ISNUMBER(MIETER!I17))),"",MIETER!I17) | AR12: =IF(OR(NOT(ISNUMBER(AQ12)),$G12="ja",NOT(ISNUMBER($H$35))),"",EDATE(AQ12,$H$35)) | AT12: =IF(NOT(ISNUMBER(F12)),"",IF(ISNUMBER(AS12),AS12,IF(NOT(ISNUMBER(AR12)),"",MAX(0,(YEAR(AR12)-YEAR(TODAY()))*12+MONTH(AR12)-MONTH(TODAY()))))) | AU12: =IF(NOT(ISNUMBER(AT12)),"",IF(ISNUMBER(AK12),AK12*AT12,IF(NOT(ISNUMBER(AJ12)),"",AJ12*AT12))) | AV12: =IF(OR(NOT(ISNUMBER(AH12)),NOT(ISNUMBER(MIETER!$P$6))),"",ROUND(AH12*(1+MIETER!$P$6)^2,0)) | AY12: =IF(NOT(ISNUMBER(F12)),"",IF(ISNUMBER(AX12),AX12,IF(AND(ISNUMBER(AW12),ISNUMBER(AH12),AH12>0),AH12*AW12,IF(OR(NOT(ISNUMBER($C$62)),NOT(ISNUMBER($C$64))),"",$C$62+$C$64*F12/12)))) | BA12: =IF(NOT(ISNUMBER(AY12)),"",IF(ISNUMBER(AZ12),MIN(AY12,AZ12),IF(OR(NOT(ISNUMBER(F12)),NOT(ISNUMBER($C$64))),0,MIN(AY12,$C$64*F12/12)))) | BB12: =IF(OR(NOT(ISNUMBER(AY12)),NOT(ISNUMBER(AH12)),AH12=0),"",AY12/AH12) | BC12: =IF(NOT(ISNUMBER(AH12)),"",AH12*0.01) | BD12: =IF(OR(NOT(ISNUMBER(AH12)),NOT(ISNUMBER($C$28)),NOT(ISNUMBER(BY12)),BY12<=0),"",AH12*0.01*(1-$C$28)/BY12) | BE12: =IF(OR(NOT(ISNUMBER(K12)),NOT(ISNUMBER($H$30))),"",$H$30*K12) | BG12: =IF(OR(NOT(ISNUMBER(BE12)),NOT(ISNUMBER(X12)),X12<=0),"",1-BE12/X12) | BH12: =IF(NOT(ISNUMBER(X12)),"",IF(ISNUMBER(BF12),BF12,IF(AND(ISNUMBER(BE12),ISNUMBER(AA12),AA12>0),1-BE12/AA12,IF(NOT(ISNUMBER($C$31)),"",$C$31)))) | BI12: =IF(NOT(ISNUMBER(F12)),"",IF(ISNUMBER(BF12),"vertrag",IF(ISNUMBER(BE12),"berechnet","standard"))) | BK12: =IF(NOT(ISNUMBER(F12)),"",IF(ISNUMBER(BJ12),BJ12,IF(NOT(ISNUMBER($C$30)),"",$C$30))) | BL12: =IF(OR(NOT(ISNUMBER(AA12)),NOT(ISNUMBER(BH12)),NOT(ISNUMBER($C$36))),"",AA12*(1+$C$36)*BH12) | BM12: =IF(OR(NOT(ISNUMBER(BL12)),NOT(ISNUMBER(BK12)),NOT(ISNUMBER($C$36)),NOT(ISNUMBER($H$34))),"",(BL12*BK12+N(Q12)*MAX(1,$H$34)*(1+$C$36)*N($H$31)+N(R12)*MAX(1,$H$34)*(1+$C$36)*N($H$32))/12) | BN12: =IF(OR(NOT(ISNUMBER(AD12)),NOT(ISNUMBER($C$26))),"",AD12*$C$26/12) | BO12: =IF(OR(NOT(ISNUMBER(AD12)),NOT(ISNUMBER($C$26)),NOT(ISNUMBER($C$27))),"",ROUND(AD12*($C$26+$C$27)/12,0)) | BP12: =IF(OR(NOT(ISNUMBER(AO12)),NOT(ISNUMBER(BM12)),NOT(ISNUMBER(BN12)),NOT(ISNUMBER(AY12))),"",AO12-BN12-BM12-(AY12-N(BA12))) | BQ12: =IF(OR(NOT(ISNUMBER(BP12)),NOT(ISNUMBER($C$28))),"",ROUND(-BP12*$C$28,0)) | BR12: =IF(OR(NOT(ISNUMBER(BA12)),NOT(ISNUMBER($C$28))),"",BA12*$C$28) | BS12: =IF(OR(NOT(ISNUMBER(AO12)),NOT(ISNUMBER(BO12)),NOT(ISNUMBER(AY12))),"",ROUND(AO12,0)-BO12-ROUND(AY12,0)) | BT12: =IF(OR(NOT(ISNUMBER(BS12)),NOT(ISNUMBER(BQ12))),"",BS12+BQ12) | BU12: =IF(OR(NOT(ISNUMBER(AN12)),NOT(ISNUMBER(BO12)),NOT(ISNUMBER(AY12)),NOT(ISNUMBER(BP12)),NOT(ISNUMBER($C$28))),"",ROUND(AN12,0)-BO12-ROUND(AY12,0)+ROUND(-(BP12-N(AJ12))*$C$28,0)) | BV12: =IF(OR(NOT(ISNUMBER(AO12)),NOT(ISNUMBER(AY12)),NOT(ISNUMBER(BK12)),NOT(ISNUMBER($C$28)),NOT(ISNUMBER($C$36))),"",(AO12-AY12)*(1-$C$28)-$C$28*N(BA12)-IF(BI12="berechnet",$C$28*(1+$C$36)*BK12*N(BE12)/12,0)) | BW12: =IF(OR(NOT(ISNUMBER(F12)),NOT(ISNUMBER($C$26)),NOT(ISNUMBER($C$27)),NOT(ISNUMBER($C$28)),NOT(ISNUMBER($C$36))),"",($C$28*(1+$C$36)*(N(Q12)*N($H$31)+N(R12)*N($H$32))-(N(Q12)+N(R12))*(($C$26+$C$27)-$C$28*$C$26))/12) | BX12: =IF(OR(NOT(ISNUMBER(BK12)),NOT(ISNUMBER($C$26)),NOT(ISNUMBER($C$27)),NOT(ISNUMBER($C$28)),NOT(ISNUMBER($C$36)),BI12=""),"",(($C$26+$C$27)-$C$28*$C$26-$C$28*(1+$C$36)*BK12*IF(BI12="berechnet",1,IF(BI12="vertrag",BF12,$C$31)))/12) | BY12: =IF(OR(NOT(ISNUMBER(BX12)),NOT(ISNUMBER($C$34))),"",$C$34*BX12) | BZ12: =IF(OR($G12="ja",NOT(ISNUMBER(AH12)),NOT(ISNUMBER(BV12)),NOT(ISNUMBER(BW12)),NOT(ISNUMBER(BX12)),BX12<=0),"",(BV12-N($C$32)+BW12)/BX12) | CA12: =IF(OR($G12="ja",NOT(ISNUMBER(AH12)),NOT(ISNUMBER(BV12)),NOT(ISNUMBER(BW12)),NOT(ISNUMBER(BY12)),BY12<=0,NOT(ISNUMBER($C$34))),"",(BV12-N($C$32)+BW12*$C$34)/BY12) | CB12: =IF(OR(NOT(ISNUMBER(CA12)),NOT(ISNUMBER($C$28))),"",CA12-N(AJ12)*(1-$C$28)/BY12) | CC12: =IF(OR(NOT(ISNUMBER(CA12)),NOT(ISNUMBER(U12)),U12<=-1,NOT(ISNUMBER(F12)),F12=0),"",((CA12+N(Q12)+N(R12))/(1+U12)-N(Q12)-N(R12)-N(O12))/F12) | CD12: =IF(OR(NOT(ISNUMBER(L12)),NOT(ISNUMBER(CC12))),"",L12-CC12) | CE12: =IF(OR(NOT(ISNUMBER(W12)),NOT(ISNUMBER(AN12)),AN12=0),"",W12/(AN12*12)) | CF12: =IF(OR(NOT(ISNUMBER(W12)),NOT(ISNUMBER(AN12)),W12=0),"",AN12*12/W12) | CG12: =IF(NOT(ISNUMBER(F12)),"",IF($G12="ja","GRAU: Leerstand - keine Mietbasis",IF(AND(ISNUMBER(AH12),AH12=0),"GRAU: Ist-Miete 0 - Leerstand pruefen",IF(NOT(ISNUMBER(AH12)),"GRAU: Wohnungsmiete fehlt",IF(NOT(ISNUMBER(AJ12)),"GRAU: keine Sollmiete/Mietspiegel",IF(AND(ISNUMBER(AW12),ISNUMBER(AX12)),"GRAU: zwei Hausgeld-Quellen gesetzt",IF(AND(OR(ISNUMBER(AX12),ISNUMBER(AW12)),NOT(ISNUMBER(AZ12))),"GRAU: Ruecklagenanteil fehlt",IF(AND(AJ12>0,NOT(ISNUMBER(AT12))),"GRAU: Subventionsdauer unbekannt",IF(AND(ISNUMBER(BH12),BH12<=0),"ROT: Bodenwert uebersteigt Kaufpreis - Daten pruefen",IF(NOT(ISNUMBER(BT12)),"GRAU: Cashflow nicht rechenbar",IF(NOT(ISNUMBER(BZ12)),"GRAU: max. tragbar nicht rechenbar",IF(BZ12<=0,"ROT: kein tragbarer Preis bei diesem Ziel-Cashflow",IF(AND(BI12="berechnet",BZ12<BE12),"ROT: max. tragbar unter Bodenwert - Modell nicht gueltig",IF(X12<=BZ12-N(AJ12)*(1-$C$28)/BX12,"GRUEN: Preis unter max. tragbar (auch ohne Subvention)",IF(X12<=BZ12,"GELB: nur mit Subvention tragbar",IF(X12<=BZ12*(1+N($H$33)),"GELB: bis Toleranz darueber","ROT: deutlich ueber max. tragbar")))))))))))))))) | CH12: =IF(NOT(ISNUMBER(F12)),"",IF($G12="ja","GRAU: Leerstand - keine Mietbasis",IF(AND(ISNUMBER(AH12),AH12=0),"GRAU: Ist-Miete 0 - Leerstand pruefen",IF(NOT(ISNUMBER(AH12)),"GRAU: Wohnungsmiete fehlt",IF(NOT(ISNUMBER(AJ12)),"GRAU: keine Sollmiete/Mietspiegel",IF(AND(ISNUMBER(AW12),ISNUMBER(AX12)),"GRAU: zwei Hausgeld-Quellen gesetzt",IF(AND(OR(ISNUMBER(AX12),ISNUMBER(AW12)),NOT(ISNUMBER(AZ12))),"GRAU: Ruecklagenanteil fehlt",IF(AND(AJ12>0,NOT(ISNUMBER(AT12))),"GRAU: Subventionsdauer unbekannt",IF(AND(ISNUMBER(BH12),BH12<=0),"ROT: Bodenwert uebersteigt Kaufpreis - Daten pruefen",IF(NOT(ISNUMBER(BT12)),"GRAU: Cashflow nicht rechenbar",IF(NOT(ISNUMBER(CA12)),"GRAU: max. tragbar nicht rechenbar",IF(CA12<=0,"ROT: kein tragbarer Preis bei diesem Ziel-Cashflow",IF(AND(BI12="berechnet",CA12<BE12),"ROT: max. tragbar unter Bodenwert - Modell nicht gueltig",IF(X12<=CB12,"GRUEN: Preis unter max. tragbar (auch ohne Subvention)",IF(X12<=CA12,"GELB: nur mit Subvention tragbar",IF(X12<=CA12*(1+N($H$33)),"GELB: bis Toleranz darueber","ROT: deutlich ueber max. tragbar"))))))))))))))))
A13: =IF(NOT(ISNUMBER(MIETER!F18)),"",ROW()-2) | B13: =IF(NOT(ISNUMBER(MIETER!F18)),"",IF(MIETER!A18="","",MIETER!A18)) | C13: =IF(NOT(ISNUMBER(MIETER!F18)),"",IF(MIETER!B18="","",MIETER!B18)) | D13: =IF(NOT(ISNUMBER(MIETER!F18)),"",IF(MIETER!C18="","",MIETER!C18)) | E13: =IF(NOT(ISNUMBER(MIETER!F18)),"",IF(MIETER!D18="","",MIETER!D18)) | F13: =IF(NOT(ISNUMBER(MIETER!F18)),"",MIETER!F18) | K13: =IF(OR(NOT(ISNUMBER(F13)),NOT(ISNUMBER(J13)),NOT(ISNUMBER($H$29)),$H$29=0),"",J13/$H$29) | M13: =IF(OR(NOT(ISNUMBER(F13)),F13=0,NOT(ISNUMBER(VERKAUFSMATRIX!U16))),"",VERKAUFSMATRIX!U16/F13) | N13: =IF(OR(NOT(ISNUMBER(L13)),NOT(ISNUMBER(M13)),M13=0),"",L13/M13-1) | P13: =IF(OR(NOT(ISNUMBER(F13)),NOT(ISNUMBER(L13))),"",F13*L13+N(O13)) | S13: =IF(NOT(ISNUMBER(P13)),"",P13+N(Q13)+N(R13)) | U13: =IF(NOT(ISNUMBER(F13)),"",IF(ISNUMBER(T13),T13,IF(NOT(ISNUMBER($H$26)),"",$H$26))) | V13: =IF(OR(NOT(ISNUMBER(S13)),NOT(ISNUMBER(U13))),"",S13*U13) | W13: =IF(OR(NOT(ISNUMBER(S13)),NOT(ISNUMBER(U13))),"",S13*(1+U13)) | X13: =IF(NOT(ISNUMBER(W13)),"",W13-N(Q13)-N(R13)) | Y13: =IF(OR(NOT(ISNUMBER(S13)),NOT(ISNUMBER(F13)),F13=0),"",S13/F13) | Z13: =IF(OR(NOT(ISNUMBER(X13)),NOT(ISNUMBER(F13)),F13=0),"",X13/F13) | AA13: =IF(OR(NOT(ISNUMBER(X13)),NOT(ISNUMBER($H$34))),"",X13*MAX(1,$H$34)) | AB13: =IF(OR(NOT(ISNUMBER(W13)),NOT(ISNUMBER($H$34)),NOT(ISNUMBER($C$36))),"",W13*MAX(1,$H$34)*$C$36) | AC13: =IF(OR(NOT(ISNUMBER(W13)),NOT(ISNUMBER(AB13))),"",W13+AB13) | AD13: =IF(OR(NOT(ISNUMBER(W13)),NOT(ISNUMBER($H$34))),"",W13*$H$34) | AE13: =IF(OR(NOT(ISNUMBER(AC13)),NOT(ISNUMBER(AD13))),"",MAX(0,AC13-AD13)) | AF13: =IF(OR(NOT(ISNUMBER(AD13)),NOT(ISNUMBER(W13))),"",AD13-W13) | AH13: =IF(OR(NOT(ISNUMBER(MIETER!F18)),$G13="ja"),"",IF(NOT(ISNUMBER(MIETER!J18)),"",IF(ISNUMBER(AG13),MAX(MIETER!J18,AG13),MIETER!J18))) | AJ13: =IF(OR(NOT(ISNUMBER(AH13)),NOT(ISNUMBER(AI13))),"",MAX(0,AI13-AH13)) | AN13: =IF(NOT(ISNUMBER(F13)),"",IF(AND(NOT(ISNUMBER(AH13)),NOT(ISNUMBER(AL13)),NOT(ISNUMBER(AM13))),"",N(AH13)+N(AL13)+N(AM13))) | AO13: =IF(OR($G13="ja",NOT(ISNUMBER(AH13)),NOT(ISNUMBER(AN13))),"",AN13+N(AJ13)) | AP13: =IF(OR(NOT(ISNUMBER(AH13)),NOT(ISNUMBER(F13)),F13=0),"",AH13/F13) | AQ13: =IF(OR(NOT(ISNUMBER(MIETER!F18)),NOT(ISNUMBER(MIETER!I18))),"",MIETER!I18) | AR13: =IF(OR(NOT(ISNUMBER(AQ13)),$G13="ja",NOT(ISNUMBER($H$35))),"",EDATE(AQ13,$H$35)) | AT13: =IF(NOT(ISNUMBER(F13)),"",IF(ISNUMBER(AS13),AS13,IF(NOT(ISNUMBER(AR13)),"",MAX(0,(YEAR(AR13)-YEAR(TODAY()))*12+MONTH(AR13)-MONTH(TODAY()))))) | AU13: =IF(NOT(ISNUMBER(AT13)),"",IF(ISNUMBER(AK13),AK13*AT13,IF(NOT(ISNUMBER(AJ13)),"",AJ13*AT13))) | AV13: =IF(OR(NOT(ISNUMBER(AH13)),NOT(ISNUMBER(MIETER!$P$6))),"",ROUND(AH13*(1+MIETER!$P$6)^2,0)) | AY13: =IF(NOT(ISNUMBER(F13)),"",IF(ISNUMBER(AX13),AX13,IF(AND(ISNUMBER(AW13),ISNUMBER(AH13),AH13>0),AH13*AW13,IF(OR(NOT(ISNUMBER($C$62)),NOT(ISNUMBER($C$64))),"",$C$62+$C$64*F13/12)))) | BA13: =IF(NOT(ISNUMBER(AY13)),"",IF(ISNUMBER(AZ13),MIN(AY13,AZ13),IF(OR(NOT(ISNUMBER(F13)),NOT(ISNUMBER($C$64))),0,MIN(AY13,$C$64*F13/12)))) | BB13: =IF(OR(NOT(ISNUMBER(AY13)),NOT(ISNUMBER(AH13)),AH13=0),"",AY13/AH13) | BC13: =IF(NOT(ISNUMBER(AH13)),"",AH13*0.01) | BD13: =IF(OR(NOT(ISNUMBER(AH13)),NOT(ISNUMBER($C$28)),NOT(ISNUMBER(BY13)),BY13<=0),"",AH13*0.01*(1-$C$28)/BY13) | BE13: =IF(OR(NOT(ISNUMBER(K13)),NOT(ISNUMBER($H$30))),"",$H$30*K13) | BG13: =IF(OR(NOT(ISNUMBER(BE13)),NOT(ISNUMBER(X13)),X13<=0),"",1-BE13/X13) | BH13: =IF(NOT(ISNUMBER(X13)),"",IF(ISNUMBER(BF13),BF13,IF(AND(ISNUMBER(BE13),ISNUMBER(AA13),AA13>0),1-BE13/AA13,IF(NOT(ISNUMBER($C$31)),"",$C$31)))) | BI13: =IF(NOT(ISNUMBER(F13)),"",IF(ISNUMBER(BF13),"vertrag",IF(ISNUMBER(BE13),"berechnet","standard"))) | BK13: =IF(NOT(ISNUMBER(F13)),"",IF(ISNUMBER(BJ13),BJ13,IF(NOT(ISNUMBER($C$30)),"",$C$30))) | BL13: =IF(OR(NOT(ISNUMBER(AA13)),NOT(ISNUMBER(BH13)),NOT(ISNUMBER($C$36))),"",AA13*(1+$C$36)*BH13) | BM13: =IF(OR(NOT(ISNUMBER(BL13)),NOT(ISNUMBER(BK13)),NOT(ISNUMBER($C$36)),NOT(ISNUMBER($H$34))),"",(BL13*BK13+N(Q13)*MAX(1,$H$34)*(1+$C$36)*N($H$31)+N(R13)*MAX(1,$H$34)*(1+$C$36)*N($H$32))/12) | BN13: =IF(OR(NOT(ISNUMBER(AD13)),NOT(ISNUMBER($C$26))),"",AD13*$C$26/12) | BO13: =IF(OR(NOT(ISNUMBER(AD13)),NOT(ISNUMBER($C$26)),NOT(ISNUMBER($C$27))),"",ROUND(AD13*($C$26+$C$27)/12,0)) | BP13: =IF(OR(NOT(ISNUMBER(AO13)),NOT(ISNUMBER(BM13)),NOT(ISNUMBER(BN13)),NOT(ISNUMBER(AY13))),"",AO13-BN13-BM13-(AY13-N(BA13))) | BQ13: =IF(OR(NOT(ISNUMBER(BP13)),NOT(ISNUMBER($C$28))),"",ROUND(-BP13*$C$28,0)) | BR13: =IF(OR(NOT(ISNUMBER(BA13)),NOT(ISNUMBER($C$28))),"",BA13*$C$28) | BS13: =IF(OR(NOT(ISNUMBER(AO13)),NOT(ISNUMBER(BO13)),NOT(ISNUMBER(AY13))),"",ROUND(AO13,0)-BO13-ROUND(AY13,0)) | BT13: =IF(OR(NOT(ISNUMBER(BS13)),NOT(ISNUMBER(BQ13))),"",BS13+BQ13) | BU13: =IF(OR(NOT(ISNUMBER(AN13)),NOT(ISNUMBER(BO13)),NOT(ISNUMBER(AY13)),NOT(ISNUMBER(BP13)),NOT(ISNUMBER($C$28))),"",ROUND(AN13,0)-BO13-ROUND(AY13,0)+ROUND(-(BP13-N(AJ13))*$C$28,0)) | BV13: =IF(OR(NOT(ISNUMBER(AO13)),NOT(ISNUMBER(AY13)),NOT(ISNUMBER(BK13)),NOT(ISNUMBER($C$28)),NOT(ISNUMBER($C$36))),"",(AO13-AY13)*(1-$C$28)-$C$28*N(BA13)-IF(BI13="berechnet",$C$28*(1+$C$36)*BK13*N(BE13)/12,0)) | BW13: =IF(OR(NOT(ISNUMBER(F13)),NOT(ISNUMBER($C$26)),NOT(ISNUMBER($C$27)),NOT(ISNUMBER($C$28)),NOT(ISNUMBER($C$36))),"",($C$28*(1+$C$36)*(N(Q13)*N($H$31)+N(R13)*N($H$32))-(N(Q13)+N(R13))*(($C$26+$C$27)-$C$28*$C$26))/12) | BX13: =IF(OR(NOT(ISNUMBER(BK13)),NOT(ISNUMBER($C$26)),NOT(ISNUMBER($C$27)),NOT(ISNUMBER($C$28)),NOT(ISNUMBER($C$36)),BI13=""),"",(($C$26+$C$27)-$C$28*$C$26-$C$28*(1+$C$36)*BK13*IF(BI13="berechnet",1,IF(BI13="vertrag",BF13,$C$31)))/12) | BY13: =IF(OR(NOT(ISNUMBER(BX13)),NOT(ISNUMBER($C$34))),"",$C$34*BX13) | BZ13: =IF(OR($G13="ja",NOT(ISNUMBER(AH13)),NOT(ISNUMBER(BV13)),NOT(ISNUMBER(BW13)),NOT(ISNUMBER(BX13)),BX13<=0),"",(BV13-N($C$32)+BW13)/BX13) | CA13: =IF(OR($G13="ja",NOT(ISNUMBER(AH13)),NOT(ISNUMBER(BV13)),NOT(ISNUMBER(BW13)),NOT(ISNUMBER(BY13)),BY13<=0,NOT(ISNUMBER($C$34))),"",(BV13-N($C$32)+BW13*$C$34)/BY13) | CB13: =IF(OR(NOT(ISNUMBER(CA13)),NOT(ISNUMBER($C$28))),"",CA13-N(AJ13)*(1-$C$28)/BY13) | CC13: =IF(OR(NOT(ISNUMBER(CA13)),NOT(ISNUMBER(U13)),U13<=-1,NOT(ISNUMBER(F13)),F13=0),"",((CA13+N(Q13)+N(R13))/(1+U13)-N(Q13)-N(R13)-N(O13))/F13) | CD13: =IF(OR(NOT(ISNUMBER(L13)),NOT(ISNUMBER(CC13))),"",L13-CC13) | CE13: =IF(OR(NOT(ISNUMBER(W13)),NOT(ISNUMBER(AN13)),AN13=0),"",W13/(AN13*12)) | CF13: =IF(OR(NOT(ISNUMBER(W13)),NOT(ISNUMBER(AN13)),W13=0),"",AN13*12/W13) | CG13: =IF(NOT(ISNUMBER(F13)),"",IF($G13="ja","GRAU: Leerstand - keine Mietbasis",IF(AND(ISNUMBER(AH13),AH13=0),"GRAU: Ist-Miete 0 - Leerstand pruefen",IF(NOT(ISNUMBER(AH13)),"GRAU: Wohnungsmiete fehlt",IF(NOT(ISNUMBER(AJ13)),"GRAU: keine Sollmiete/Mietspiegel",IF(AND(ISNUMBER(AW13),ISNUMBER(AX13)),"GRAU: zwei Hausgeld-Quellen gesetzt",IF(AND(OR(ISNUMBER(AX13),ISNUMBER(AW13)),NOT(ISNUMBER(AZ13))),"GRAU: Ruecklagenanteil fehlt",IF(AND(AJ13>0,NOT(ISNUMBER(AT13))),"GRAU: Subventionsdauer unbekannt",IF(AND(ISNUMBER(BH13),BH13<=0),"ROT: Bodenwert uebersteigt Kaufpreis - Daten pruefen",IF(NOT(ISNUMBER(BT13)),"GRAU: Cashflow nicht rechenbar",IF(NOT(ISNUMBER(BZ13)),"GRAU: max. tragbar nicht rechenbar",IF(BZ13<=0,"ROT: kein tragbarer Preis bei diesem Ziel-Cashflow",IF(AND(BI13="berechnet",BZ13<BE13),"ROT: max. tragbar unter Bodenwert - Modell nicht gueltig",IF(X13<=BZ13-N(AJ13)*(1-$C$28)/BX13,"GRUEN: Preis unter max. tragbar (auch ohne Subvention)",IF(X13<=BZ13,"GELB: nur mit Subvention tragbar",IF(X13<=BZ13*(1+N($H$33)),"GELB: bis Toleranz darueber","ROT: deutlich ueber max. tragbar")))))))))))))))) | CH13: =IF(NOT(ISNUMBER(F13)),"",IF($G13="ja","GRAU: Leerstand - keine Mietbasis",IF(AND(ISNUMBER(AH13),AH13=0),"GRAU: Ist-Miete 0 - Leerstand pruefen",IF(NOT(ISNUMBER(AH13)),"GRAU: Wohnungsmiete fehlt",IF(NOT(ISNUMBER(AJ13)),"GRAU: keine Sollmiete/Mietspiegel",IF(AND(ISNUMBER(AW13),ISNUMBER(AX13)),"GRAU: zwei Hausgeld-Quellen gesetzt",IF(AND(OR(ISNUMBER(AX13),ISNUMBER(AW13)),NOT(ISNUMBER(AZ13))),"GRAU: Ruecklagenanteil fehlt",IF(AND(AJ13>0,NOT(ISNUMBER(AT13))),"GRAU: Subventionsdauer unbekannt",IF(AND(ISNUMBER(BH13),BH13<=0),"ROT: Bodenwert uebersteigt Kaufpreis - Daten pruefen",IF(NOT(ISNUMBER(BT13)),"GRAU: Cashflow nicht rechenbar",IF(NOT(ISNUMBER(CA13)),"GRAU: max. tragbar nicht rechenbar",IF(CA13<=0,"ROT: kein tragbarer Preis bei diesem Ziel-Cashflow",IF(AND(BI13="berechnet",CA13<BE13),"ROT: max. tragbar unter Bodenwert - Modell nicht gueltig",IF(X13<=CB13,"GRUEN: Preis unter max. tragbar (auch ohne Subvention)",IF(X13<=CA13,"GELB: nur mit Subvention tragbar",IF(X13<=CA13*(1+N($H$33)),"GELB: bis Toleranz darueber","ROT: deutlich ueber max. tragbar"))))))))))))))))
A14: =IF(NOT(ISNUMBER(MIETER!F19)),"",ROW()-2) | B14: =IF(NOT(ISNUMBER(MIETER!F19)),"",IF(MIETER!A19="","",MIETER!A19)) | C14: =IF(NOT(ISNUMBER(MIETER!F19)),"",IF(MIETER!B19="","",MIETER!B19)) | D14: =IF(NOT(ISNUMBER(MIETER!F19)),"",IF(MIETER!C19="","",MIETER!C19)) | E14: =IF(NOT(ISNUMBER(MIETER!F19)),"",IF(MIETER!D19="","",MIETER!D19)) | F14: =IF(NOT(ISNUMBER(MIETER!F19)),"",MIETER!F19) | K14: =IF(OR(NOT(ISNUMBER(F14)),NOT(ISNUMBER(J14)),NOT(ISNUMBER($H$29)),$H$29=0),"",J14/$H$29) | M14: =IF(OR(NOT(ISNUMBER(F14)),F14=0,NOT(ISNUMBER(VERKAUFSMATRIX!U17))),"",VERKAUFSMATRIX!U17/F14) | N14: =IF(OR(NOT(ISNUMBER(L14)),NOT(ISNUMBER(M14)),M14=0),"",L14/M14-1) | P14: =IF(OR(NOT(ISNUMBER(F14)),NOT(ISNUMBER(L14))),"",F14*L14+N(O14)) | S14: =IF(NOT(ISNUMBER(P14)),"",P14+N(Q14)+N(R14)) | U14: =IF(NOT(ISNUMBER(F14)),"",IF(ISNUMBER(T14),T14,IF(NOT(ISNUMBER($H$26)),"",$H$26))) | V14: =IF(OR(NOT(ISNUMBER(S14)),NOT(ISNUMBER(U14))),"",S14*U14) | W14: =IF(OR(NOT(ISNUMBER(S14)),NOT(ISNUMBER(U14))),"",S14*(1+U14)) | X14: =IF(NOT(ISNUMBER(W14)),"",W14-N(Q14)-N(R14)) | Y14: =IF(OR(NOT(ISNUMBER(S14)),NOT(ISNUMBER(F14)),F14=0),"",S14/F14) | Z14: =IF(OR(NOT(ISNUMBER(X14)),NOT(ISNUMBER(F14)),F14=0),"",X14/F14) | AA14: =IF(OR(NOT(ISNUMBER(X14)),NOT(ISNUMBER($H$34))),"",X14*MAX(1,$H$34)) | AB14: =IF(OR(NOT(ISNUMBER(W14)),NOT(ISNUMBER($H$34)),NOT(ISNUMBER($C$36))),"",W14*MAX(1,$H$34)*$C$36) | AC14: =IF(OR(NOT(ISNUMBER(W14)),NOT(ISNUMBER(AB14))),"",W14+AB14) | AD14: =IF(OR(NOT(ISNUMBER(W14)),NOT(ISNUMBER($H$34))),"",W14*$H$34) | AE14: =IF(OR(NOT(ISNUMBER(AC14)),NOT(ISNUMBER(AD14))),"",MAX(0,AC14-AD14)) | AF14: =IF(OR(NOT(ISNUMBER(AD14)),NOT(ISNUMBER(W14))),"",AD14-W14) | AH14: =IF(OR(NOT(ISNUMBER(MIETER!F19)),$G14="ja"),"",IF(NOT(ISNUMBER(MIETER!J19)),"",IF(ISNUMBER(AG14),MAX(MIETER!J19,AG14),MIETER!J19))) | AJ14: =IF(OR(NOT(ISNUMBER(AH14)),NOT(ISNUMBER(AI14))),"",MAX(0,AI14-AH14)) | AN14: =IF(NOT(ISNUMBER(F14)),"",IF(AND(NOT(ISNUMBER(AH14)),NOT(ISNUMBER(AL14)),NOT(ISNUMBER(AM14))),"",N(AH14)+N(AL14)+N(AM14))) | AO14: =IF(OR($G14="ja",NOT(ISNUMBER(AH14)),NOT(ISNUMBER(AN14))),"",AN14+N(AJ14)) | AP14: =IF(OR(NOT(ISNUMBER(AH14)),NOT(ISNUMBER(F14)),F14=0),"",AH14/F14) | AQ14: =IF(OR(NOT(ISNUMBER(MIETER!F19)),NOT(ISNUMBER(MIETER!I19))),"",MIETER!I19) | AR14: =IF(OR(NOT(ISNUMBER(AQ14)),$G14="ja",NOT(ISNUMBER($H$35))),"",EDATE(AQ14,$H$35)) | AT14: =IF(NOT(ISNUMBER(F14)),"",IF(ISNUMBER(AS14),AS14,IF(NOT(ISNUMBER(AR14)),"",MAX(0,(YEAR(AR14)-YEAR(TODAY()))*12+MONTH(AR14)-MONTH(TODAY()))))) | AU14: =IF(NOT(ISNUMBER(AT14)),"",IF(ISNUMBER(AK14),AK14*AT14,IF(NOT(ISNUMBER(AJ14)),"",AJ14*AT14))) | AV14: =IF(OR(NOT(ISNUMBER(AH14)),NOT(ISNUMBER(MIETER!$P$6))),"",ROUND(AH14*(1+MIETER!$P$6)^2,0)) | AY14: =IF(NOT(ISNUMBER(F14)),"",IF(ISNUMBER(AX14),AX14,IF(AND(ISNUMBER(AW14),ISNUMBER(AH14),AH14>0),AH14*AW14,IF(OR(NOT(ISNUMBER($C$62)),NOT(ISNUMBER($C$64))),"",$C$62+$C$64*F14/12)))) | BA14: =IF(NOT(ISNUMBER(AY14)),"",IF(ISNUMBER(AZ14),MIN(AY14,AZ14),IF(OR(NOT(ISNUMBER(F14)),NOT(ISNUMBER($C$64))),0,MIN(AY14,$C$64*F14/12)))) | BB14: =IF(OR(NOT(ISNUMBER(AY14)),NOT(ISNUMBER(AH14)),AH14=0),"",AY14/AH14) | BC14: =IF(NOT(ISNUMBER(AH14)),"",AH14*0.01) | BD14: =IF(OR(NOT(ISNUMBER(AH14)),NOT(ISNUMBER($C$28)),NOT(ISNUMBER(BY14)),BY14<=0),"",AH14*0.01*(1-$C$28)/BY14) | BE14: =IF(OR(NOT(ISNUMBER(K14)),NOT(ISNUMBER($H$30))),"",$H$30*K14) | BG14: =IF(OR(NOT(ISNUMBER(BE14)),NOT(ISNUMBER(X14)),X14<=0),"",1-BE14/X14) | BH14: =IF(NOT(ISNUMBER(X14)),"",IF(ISNUMBER(BF14),BF14,IF(AND(ISNUMBER(BE14),ISNUMBER(AA14),AA14>0),1-BE14/AA14,IF(NOT(ISNUMBER($C$31)),"",$C$31)))) | BI14: =IF(NOT(ISNUMBER(F14)),"",IF(ISNUMBER(BF14),"vertrag",IF(ISNUMBER(BE14),"berechnet","standard"))) | BK14: =IF(NOT(ISNUMBER(F14)),"",IF(ISNUMBER(BJ14),BJ14,IF(NOT(ISNUMBER($C$30)),"",$C$30))) | BL14: =IF(OR(NOT(ISNUMBER(AA14)),NOT(ISNUMBER(BH14)),NOT(ISNUMBER($C$36))),"",AA14*(1+$C$36)*BH14) | BM14: =IF(OR(NOT(ISNUMBER(BL14)),NOT(ISNUMBER(BK14)),NOT(ISNUMBER($C$36)),NOT(ISNUMBER($H$34))),"",(BL14*BK14+N(Q14)*MAX(1,$H$34)*(1+$C$36)*N($H$31)+N(R14)*MAX(1,$H$34)*(1+$C$36)*N($H$32))/12) | BN14: =IF(OR(NOT(ISNUMBER(AD14)),NOT(ISNUMBER($C$26))),"",AD14*$C$26/12) | BO14: =IF(OR(NOT(ISNUMBER(AD14)),NOT(ISNUMBER($C$26)),NOT(ISNUMBER($C$27))),"",ROUND(AD14*($C$26+$C$27)/12,0)) | BP14: =IF(OR(NOT(ISNUMBER(AO14)),NOT(ISNUMBER(BM14)),NOT(ISNUMBER(BN14)),NOT(ISNUMBER(AY14))),"",AO14-BN14-BM14-(AY14-N(BA14))) | BQ14: =IF(OR(NOT(ISNUMBER(BP14)),NOT(ISNUMBER($C$28))),"",ROUND(-BP14*$C$28,0)) | BR14: =IF(OR(NOT(ISNUMBER(BA14)),NOT(ISNUMBER($C$28))),"",BA14*$C$28) | BS14: =IF(OR(NOT(ISNUMBER(AO14)),NOT(ISNUMBER(BO14)),NOT(ISNUMBER(AY14))),"",ROUND(AO14,0)-BO14-ROUND(AY14,0)) | BT14: =IF(OR(NOT(ISNUMBER(BS14)),NOT(ISNUMBER(BQ14))),"",BS14+BQ14) | BU14: =IF(OR(NOT(ISNUMBER(AN14)),NOT(ISNUMBER(BO14)),NOT(ISNUMBER(AY14)),NOT(ISNUMBER(BP14)),NOT(ISNUMBER($C$28))),"",ROUND(AN14,0)-BO14-ROUND(AY14,0)+ROUND(-(BP14-N(AJ14))*$C$28,0)) | BV14: =IF(OR(NOT(ISNUMBER(AO14)),NOT(ISNUMBER(AY14)),NOT(ISNUMBER(BK14)),NOT(ISNUMBER($C$28)),NOT(ISNUMBER($C$36))),"",(AO14-AY14)*(1-$C$28)-$C$28*N(BA14)-IF(BI14="berechnet",$C$28*(1+$C$36)*BK14*N(BE14)/12,0)) | BW14: =IF(OR(NOT(ISNUMBER(F14)),NOT(ISNUMBER($C$26)),NOT(ISNUMBER($C$27)),NOT(ISNUMBER($C$28)),NOT(ISNUMBER($C$36))),"",($C$28*(1+$C$36)*(N(Q14)*N($H$31)+N(R14)*N($H$32))-(N(Q14)+N(R14))*(($C$26+$C$27)-$C$28*$C$26))/12) | BX14: =IF(OR(NOT(ISNUMBER(BK14)),NOT(ISNUMBER($C$26)),NOT(ISNUMBER($C$27)),NOT(ISNUMBER($C$28)),NOT(ISNUMBER($C$36)),BI14=""),"",(($C$26+$C$27)-$C$28*$C$26-$C$28*(1+$C$36)*BK14*IF(BI14="berechnet",1,IF(BI14="vertrag",BF14,$C$31)))/12) | BY14: =IF(OR(NOT(ISNUMBER(BX14)),NOT(ISNUMBER($C$34))),"",$C$34*BX14) | BZ14: =IF(OR($G14="ja",NOT(ISNUMBER(AH14)),NOT(ISNUMBER(BV14)),NOT(ISNUMBER(BW14)),NOT(ISNUMBER(BX14)),BX14<=0),"",(BV14-N($C$32)+BW14)/BX14) | CA14: =IF(OR($G14="ja",NOT(ISNUMBER(AH14)),NOT(ISNUMBER(BV14)),NOT(ISNUMBER(BW14)),NOT(ISNUMBER(BY14)),BY14<=0,NOT(ISNUMBER($C$34))),"",(BV14-N($C$32)+BW14*$C$34)/BY14) | CB14: =IF(OR(NOT(ISNUMBER(CA14)),NOT(ISNUMBER($C$28))),"",CA14-N(AJ14)*(1-$C$28)/BY14) | CC14: =IF(OR(NOT(ISNUMBER(CA14)),NOT(ISNUMBER(U14)),U14<=-1,NOT(ISNUMBER(F14)),F14=0),"",((CA14+N(Q14)+N(R14))/(1+U14)-N(Q14)-N(R14)-N(O14))/F14) | CD14: =IF(OR(NOT(ISNUMBER(L14)),NOT(ISNUMBER(CC14))),"",L14-CC14) | CE14: =IF(OR(NOT(ISNUMBER(W14)),NOT(ISNUMBER(AN14)),AN14=0),"",W14/(AN14*12)) | CF14: =IF(OR(NOT(ISNUMBER(W14)),NOT(ISNUMBER(AN14)),W14=0),"",AN14*12/W14) | CG14: =IF(NOT(ISNUMBER(F14)),"",IF($G14="ja","GRAU: Leerstand - keine Mietbasis",IF(AND(ISNUMBER(AH14),AH14=0),"GRAU: Ist-Miete 0 - Leerstand pruefen",IF(NOT(ISNUMBER(AH14)),"GRAU: Wohnungsmiete fehlt",IF(NOT(ISNUMBER(AJ14)),"GRAU: keine Sollmiete/Mietspiegel",IF(AND(ISNUMBER(AW14),ISNUMBER(AX14)),"GRAU: zwei Hausgeld-Quellen gesetzt",IF(AND(OR(ISNUMBER(AX14),ISNUMBER(AW14)),NOT(ISNUMBER(AZ14))),"GRAU: Ruecklagenanteil fehlt",IF(AND(AJ14>0,NOT(ISNUMBER(AT14))),"GRAU: Subventionsdauer unbekannt",IF(AND(ISNUMBER(BH14),BH14<=0),"ROT: Bodenwert uebersteigt Kaufpreis - Daten pruefen",IF(NOT(ISNUMBER(BT14)),"GRAU: Cashflow nicht rechenbar",IF(NOT(ISNUMBER(BZ14)),"GRAU: max. tragbar nicht rechenbar",IF(BZ14<=0,"ROT: kein tragbarer Preis bei diesem Ziel-Cashflow",IF(AND(BI14="berechnet",BZ14<BE14),"ROT: max. tragbar unter Bodenwert - Modell nicht gueltig",IF(X14<=BZ14-N(AJ14)*(1-$C$28)/BX14,"GRUEN: Preis unter max. tragbar (auch ohne Subvention)",IF(X14<=BZ14,"GELB: nur mit Subvention tragbar",IF(X14<=BZ14*(1+N($H$33)),"GELB: bis Toleranz darueber","ROT: deutlich ueber max. tragbar")))))))))))))))) | CH14: =IF(NOT(ISNUMBER(F14)),"",IF($G14="ja","GRAU: Leerstand - keine Mietbasis",IF(AND(ISNUMBER(AH14),AH14=0),"GRAU: Ist-Miete 0 - Leerstand pruefen",IF(NOT(ISNUMBER(AH14)),"GRAU: Wohnungsmiete fehlt",IF(NOT(ISNUMBER(AJ14)),"GRAU: keine Sollmiete/Mietspiegel",IF(AND(ISNUMBER(AW14),ISNUMBER(AX14)),"GRAU: zwei Hausgeld-Quellen gesetzt",IF(AND(OR(ISNUMBER(AX14),ISNUMBER(AW14)),NOT(ISNUMBER(AZ14))),"GRAU: Ruecklagenanteil fehlt",IF(AND(AJ14>0,NOT(ISNUMBER(AT14))),"GRAU: Subventionsdauer unbekannt",IF(AND(ISNUMBER(BH14),BH14<=0),"ROT: Bodenwert uebersteigt Kaufpreis - Daten pruefen",IF(NOT(ISNUMBER(BT14)),"GRAU: Cashflow nicht rechenbar",IF(NOT(ISNUMBER(CA14)),"GRAU: max. tragbar nicht rechenbar",IF(CA14<=0,"ROT: kein tragbarer Preis bei diesem Ziel-Cashflow",IF(AND(BI14="berechnet",CA14<BE14),"ROT: max. tragbar unter Bodenwert - Modell nicht gueltig",IF(X14<=CB14,"GRUEN: Preis unter max. tragbar (auch ohne Subvention)",IF(X14<=CA14,"GELB: nur mit Subvention tragbar",IF(X14<=CA14*(1+N($H$33)),"GELB: bis Toleranz darueber","ROT: deutlich ueber max. tragbar"))))))))))))))))
... A22: =IF(NOT(ISNUMBER(MIETER!F27)),"",ROW()-2) | B22: =IF(NOT(ISNUMBER(MIETER!F27)),"",IF(MIETER!A27="","",MIETER!A27)) | C22: =IF(NOT(ISNUMBER(MIETER!F27)),"",IF(MIETER!B27="","",MIETER!B27)) | D22: =IF(NOT(ISNUMBER(MIETER!F27)),"",IF(MIETER!C27="","",MIETER!C27)) | E22: =IF(NOT(ISNUMBER(MIETER!F27)),"",IF(MIETER!D27="","",MIETER!D27)) | F22: =IF(NOT(ISNUMBER(MIETER!F27)),"",MIETER!F27) | K22: =IF(OR(NOT(ISNUMBER(F22)),NOT(ISNUMBER(J22)),NOT(ISNUMBER($H$29)),$H$29=0),"",J22/$H$29) | M22: =IF(OR(NOT(ISNUMBER(F22)),F22=0,NOT(ISNUMBER(VERKAUFSMATRIX!U25))),"",VERKAUFSMATRIX!U25/F22) | N22: =IF(OR(NOT(ISNUMBER(L22)),NOT(ISNUMBER(M22)),M22=0),"",L22/M22-1) | P22: =IF(OR(NOT(ISNUMBER(F22)),NOT(ISNUMBER(L22))),"",F22*L22+N(O22)) | S22: =IF(NOT(ISNUMBER(P22)),"",P22+N(Q22)+N(R22)) | U22: =IF(NOT(ISNUMBER(F22)),"",IF(ISNUMBER(T22),T22,IF(NOT(ISNUMBER($H$26)),"",$H$26))) | V22: =IF(OR(NOT(ISNUMBER(S22)),NOT(ISNUMBER(U22))),"",S22*U22) | W22: =IF(OR(NOT(ISNUMBER(S22)),NOT(ISNUMBER(U22))),"",S22*(1+U22)) | X22: =IF(NOT(ISNUMBER(W22)),"",W22-N(Q22)-N(R22)) | Y22: =IF(OR(NOT(ISNUMBER(S22)),NOT(ISNUMBER(F22)),F22=0),"",S22/F22) | Z22: =IF(OR(NOT(ISNUMBER(X22)),NOT(ISNUMBER(F22)),F22=0),"",X22/F22) | AA22: =IF(OR(NOT(ISNUMBER(X22)),NOT(ISNUMBER($H$34))),"",X22*MAX(1,$H$34)) | AB22: =IF(OR(NOT(ISNUMBER(W22)),NOT(ISNUMBER($H$34)),NOT(ISNUMBER($C$36))),"",W22*MAX(1,$H$34)*$C$36) | AC22: =IF(OR(NOT(ISNUMBER(W22)),NOT(ISNUMBER(AB22))),"",W22+AB22) | AD22: =IF(OR(NOT(ISNUMBER(W22)),NOT(ISNUMBER($H$34))),"",W22*$H$34) | AE22: =IF(OR(NOT(ISNUMBER(AC22)),NOT(ISNUMBER(AD22))),"",MAX(0,AC22-AD22)) | AF22: =IF(OR(NOT(ISNUMBER(AD22)),NOT(ISNUMBER(W22))),"",AD22-W22) | AH22: =IF(OR(NOT(ISNUMBER(MIETER!F27)),$G22="ja"),"",IF(NOT(ISNUMBER(MIETER!J27)),"",IF(ISNUMBER(AG22),MAX(MIETER!J27,AG22),MIETER!J27))) | AJ22: =IF(OR(NOT(ISNUMBER(AH22)),NOT(ISNUMBER(AI22))),"",MAX(0,AI22-AH22)) | AN22: =IF(NOT(ISNUMBER(F22)),"",IF(AND(NOT(ISNUMBER(AH22)),NOT(ISNUMBER(AL22)),NOT(ISNUMBER(AM22))),"",N(AH22)+N(AL22)+N(AM22))) | AO22: =IF(OR($G22="ja",NOT(ISNUMBER(AH22)),NOT(ISNUMBER(AN22))),"",AN22+N(AJ22)) | AP22: =IF(OR(NOT(ISNUMBER(AH22)),NOT(ISNUMBER(F22)),F22=0),"",AH22/F22) | AQ22: =IF(OR(NOT(ISNUMBER(MIETER!F27)),NOT(ISNUMBER(MIETER!I27))),"",MIETER!I27) | AR22: =IF(OR(NOT(ISNUMBER(AQ22)),$G22="ja",NOT(ISNUMBER($H$35))),"",EDATE(AQ22,$H$35)) | AT22: =IF(NOT(ISNUMBER(F22)),"",IF(ISNUMBER(AS22),AS22,IF(NOT(ISNUMBER(AR22)),"",MAX(0,(YEAR(AR22)-YEAR(TODAY()))*12+MONTH(AR22)-MONTH(TODAY()))))) | AU22: =IF(NOT(ISNUMBER(AT22)),"",IF(ISNUMBER(AK22),AK22*AT22,IF(NOT(ISNUMBER(AJ22)),"",AJ22*AT22))) | AV22: =IF(OR(NOT(ISNUMBER(AH22)),NOT(ISNUMBER(MIETER!$P$6))),"",ROUND(AH22*(1+MIETER!$P$6)^2,0)) | AY22: =IF(NOT(ISNUMBER(F22)),"",IF(ISNUMBER(AX22),AX22,IF(AND(ISNUMBER(AW22),ISNUMBER(AH22),AH22>0),AH22*AW22,IF(OR(NOT(ISNUMBER($C$62)),NOT(ISNUMBER($C$64))),"",$C$62+$C$64*F22/12)))) | BA22: =IF(NOT(ISNUMBER(AY22)),"",IF(ISNUMBER(AZ22),MIN(AY22,AZ22),IF(OR(NOT(ISNUMBER(F22)),NOT(ISNUMBER($C$64))),0,MIN(AY22,$C$64*F22/12)))) | BB22: =IF(OR(NOT(ISNUMBER(AY22)),NOT(ISNUMBER(AH22)),AH22=0),"",AY22/AH22) | BC22: =IF(NOT(ISNUMBER(AH22)),"",AH22*0.01) | BD22: =IF(OR(NOT(ISNUMBER(AH22)),NOT(ISNUMBER($C$28)),NOT(ISNUMBER(BY22)),BY22<=0),"",AH22*0.01*(1-$C$28)/BY22) | BE22: =IF(OR(NOT(ISNUMBER(K22)),NOT(ISNUMBER($H$30))),"",$H$30*K22) | BG22: =IF(OR(NOT(ISNUMBER(BE22)),NOT(ISNUMBER(X22)),X22<=0),"",1-BE22/X22) | BH22: =IF(NOT(ISNUMBER(X22)),"",IF(ISNUMBER(BF22),BF22,IF(AND(ISNUMBER(BE22),ISNUMBER(AA22),AA22>0),1-BE22/AA22,IF(NOT(ISNUMBER($C$31)),"",$C$31)))) | BI22: =IF(NOT(ISNUMBER(F22)),"",IF(ISNUMBER(BF22),"vertrag",IF(ISNUMBER(BE22),"berechnet","standard"))) | BK22: =IF(NOT(ISNUMBER(F22)),"",IF(ISNUMBER(BJ22),BJ22,IF(NOT(ISNUMBER($C$30)),"",$C$30))) | BL22: =IF(OR(NOT(ISNUMBER(AA22)),NOT(ISNUMBER(BH22)),NOT(ISNUMBER($C$36))),"",AA22*(1+$C$36)*BH22) | BM22: =IF(OR(NOT(ISNUMBER(BL22)),NOT(ISNUMBER(BK22)),NOT(ISNUMBER($C$36)),NOT(ISNUMBER($H$34))),"",(BL22*BK22+N(Q22)*MAX(1,$H$34)*(1+$C$36)*N($H$31)+N(R22)*MAX(1,$H$34)*(1+$C$36)*N($H$32))/12) | BN22: =IF(OR(NOT(ISNUMBER(AD22)),NOT(ISNUMBER($C$26))),"",AD22*$C$26/12) | BO22: =IF(OR(NOT(ISNUMBER(AD22)),NOT(ISNUMBER($C$26)),NOT(ISNUMBER($C$27))),"",ROUND(AD22*($C$26+$C$27)/12,0)) | BP22: =IF(OR(NOT(ISNUMBER(AO22)),NOT(ISNUMBER(BM22)),NOT(ISNUMBER(BN22)),NOT(ISNUMBER(AY22))),"",AO22-BN22-BM22-(AY22-N(BA22))) | BQ22: =IF(OR(NOT(ISNUMBER(BP22)),NOT(ISNUMBER($C$28))),"",ROUND(-BP22*$C$28,0)) | BR22: =IF(OR(NOT(ISNUMBER(BA22)),NOT(ISNUMBER($C$28))),"",BA22*$C$28) | BS22: =IF(OR(NOT(ISNUMBER(AO22)),NOT(ISNUMBER(BO22)),NOT(ISNUMBER(AY22))),"",ROUND(AO22,0)-BO22-ROUND(AY22,0)) | BT22: =IF(OR(NOT(ISNUMBER(BS22)),NOT(ISNUMBER(BQ22))),"",BS22+BQ22) | BU22: =IF(OR(NOT(ISNUMBER(AN22)),NOT(ISNUMBER(BO22)),NOT(ISNUMBER(AY22)),NOT(ISNUMBER(BP22)),NOT(ISNUMBER($C$28))),"",ROUND(AN22,0)-BO22-ROUND(AY22,0)+ROUND(-(BP22-N(AJ22))*$C$28,0)) | BV22: =IF(OR(NOT(ISNUMBER(AO22)),NOT(ISNUMBER(AY22)),NOT(ISNUMBER(BK22)),NOT(ISNUMBER($C$28)),NOT(ISNUMBER($C$36))),"",(AO22-AY22)*(1-$C$28)-$C$28*N(BA22)-IF(BI22="berechnet",$C$28*(1+$C$36)*BK22*N(BE22)/12,0)) | BW22: =IF(OR(NOT(ISNUMBER(F22)),NOT(ISNUMBER($C$26)),NOT(ISNUMBER($C$27)),NOT(ISNUMBER($C$28)),NOT(ISNUMBER($C$36))),"",($C$28*(1+$C$36)*(N(Q22)*N($H$31)+N(R22)*N($H$32))-(N(Q22)+N(R22))*(($C$26+$C$27)-$C$28*$C$26))/12) | BX22: =IF(OR(NOT(ISNUMBER(BK22)),NOT(ISNUMBER($C$26)),NOT(ISNUMBER($C$27)),NOT(ISNUMBER($C$28)),NOT(ISNUMBER($C$36)),BI22=""),"",(($C$26+$C$27)-$C$28*$C$26-$C$28*(1+$C$36)*BK22*IF(BI22="berechnet",1,IF(BI22="vertrag",BF22,$C$31)))/12) | BY22: =IF(OR(NOT(ISNUMBER(BX22)),NOT(ISNUMBER($C$34))),"",$C$34*BX22) | BZ22: =IF(OR($G22="ja",NOT(ISNUMBER(AH22)),NOT(ISNUMBER(BV22)),NOT(ISNUMBER(BW22)),NOT(ISNUMBER(BX22)),BX22<=0),"",(BV22-N($C$32)+BW22)/BX22) | CA22: =IF(OR($G22="ja",NOT(ISNUMBER(AH22)),NOT(ISNUMBER(BV22)),NOT(ISNUMBER(BW22)),NOT(ISNUMBER(BY22)),BY22<=0,NOT(ISNUMBER($C$34))),"",(BV22-N($C$32)+BW22*$C$34)/BY22) | CB22: =IF(OR(NOT(ISNUMBER(CA22)),NOT(ISNUMBER($C$28))),"",CA22-N(AJ22)*(1-$C$28)/BY22) | CC22: =IF(OR(NOT(ISNUMBER(CA22)),NOT(ISNUMBER(U22)),U22<=-1,NOT(ISNUMBER(F22)),F22=0),"",((CA22+N(Q22)+N(R22))/(1+U22)-N(Q22)-N(R22)-N(O22))/F22) | CD22: =IF(OR(NOT(ISNUMBER(L22)),NOT(ISNUMBER(CC22))),"",L22-CC22) | CE22: =IF(OR(NOT(ISNUMBER(W22)),NOT(ISNUMBER(AN22)),AN22=0),"",W22/(AN22*12)) | CF22: =IF(OR(NOT(ISNUMBER(W22)),NOT(ISNUMBER(AN22)),W22=0),"",AN22*12/W22) | CG22: =IF(NOT(ISNUMBER(F22)),"",IF($G22="ja","GRAU: Leerstand - keine Mietbasis",IF(AND(ISNUMBER(AH22),AH22=0),"GRAU: Ist-Miete 0 - Leerstand pruefen",IF(NOT(ISNUMBER(AH22)),"GRAU: Wohnungsmiete fehlt",IF(NOT(ISNUMBER(AJ22)),"GRAU: keine Sollmiete/Mietspiegel",IF(AND(ISNUMBER(AW22),ISNUMBER(AX22)),"GRAU: zwei Hausgeld-Quellen gesetzt",IF(AND(OR(ISNUMBER(AX22),ISNUMBER(AW22)),NOT(ISNUMBER(AZ22))),"GRAU: Ruecklagenanteil fehlt",IF(AND(AJ22>0,NOT(ISNUMBER(AT22))),"GRAU: Subventionsdauer unbekannt",IF(AND(ISNUMBER(BH22),BH22<=0),"ROT: Bodenwert uebersteigt Kaufpreis - Daten pruefen",IF(NOT(ISNUMBER(BT22)),"GRAU: Cashflow nicht rechenbar",IF(NOT(ISNUMBER(BZ22)),"GRAU: max. tragbar nicht rechenbar",IF(BZ22<=0,"ROT: kein tragbarer Preis bei diesem Ziel-Cashflow",IF(AND(BI22="berechnet",BZ22<BE22),"ROT: max. tragbar unter Bodenwert - Modell nicht gueltig",IF(X22<=BZ22-N(AJ22)*(1-$C$28)/BX22,"GRUEN: Preis unter max. tragbar (auch ohne Subvention)",IF(X22<=BZ22,"GELB: nur mit Subvention tragbar",IF(X22<=BZ22*(1+N($H$33)),"GELB: bis Toleranz darueber","ROT: deutlich ueber max. tragbar")))))))))))))))) | CH22: =IF(NOT(ISNUMBER(F22)),"",IF($G22="ja","GRAU: Leerstand - keine Mietbasis",IF(AND(ISNUMBER(AH22),AH22=0),"GRAU: Ist-Miete 0 - Leerstand pruefen",IF(NOT(ISNUMBER(AH22)),"GRAU: Wohnungsmiete fehlt",IF(NOT(ISNUMBER(AJ22)),"GRAU: keine Sollmiete/Mietspiegel",IF(AND(ISNUMBER(AW22),ISNUMBER(AX22)),"GRAU: zwei Hausgeld-Quellen gesetzt",IF(AND(OR(ISNUMBER(AX22),ISNUMBER(AW22)),NOT(ISNUMBER(AZ22))),"GRAU: Ruecklagenanteil fehlt",IF(AND(AJ22>0,NOT(ISNUMBER(AT22))),"GRAU: Subventionsdauer unbekannt",IF(AND(ISNUMBER(BH22),BH22<=0),"ROT: Bodenwert uebersteigt Kaufpreis - Daten pruefen",IF(NOT(ISNUMBER(BT22)),"GRAU: Cashflow nicht rechenbar",IF(NOT(ISNUMBER(CA22)),"GRAU: max. tragbar nicht rechenbar",IF(CA22<=0,"ROT: kein tragbarer Preis bei diesem Ziel-Cashflow",IF(AND(BI22="berechnet",CA22<BE22),"ROT: max. tragbar unter Bodenwert - Modell nicht gueltig",IF(X22<=CB22,"GRUEN: Preis unter max. tragbar (auch ohne Subvention)",IF(X22<=CA22,"GELB: nur mit Subvention tragbar",IF(X22<=CA22*(1+N($H$33)),"GELB: bis Toleranz darueber","ROT: deutlich ueber max. tragbar"))))))))))))))))
A23: SUMME / Ø | F23: =SUM(F3:F22) | G23: =COUNTIF(G3:G22,"ja") | H23: =SUM(H3:H22) | I23: =SUM(I3:I22) | J23: =SUM(J3:J22) | K23: =IF(OR(NOT(ISNUMBER(J23)),NOT(ISNUMBER($H$29)),$H$29=0),"",J23/$H$29) | L23: =IF(SUMIF(L3:L22,">0",F3:F22)=0,"",SUMPRODUCT(F3:F22,L3:L22)/SUMIF(L3:L22,">0",F3:F22)) | M23: =IF(OR(NOT(ISNUMBER(F23)),F23=0,NOT(ISNUMBER(VERKAUFSMATRIX!U28))),"",VERKAUFSMATRIX!U28/F23) | N23: =IF(OR(NOT(ISNUMBER(L23)),NOT(ISNUMBER(M23)),M23=0),"",L23/M23-1) | O23: =SUM(O3:O22) | P23: =SUM(P3:P22) | Q23: =SUM(Q3:Q22) | R23: =SUM(R3:R22) | S23: =SUM(S3:S22) | T23: =IF(OR(NOT(ISNUMBER(V23)),NOT(ISNUMBER(S23)),S23=0),"",V23/S23) | V23: =SUM(V3:V22) | W23: =SUM(W3:W22) | X23: =SUM(X3:X22) | Y23: =IF(OR(NOT(ISNUMBER(S23)),NOT(ISNUMBER(F23)),F23=0),"",S23/F23) | Z23: =IF(OR(NOT(ISNUMBER(X23)),NOT(ISNUMBER(F23)),F23=0),"",X23/F23) | AA23: =SUM(AA3:AA22) | AB23: =SUM(AB3:AB22) | AC23: =SUM(AC3:AC22) | AD23: =SUM(AD3:AD22) | AE23: =SUM(AE3:AE22) | AF23: =SUM(AF3:AF22) | AG23: =COUNT(AG3:AG22)&" WE manuell" | AH23: =SUM(AH3:AH22) | AI23: =SUM(AI3:AI22) | AJ23: =SUM(AJ3:AJ22) | AK23: =SUM(AK3:AK22) | AL23: =SUM(AL3:AL22) | AM23: =SUM(AM3:AM22) | AN23: =SUM(AN3:AN22) | AO23: =SUM(AO3:AO22) | AP23: =IF(SUMPRODUCT(--ISNUMBER(AH3:AH22),F3:F22)=0,"",AH23/SUMPRODUCT(--ISNUMBER(AH3:AH22),F3:F22)) | AQ23: =IF(COUNT(AQ3:AQ22)=0,"",MIN(AQ3:AQ22)) | AR23: =IF(COUNT(AR3:AR22)=0,"",MAX(AR3:AR22)) | AT23: =IF(COUNT(AT3:AT22)=0,"",MAX(AT3:AT22)) | AU23: =SUM(AU3:AU22) | AV23: =SUM(AV3:AV22) | AY23: =SUM(AY3:AY22) | BA23: =SUM(BA3:BA22) | BB23: =IF(OR(NOT(ISNUMBER(AY23)),NOT(ISNUMBER(AH23)),AH23=0),"",AY23/AH23) | BC23: =SUM(BC3:BC22) | BD23: =SUM(BD3:BD22) | BE23: =SUM(BE3:BE22) | BG23: =IF(OR(NOT(ISNUMBER(BE23)),NOT(ISNUMBER(X23)),X23=0),"",1-BE23/X23) | BH23: =IF(OR(NOT(ISNUMBER(BE23)),NOT(ISNUMBER(AA23)),AA23=0),"",1-BE23/AA23) | BL23: =SUM(BL3:BL22) | BM23: =SUM(BM3:BM22) | BN23: =SUM(BN3:BN22) | BO23: =SUM(BO3:BO22) | BP23: =SUM(BP3:BP22) | BQ23: =SUM(BQ3:BQ22) | BR23: =SUM(BR3:BR22) | BS23: =SUM(BS3:BS22) | ... BW23: =SUM(BW3:BW22) | BZ23: =IF(COUNT(BZ3:BZ22)=0,"",SUMIF(BZ3:BZ22,">0")) | CA23: =IF(COUNT(CA3:CA22)=0,"",SUMIF(CA3:CA22,">0")) | CB23: =IF(COUNT(CB3:CB22)=0,"",SUMIF(CB3:CB22,">0")) | CC23: =IF(OR(NOT(ISNUMBER(CA23)),NOT(ISNUMBER(T23)),T23<=-1,NOT(ISNUMBER(F23)),F23=0),"",((CA23+N(Q23)+N(R23))/(1+T23)-N(Q23)-N(R23)-N(O23))/F23) | CD23: =IF(OR(NOT(ISNUMBER(L23)),NOT(ISNUMBER(CC23))),"",L23-CC23) | CE23: =IF(OR(NOT(ISNUMBER(W23)),NOT(ISNUMBER(AN23)),AN23=0),"",W23/(AN23*12)) | CF23: =IF(OR(NOT(ISNUMBER(W23)),NOT(ISNUMBER(AN23)),W23=0),"",AN23*12/W23) | CG23: =COUNTIF(CG3:CG22,"GRUEN*")&" gruen / "&COUNTIF(CG3:CG22,"GELB*")&" gelb / "&COUNTIF(CG3:CG22,"ROT*")&" rot / "&COUNTIF(CG3:CG22,"GRAU*")&" grau" | CH23: =COUNTIF(CH3:CH22,"GRUEN*")&" gruen / "&COUNTIF(CH3:CH22,"GELB*")&" gelb / "&COUNTIF(CH3:CH22,"ROT*")&" rot / "&COUNTIF(CH3:CH22,"GRAU*")&" grau"
A25: KÄUFER-PROFIL (Standard für alle Wohnungen — je Wohnung überschreibbar) | E25: OBJEKT, ASSETS, STEUERUNG | J25: LEGENDE
A26: Zins Käufer (p.a.) | C26: 0.048 | E26: Provision Standard (% vom Abgabepreis) | H26: 0.07 | J26: Hellgelb = Eingabe je Wohnung; leer = Standard aus dem Käuferprofil greift
A27: Tilgung Käufer (p.a.) | C27: 0.01 | E27: Grundstücksfläche gesamt (m²) | J27: Ampel: Grün = Preis trägt, Gelb = knapp (Toleranz), Rot = über max. tragbar oder Datenfehler, Grau = Angabe fehlt
A28: Grenzsteuersatz | C28: 0.42 | E28: Bodenrichtwert (€/m²) | J28: Mint = Standard-Rückfall aktiv (Feld leer); Orange = Ist-Miete manuell angehoben / Eigenkapital trotz Vollfinanzierung
A29: Bewirtschaftungsquote (Alt-Kontrolle) | C29: =IF(OR(NOT(ISNUMBER(C66)),NOT(ISNUMBER(C67)),NOT(ISNUMBER($C$69)),$C$69=0),"",(C66+C67)/$C$69) | E29: MEA-Nenner (Teilungserklärung) | J29: Rücklage mindert nur den Cashflow, nicht die Steuer (BFH IX R 19/24); Hausgeld ohne Wirtschaftsplan = Verwaltung + Rücklage-Standard
A30: AfA-Satz Wohnung (Standard) | C30: 0.02 | E30: Bodenwert Haus gesamt (€) | H30: =IF(OR(NOT(ISNUMBER($H$27)),NOT(ISNUMBER($H$28))),"",$H$27*$H$28) | J30: Kontrollspalten: max. tragbar = (Ertrag nach Steuer ohne Finanzierung − Ziel-CF + Garage/Stellplatz netto) / k
A31: Gebäudeanteil (Standard) | C31: 0.8 | E31: AfA-Satz Garage (p.a.) | H31: 0.02 | J31: k = Loan-Faktor × [(Zins + Tilgung) − s × Zins − s × (1 + KNK) × AfA × Grenz-Gebäudeanteil] / 12
A32: Ziel-Cashflow nach Steuer (€/Mo) | C32: 0 | E32: AfA-Satz Außenstellplatz (0 %) | H32: 0 | J32: Hilfsspalten sind per Gruppierung eingeklappt — Schaltfläche + über der Tabelle
A33: Finanzierung: 1 = 100 % KP, 2 = alles finanziert | C33: 1 | E33: Ampel-Toleranz über max. tragbar | H33: 0.1
A34: Loan-Faktor alles finanziert = 1/(1−KNK) | C34: =IF(OR(NOT(ISNUMBER($C$36)),$C$36<0,$C$36>=1),"",1/(1-$C$36)) | E34: Loan-Faktor Vorwärtsrechnung (aus Finanzierung) | H34: =IF(NOT(ISNUMBER($C$33)),"",IF($C$33=1,1,IF(NOT(ISNUMBER($C$34)),"",$C$34)))
A35: k-Faktor global (Alt-Kontrolle) | C35: =IF(OR(NOT(ISNUMBER($H$34)),NOT(ISNUMBER($C$26)),NOT(ISNUMBER($C$27)),NOT(ISNUMBER($C$28)),NOT(ISNUMBER($C$30)),NOT(ISNUMBER($C$31)),NOT(ISNUMBER($C$36))),"",$H$34*(($C$26+$C$27)-$C$28*$C$26-$C$28*$C$31*$C$30*(1+$C$36))/12) | E35: Sperrfrist Mieterhöhung (Monate) | H35: 36
A36: Kaufnebenkosten (GrESt 6,5 % + Notar/GB 2 %) | C36: 0.085
A41: VERGLEICH: MARKT-ANSATZ vs. VORWAERTS-ANSATZ
A43: VK Wohnungen MARKT-ANSATZ (VERKAUFSMATRIX!U28) | C43: =IFERROR(VERKAUFSMATRIX!U28,0)
A44: VK Wohnungen VORWAERTS-ANSATZ (Abgabepreis inkl. Aufschlag, ohne Garage/Provision) | C44: =P23
A45: Kaufpreis Garagen + Stellplätze gesamt (€) | C45: =IF(AND(NOT(ISNUMBER(Q23)),NOT(ISNUMBER(R23))),"",N(Q23)+N(R23))
A48: Delta (CF − Markt) in EUR | C48: =IFERROR(C44-C43,"")
A49: Delta (CF − Markt) in % | C49: =IFERROR((C44-C43)/C43,"")
A50: Empfehlung | C50: =IF(C49="","",IF(ABS(C49)<0.1,"GRÜN: VK robust",IF(ABS(C49)<0.25,"GELB: Delta beachten","ROT: Starker Spread - prüfen")))
A53: SENSITIVITAET: SUMME MAX. TRAGBAR (109,3 %) BEI ZINS-SHIFT (Alt-Kontrolle, globale Annahmen)
A55: Zins-Szenario | B55: Zins | C55: k-Faktor | D55: VK CF gesamt (WEs + Garagen) | E55: Delta zu Basis
A56: Zins −0,5% | B56: =$C$26+-0.005 | C56: =$H$34*((B56+$C$27)-$C$28*B56-$C$28*$C$31*$C$30*(1+$C$36))/12 | D56: =IFERROR(($C$35/C56)*$CA$23+$C$45,"") | E56: =IFERROR(D56-D57,"")
A57: Aktuell (Basis) | B57: =$C$26+0 | C57: =$H$34*((B57+$C$27)-$C$28*B57-$C$28*$C$31*$C$30*(1+$C$36))/12 | D57: =IFERROR($CA$23+$C$45,"")
A58: Zins +0,5% | B58: =$C$26+0.005 | C58: =$H$34*((B58+$C$27)-$C$28*B58-$C$28*$C$31*$C$30*(1+$C$36))/12 | D58: =IFERROR(($C$35/C58)*$CA$23+$C$45,"") | E58: =IFERROR(D58-D57,"")
A59: Zins +1,0% | B59: =$C$26+0.01 | C59: =$H$34*((B59+$C$27)-$C$28*B59-$C$28*$C$31*$C$30*(1+$C$36))/12 | D59: =IFERROR(($C$35/C59)*$CA$23+$C$45,"") | E59: =IFERROR(D59-D57,"")
A61: BEWIRTSCHAFTUNG (nicht umlagefaehig) - Standard fuer Wohnungen ohne Hausgeld-Angabe; speist die Alt-Kontrolle
A62: Verwaltung (EUR/WE/Monat) - Standardquelle Stufe 3 fuer AY | C62: 35
A63: Anzahl WE | C63: =COUNT(F3:F22)
A64: Laufende Rücklage (€/m²/Jahr) - Standard/Obergrenze fuer AY und BA | C64: 14
A65: Wohnfläche gesamt (m2) | C65: =F23
A66: Verwaltung gesamt (EUR/Jahr) | C66: =C62*C63*12
A67: Ruecklage gesamt (EUR/Jahr) | C67: =C64*C65
A68: Ruecklage ueber 10 Jahre (EUR) | C68: =C67*10
A69: Nettokaltmiete IST (€/Jahr) | C69: =IF(NOT(ISNUMBER(AH23)),"",AH23*12)
A70: -> Bewirtschaftungsquote C8 | C70: =$C$29
A73: RUECKLAGEN-TOPF -> Quote & max. Verkaufspreis (Alt-Kontrolle, globale Annahmen)
A74: Vorhandene WEG-Ruecklage (Referenz) | C74: =IFERROR(BESICHTIGUNG!B11,0)
A75: 10-Jahres-Bedarf (EUR) | C75: =C68
A76: Topf EUR | B76: Rueckl. EUR/m2 | C76: Rueckl. EUR/Jahr | D76: Quote C8 | E76: max. VK-Preis
A77: 0 | B77: =MAX(0,($C$75-A77)/10)/$C$65 | C77: =MAX(0,($C$75-A77)/10) | D77: =IF(OR(NOT(ISNUMBER($C$69)),$C$69=0),"",($C$66+C77)/$C$69) | E77: =(((1-$C$28)*(1-D77)*$AH$23)-$C$63*$C$32)/$C$35
A78: 5000 | B78: =MAX(0,($C$75-A78)/10)/$C$65 | C78: =MAX(0,($C$75-A78)/10) | D78: =IF(OR(NOT(ISNUMBER($C$69)),$C$69=0),"",($C$66+C78)/$C$69) | E78: =(((1-$C$28)*(1-D78)*$AH$23)-$C$63*$C$32)/$C$35
A79: 10000 | B79: =MAX(0,($C$75-A79)/10)/$C$65 | C79: =MAX(0,($C$75-A79)/10) | D79: =IF(OR(NOT(ISNUMBER($C$69)),$C$69=0),"",($C$66+C79)/$C$69) | E79: =(((1-$C$28)*(1-D79)*$AH$23)-$C$63*$C$32)/$C$35
A80: 15000 | B80: =MAX(0,($C$75-A80)/10)/$C$65 | C80: =MAX(0,($C$75-A80)/10) | D80: =IF(OR(NOT(ISNUMBER($C$69)),$C$69=0),"",($C$66+C80)/$C$69) | E80: =(((1-$C$28)*(1-D80)*$AH$23)-$C$63*$C$32)/$C$35
A81: 20000 | B81: =MAX(0,($C$75-A81)/10)/$C$65 | C81: =MAX(0,($C$75-A81)/10) | D81: =IF(OR(NOT(ISNUMBER($C$69)),$C$69=0),"",($C$66+C81)/$C$69) | E81: =(((1-$C$28)*(1-D81)*$AH$23)-$C$63*$C$32)/$C$35
A82: 25000 | B82: =MAX(0,($C$75-A82)/10)/$C$65 | C82: =MAX(0,($C$75-A82)/10) | D82: =IF(OR(NOT(ISNUMBER($C$69)),$C$69=0),"",($C$66+C82)/$C$69) | E82: =(((1-$C$28)*(1-D82)*$AH$23)-$C$63*$C$32)/$C$35
A83: 30000 | B83: =MAX(0,($C$75-A83)/10)/$C$65 | C83: =MAX(0,($C$75-A83)/10) | D83: =IF(OR(NOT(ISNUMBER($C$69)),$C$69=0),"",($C$66+C83)/$C$69) | E83: =(((1-$C$28)*(1-D83)*$AH$23)-$C$63*$C$32)/$C$35
A84: 35000 | B84: =MAX(0,($C$75-A84)/10)/$C$65 | C84: =MAX(0,($C$75-A84)/10) | D84: =IF(OR(NOT(ISNUMBER($C$69)),$C$69=0),"",($C$66+C84)/$C$69) | E84: =(((1-$C$28)*(1-D84)*$AH$23)-$C$63*$C$32)/$C$35
A85: 40000 | B85: =MAX(0,($C$75-A85)/10)/$C$65 | C85: =MAX(0,($C$75-A85)/10) | D85: =IF(OR(NOT(ISNUMBER($C$69)),$C$69=0),"",($C$66+C85)/$C$69) | E85: =(((1-$C$28)*(1-D85)*$AH$23)-$C$63*$C$32)/$C$35
A86: 45000 | B86: =MAX(0,($C$75-A86)/10)/$C$65 | C86: =MAX(0,($C$75-A86)/10) | D86: =IF(OR(NOT(ISNUMBER($C$69)),$C$69=0),"",($C$66+C86)/$C$69) | E86: =(((1-$C$28)*(1-D86)*$AH$23)-$C$63*$C$32)/$C$35
A87: 50000 | B87: =MAX(0,($C$75-A87)/10)/$C$65 | C87: =MAX(0,($C$75-A87)/10) | D87: =IF(OR(NOT(ISNUMBER($C$69)),$C$69=0),"",($C$66+C87)/$C$69) | E87: =(((1-$C$28)*(1-D87)*$AH$23)-$C$63*$C$32)/$C$35

Sheet Marktpreis Verifizierung
C2: Name | D2: Firma | F2: Telefon | G2: Worst-Case | H2: Best Case
B3: 1 | C3: Max Makler | D3: Homeday | F3: 0151/12626547 | G3: 2700 | H3: 3000
B4: 2
B5: 3
B6: 4
B7: 5
B8: 6
B9: 7
B10: 8
B11: 9
B12: 10
F14: Durschnitt | G14: =AVERAGE(G3:G12) | H14: =AVERAGE(H3:H12)
F15: Gesamt Durschnitt | G15: =AVERAGE(G14,H14)
B18: TEST BALLON 1 (leerstehend) | F18: TEST BALLON 2 (vermietet)
G19: Kaltmiete = | H19: 500
B20: Ballon Inseriert am | D20: 45485 | F20: Ballon Inseriert am
B21: Ballon war X Tage online | F21: Ballon war X Tage online
B22: Welches Bildmaterial wurde verwendet | F22: Welches Bildmaterial wurde verwendet
B23: Zustand der Wohnung | F23: Zustand der Wohnung
B24: Wie viele Anfragen? | F24: Wie viele Anfragen?
B25: Davon Makler Anfragen | F25: Davon Makler Anfragen
B26: Rest Anfragen | D26: =D24-D25 | F26: Rest Anfragen | H26: =H24-H25
B28: Link zum Inserat | F28: Link zum Inserat

Sheet Checkliste Objektprüfung
B2: OBJEKTUNTERLAGEN | G2: ZIELGRUPPE VERKAUF
B3: ERFORDERLICH FÜR OBJEKTPRÜFUNG | C3: VORHANDEN? | D3: GEPRÜFT? | E3: BESONDERHEITEN | G3: Beschreibung
B4: Expose/Bilder | C4: Ja | D4: Ja
B5: Grundbuch (nicht älter als 3 Monate) | C5: Ja | D5: Ja
B6: Grundrisse | C6: Ja | D6: Ja
B7: Wohnflächenberechnung | C7: Ja | D7: Ja | G7: STRATEGIE
C8: =IF(OR(COUNTIF(C4:C5,"Nein")>0, COUNTIF(C6:C7,"Nein")>0), "Objektunterlagen noch nicht vollständig!", "Objektunterlagen vollständig!") | D8: =IF(OR(COUNTIF(D4:D5,"Nein")>0, COUNTIF(D6:D7,"Nein")>0), "Objektunterlagen noch nicht vollständig!", "Objektunterlagen vollständig!") | E8: =IF(OR(COUNTIF(C4:C5,"Nein")>0, COUNTIF(C6:C7,"Nein")>0, COUNTIF(D4:D5,"Nein")>0, COUNTIF(D6:D7,"Nein")>0), "Objektunterlagen noch nicht vollständig/geprüft!", HYPERLINK("https://freiheit-mit-immobilien.mymemberspot.de/library/baGnXp5W4n1asNko0Rmx/4uzt76RlLRjCUoTXLc5B/6enCHKFepesO93y22M4v/details", "OBJEKTPRÜFUNG EINREICHEN")) | G8: Beschreibung
B10: ERFORDERLICH FÜR FINANZIERUNG | C10: VORHANDEN? | D10: GEPRÜFT? | E10: BESONDERHEITEN | G10: OBJEKTGESCHICHTE
B11: Energieausweis | C11: Ja | D11: Ja | G11: Lead Herkunft | H11: =BESICHTIGUNG!B3
B12: Nebenkostenabrechnung | C12: Ja | D12: Ja | G12: Wer ist der Eigentümer? | H12: =BESICHTIGUNG!B26
B13: Lageplan | C13: Ja | D13: Ja | G13: Warum wird das Objekt verkauft? | H13: =BESICHTIGUNG!B27
B14: Baulastenauskunft | C14: Ja | D14: Ja | G14: Schmerzgrenze Preis? | H14: =BESICHTIGUNG!B28
B15: Gebäudeversicherung | C15: Ja | D15: Ja | G15: Besonderheiten zum Haus / Erster Eindruck Umgebung | H15: =BESICHTIGUNG!B15
C16: =IF(COUNTIF(C11:C15,"Nein")>0, "Objektunterlagen noch nicht vollständig!", "Objektunterlagen vollständig!") | D16: =IF(COUNTIF(D11:D15,"Nein")>0, "Objektunterlagen noch nicht geprüft!", "Objektunterlagen geprüft!")
B18: FALLS VORHANDEN | C18: VORHANDEN? | D18: GEPRÜFT? | E18: BESONDERHEITEN
B19: Teilungserklärung | C19: Nein | D19: Nein
B20: Protokolle der Eigentümerversammlung | C20: Nein | D20: Nein
B21: Mietverträge (wenn vermietet) | C21: Ja | D21: Nein
G22: FINANZIERUNG
G23: =KALKU!M21 | I23: =KALKU!J39
B24: VERMIETUNG | G24: =KALKU!M22 | H24: =I24/I23 | I24: =KALKU!P22
B25: Wie viele Einheiten sind vermietet / leer? | C25: =BESICHTIGUNG!B31 | D25: =BESICHTIGUNG!B32 | G25: =KALKU!M23 | H25: =I25/I23 | I25: =KALKU!P23
B26: JNKM IST / Rendite IST | C26: =MIETER!J31 | D26: =MIETER!K32 | G26: =KALKU!M24 | I26: =KALKU!P24
B27: JNKM SOLL / Rendite SOLL | C27: =MIETER!N31 | D27: =MIETER!O32 | G27: Genügend EK für Deal vorhanden | H27: Ja
B28: JNKM Modernisierung / Rendite | C28: =MIETER!R31 | D28: =MIETER!S32 | G28: EK soll für diesen Deal verwendet werden | H28: Ja
G29: Kontakt zu Bank / Finanzierungsvermittler vorhanden? | H29: Ja
B30: KAUFPREIS HISTORIE | D30: SONSTIGE HINWEISE | G30: Notizen zur Finanzierung
B31: Inseratspreis | C31: =BESICHTIGUNG!B13 | D31: Hinweise
B32: Schmerzgrenze Preis | C32: =BESICHTIGUNG!B28
B33: Angebotspreis laut Kalkulation | C33: =KALKU!P37
B34: Schriftlich abgegebener Angebotspreis | C34: 800000
B35: Geeinigter Kaufpreis (geclosed) | C35: 900000
B37: GEPLANTE AUFWERTUNGSMAßNAHMEN
B38: Renovierung durch Fachmann verifiziert | C38: Ja | D38: Bemerkung | G38: =RENO!K6 | H38: =RENO!O6 | I38: =RENO!P6
A40: Nr | B40: Gewerk | C40: Maßnahme | E40: Menge | F40: Einheit | G40: Lohnkosten | H40: Materialkosten | I40: Gesamtkosten
A41: =IF(MAX(RENO!$C$12:$C$105)>0,1,"") | B41: =IF(A41<>"",IFERROR(VLOOKUP($A41,RENO!$C$12:$P$105,2,0),""),"") | C41: =IF(A41<>"",IFERROR(VLOOKUP($A41,RENO!$C$12:$P$105,4,0),""),"") | E41: =IF(A41<>"",IFERROR(VLOOKUP($A41,RENO!$C$12:$P$105,7,0),""),"") | F41: =IF(A41<>"",IFERROR(VLOOKUP($A41,RENO!$C$12:$P$105,8,0),""),"") | G41: =IF(A41<>"",IFERROR(VLOOKUP($A41,RENO!$C$12:$P$105,12,0),""),"") | H41: =IF(A41<>"",IFERROR(VLOOKUP($A41,RENO!$C$12:$P$105,13,0),""),"") | I41: =IF(A41<>"",IFERROR(VLOOKUP($A41,RENO!$C$12:$P$105,14,0),""),"")
A42: =IF(MAX(RENO!$C$12:$C$93)>A41,A41+1,"") | B42: =IF(A42<>"",IFERROR(VLOOKUP($A42,RENO!$C$12:$P$105,2,0),""),"") | C42: =IF(A42<>"",IFERROR(VLOOKUP($A42,RENO!$C$12:$P$105,4,0),""),"") | E42: =IF(A42<>"",IFERROR(VLOOKUP($A42,RENO!$C$12:$P$105,7,0),""),"") | F42: =IF(A42<>"",IFERROR(VLOOKUP($A42,RENO!$C$12:$P$105,8,0),""),"") | G42: =IF(A42<>"",IFERROR(VLOOKUP($A42,RENO!$C$12:$P$105,12,0),""),"") | H42: =IF(A42<>"",IFERROR(VLOOKUP($A42,RENO!$C$12:$P$105,13,0),""),"") | I42: =IF(A42<>"",IFERROR(VLOOKUP($A42,RENO!$C$12:$P$105,14,0),""),"")
A43: =IF(MAX(RENO!$C$12:$C$93)>A42,A42+1,"") | B43: =IF(A43<>"",IFERROR(VLOOKUP($A43,RENO!$C$12:$P$105,2,0),""),"") | C43: =IF(A43<>"",IFERROR(VLOOKUP($A43,RENO!$C$12:$P$105,4,0),""),"") | E43: =IF(A43<>"",IFERROR(VLOOKUP($A43,RENO!$C$12:$P$105,7,0),""),"") | F43: =IF(A43<>"",IFERROR(VLOOKUP($A43,RENO!$C$12:$P$105,8,0),""),"") | G43: =IF(A43<>"",IFERROR(VLOOKUP($A43,RENO!$C$12:$P$105,12,0),""),"") | H43: =IF(A43<>"",IFERROR(VLOOKUP($A43,RENO!$C$12:$P$105,13,0),""),"") | I43: =IF(A43<>"",IFERROR(VLOOKUP($A43,RENO!$C$12:$P$105,14,0),""),"")
A44: =IF(MAX(RENO!$C$12:$C$93)>A43,A43+1,"") | B44: =IF(A44<>"",IFERROR(VLOOKUP($A44,RENO!$C$12:$P$105,2,0),""),"") | C44: =IF(A44<>"",IFERROR(VLOOKUP($A44,RENO!$C$12:$P$105,4,0),""),"") | E44: =IF(A44<>"",IFERROR(VLOOKUP($A44,RENO!$C$12:$P$105,7,0),""),"") | F44: =IF(A44<>"",IFERROR(VLOOKUP($A44,RENO!$C$12:$P$105,8,0),""),"") | G44: =IF(A44<>"",IFERROR(VLOOKUP($A44,RENO!$C$12:$P$105,12,0),""),"") | H44: =IF(A44<>"",IFERROR(VLOOKUP($A44,RENO!$C$12:$P$105,13,0),""),"") | I44: =IF(A44<>"",IFERROR(VLOOKUP($A44,RENO!$C$12:$P$105,14,0),""),"")
A45: =IF(MAX(RENO!$C$12:$C$93)>A44,A44+1,"") | B45: =IF(A45<>"",IFERROR(VLOOKUP($A45,RENO!$C$12:$P$105,2,0),""),"") | C45: =IF(A45<>"",IFERROR(VLOOKUP($A45,RENO!$C$12:$P$105,4,0),""),"") | E45: =IF(A45<>"",IFERROR(VLOOKUP($A45,RENO!$C$12:$P$105,7,0),""),"") | F45: =IF(A45<>"",IFERROR(VLOOKUP($A45,RENO!$C$12:$P$105,8,0),""),"") | G45: =IF(A45<>"",IFERROR(VLOOKUP($A45,RENO!$C$12:$P$105,12,0),""),"") | H45: =IF(A45<>"",IFERROR(VLOOKUP($A45,RENO!$C$12:$P$105,13,0),""),"") | I45: =IF(A45<>"",IFERROR(VLOOKUP($A45,RENO!$C$12:$P$105,14,0),""),"")
A46: =IF(MAX(RENO!$C$12:$C$93)>A45,A45+1,"") | B46: =IF(A46<>"",IFERROR(VLOOKUP($A46,RENO!$C$12:$P$105,2,0),""),"") | C46: =IF(A46<>"",IFERROR(VLOOKUP($A46,RENO!$C$12:$P$105,4,0),""),"") | E46: =IF(A46<>"",IFERROR(VLOOKUP($A46,RENO!$C$12:$P$105,7,0),""),"") | F46: =IF(A46<>"",IFERROR(VLOOKUP($A46,RENO!$C$12:$P$105,8,0),""),"") | G46: =IF(A46<>"",IFERROR(VLOOKUP($A46,RENO!$C$12:$P$105,12,0),""),"") | H46: =IF(A46<>"",IFERROR(VLOOKUP($A46,RENO!$C$12:$P$105,13,0),""),"") | I46: =IF(A46<>"",IFERROR(VLOOKUP($A46,RENO!$C$12:$P$105,14,0),""),"")
A47: =IF(MAX(RENO!$C$12:$C$93)>A46,A46+1,"") | B47: =IF(A47<>"",IFERROR(VLOOKUP($A47,RENO!$C$12:$P$105,2,0),""),"") | C47: =IF(A47<>"",IFERROR(VLOOKUP($A47,RENO!$C$12:$P$105,4,0),""),"") | E47: =IF(A47<>"",IFERROR(VLOOKUP($A47,RENO!$C$12:$P$105,7,0),""),"") | F47: =IF(A47<>"",IFERROR(VLOOKUP($A47,RENO!$C$12:$P$105,8,0),""),"") | G47: =IF(A47<>"",IFERROR(VLOOKUP($A47,RENO!$C$12:$P$105,12,0),""),"") | H47: =IF(A47<>"",IFERROR(VLOOKUP($A47,RENO!$C$12:$P$105,13,0),""),"") | I47: =IF(A47<>"",IFERROR(VLOOKUP($A47,RENO!$C$12:$P$105,14,0),""),"")
A48: =IF(MAX(RENO!$C$12:$C$93)>A47,A47+1,"") | B48: =IF(A48<>"",IFERROR(VLOOKUP($A48,RENO!$C$12:$P$105,2,0),""),"") | C48: =IF(A48<>"",IFERROR(VLOOKUP($A48,RENO!$C$12:$P$105,4,0),""),"") | E48: =IF(A48<>"",IFERROR(VLOOKUP($A48,RENO!$C$12:$P$105,7,0),""),"") | F48: =IF(A48<>"",IFERROR(VLOOKUP($A48,RENO!$C$12:$P$105,8,0),""),"") | G48: =IF(A48<>"",IFERROR(VLOOKUP($A48,RENO!$C$12:$P$105,12,0),""),"") | H48: =IF(A48<>"",IFERROR(VLOOKUP($A48,RENO!$C$12:$P$105,13,0),""),"") | I48: =IF(A48<>"",IFERROR(VLOOKUP($A48,RENO!$C$12:$P$105,14,0),""),"")
A49: =IF(MAX(RENO!$C$12:$C$93)>A48,A48+1,"") | B49: =IF(A49<>"",IFERROR(VLOOKUP($A49,RENO!$C$12:$P$105,2,0),""),"") | C49: =IF(A49<>"",IFERROR(VLOOKUP($A49,RENO!$C$12:$P$105,4,0),""),"") | E49: =IF(A49<>"",IFERROR(VLOOKUP($A49,RENO!$C$12:$P$105,7,0),""),"") | F49: =IF(A49<>"",IFERROR(VLOOKUP($A49,RENO!$C$12:$P$105,8,0),""),"") | G49: =IF(A49<>"",IFERROR(VLOOKUP($A49,RENO!$C$12:$P$105,12,0),""),"") | H49: =IF(A49<>"",IFERROR(VLOOKUP($A49,RENO!$C$12:$P$105,13,0),""),"") | I49: =IF(A49<>"",IFERROR(VLOOKUP($A49,RENO!$C$12:$P$105,14,0),""),"")
A50: =IF(MAX(RENO!$C$12:$C$93)>A49,A49+1,"") | B50: =IF(A50<>"",IFERROR(VLOOKUP($A50,RENO!$C$12:$P$105,2,0),""),"") | C50: =IF(A50<>"",IFERROR(VLOOKUP($A50,RENO!$C$12:$P$105,4,0),""),"") | E50: =IF(A50<>"",IFERROR(VLOOKUP($A50,RENO!$C$12:$P$105,7,0),""),"") | F50: =IF(A50<>"",IFERROR(VLOOKUP($A50,RENO!$C$12:$P$105,8,0),""),"") | G50: =IF(A50<>"",IFERROR(VLOOKUP($A50,RENO!$C$12:$P$105,12,0),""),"") | H50: =IF(A50<>"",IFERROR(VLOOKUP($A50,RENO!$C$12:$P$105,13,0),""),"") | I50: =IF(A50<>"",IFERROR(VLOOKUP($A50,RENO!$C$12:$P$105,14,0),""),"")
A51: =IF(MAX(RENO!$C$12:$C$93)>A50,A50+1,"") | B51: =IF(A51<>"",IFERROR(VLOOKUP($A51,RENO!$C$12:$P$105,2,0),""),"") | C51: =IF(A51<>"",IFERROR(VLOOKUP($A51,RENO!$C$12:$P$105,4,0),""),"") | E51: =IF(A51<>"",IFERROR(VLOOKUP($A51,RENO!$C$12:$P$105,7,0),""),"") | F51: =IF(A51<>"",IFERROR(VLOOKUP($A51,RENO!$C$12:$P$105,8,0),""),"") | G51: =IF(A51<>"",IFERROR(VLOOKUP($A51,RENO!$C$12:$P$105,12,0),""),"") | H51: =IF(A51<>"",IFERROR(VLOOKUP($A51,RENO!$C$12:$P$105,13,0),""),"") | I51: =IF(A51<>"",IFERROR(VLOOKUP($A51,RENO!$C$12:$P$105,14,0),""),"")
A52: =IF(MAX(RENO!$C$12:$C$93)>A51,A51+1,"") | B52: =IF(A52<>"",IFERROR(VLOOKUP($A52,RENO!$C$12:$P$105,2,0),""),"") | C52: =IF(A52<>"",IFERROR(VLOOKUP($A52,RENO!$C$12:$P$105,4,0),""),"") | E52: =IF(A52<>"",IFERROR(VLOOKUP($A52,RENO!$C$12:$P$105,7,0),""),"") | F52: =IF(A52<>"",IFERROR(VLOOKUP($A52,RENO!$C$12:$P$105,8,0),""),"") | G52: =IF(A52<>"",IFERROR(VLOOKUP($A52,RENO!$C$12:$P$105,12,0),""),"") | H52: =IF(A52<>"",IFERROR(VLOOKUP($A52,RENO!$C$12:$P$105,13,0),""),"") | I52: =IF(A52<>"",IFERROR(VLOOKUP($A52,RENO!$C$12:$P$105,14,0),""),"")
A53: =IF(MAX(RENO!$C$12:$C$93)>A52,A52+1,"") | B53: =IF(A53<>"",IFERROR(VLOOKUP($A53,RENO!$C$12:$P$105,2,0),""),"") | C53: =IF(A53<>"",IFERROR(VLOOKUP($A53,RENO!$C$12:$P$105,4,0),""),"") | E53: =IF(A53<>"",IFERROR(VLOOKUP($A53,RENO!$C$12:$P$105,7,0),""),"") | F53: =IF(A53<>"",IFERROR(VLOOKUP($A53,RENO!$C$12:$P$105,8,0),""),"") | G53: =IF(A53<>"",IFERROR(VLOOKUP($A53,RENO!$C$12:$P$105,12,0),""),"") | H53: =IF(A53<>"",IFERROR(VLOOKUP($A53,RENO!$C$12:$P$105,13,0),""),"") | I53: =IF(A53<>"",IFERROR(VLOOKUP($A53,RENO!$C$12:$P$105,14,0),""),"")
... A132: =IF(MAX(RENO!$C$12:$C$93)>A131,A131+1,"") | B132: =IF(A132<>"",IFERROR(VLOOKUP($A132,RENO!$C$12:$P$105,2,0),""),"") | C132: =IF(A132<>"",IFERROR(VLOOKUP($A132,RENO!$C$12:$P$105,4,0),""),"") | E132: =IF(A132<>"",IFERROR(VLOOKUP($A132,RENO!$C$12:$P$105,7,0),""),"") | F132: =IF(A132<>"",IFERROR(VLOOKUP($A132,RENO!$C$12:$P$105,8,0),""),"") | G132: =IF(A132<>"",IFERROR(VLOOKUP($A132,RENO!$C$12:$P$105,12,0),""),"") | H132: =IF(A132<>"",IFERROR(VLOOKUP($A132,RENO!$C$12:$P$105,13,0),""),"") | I132: =IF(A132<>"",IFERROR(VLOOKUP($A132,RENO!$C$12:$P$105,14,0),""),"")
